Workbook

Sheet 0 logica
A1: Regresión logística con regularización: L2 (ridge), L1 (lasso) y elastic net, sobre german credit
A2: Preparado por David Díaz, con asistencia de Claude (Anthropic).
A4: Este archivo es la variante con regularización del Excel base (logistica_01_german_credit.xlsx). Usa exactamente los mismos 1.000 clientes, las mismas 18 columnas ya transformadas y escaladas y la misma partición 700 training / 300 testing; la hoja 1 los trae como valores para no repetir la preparación. Lo único que cambia es la función de costo que Solver minimiza.
A5: La idea viene de las clases de regresión lineal: cuando un modelo tiene libertad para mover muchos pesos, tiende a ajustarse al ruido de training, y una forma de frenarlo es cobrarle por el tamaño de los pesos. Con la logística es igual de fácil: a la suma de la entropía cruzada le agregamos un término de penalización, y ese término es lo que distingue a ridge, lasso y elastic net. Ridge (L2) cobra λ/2 por la suma de los pesos al cuadrado: encoge todos los pesos hacia cero, más a los grandes, pero nunca los deja exactamente en cero. Lasso (L1) cobra λ por la suma de los valores absolutos: también encoge, pero además deja pesos exactamente en cero, es decir, elimina variables. Elastic net mezcla las dos con un parámetro α que dice qué fracción del castigo es L1. El intercepto nunca se penaliza: no dice nada sobre ninguna variable, solo fija el nivel base.
A6: Cada hoja de modelo (2, 3 y 4) tiene la tabla de clientes con Z, p y pérdida, el bloque de pesos en celeste, la celda λ en celeste, el término de penalización calculado a la vista y la función de costo J = suma de pérdidas en training + penalización, que es la celda objetivo de Solver. Los pesos parten desde la solución sin regularizar (el óptimo del Excel base), así que Solver solo tiene que encoger. Con λ = 0 cada hoja reproduce el Excel base; con λ grande los pesos se van a cero y el modelo se vuelve el de 'todos pagan'. Al lado quedan la matriz de confusión y el reporte en testing, y la referencia de scikit-learn para la misma λ.
A7: La hoja 5 compara los tres métodos para varios valores de λ, con los pesos calculados en Python (gris): la trayectoria de cada peso a medida que λ crece (el gráfico clásico de regularización), y la pérdida y el AUC en training y en testing. Lo que muestra es honesto y conviene decirlo tal cual: en esta base, con 700 clientes y 18 variables, el sobreajuste de la logística sin regularizar es leve, así que la regularización casi no mejora el desempeño en testing; lo que sí hace es estabilizar los pesos y, con L1, dejar un modelo con menos variables que rinde casi igual. Regularizar sirve mucho cuando hay muchas variables respecto de las filas, o variables muy correlacionadas, o polinomios; aquí sirve sobre todo para entender la mecánica.
A8: Un detalle de escala que importa para comparar con scikit-learn: su parámetro es C = 1 / λ, y penaliza la suma de las pérdidas (no el promedio), que es exactamente como está planteado J en estas hojas. Por eso los pesos de referencia coinciden con los de Solver para la misma λ. Solver con L1 tiene una dificultad real: el valor absoluto no es derivable en cero, y GRG puede dejar pesos en 0,001 en vez de 0; hay que leer esos pesos como cero.
A9: Colores: celeste son parámetros (pesos, λ, α, umbral), amarillo cálculos intermedios, verde resultados, gris valores que vienen de Python.

Sheet 1 datos preparados
A1: Los 1.000 clientes ya transformados y escalados (valores; la preparación está en el Excel base, hojas 2 y 3)
A2: Mismas columnas y misma partición que logistica_01_german_credit.xlsx: y = 1 si mal pagador; cuatro numéricas escaladas con media y desviación de training; 14 columnas 0/1 con su categoría base; columna conjunto con 700 training y 300 testing. Aquí vienen pegados como valores para que este archivo se pueda abrir solo.
A4: id | B4: y | C4: duracion | D4: monto | E4: edad | F4: cuota_pct_ingreso | G4: cta_negativa | H4: cta_0_200 | I4: cta_sobre_200 | J4: hist_critico | K4: hist_atrasos | L4: hist_sin_creditos | M4: ahorro_100_1000 | N4: ahorro_sobre_1000 | O4: ahorro_desconocido | P4: vivienda_arriendo | Q4: vivienda_gratis | R4: proposito_auto | S4: proposito_radio_tv | T4: proposito_muebles | U4: conjunto
A5: 1 | B5: 0 | C5: -1.2412547 | D5: -0.72837022 | E5: 2.7361712 | F5: 0.91854372 | G5: 1 | H5: 0 | I5: 0 | J5: 1 | K5: 0 | L5: 0 | M5: 0 | N5: 0 | O5: 1 | P5: 0 | Q5: 0 | R5: 0 | S5: 1 | T5: 0 | U5: training
A6: 2 | B6: 1 | C6: 2.2976212 | D6: 0.94481687 | E6: -1.1776147 | F6: -0.88504844 | G6: 0 | H6: 1 | I6: 0 | J6: 0 | K6: 0 | L6: 0 | M6: 0 | N6: 0 | O6: 0 | P6: 0 | Q6: 0 | R6: 0 | S6: 1 | T6: 0 | U6: training
A7: 3 | B7: 0 | C7: -0.73570101 | D7: -0.40401965 | E7: 1.1706569 | F7: -0.88504844 | G7: 0 | H7: 0 | I7: 0 | J7: 1 | K7: 0 | L7: 0 | M7: 0 | N7: 0 | O7: 0 | P7: 0 | Q7: 0 | R7: 0 | S7: 0 | T7: 0 | U7: training
A8: 4 | B8: 0 | C8: 1.7920675 | D8: 1.6204598 | E8: 0.82276478 | F8: -0.88504844 | G8: 1 | H8: 0 | I8: 0 | J8: 0 | K8: 0 | L8: 0 | M8: 0 | N8: 0 | O8: 0 | P8: 0 | Q8: 1 | R8: 0 | S8: 0 | T8: 1 | U8: testing
A9: 5 | B9: 1 | C9: 0.2754064 | D9: 0.56658282 | E9: 1.5185489 | F9: 0.016747641 | G9: 1 | H9: 0 | I9: 0 | J9: 0 | K9: 1 | L9: 0 | M9: 0 | N9: 0 | O9: 0 | P9: 0 | Q9: 1 | R9: 1 | S9: 0 | T9: 0 | U9: training
A10: 6 | B10: 0 | C10: 1.2865138 | D10: 2.0308839 | E10: -0.046965431 | F10: -0.88504844 | G10: 0 | H10: 0 | I10: 0 | J10: 0 | K10: 0 | L10: 0 | M10: 0 | N10: 0 | O10: 1 | P10: 0 | Q10: 1 | R10: 0 | S10: 0 | T10: 0 | U10: testing
A11: 7 | B11: 0 | C11: 0.2754064 | D11: -0.14544891 | E11: 1.5185489 | F11: 0.016747641 | G11: 0 | H11: 0 | I11: 0 | J11: 0 | K11: 0 | L11: 0 | M11: 1 | N11: 0 | O11: 0 | P11: 0 | Q11: 0 | R11: 0 | S11: 0 | T11: 1 | U11: training
A12: 8 | B12: 0 | C12: 1.2865138 | D12: 1.2936599 | E12: -0.046965431 | F12: -0.88504844 | G12: 0 | H12: 1 | I12: 0 | J12: 0 | K12: 0 | L12: 0 | M12: 0 | N12: 0 | O12: 0 | P12: 1 | Q12: 0 | R12: 1 | S12: 0 | T12: 0 | U12: training
A13: 9 | B13: 0 | C13: -0.73570101 | D13: -0.067072939 | E13: 2.2143331 | F13: -0.88504844 | G13: 0 | H13: 0 | I13: 0 | J13: 0 | K13: 0 | L13: 0 | M13: 0 | N13: 1 | O13: 0 | P13: 0 | Q13: 0 | R13: 0 | S13: 1 | T13: 0 | U13: training
A14: 10 | B14: 1 | C14: 0.78096011 | D14: 0.69394377 | E14: -0.65577658 | F14: 0.91854372 | G14: 0 | H14: 1 | I14: 0 | J14: 1 | K14: 0 | L14: 0 | M14: 0 | N14: 0 | O14: 0 | P14: 0 | Q14: 0 | R14: 1 | S14: 0 | T14: 0 | U14: training
A15: 11 | B15: 1 | C15: -0.73570101 | D15: -0.68428374 | E15: -0.91669564 | F15: 0.016747641 | G15: 0 | H15: 1 | I15: 0 | J15: 0 | K15: 0 | L15: 0 | M15: 0 | N15: 0 | O15: 0 | P15: 1 | Q15: 0 | R15: 1 | S15: 0 | T15: 0 | U15: training
A16: 12 | B16: 1 | C16: 2.2976212 | D16: 0.3699431 | E16: -1.0036687 | F16: 0.016747641 | G16: 1 | H16: 0 | I16: 0 | J16: 0 | K16: 0 | L16: 0 | M16: 0 | N16: 0 | O16: 0 | P16: 1 | Q16: 0 | R16: 0 | S16: 0 | T16: 0 | U16: training
... A1004: 1000 | B1004: 0 | C1004: 2.0448444 | D1004: 0.46371435 | E1004: -0.7427496 | F1004: 0.016747641 | G1004: 0 | H1004: 1 | I1004: 0 | J1004: 1 | K1004: 0 | L1004: 0 | M1004: 1 | N1004: 0 | O1004: 0 | P1004: 0 | Q1004: 0 | R1004: 1 | S1004: 0 | T1004: 0 | U1004: training

Sheet 2 ridge L2
A1: Ridge (L2): cobrar por la suma de los cuadrados de los pesos
A2: Ridge (L2). La función de costo pasa a ser J = Σ pérdidas + λ/2 · Σ theta², con la suma sobre los 18 pesos (el intercepto queda fuera). El término nuevo crece con el cuadrado de cada peso, así que castiga mucho a los pesos grandes y poco a los chicos: Solver los encoge a todos hacia cero, en proporción, pero ninguno llega exactamente a cero. λ dice cuánto cuesta el tamaño: con λ = 0 estamos en el Excel base; con λ = 300 casi todos los pesos son pequeños y el modelo predice cerca de la tasa base para todos.
A3: Los pesos parten desde la solución sin regularizar (columna celeste), la referencia gris es la solución de scikit-learn para λ = 10, y las columnas amarillas son los theta² que suma la penalización. Corre Solver sobre J y compara los pesos con la referencia; después cambia λ y vuelve a correrlo. Mira la columna de pérdida promedio en testing: es lo que debería mejorar si hubiera sobreajuste, y en esta base casi no se mueve, porque con 700 filas y 18 variables el modelo sin regularizar no estaba sobreajustando mucho.
AB10: Pesos (theta): parten de la solución sin regularizar del Excel base | AH10: EVALUACIÓN EN TESTING (con el umbral celeste)
A11: id | B11: conjunto | C11: y | D11: duracion | E11: monto | F11: edad | G11: cuota_pct_ingreso | H11: cta_negativa | I11: cta_0_200 | J11: cta_sobre_200 | K11: hist_critico | L11: hist_atrasos | M11: hist_sin_creditos | N11: ahorro_100_1000 | O11: ahorro_sobre_1000 | P11: ahorro_desconocido | Q11: vivienda_arriendo | R11: vivienda_gratis | S11: proposito_auto | T11: proposito_radio_tv | U11: proposito_muebles | V11: Z (recta) | W11: p (logística) | X11: pérdida | Y11: predicción | Z11: acierto | AB11: variable | AC11: theta (celeste) | AD11: referencia scikit-learn, λ = 10 | AE11: theta²
A12: ='1 datos preparados'!A5 | B12: ='1 datos preparados'!U5 | C12: ='1 datos preparados'!B5 | D12: ='1 datos preparados'!C5 | E12: ='1 datos preparados'!D5 | F12: ='1 datos preparados'!E5 | G12: ='1 datos preparados'!F5 | H12: ='1 datos preparados'!G5 | I12: ='1 datos preparados'!H5 | J12: ='1 datos preparados'!I5 | ... U12: ='1 datos preparados'!T5 | V12: =$AC$12+D12*$AC$13+E12*$AC$14+F12*$AC$15+G12*$AC$16+H12*$AC$17+I12*$AC$18+J12*$AC$19+K12*$AC$20+L12*$AC$21+M12*$AC$22+N12*$AC$23+O12*$AC$24+P12*$AC$25+Q12*$AC$26+R12*$AC$27+S12*$AC$28+T12*$AC$29+U12*$AC$30 | W12: =1/(1+EXP(-V12)) | X12: =-IF(C12=1,LN(W12),LN(1-W12)) | Y12: =IF(W12>$AC$33,1,0) | Z12: =IF(Y12=C12,1,0) | AB12: intercepto | AC12: -1.341271 | AD12: -1.1287862 | AE12: (no se penaliza)
A13: ='1 datos preparados'!A6 | B13: ='1 datos preparados'!U6 | C13: ='1 datos preparados'!B6 | D13: ='1 datos preparados'!C6 | E13: ='1 datos preparados'!D6 | F13: ='1 datos preparados'!E6 | G13: ='1 datos preparados'!F6 | H13: ='1 datos preparados'!G6 | I13: ='1 datos preparados'!H6 | J13: ='1 datos preparados'!I6 | ... U13: ='1 datos preparados'!T6 | V13: =$AC$12+D13*$AC$13+E13*$AC$14+F13*$AC$15+G13*$AC$16+H13*$AC$17+I13*$AC$18+J13*$AC$19+K13*$AC$20+L13*$AC$21+M13*$AC$22+N13*$AC$23+O13*$AC$24+P13*$AC$25+Q13*$AC$26+R13*$AC$27+S13*$AC$28+T13*$AC$29+U13*$AC$30 | W13: =1/(1+EXP(-V13)) | X13: =-IF(C13=1,LN(W13),LN(1-W13)) | Y13: =IF(W13>$AC$33,1,0) | Z13: =IF(Y13=C13,1,0) | AB13: duracion | AC13: 0.32470125 | AD13: 0.28934872 | AE13: =AC13^2 | AJ13: predicho 0 | AK13: predicho 1 | AL13: total
A14: ='1 datos preparados'!A7 | B14: ='1 datos preparados'!U7 | C14: ='1 datos preparados'!B7 | D14: ='1 datos preparados'!C7 | E14: ='1 datos preparados'!D7 | F14: ='1 datos preparados'!E7 | G14: ='1 datos preparados'!F7 | H14: ='1 datos preparados'!G7 | I14: ='1 datos preparados'!H7 | J14: ='1 datos preparados'!I7 | ... U14: ='1 datos preparados'!T7 | V14: =$AC$12+D14*$AC$13+E14*$AC$14+F14*$AC$15+G14*$AC$16+H14*$AC$17+I14*$AC$18+J14*$AC$19+K14*$AC$20+L14*$AC$21+M14*$AC$22+N14*$AC$23+O14*$AC$24+P14*$AC$25+Q14*$AC$26+R14*$AC$27+S14*$AC$28+T14*$AC$29+U14*$AC$30 | W14: =1/(1+EXP(-V14)) | X14: =-IF(C14=1,LN(W14),LN(1-W14)) | Y14: =IF(W14>$AC$33,1,0) | Z14: =IF(Y14=C14,1,0) | AB14: monto | AC14: 0.11635359 | AD14: 0.10179157 | AE14: =AC14^2 | AH14: real 0 (buen pagador) | AI14: TN | FP | AJ14: =COUNTIFS($B$12:$B$1011,"testing",$C$12:$C$1011,0,$Y$12:$Y$1011,0) | AK14: =COUNTIFS($B$12:$B$1011,"testing",$C$12:$C$1011,0,$Y$12:$Y$1011,1) | AL14: =AJ14+AK14
A15: ='1 datos preparados'!A8 | B15: ='1 datos preparados'!U8 | C15: ='1 datos preparados'!B8 | D15: ='1 datos preparados'!C8 | E15: ='1 datos preparados'!D8 | F15: ='1 datos preparados'!E8 | G15: ='1 datos preparados'!F8 | H15: ='1 datos preparados'!G8 | I15: ='1 datos preparados'!H8 | J15: ='1 datos preparados'!I8 | ... U15: ='1 datos preparados'!T8 | V15: =$AC$12+D15*$AC$13+E15*$AC$14+F15*$AC$15+G15*$AC$16+H15*$AC$17+I15*$AC$18+J15*$AC$19+K15*$AC$20+L15*$AC$21+M15*$AC$22+N15*$AC$23+O15*$AC$24+P15*$AC$25+Q15*$AC$26+R15*$AC$27+S15*$AC$28+T15*$AC$29+U15*$AC$30 | W15: =1/(1+EXP(-V15)) | X15: =-IF(C15=1,LN(W15),LN(1-W15)) | Y15: =IF(W15>$AC$33,1,0) | Z15: =IF(Y15=C15,1,0) | AB15: edad | AC15: -0.099145225 | AD15: -0.11532177 | AE15: =AC15^2 | AH15: real 1 (mal pagador) | AI15: FN | TP | AJ15: =COUNTIFS($B$12:$B$1011,"testing",$C$12:$C$1011,1,$Y$12:$Y$1011,0) | AK15: =COUNTIFS($B$12:$B$1011,"testing",$C$12:$C$1011,1,$Y$12:$Y$1011,1) | AL15: =AJ15+AK15
A16: ='1 datos preparados'!A9 | B16: ='1 datos preparados'!U9 | C16: ='1 datos preparados'!B9 | D16: ='1 datos preparados'!C9 | E16: ='1 datos preparados'!D9 | F16: ='1 datos preparados'!E9 | G16: ='1 datos preparados'!F9 | H16: ='1 datos preparados'!G9 | I16: ='1 datos preparados'!H9 | J16: ='1 datos preparados'!I9 | ... U16: ='1 datos preparados'!T9 | V16: =$AC$12+D16*$AC$13+E16*$AC$14+F16*$AC$15+G16*$AC$16+H16*$AC$17+I16*$AC$18+J16*$AC$19+K16*$AC$20+L16*$AC$21+M16*$AC$22+N16*$AC$23+O16*$AC$24+P16*$AC$25+Q16*$AC$26+R16*$AC$27+S16*$AC$28+T16*$AC$29+U16*$AC$30 | W16: =1/(1+EXP(-V16)) | X16: =-IF(C16=1,LN(W16),LN(1-W16)) | Y16: =IF(W16>$AC$33,1,0) | Z16: =IF(Y16=C16,1,0) | AB16: cuota_pct_ingreso | AC16: 0.28721577 | AD16: 0.22222887 | AE16: =AC16^2 | AH16: total | AJ16: =AJ14+AJ15 | AK16: =AK14+AK15 | AL16: =AL14+AL15
A17: ='1 datos preparados'!A10 | B17: ='1 datos preparados'!U10 | C17: ='1 datos preparados'!B10 | D17: ='1 datos preparados'!C10 | E17: ='1 datos preparados'!D10 | F17: ='1 datos preparados'!E10 | G17: ='1 datos preparados'!F10 | H17: ='1 datos preparados'!G10 | I17: ='1 datos preparados'!H10 | J17: ='1 datos preparados'!I10 | ... U17: ='1 datos preparados'!T10 | V17: =$AC$12+D17*$AC$13+E17*$AC$14+F17*$AC$15+G17*$AC$16+H17*$AC$17+I17*$AC$18+J17*$AC$19+K17*$AC$20+L17*$AC$21+M17*$AC$22+N17*$AC$23+O17*$AC$24+P17*$AC$25+Q17*$AC$26+R17*$AC$27+S17*$AC$28+T17*$AC$29+U17*$AC$30 | W17: =1/(1+EXP(-V17)) | X17: =-IF(C17=1,LN(W17),LN(1-W17)) | Y17: =IF(W17>$AC$33,1,0) | Z17: =IF(Y17=C17,1,0) | AB17: cta_negativa | AC17: 1.5464027 | AD17: 0.92017635 | AE17: =AC17^2
A18: ='1 datos preparados'!A11 | B18: ='1 datos preparados'!U11 | C18: ='1 datos preparados'!B11 | D18: ='1 datos preparados'!C11 | E18: ='1 datos preparados'!D11 | F18: ='1 datos preparados'!E11 | G18: ='1 datos preparados'!F11 | H18: ='1 datos preparados'!G11 | I18: ='1 datos preparados'!H11 | J18: ='1 datos preparados'!I11 | ... U18: ='1 datos preparados'!T11 | V18: =$AC$12+D18*$AC$13+E18*$AC$14+F18*$AC$15+G18*$AC$16+H18*$AC$17+I18*$AC$18+J18*$AC$19+K18*$AC$20+L18*$AC$21+M18*$AC$22+N18*$AC$23+O18*$AC$24+P18*$AC$25+Q18*$AC$26+R18*$AC$27+S18*$AC$28+T18*$AC$29+U18*$AC$30 | W18: =1/(1+EXP(-V18)) | X18: =-IF(C18=1,LN(W18),LN(1-W18)) | Y18: =IF(W18>$AC$33,1,0) | Z18: =IF(Y18=C18,1,0) | AB18: cta_0_200 | AC18: 1.2949978 | AD18: 0.69158747 | AE18: =AC18^2 | AI18: precision | AJ18: recall | AK18: f1-score | AL18: support
A19: ='1 datos preparados'!A12 | B19: ='1 datos preparados'!U12 | C19: ='1 datos preparados'!B12 | D19: ='1 datos preparados'!C12 | E19: ='1 datos preparados'!D12 | F19: ='1 datos preparados'!E12 | G19: ='1 datos preparados'!F12 | H19: ='1 datos preparados'!G12 | I19: ='1 datos preparados'!H12 | J19: ='1 datos preparados'!I12 | ... U19: ='1 datos preparados'!T12 | V19: =$AC$12+D19*$AC$13+E19*$AC$14+F19*$AC$15+G19*$AC$16+H19*$AC$17+I19*$AC$18+J19*$AC$19+K19*$AC$20+L19*$AC$21+M19*$AC$22+N19*$AC$23+O19*$AC$24+P19*$AC$25+Q19*$AC$26+R19*$AC$27+S19*$AC$28+T19*$AC$29+U19*$AC$30 | W19: =1/(1+EXP(-V19)) | X19: =-IF(C19=1,LN(W19),LN(1-W19)) | Y19: =IF(W19>$AC$33,1,0) | Z19: =IF(Y19=C19,1,0) | AB19: cta_sobre_200 | AC19: 0.66836159 | AD19: 0.082674509 | AE19: =AC19^2 | AH19: clase 0 (paga) | AI19: =IF(AJ14+AJ15=0,0,AJ14/(AJ14+AJ15)) | AJ19: =IF(AJ14+AK14=0,0,AJ14/(AJ14+AK14)) | AK19: =IF(AI19+AJ19=0,0,2*AI19*AJ19/(AI19+AJ19)) | AL19: =AL14
A20: ='1 datos preparados'!A13 | B20: ='1 datos preparados'!U13 | C20: ='1 datos preparados'!B13 | D20: ='1 datos preparados'!C13 | E20: ='1 datos preparados'!D13 | F20: ='1 datos preparados'!E13 | G20: ='1 datos preparados'!F13 | H20: ='1 datos preparados'!G13 | I20: ='1 datos preparados'!H13 | J20: ='1 datos preparados'!I13 | ... U20: ='1 datos preparados'!T13 | V20: =$AC$12+D20*$AC$13+E20*$AC$14+F20*$AC$15+G20*$AC$16+H20*$AC$17+I20*$AC$18+J20*$AC$19+K20*$AC$20+L20*$AC$21+M20*$AC$22+N20*$AC$23+O20*$AC$24+P20*$AC$25+Q20*$AC$26+R20*$AC$27+S20*$AC$28+T20*$AC$29+U20*$AC$30 | W20: =1/(1+EXP(-V20)) | X20: =-IF(C20=1,LN(W20),LN(1-W20)) | Y20: =IF(W20>$AC$33,1,0) | Z20: =IF(Y20=C20,1,0) | AB20: hist_critico | AC20: -0.65734494 | AD20: -0.50285706 | AE20: =AC20^2 | AH20: clase 1 (no paga) | AI20: =IF(AK15+AK14=0,0,AK15/(AK15+AK14)) | AJ20: =IF(AK15+AJ15=0,0,AK15/(AK15+AJ15)) | AK20: =IF(AI20+AJ20=0,0,2*AI20*AJ20/(AI20+AJ20)) | AL20: =AL15
A21: ='1 datos preparados'!A14 | B21: ='1 datos preparados'!U14 | C21: ='1 datos preparados'!B14 | D21: ='1 datos preparados'!C14 | E21: ='1 datos preparados'!D14 | F21: ='1 datos preparados'!E14 | G21: ='1 datos preparados'!F14 | H21: ='1 datos preparados'!G14 | I21: ='1 datos preparados'!H14 | J21: ='1 datos preparados'!I14 | ... U21: ='1 datos preparados'!T14 | V21: =$AC$12+D21*$AC$13+E21*$AC$14+F21*$AC$15+G21*$AC$16+H21*$AC$17+I21*$AC$18+J21*$AC$19+K21*$AC$20+L21*$AC$21+M21*$AC$22+N21*$AC$23+O21*$AC$24+P21*$AC$25+Q21*$AC$26+R21*$AC$27+S21*$AC$28+T21*$AC$29+U21*$AC$30 | W21: =1/(1+EXP(-V21)) | X21: =-IF(C21=1,LN(W21),LN(1-W21)) | Y21: =IF(W21>$AC$33,1,0) | Z21: =IF(Y21=C21,1,0) | AB21: hist_atrasos | AC21: -0.040195519 | AD21: -0.032989077 | AE21: =AC21^2 | AH21: accuracy | AK21: =(AK15+AJ14)/AL16
A22: ='1 datos preparados'!A15 | B22: ='1 datos preparados'!U15 | C22: ='1 datos preparados'!B15 | D22: ='1 datos preparados'!C15 | E22: ='1 datos preparados'!D15 | F22: ='1 datos preparados'!E15 | G22: ='1 datos preparados'!F15 | H22: ='1 datos preparados'!G15 | I22: ='1 datos preparados'!H15 | J22: ='1 datos preparados'!I15 | ... U22: ='1 datos preparados'!T15 | V22: =$AC$12+D22*$AC$13+E22*$AC$14+F22*$AC$15+G22*$AC$16+H22*$AC$17+I22*$AC$18+J22*$AC$19+K22*$AC$20+L22*$AC$21+M22*$AC$22+N22*$AC$23+O22*$AC$24+P22*$AC$25+Q22*$AC$26+R22*$AC$27+S22*$AC$28+T22*$AC$29+U22*$AC$30 | W22: =1/(1+EXP(-V22)) | X22: =-IF(C22=1,LN(W22),LN(1-W22)) | Y22: =IF(W22>$AC$33,1,0) | Z22: =IF(Y22=C22,1,0) | AB22: hist_sin_creditos | AC22: 0.66906563 | AD22: 0.45665963 | AE22: =AC22^2
A23: ='1 datos preparados'!A16 | B23: ='1 datos preparados'!U16 | C23: ='1 datos preparados'!B16 | D23: ='1 datos preparados'!C16 | E23: ='1 datos preparados'!D16 | F23: ='1 datos preparados'!E16 | G23: ='1 datos preparados'!F16 | H23: ='1 datos preparados'!G16 | I23: ='1 datos preparados'!H16 | J23: ='1 datos preparados'!I16 | ... U23: ='1 datos preparados'!T16 | V23: =$AC$12+D23*$AC$13+E23*$AC$14+F23*$AC$15+G23*$AC$16+H23*$AC$17+I23*$AC$18+J23*$AC$19+K23*$AC$20+L23*$AC$21+M23*$AC$22+N23*$AC$23+O23*$AC$24+P23*$AC$25+Q23*$AC$26+R23*$AC$27+S23*$AC$28+T23*$AC$29+U23*$AC$30 | W23: =1/(1+EXP(-V23)) | X23: =-IF(C23=1,LN(W23),LN(1-W23)) | Y23: =IF(W23>$AC$33,1,0) | Z23: =IF(Y23=C23,1,0) | AB23: ahorro_100_1000 | AC23: -0.38958343 | AD23: -0.19262314 | AE23: =AC23^2
A24: ='1 datos preparados'!A17 | B24: ='1 datos preparados'!U17 | C24: ='1 datos preparados'!B17 | D24: ='1 datos preparados'!C17 | E24: ='1 datos preparados'!D17 | F24: ='1 datos preparados'!E17 | G24: ='1 datos preparados'!F17 | H24: ='1 datos preparados'!G17 | I24: ='1 datos preparados'!H17 | J24: ='1 datos preparados'!I17 | ... U24: ='1 datos preparados'!T17 | V24: =$AC$12+D24*$AC$13+E24*$AC$14+F24*$AC$15+G24*$AC$16+H24*$AC$17+I24*$AC$18+J24*$AC$19+K24*$AC$20+L24*$AC$21+M24*$AC$22+N24*$AC$23+O24*$AC$24+P24*$AC$25+Q24*$AC$26+R24*$AC$27+S24*$AC$28+T24*$AC$29+U24*$AC$30 | W24: =1/(1+EXP(-V24)) | X24: =-IF(C24=1,LN(W24),LN(1-W24)) | Y24: =IF(W24>$AC$33,1,0) | Z24: =IF(Y24=C24,1,0) | AB24: ahorro_sobre_1000 | AC24: -0.88922386 | AD24: -0.25447519 | AE24: =AC24^2
A25: ='1 datos preparados'!A18 | B25: ='1 datos preparados'!U18 | C25: ='1 datos preparados'!B18 | D25: ='1 datos preparados'!C18 | E25: ='1 datos preparados'!D18 | F25: ='1 datos preparados'!E18 | G25: ='1 datos preparados'!F18 | H25: ='1 datos preparados'!G18 | I25: ='1 datos preparados'!H18 | J25: ='1 datos preparados'!I18 | ... U25: ='1 datos preparados'!T18 | V25: =$AC$12+D25*$AC$13+E25*$AC$14+F25*$AC$15+G25*$AC$16+H25*$AC$17+I25*$AC$18+J25*$AC$19+K25*$AC$20+L25*$AC$21+M25*$AC$22+N25*$AC$23+O25*$AC$24+P25*$AC$25+Q25*$AC$26+R25*$AC$27+S25*$AC$28+T25*$AC$29+U25*$AC$30 | W25: =1/(1+EXP(-V25)) | X25: =-IF(C25=1,LN(W25),LN(1-W25)) | Y25: =IF(W25>$AC$33,1,0) | Z25: =IF(Y25=C25,1,0) | AB25: ahorro_desconocido | AC25: -1.0760929 | AD25: -0.58281045 | AE25: =AC25^2
A26: ='1 datos preparados'!A19 | B26: ='1 datos preparados'!U19 | C26: ='1 datos preparados'!B19 | D26: ='1 datos preparados'!C19 | E26: ='1 datos preparados'!D19 | F26: ='1 datos preparados'!E19 | G26: ='1 datos preparados'!F19 | H26: ='1 datos preparados'!G19 | I26: ='1 datos preparados'!H19 | J26: ='1 datos preparados'!I19 | ... U26: ='1 datos preparados'!T19 | V26: =$AC$12+D26*$AC$13+E26*$AC$14+F26*$AC$15+G26*$AC$16+H26*$AC$17+I26*$AC$18+J26*$AC$19+K26*$AC$20+L26*$AC$21+M26*$AC$22+N26*$AC$23+O26*$AC$24+P26*$AC$25+Q26*$AC$26+R26*$AC$27+S26*$AC$28+T26*$AC$29+U26*$AC$30 | W26: =1/(1+EXP(-V26)) | X26: =-IF(C26=1,LN(W26),LN(1-W26)) | Y26: =IF(W26>$AC$33,1,0) | Z26: =IF(Y26=C26,1,0) | AB26: vivienda_arriendo | AC26: 0.65383718 | AD26: 0.38387334 | AE26: =AC26^2
A27: ='1 datos preparados'!A20 | B27: ='1 datos preparados'!U20 | C27: ='1 datos preparados'!B20 | D27: ='1 datos preparados'!C20 | E27: ='1 datos preparados'!D20 | F27: ='1 datos preparados'!E20 | G27: ='1 datos preparados'!F20 | H27: ='1 datos preparados'!G20 | I27: ='1 datos preparados'!H20 | J27: ='1 datos preparados'!I20 | ... U27: ='1 datos preparados'!T20 | V27: =$AC$12+D27*$AC$13+E27*$AC$14+F27*$AC$15+G27*$AC$16+H27*$AC$17+I27*$AC$18+J27*$AC$19+K27*$AC$20+L27*$AC$21+M27*$AC$22+N27*$AC$23+O27*$AC$24+P27*$AC$25+Q27*$AC$26+R27*$AC$27+S27*$AC$28+T27*$AC$29+U27*$AC$30 | W27: =1/(1+EXP(-V27)) | X27: =-IF(C27=1,LN(W27),LN(1-W27)) | Y27: =IF(W27>$AC$33,1,0) | Z27: =IF(Y27=C27,1,0) | AB27: vivienda_gratis | AC27: 0.19536536 | AD27: 0.15826888 | AE27: =AC27^2
A28: ='1 datos preparados'!A21 | B28: ='1 datos preparados'!U21 | C28: ='1 datos preparados'!B21 | D28: ='1 datos preparados'!C21 | E28: ='1 datos preparados'!D21 | F28: ='1 datos preparados'!E21 | G28: ='1 datos preparados'!F21 | H28: ='1 datos preparados'!G21 | I28: ='1 datos preparados'!H21 | J28: ='1 datos preparados'!I21 | ... U28: ='1 datos preparados'!T21 | V28: =$AC$12+D28*$AC$13+E28*$AC$14+F28*$AC$15+G28*$AC$16+H28*$AC$17+I28*$AC$18+J28*$AC$19+K28*$AC$20+L28*$AC$21+M28*$AC$22+N28*$AC$23+O28*$AC$24+P28*$AC$25+Q28*$AC$26+R28*$AC$27+S28*$AC$28+T28*$AC$29+U28*$AC$30 | W28: =1/(1+EXP(-V28)) | X28: =-IF(C28=1,LN(W28),LN(1-W28)) | Y28: =IF(W28>$AC$33,1,0) | Z28: =IF(Y28=C28,1,0) | AB28: proposito_auto | AC28: -0.080165476 | AD28: 0.034595626 | AE28: =AC28^2
A29: ='1 datos preparados'!A22 | B29: ='1 datos preparados'!U22 | C29: ='1 datos preparados'!B22 | D29: ='1 datos preparados'!C22 | E29: ='1 datos preparados'!D22 | F29: ='1 datos preparados'!E22 | G29: ='1 datos preparados'!F22 | H29: ='1 datos preparados'!G22 | I29: ='1 datos preparados'!H22 | J29: ='1 datos preparados'!I22 | ... U29: ='1 datos preparados'!T22 | V29: =$AC$12+D29*$AC$13+E29*$AC$14+F29*$AC$15+G29*$AC$16+H29*$AC$17+I29*$AC$18+J29*$AC$19+K29*$AC$20+L29*$AC$21+M29*$AC$22+N29*$AC$23+O29*$AC$24+P29*$AC$25+Q29*$AC$26+R29*$AC$27+S29*$AC$28+T29*$AC$29+U29*$AC$30 | W29: =1/(1+EXP(-V29)) | X29: =-IF(C29=1,LN(W29),LN(1-W29)) | Y29: =IF(W29>$AC$33,1,0) | Z29: =IF(Y29=C29,1,0) | AB29: proposito_radio_tv | AC29: -0.52021065 | AD29: -0.3058125 | AE29: =AC29^2
A30: ='1 datos preparados'!A23 | B30: ='1 datos preparados'!U23 | C30: ='1 datos preparados'!B23 | D30: ='1 datos preparados'!C23 | E30: ='1 datos preparados'!D23 | F30: ='1 datos preparados'!E23 | G30: ='1 datos preparados'!F23 | H30: ='1 datos preparados'!G23 | I30: ='1 datos preparados'!H23 | J30: ='1 datos preparados'!I23 | ... U30: ='1 datos preparados'!T23 | V30: =$AC$12+D30*$AC$13+E30*$AC$14+F30*$AC$15+G30*$AC$16+H30*$AC$17+I30*$AC$18+J30*$AC$19+K30*$AC$20+L30*$AC$21+M30*$AC$22+N30*$AC$23+O30*$AC$24+P30*$AC$25+Q30*$AC$26+R30*$AC$27+S30*$AC$28+T30*$AC$29+U30*$AC$30 | W30: =1/(1+EXP(-V30)) | X30: =-IF(C30=1,LN(W30),LN(1-W30)) | Y30: =IF(W30>$AC$33,1,0) | Z30: =IF(Y30=C30,1,0) | AB30: proposito_muebles | AC30: -0.28180274 | AD30: -0.025436476 | AE30: =AC30^2
A31: ='1 datos preparados'!A24 | B31: ='1 datos preparados'!U24 | C31: ='1 datos preparados'!B24 | D31: ='1 datos preparados'!C24 | E31: ='1 datos preparados'!D24 | F31: ='1 datos preparados'!E24 | G31: ='1 datos preparados'!F24 | H31: ='1 datos preparados'!G24 | I31: ='1 datos preparados'!H24 | J31: ='1 datos preparados'!I24 | ... U31: ='1 datos preparados'!T24 | V31: =$AC$12+D31*$AC$13+E31*$AC$14+F31*$AC$15+G31*$AC$16+H31*$AC$17+I31*$AC$18+J31*$AC$19+K31*$AC$20+L31*$AC$21+M31*$AC$22+N31*$AC$23+O31*$AC$24+P31*$AC$25+Q31*$AC$26+R31*$AC$27+S31*$AC$28+T31*$AC$29+U31*$AC$30 | W31: =1/(1+EXP(-V31)) | X31: =-IF(C31=1,LN(W31),LN(1-W31)) | Y31: =IF(W31>$AC$33,1,0) | Z31: =IF(Y31=C31,1,0)
A32: ='1 datos preparados'!A25 | B32: ='1 datos preparados'!U25 | C32: ='1 datos preparados'!B25 | D32: ='1 datos preparados'!C25 | E32: ='1 datos preparados'!D25 | F32: ='1 datos preparados'!E25 | G32: ='1 datos preparados'!F25 | H32: ='1 datos preparados'!G25 | I32: ='1 datos preparados'!H25 | J32: ='1 datos preparados'!I25 | ... U32: ='1 datos preparados'!T25 | V32: =$AC$12+D32*$AC$13+E32*$AC$14+F32*$AC$15+G32*$AC$16+H32*$AC$17+I32*$AC$18+J32*$AC$19+K32*$AC$20+L32*$AC$21+M32*$AC$22+N32*$AC$23+O32*$AC$24+P32*$AC$25+Q32*$AC$26+R32*$AC$27+S32*$AC$28+T32*$AC$29+U32*$AC$30 | W32: =1/(1+EXP(-V32)) | X32: =-IF(C32=1,LN(W32),LN(1-W32)) | Y32: =IF(W32>$AC$33,1,0) | Z32: =IF(Y32=C32,1,0) | AB32: λ (lambda): cuánto cuesta el tamaño de los pesos | AC32: 10
A33: ='1 datos preparados'!A26 | B33: ='1 datos preparados'!U26 | C33: ='1 datos preparados'!B26 | D33: ='1 datos preparados'!C26 | E33: ='1 datos preparados'!D26 | F33: ='1 datos preparados'!E26 | G33: ='1 datos preparados'!F26 | H33: ='1 datos preparados'!G26 | I33: ='1 datos preparados'!H26 | J33: ='1 datos preparados'!I26 | ... U33: ='1 datos preparados'!T26 | V33: =$AC$12+D33*$AC$13+E33*$AC$14+F33*$AC$15+G33*$AC$16+H33*$AC$17+I33*$AC$18+J33*$AC$19+K33*$AC$20+L33*$AC$21+M33*$AC$22+N33*$AC$23+O33*$AC$24+P33*$AC$25+Q33*$AC$26+R33*$AC$27+S33*$AC$28+T33*$AC$29+U33*$AC$30 | W33: =1/(1+EXP(-V33)) | X33: =-IF(C33=1,LN(W33),LN(1-W33)) | Y33: =IF(W33>$AC$33,1,0) | Z33: =IF(Y33=C33,1,0) | AB33: umbral | AC33: 0.5
A34: ='1 datos preparados'!A27 | B34: ='1 datos preparados'!U27 | C34: ='1 datos preparados'!B27 | D34: ='1 datos preparados'!C27 | E34: ='1 datos preparados'!D27 | F34: ='1 datos preparados'!E27 | G34: ='1 datos preparados'!F27 | H34: ='1 datos preparados'!G27 | I34: ='1 datos preparados'!H27 | J34: ='1 datos preparados'!I27 | ... U34: ='1 datos preparados'!T27 | V34: =$AC$12+D34*$AC$13+E34*$AC$14+F34*$AC$15+G34*$AC$16+H34*$AC$17+I34*$AC$18+J34*$AC$19+K34*$AC$20+L34*$AC$21+M34*$AC$22+N34*$AC$23+O34*$AC$24+P34*$AC$25+Q34*$AC$26+R34*$AC$27+S34*$AC$28+T34*$AC$29+U34*$AC$30 | W34: =1/(1+EXP(-V34)) | X34: =-IF(C34=1,LN(W34),LN(1-W34)) | Y34: =IF(W34>$AC$33,1,0) | Z34: =IF(Y34=C34,1,0)
A35: ='1 datos preparados'!A28 | B35: ='1 datos preparados'!U28 | C35: ='1 datos preparados'!B28 | D35: ='1 datos preparados'!C28 | E35: ='1 datos preparados'!D28 | F35: ='1 datos preparados'!E28 | G35: ='1 datos preparados'!F28 | H35: ='1 datos preparados'!G28 | I35: ='1 datos preparados'!H28 | J35: ='1 datos preparados'!I28 | ... U35: ='1 datos preparados'!T28 | V35: =$AC$12+D35*$AC$13+E35*$AC$14+F35*$AC$15+G35*$AC$16+H35*$AC$17+I35*$AC$18+J35*$AC$19+K35*$AC$20+L35*$AC$21+M35*$AC$22+N35*$AC$23+O35*$AC$24+P35*$AC$25+Q35*$AC$26+R35*$AC$27+S35*$AC$28+T35*$AC$29+U35*$AC$30 | W35: =1/(1+EXP(-V35)) | X35: =-IF(C35=1,LN(W35),LN(1-W35)) | Y35: =IF(W35>$AC$33,1,0) | Z35: =IF(Y35=C35,1,0) | AB35: RESULTADOS
A36: ='1 datos preparados'!A29 | B36: ='1 datos preparados'!U29 | C36: ='1 datos preparados'!B29 | D36: ='1 datos preparados'!C29 | E36: ='1 datos preparados'!D29 | F36: ='1 datos preparados'!E29 | G36: ='1 datos preparados'!F29 | H36: ='1 datos preparados'!G29 | I36: ='1 datos preparados'!H29 | J36: ='1 datos preparados'!I29 | ... U36: ='1 datos preparados'!T29 | V36: =$AC$12+D36*$AC$13+E36*$AC$14+F36*$AC$15+G36*$AC$16+H36*$AC$17+I36*$AC$18+J36*$AC$19+K36*$AC$20+L36*$AC$21+M36*$AC$22+N36*$AC$23+O36*$AC$24+P36*$AC$25+Q36*$AC$26+R36*$AC$27+S36*$AC$28+T36*$AC$29+U36*$AC$30 | W36: =1/(1+EXP(-V36)) | X36: =-IF(C36=1,LN(W36),LN(1-W36)) | Y36: =IF(W36>$AC$33,1,0) | Z36: =IF(Y36=C36,1,0) | AB36: suma de pérdidas en training | AC36: =SUMPRODUCT(($B$12:$B$1011="training")*$X$12:$X$1011)
A37: ='1 datos preparados'!A30 | B37: ='1 datos preparados'!U30 | C37: ='1 datos preparados'!B30 | D37: ='1 datos preparados'!C30 | E37: ='1 datos preparados'!D30 | F37: ='1 datos preparados'!E30 | G37: ='1 datos preparados'!F30 | H37: ='1 datos preparados'!G30 | I37: ='1 datos preparados'!H30 | J37: ='1 datos preparados'!I30 | ... U37: ='1 datos preparados'!T30 | V37: =$AC$12+D37*$AC$13+E37*$AC$14+F37*$AC$15+G37*$AC$16+H37*$AC$17+I37*$AC$18+J37*$AC$19+K37*$AC$20+L37*$AC$21+M37*$AC$22+N37*$AC$23+O37*$AC$24+P37*$AC$25+Q37*$AC$26+R37*$AC$27+S37*$AC$28+T37*$AC$29+U37*$AC$30 | W37: =1/(1+EXP(-V37)) | X37: =-IF(C37=1,LN(W37),LN(1-W37)) | Y37: =IF(W37>$AC$33,1,0) | Z37: =IF(Y37=C37,1,0) | AB37: penalización L2 = λ/2 · Σ theta² | AC37: =$AC$32/2*SUM($AE$13:$AE$30)
A38: ='1 datos preparados'!A31 | B38: ='1 datos preparados'!U31 | C38: ='1 datos preparados'!B31 | D38: ='1 datos preparados'!C31 | E38: ='1 datos preparados'!D31 | F38: ='1 datos preparados'!E31 | G38: ='1 datos preparados'!F31 | H38: ='1 datos preparados'!G31 | I38: ='1 datos preparados'!H31 | J38: ='1 datos preparados'!I31 | ... U38: ='1 datos preparados'!T31 | V38: =$AC$12+D38*$AC$13+E38*$AC$14+F38*$AC$15+G38*$AC$16+H38*$AC$17+I38*$AC$18+J38*$AC$19+K38*$AC$20+L38*$AC$21+M38*$AC$22+N38*$AC$23+O38*$AC$24+P38*$AC$25+Q38*$AC$26+R38*$AC$27+S38*$AC$28+T38*$AC$29+U38*$AC$30 | W38: =1/(1+EXP(-V38)) | X38: =-IF(C38=1,LN(W38),LN(1-W38)) | Y38: =IF(W38>$AC$33,1,0) | Z38: =IF(Y38=C38,1,0) | AB38: J = suma de pérdidas + penalización (OBJETIVO DE SOLVER) | AC38: =AC36+AC37
A39: ='1 datos preparados'!A32 | B39: ='1 datos preparados'!U32 | C39: ='1 datos preparados'!B32 | D39: ='1 datos preparados'!C32 | E39: ='1 datos preparados'!D32 | F39: ='1 datos preparados'!E32 | G39: ='1 datos preparados'!F32 | H39: ='1 datos preparados'!G32 | I39: ='1 datos preparados'!H32 | J39: ='1 datos preparados'!I32 | ... U39: ='1 datos preparados'!T32 | V39: =$AC$12+D39*$AC$13+E39*$AC$14+F39*$AC$15+G39*$AC$16+H39*$AC$17+I39*$AC$18+J39*$AC$19+K39*$AC$20+L39*$AC$21+M39*$AC$22+N39*$AC$23+O39*$AC$24+P39*$AC$25+Q39*$AC$26+R39*$AC$27+S39*$AC$28+T39*$AC$29+U39*$AC$30 | W39: =1/(1+EXP(-V39)) | X39: =-IF(C39=1,LN(W39),LN(1-W39)) | Y39: =IF(W39>$AC$33,1,0) | Z39: =IF(Y39=C39,1,0) | AB39: pérdida promedio training | AC39: =AC36/COUNTIF($B$12:$B$1011,"training")
A40: ='1 datos preparados'!A33 | B40: ='1 datos preparados'!U33 | C40: ='1 datos preparados'!B33 | D40: ='1 datos preparados'!C33 | E40: ='1 datos preparados'!D33 | F40: ='1 datos preparados'!E33 | G40: ='1 datos preparados'!F33 | H40: ='1 datos preparados'!G33 | I40: ='1 datos preparados'!H33 | J40: ='1 datos preparados'!I33 | ... U40: ='1 datos preparados'!T33 | V40: =$AC$12+D40*$AC$13+E40*$AC$14+F40*$AC$15+G40*$AC$16+H40*$AC$17+I40*$AC$18+J40*$AC$19+K40*$AC$20+L40*$AC$21+M40*$AC$22+N40*$AC$23+O40*$AC$24+P40*$AC$25+Q40*$AC$26+R40*$AC$27+S40*$AC$28+T40*$AC$29+U40*$AC$30 | W40: =1/(1+EXP(-V40)) | X40: =-IF(C40=1,LN(W40),LN(1-W40)) | Y40: =IF(W40>$AC$33,1,0) | Z40: =IF(Y40=C40,1,0) | AB40: pérdida promedio testing | AC40: =SUMPRODUCT(($B$12:$B$1011="testing")*$X$12:$X$1011)/COUNTIF($B$12:$B$1011,"testing")
A41: ='1 datos preparados'!A34 | B41: ='1 datos preparados'!U34 | C41: ='1 datos preparados'!B34 | D41: ='1 datos preparados'!C34 | E41: ='1 datos preparados'!D34 | F41: ='1 datos preparados'!E34 | G41: ='1 datos preparados'!F34 | H41: ='1 datos preparados'!G34 | I41: ='1 datos preparados'!H34 | J41: ='1 datos preparados'!I34 | ... U41: ='1 datos preparados'!T34 | V41: =$AC$12+D41*$AC$13+E41*$AC$14+F41*$AC$15+G41*$AC$16+H41*$AC$17+I41*$AC$18+J41*$AC$19+K41*$AC$20+L41*$AC$21+M41*$AC$22+N41*$AC$23+O41*$AC$24+P41*$AC$25+Q41*$AC$26+R41*$AC$27+S41*$AC$28+T41*$AC$29+U41*$AC$30 | W41: =1/(1+EXP(-V41)) | X41: =-IF(C41=1,LN(W41),LN(1-W41)) | Y41: =IF(W41>$AC$33,1,0) | Z41: =IF(Y41=C41,1,0) | AB41: acierto testing | AC41: =SUMPRODUCT(($B$12:$B$1011="testing")*$Z$12:$Z$1011)/COUNTIF($B$12:$B$1011,"testing")
A42: ='1 datos preparados'!A35 | B42: ='1 datos preparados'!U35 | C42: ='1 datos preparados'!B35 | D42: ='1 datos preparados'!C35 | E42: ='1 datos preparados'!D35 | F42: ='1 datos preparados'!E35 | G42: ='1 datos preparados'!F35 | H42: ='1 datos preparados'!G35 | I42: ='1 datos preparados'!H35 | J42: ='1 datos preparados'!I35 | ... U42: ='1 datos preparados'!T35 | V42: =$AC$12+D42*$AC$13+E42*$AC$14+F42*$AC$15+G42*$AC$16+H42*$AC$17+I42*$AC$18+J42*$AC$19+K42*$AC$20+L42*$AC$21+M42*$AC$22+N42*$AC$23+O42*$AC$24+P42*$AC$25+Q42*$AC$26+R42*$AC$27+S42*$AC$28+T42*$AC$29+U42*$AC$30 | W42: =1/(1+EXP(-V42)) | X42: =-IF(C42=1,LN(W42),LN(1-W42)) | Y42: =IF(W42>$AC$33,1,0) | Z42: =IF(Y42=C42,1,0) | AB42: pesos (sin intercepto) con |theta| < 0,01 | AC42: =COUNTIF(AC13:AC30,"<0.01")-COUNTIF(AC13:AC30,"<-0.01")
A43: ='1 datos preparados'!A36 | B43: ='1 datos preparados'!U36 | C43: ='1 datos preparados'!B36 | D43: ='1 datos preparados'!C36 | E43: ='1 datos preparados'!D36 | F43: ='1 datos preparados'!E36 | G43: ='1 datos preparados'!F36 | H43: ='1 datos preparados'!G36 | I43: ='1 datos preparados'!H36 | J43: ='1 datos preparados'!I36 | ... U43: ='1 datos preparados'!T36 | V43: =$AC$12+D43*$AC$13+E43*$AC$14+F43*$AC$15+G43*$AC$16+H43*$AC$17+I43*$AC$18+J43*$AC$19+K43*$AC$20+L43*$AC$21+M43*$AC$22+N43*$AC$23+O43*$AC$24+P43*$AC$25+Q43*$AC$26+R43*$AC$27+S43*$AC$28+T43*$AC$29+U43*$AC$30 | W43: =1/(1+EXP(-V43)) | X43: =-IF(C43=1,LN(W43),LN(1-W43)) | Y43: =IF(W43>$AC$33,1,0) | Z43: =IF(Y43=C43,1,0) | AB43: referencia scikit-learn (λ = 10): J | AC43: 372.52712
A44: ='1 datos preparados'!A37 | B44: ='1 datos preparados'!U37 | C44: ='1 datos preparados'!B37 | D44: ='1 datos preparados'!C37 | E44: ='1 datos preparados'!D37 | F44: ='1 datos preparados'!E37 | G44: ='1 datos preparados'!F37 | H44: ='1 datos preparados'!G37 | I44: ='1 datos preparados'!H37 | J44: ='1 datos preparados'!I37 | ... U44: ='1 datos preparados'!T37 | V44: =$AC$12+D44*$AC$13+E44*$AC$14+F44*$AC$15+G44*$AC$16+H44*$AC$17+I44*$AC$18+J44*$AC$19+K44*$AC$20+L44*$AC$21+M44*$AC$22+N44*$AC$23+O44*$AC$24+P44*$AC$25+Q44*$AC$26+R44*$AC$27+S44*$AC$28+T44*$AC$29+U44*$AC$30 | W44: =1/(1+EXP(-V44)) | X44: =-IF(C44=1,LN(W44),LN(1-W44)) | Y44: =IF(W44>$AC$33,1,0) | Z44: =IF(Y44=C44,1,0) | AB44: referencia scikit-learn (λ = 10): pérdida promedio testing | AC44: 0.48479331
A45: ='1 datos preparados'!A38 | B45: ='1 datos preparados'!U38 | C45: ='1 datos preparados'!B38 | D45: ='1 datos preparados'!C38 | E45: ='1 datos preparados'!D38 | F45: ='1 datos preparados'!E38 | G45: ='1 datos preparados'!F38 | H45: ='1 datos preparados'!G38 | I45: ='1 datos preparados'!H38 | J45: ='1 datos preparados'!I38 | ... U45: ='1 datos preparados'!T38 | V45: =$AC$12+D45*$AC$13+E45*$AC$14+F45*$AC$15+G45*$AC$16+H45*$AC$17+I45*$AC$18+J45*$AC$19+K45*$AC$20+L45*$AC$21+M45*$AC$22+N45*$AC$23+O45*$AC$24+P45*$AC$25+Q45*$AC$26+R45*$AC$27+S45*$AC$28+T45*$AC$29+U45*$AC$30 | W45: =1/(1+EXP(-V45)) | X45: =-IF(C45=1,LN(W45),LN(1-W45)) | Y45: =IF(W45>$AC$33,1,0) | Z45: =IF(Y45=C45,1,0) | AB45: referencia scikit-learn (λ = 10): pesos en cero | AC45: 0
A46: ='1 datos preparados'!A39 | B46: ='1 datos preparados'!U39 | C46: ='1 datos preparados'!B39 | D46: ='1 datos preparados'!C39 | E46: ='1 datos preparados'!D39 | F46: ='1 datos preparados'!E39 | G46: ='1 datos preparados'!F39 | H46: ='1 datos preparados'!G39 | I46: ='1 datos preparados'!H39 | J46: ='1 datos preparados'!I39 | ... U46: ='1 datos preparados'!T39 | V46: =$AC$12+D46*$AC$13+E46*$AC$14+F46*$AC$15+G46*$AC$16+H46*$AC$17+I46*$AC$18+J46*$AC$19+K46*$AC$20+L46*$AC$21+M46*$AC$22+N46*$AC$23+O46*$AC$24+P46*$AC$25+Q46*$AC$26+R46*$AC$27+S46*$AC$28+T46*$AC$29+U46*$AC$30 | W46: =1/(1+EXP(-V46)) | X46: =-IF(C46=1,LN(W46),LN(1-W46)) | Y46: =IF(W46>$AC$33,1,0) | Z46: =IF(Y46=C46,1,0) | AB46: referencia sin regularizar (Excel base): pérdida promedio testing | AC46: 0.46905992
A47: ='1 datos preparados'!A40 | B47: ='1 datos preparados'!U40 | C47: ='1 datos preparados'!B40 | D47: ='1 datos preparados'!C40 | E47: ='1 datos preparados'!D40 | F47: ='1 datos preparados'!E40 | G47: ='1 datos preparados'!F40 | H47: ='1 datos preparados'!G40 | I47: ='1 datos preparados'!H40 | J47: ='1 datos preparados'!I40 | ... U47: ='1 datos preparados'!T40 | V47: =$AC$12+D47*$AC$13+E47*$AC$14+F47*$AC$15+G47*$AC$16+H47*$AC$17+I47*$AC$18+J47*$AC$19+K47*$AC$20+L47*$AC$21+M47*$AC$22+N47*$AC$23+O47*$AC$24+P47*$AC$25+Q47*$AC$26+R47*$AC$27+S47*$AC$28+T47*$AC$29+U47*$AC$30 | W47: =1/(1+EXP(-V47)) | X47: =-IF(C47=1,LN(W47),LN(1-W47)) | Y47: =IF(W47>$AC$33,1,0) | Z47: =IF(Y47=C47,1,0)
A48: ='1 datos preparados'!A41 | B48: ='1 datos preparados'!U41 | C48: ='1 datos preparados'!B41 | D48: ='1 datos preparados'!C41 | E48: ='1 datos preparados'!D41 | F48: ='1 datos preparados'!E41 | G48: ='1 datos preparados'!F41 | H48: ='1 datos preparados'!G41 | I48: ='1 datos preparados'!H41 | J48: ='1 datos preparados'!I41 | ... U48: ='1 datos preparados'!T41 | V48: =$AC$12+D48*$AC$13+E48*$AC$14+F48*$AC$15+G48*$AC$16+H48*$AC$17+I48*$AC$18+J48*$AC$19+K48*$AC$20+L48*$AC$21+M48*$AC$22+N48*$AC$23+O48*$AC$24+P48*$AC$25+Q48*$AC$26+R48*$AC$27+S48*$AC$28+T48*$AC$29+U48*$AC$30 | W48: =1/(1+EXP(-V48)) | X48: =-IF(C48=1,LN(W48),LN(1-W48)) | Y48: =IF(W48>$AC$33,1,0) | Z48: =IF(Y48=C48,1,0) | AB48: Solver: minimizar J (celda del objetivo) cambiando las celdas celestes de los pesos, GRG no lineal, derivadas centrales, convergencia 0,000001, sin restricciones y con la casilla 'Convertir variables sin restricciones en no negativas' DESMARCADA. Correr dos veces si se detiene antes.
A49: ='1 datos preparados'!A42 | B49: ='1 datos preparados'!U42 | C49: ='1 datos preparados'!B42 | D49: ='1 datos preparados'!C42 | E49: ='1 datos preparados'!D42 | F49: ='1 datos preparados'!E42 | G49: ='1 datos preparados'!F42 | H49: ='1 datos preparados'!G42 | I49: ='1 datos preparados'!H42 | J49: ='1 datos preparados'!I42 | ... U49: ='1 datos preparados'!T42 | V49: =$AC$12+D49*$AC$13+E49*$AC$14+F49*$AC$15+G49*$AC$16+H49*$AC$17+I49*$AC$18+J49*$AC$19+K49*$AC$20+L49*$AC$21+M49*$AC$22+N49*$AC$23+O49*$AC$24+P49*$AC$25+Q49*$AC$26+R49*$AC$27+S49*$AC$28+T49*$AC$29+U49*$AC$30 | W49: =1/(1+EXP(-V49)) | X49: =-IF(C49=1,LN(W49),LN(1-W49)) | Y49: =IF(W49>$AC$33,1,0) | Z49: =IF(Y49=C49,1,0)
A50: ='1 datos preparados'!A43 | B50: ='1 datos preparados'!U43 | C50: ='1 datos preparados'!B43 | D50: ='1 datos preparados'!C43 | E50: ='1 datos preparados'!D43 | F50: ='1 datos preparados'!E43 | G50: ='1 datos preparados'!F43 | H50: ='1 datos preparados'!G43 | I50: ='1 datos preparados'!H43 | J50: ='1 datos preparados'!I43 | ... U50: ='1 datos preparados'!T43 | V50: =$AC$12+D50*$AC$13+E50*$AC$14+F50*$AC$15+G50*$AC$16+H50*$AC$17+I50*$AC$18+J50*$AC$19+K50*$AC$20+L50*$AC$21+M50*$AC$22+N50*$AC$23+O50*$AC$24+P50*$AC$25+Q50*$AC$26+R50*$AC$27+S50*$AC$28+T50*$AC$29+U50*$AC$30 | W50: =1/(1+EXP(-V50)) | X50: =-IF(C50=1,LN(W50),LN(1-W50)) | Y50: =IF(W50>$AC$33,1,0) | Z50: =IF(Y50=C50,1,0)
A51: ='1 datos preparados'!A44 | B51: ='1 datos preparados'!U44 | C51: ='1 datos preparados'!B44 | D51: ='1 datos preparados'!C44 | E51: ='1 datos preparados'!D44 | F51: ='1 datos preparados'!E44 | G51: ='1 datos preparados'!F44 | H51: ='1 datos preparados'!G44 | I51: ='1 datos preparados'!H44 | J51: ='1 datos preparados'!I44 | ... U51: ='1 datos preparados'!T44 | V51: =$AC$12+D51*$AC$13+E51*$AC$14+F51*$AC$15+G51*$AC$16+H51*$AC$17+I51*$AC$18+J51*$AC$19+K51*$AC$20+L51*$AC$21+M51*$AC$22+N51*$AC$23+O51*$AC$24+P51*$AC$25+Q51*$AC$26+R51*$AC$27+S51*$AC$28+T51*$AC$29+U51*$AC$30 | W51: =1/(1+EXP(-V51)) | X51: =-IF(C51=1,LN(W51),LN(1-W51)) | Y51: =IF(W51>$AC$33,1,0) | Z51: =IF(Y51=C51,1,0)
A52: ='1 datos preparados'!A45 | B52: ='1 datos preparados'!U45 | C52: ='1 datos preparados'!B45 | D52: ='1 datos preparados'!C45 | E52: ='1 datos preparados'!D45 | F52: ='1 datos preparados'!E45 | G52: ='1 datos preparados'!F45 | H52: ='1 datos preparados'!G45 | I52: ='1 datos preparados'!H45 | J52: ='1 datos preparados'!I45 | ... U52: ='1 datos preparados'!T45 | V52: =$AC$12+D52*$AC$13+E52*$AC$14+F52*$AC$15+G52*$AC$16+H52*$AC$17+I52*$AC$18+J52*$AC$19+K52*$AC$20+L52*$AC$21+M52*$AC$22+N52*$AC$23+O52*$AC$24+P52*$AC$25+Q52*$AC$26+R52*$AC$27+S52*$AC$28+T52*$AC$29+U52*$AC$30 | W52: =1/(1+EXP(-V52)) | X52: =-IF(C52=1,LN(W52),LN(1-W52)) | Y52: =IF(W52>$AC$33,1,0) | Z52: =IF(Y52=C52,1,0)
A53: ='1 datos preparados'!A46 | B53: ='1 datos preparados'!U46 | C53: ='1 datos preparados'!B46 | D53: ='1 datos preparados'!C46 | E53: ='1 datos preparados'!D46 | F53: ='1 datos preparados'!E46 | G53: ='1 datos preparados'!F46 | H53: ='1 datos preparados'!G46 | I53: ='1 datos preparados'!H46 | J53: ='1 datos preparados'!I46 | ... U53: ='1 datos preparados'!T46 | V53: =$AC$12+D53*$AC$13+E53*$AC$14+F53*$AC$15+G53*$AC$16+H53*$AC$17+I53*$AC$18+J53*$AC$19+K53*$AC$20+L53*$AC$21+M53*$AC$22+N53*$AC$23+O53*$AC$24+P53*$AC$25+Q53*$AC$26+R53*$AC$27+S53*$AC$28+T53*$AC$29+U53*$AC$30 | W53: =1/(1+EXP(-V53)) | X53: =-IF(C53=1,LN(W53),LN(1-W53)) | Y53: =IF(W53>$AC$33,1,0) | Z53: =IF(Y53=C53,1,0)
A54: ='1 datos preparados'!A47 | B54: ='1 datos preparados'!U47 | C54: ='1 datos preparados'!B47 | D54: ='1 datos preparados'!C47 | E54: ='1 datos preparados'!D47 | F54: ='1 datos preparados'!E47 | G54: ='1 datos preparados'!F47 | H54: ='1 datos preparados'!G47 | I54: ='1 datos preparados'!H47 | J54: ='1 datos preparados'!I47 | ... U54: ='1 datos preparados'!T47 | V54: =$AC$12+D54*$AC$13+E54*$AC$14+F54*$AC$15+G54*$AC$16+H54*$AC$17+I54*$AC$18+J54*$AC$19+K54*$AC$20+L54*$AC$21+M54*$AC$22+N54*$AC$23+O54*$AC$24+P54*$AC$25+Q54*$AC$26+R54*$AC$27+S54*$AC$28+T54*$AC$29+U54*$AC$30 | W54: =1/(1+EXP(-V54)) | X54: =-IF(C54=1,LN(W54),LN(1-W54)) | Y54: =IF(W54>$AC$33,1,0) | Z54: =IF(Y54=C54,1,0)
A55: ='1 datos preparados'!A48 | B55: ='1 datos preparados'!U48 | C55: ='1 datos preparados'!B48 | D55: ='1 datos preparados'!C48 | E55: ='1 datos preparados'!D48 | F55: ='1 datos preparados'!E48 | G55: ='1 datos preparados'!F48 | H55: ='1 datos preparados'!G48 | I55: ='1 datos preparados'!H48 | J55: ='1 datos preparados'!I48 | ... U55: ='1 datos preparados'!T48 | V55: =$AC$12+D55*$AC$13+E55*$AC$14+F55*$AC$15+G55*$AC$16+H55*$AC$17+I55*$AC$18+J55*$AC$19+K55*$AC$20+L55*$AC$21+M55*$AC$22+N55*$AC$23+O55*$AC$24+P55*$AC$25+Q55*$AC$26+R55*$AC$27+S55*$AC$28+T55*$AC$29+U55*$AC$30 | W55: =1/(1+EXP(-V55)) | X55: =-IF(C55=1,LN(W55),LN(1-W55)) | Y55: =IF(W55>$AC$33,1,0) | Z55: =IF(Y55=C55,1,0)
A56: ='1 datos preparados'!A49 | B56: ='1 datos preparados'!U49 | C56: ='1 datos preparados'!B49 | D56: ='1 datos preparados'!C49 | E56: ='1 datos preparados'!D49 | F56: ='1 datos preparados'!E49 | G56: ='1 datos preparados'!F49 | H56: ='1 datos preparados'!G49 | I56: ='1 datos preparados'!H49 | J56: ='1 datos preparados'!I49 | ... U56: ='1 datos preparados'!T49 | V56: =$AC$12+D56*$AC$13+E56*$AC$14+F56*$AC$15+G56*$AC$16+H56*$AC$17+I56*$AC$18+J56*$AC$19+K56*$AC$20+L56*$AC$21+M56*$AC$22+N56*$AC$23+O56*$AC$24+P56*$AC$25+Q56*$AC$26+R56*$AC$27+S56*$AC$28+T56*$AC$29+U56*$AC$30 | W56: =1/(1+EXP(-V56)) | X56: =-IF(C56=1,LN(W56),LN(1-W56)) | Y56: =IF(W56>$AC$33,1,0) | Z56: =IF(Y56=C56,1,0)
A57: ='1 datos preparados'!A50 | B57: ='1 datos preparados'!U50 | C57: ='1 datos preparados'!B50 | D57: ='1 datos preparados'!C50 | E57: ='1 datos preparados'!D50 | F57: ='1 datos preparados'!E50 | G57: ='1 datos preparados'!F50 | H57: ='1 datos preparados'!G50 | I57: ='1 datos preparados'!H50 | J57: ='1 datos preparados'!I50 | ... U57: ='1 datos preparados'!T50 | V57: =$AC$12+D57*$AC$13+E57*$AC$14+F57*$AC$15+G57*$AC$16+H57*$AC$17+I57*$AC$18+J57*$AC$19+K57*$AC$20+L57*$AC$21+M57*$AC$22+N57*$AC$23+O57*$AC$24+P57*$AC$25+Q57*$AC$26+R57*$AC$27+S57*$AC$28+T57*$AC$29+U57*$AC$30 | W57: =1/(1+EXP(-V57)) | X57: =-IF(C57=1,LN(W57),LN(1-W57)) | Y57: =IF(W57>$AC$33,1,0) | Z57: =IF(Y57=C57,1,0)
A58: ='1 datos preparados'!A51 | B58: ='1 datos preparados'!U51 | C58: ='1 datos preparados'!B51 | D58: ='1 datos preparados'!C51 | E58: ='1 datos preparados'!D51 | F58: ='1 datos preparados'!E51 | G58: ='1 datos preparados'!F51 | H58: ='1 datos preparados'!G51 | I58: ='1 datos preparados'!H51 | J58: ='1 datos preparados'!I51 | ... U58: ='1 datos preparados'!T51 | V58: =$AC$12+D58*$AC$13+E58*$AC$14+F58*$AC$15+G58*$AC$16+H58*$AC$17+I58*$AC$18+J58*$AC$19+K58*$AC$20+L58*$AC$21+M58*$AC$22+N58*$AC$23+O58*$AC$24+P58*$AC$25+Q58*$AC$26+R58*$AC$27+S58*$AC$28+T58*$AC$29+U58*$AC$30 | W58: =1/(1+EXP(-V58)) | X58: =-IF(C58=1,LN(W58),LN(1-W58)) | Y58: =IF(W58>$AC$33,1,0) | Z58: =IF(Y58=C58,1,0)
A59: ='1 datos preparados'!A52 | B59: ='1 datos preparados'!U52 | C59: ='1 datos preparados'!B52 | D59: ='1 datos preparados'!C52 | E59: ='1 datos preparados'!D52 | F59: ='1 datos preparados'!E52 | G59: ='1 datos preparados'!F52 | H59: ='1 datos preparados'!G52 | I59: ='1 datos preparados'!H52 | J59: ='1 datos preparados'!I52 | ... U59: ='1 datos preparados'!T52 | V59: =$AC$12+D59*$AC$13+E59*$AC$14+F59*$AC$15+G59*$AC$16+H59*$AC$17+I59*$AC$18+J59*$AC$19+K59*$AC$20+L59*$AC$21+M59*$AC$22+N59*$AC$23+O59*$AC$24+P59*$AC$25+Q59*$AC$26+R59*$AC$27+S59*$AC$28+T59*$AC$29+U59*$AC$30 | W59: =1/(1+EXP(-V59)) | X59: =-IF(C59=1,LN(W59),LN(1-W59)) | Y59: =IF(W59>$AC$33,1,0) | Z59: =IF(Y59=C59,1,0)
A60: ='1 datos preparados'!A53 | B60: ='1 datos preparados'!U53 | C60: ='1 datos preparados'!B53 | D60: ='1 datos preparados'!C53 | E60: ='1 datos preparados'!D53 | F60: ='1 datos preparados'!E53 | G60: ='1 datos preparados'!F53 | H60: ='1 datos preparados'!G53 | I60: ='1 datos preparados'!H53 | J60: ='1 datos preparados'!I53 | ... U60: ='1 datos preparados'!T53 | V60: =$AC$12+D60*$AC$13+E60*$AC$14+F60*$AC$15+G60*$AC$16+H60*$AC$17+I60*$AC$18+J60*$AC$19+K60*$AC$20+L60*$AC$21+M60*$AC$22+N60*$AC$23+O60*$AC$24+P60*$AC$25+Q60*$AC$26+R60*$AC$27+S60*$AC$28+T60*$AC$29+U60*$AC$30 | W60: =1/(1+EXP(-V60)) | X60: =-IF(C60=1,LN(W60),LN(1-W60)) | Y60: =IF(W60>$AC$33,1,0) | Z60: =IF(Y60=C60,1,0)
... A1011: ='1 datos preparados'!A1004 | B1011: ='1 datos preparados'!U1004 | C1011: ='1 datos preparados'!B1004 | D1011: ='1 datos preparados'!C1004 | E1011: ='1 datos preparados'!D1004 | F1011: ='1 datos preparados'!E1004 | G1011: ='1 datos preparados'!F1004 | H1011: ='1 datos preparados'!G1004 | I1011: ='1 datos preparados'!H1004 | J1011: ='1 datos preparados'!I1004 | ... U1011: ='1 datos preparados'!T1004 | V1011: =$AC$12+D1011*$AC$13+E1011*$AC$14+F1011*$AC$15+G1011*$AC$16+H1011*$AC$17+I1011*$AC$18+J1011*$AC$19+K1011*$AC$20+L1011*$AC$21+M1011*$AC$22+N1011*$AC$23+O1011*$AC$24+P1011*$AC$25+Q1011*$AC$26+R1011*$AC$27+S1011*$AC$28+T1011*$AC$29+U1011*$AC$30 | W1011: =1/(1+EXP(-V1011)) | X1011: =-IF(C1011=1,LN(W1011),LN(1-W1011)) | Y1011: =IF(W1011>$AC$33,1,0) | Z1011: =IF(Y1011=C1011,1,0)

Sheet 3 lasso L1
A1: Lasso (L1): cobrar por la suma de los valores absolutos, y dejar pesos en cero
A2: Lasso (L1). Ahora J = Σ pérdidas + λ · Σ |theta|. La diferencia con ridge parece de detalle y no lo es: el valor absoluto tiene la misma pendiente λ para un peso grande que para uno chico, así que los pesos pequeños, que aportan poco a la pérdida, terminan exactamente en cero. Lasso hace selección de variables: con λ = 10, siete de los 18 pesos son cero en scikit-learn, y el modelo queda con once variables que rinden casi igual. Es la forma más simple de responder 'qué variables importan de verdad' sin salir de la logística.
A3: Solver y el valor absoluto no se llevan bien, porque |theta| no tiene derivada en cero: GRG se acerca y deja pesos en 0,002 o −0,004 en vez de exactamente 0. La celda 'pesos con |theta| < 0,01' los cuenta como cero; compárala con la referencia. Si Solver se traba, corre dos veces, o parte desde la referencia gris y verifica que J no baja.
AB10: Pesos (theta): parten de la solución sin regularizar del Excel base | AH10: EVALUACIÓN EN TESTING (con el umbral celeste)
A11: id | B11: conjunto | C11: y | D11: duracion | E11: monto | F11: edad | G11: cuota_pct_ingreso | H11: cta_negativa | I11: cta_0_200 | J11: cta_sobre_200 | K11: hist_critico | L11: hist_atrasos | M11: hist_sin_creditos | N11: ahorro_100_1000 | O11: ahorro_sobre_1000 | P11: ahorro_desconocido | Q11: vivienda_arriendo | R11: vivienda_gratis | S11: proposito_auto | T11: proposito_radio_tv | U11: proposito_muebles | V11: Z (recta) | W11: p (logística) | X11: pérdida | Y11: predicción | Z11: acierto | AB11: variable | AC11: theta (celeste) | AD11: referencia scikit-learn, λ = 10 | AE11: |theta|
A12: ='1 datos preparados'!A5 | B12: ='1 datos preparados'!U5 | C12: ='1 datos preparados'!B5 | D12: ='1 datos preparados'!C5 | E12: ='1 datos preparados'!D5 | F12: ='1 datos preparados'!E5 | G12: ='1 datos preparados'!F5 | H12: ='1 datos preparados'!G5 | I12: ='1 datos preparados'!H5 | J12: ='1 datos preparados'!I5 | ... U12: ='1 datos preparados'!T5 | V12: =$AC$12+D12*$AC$13+E12*$AC$14+F12*$AC$15+G12*$AC$16+H12*$AC$17+I12*$AC$18+J12*$AC$19+K12*$AC$20+L12*$AC$21+M12*$AC$22+N12*$AC$23+O12*$AC$24+P12*$AC$25+Q12*$AC$26+R12*$AC$27+S12*$AC$28+T12*$AC$29+U12*$AC$30 | W12: =1/(1+EXP(-V12)) | X12: =-IF(C12=1,LN(W12),LN(1-W12)) | Y12: =IF(W12>$AC$33,1,0) | Z12: =IF(Y12=C12,1,0) | AB12: intercepto | AC12: -1.341271 | AD12: -1.1904713 | AE12: (no se penaliza)
A13: ='1 datos preparados'!A6 | B13: ='1 datos preparados'!U6 | C13: ='1 datos preparados'!B6 | D13: ='1 datos preparados'!C6 | E13: ='1 datos preparados'!D6 | F13: ='1 datos preparados'!E6 | G13: ='1 datos preparados'!F6 | H13: ='1 datos preparados'!G6 | I13: ='1 datos preparados'!H6 | J13: ='1 datos preparados'!I6 | ... U13: ='1 datos preparados'!T6 | V13: =$AC$12+D13*$AC$13+E13*$AC$14+F13*$AC$15+G13*$AC$16+H13*$AC$17+I13*$AC$18+J13*$AC$19+K13*$AC$20+L13*$AC$21+M13*$AC$22+N13*$AC$23+O13*$AC$24+P13*$AC$25+Q13*$AC$26+R13*$AC$27+S13*$AC$28+T13*$AC$29+U13*$AC$30 | W13: =1/(1+EXP(-V13)) | X13: =-IF(C13=1,LN(W13),LN(1-W13)) | Y13: =IF(W13>$AC$33,1,0) | Z13: =IF(Y13=C13,1,0) | AB13: duracion | AC13: 0.32470125 | AD13: 0.29144233 | AE13: =ABS(AC13) | AJ13: predicho 0 | AK13: predicho 1 | AL13: total
A14: ='1 datos preparados'!A7 | B14: ='1 datos preparados'!U7 | C14: ='1 datos preparados'!B7 | D14: ='1 datos preparados'!C7 | E14: ='1 datos preparados'!D7 | F14: ='1 datos preparados'!E7 | G14: ='1 datos preparados'!F7 | H14: ='1 datos preparados'!G7 | I14: ='1 datos preparados'!H7 | J14: ='1 datos preparados'!I7 | ... U14: ='1 datos preparados'!T7 | V14: =$AC$12+D14*$AC$13+E14*$AC$14+F14*$AC$15+G14*$AC$16+H14*$AC$17+I14*$AC$18+J14*$AC$19+K14*$AC$20+L14*$AC$21+M14*$AC$22+N14*$AC$23+O14*$AC$24+P14*$AC$25+Q14*$AC$26+R14*$AC$27+S14*$AC$28+T14*$AC$29+U14*$AC$30 | W14: =1/(1+EXP(-V14)) | X14: =-IF(C14=1,LN(W14),LN(1-W14)) | Y14: =IF(W14>$AC$33,1,0) | Z14: =IF(Y14=C14,1,0) | AB14: monto | AC14: 0.11635359 | AD14: 0.014975721 | AE14: =ABS(AC14) | AH14: real 0 (buen pagador) | AI14: TN | FP | AJ14: =COUNTIFS($B$12:$B$1011,"testing",$C$12:$C$1011,0,$Y$12:$Y$1011,0) | AK14: =COUNTIFS($B$12:$B$1011,"testing",$C$12:$C$1011,0,$Y$12:$Y$1011,1) | AL14: =AJ14+AK14
A15: ='1 datos preparados'!A8 | B15: ='1 datos preparados'!U8 | C15: ='1 datos preparados'!B8 | D15: ='1 datos preparados'!C8 | E15: ='1 datos preparados'!D8 | F15: ='1 datos preparados'!E8 | G15: ='1 datos preparados'!F8 | H15: ='1 datos preparados'!G8 | I15: ='1 datos preparados'!H8 | J15: ='1 datos preparados'!I8 | ... U15: ='1 datos preparados'!T8 | V15: =$AC$12+D15*$AC$13+E15*$AC$14+F15*$AC$15+G15*$AC$16+H15*$AC$17+I15*$AC$18+J15*$AC$19+K15*$AC$20+L15*$AC$21+M15*$AC$22+N15*$AC$23+O15*$AC$24+P15*$AC$25+Q15*$AC$26+R15*$AC$27+S15*$AC$28+T15*$AC$29+U15*$AC$30 | W15: =1/(1+EXP(-V15)) | X15: =-IF(C15=1,LN(W15),LN(1-W15)) | Y15: =IF(W15>$AC$33,1,0) | Z15: =IF(Y15=C15,1,0) | AB15: edad | AC15: -0.099145225 | AD15: -0.044617039 | AE15: =ABS(AC15) | AH15: real 1 (mal pagador) | AI15: FN | TP | AJ15: =COUNTIFS($B$12:$B$1011,"testing",$C$12:$C$1011,1,$Y$12:$Y$1011,0) | AK15: =COUNTIFS($B$12:$B$1011,"testing",$C$12:$C$1011,1,$Y$12:$Y$1011,1) | AL15: =AJ15+AK15
A16: ='1 datos preparados'!A9 | B16: ='1 datos preparados'!U9 | C16: ='1 datos preparados'!B9 | D16: ='1 datos preparados'!C9 | E16: ='1 datos preparados'!D9 | F16: ='1 datos preparados'!E9 | G16: ='1 datos preparados'!F9 | H16: ='1 datos preparados'!G9 | I16: ='1 datos preparados'!H9 | J16: ='1 datos preparados'!I9 | ... U16: ='1 datos preparados'!T9 | V16: =$AC$12+D16*$AC$13+E16*$AC$14+F16*$AC$15+G16*$AC$16+H16*$AC$17+I16*$AC$18+J16*$AC$19+K16*$AC$20+L16*$AC$21+M16*$AC$22+N16*$AC$23+O16*$AC$24+P16*$AC$25+Q16*$AC$26+R16*$AC$27+S16*$AC$28+T16*$AC$29+U16*$AC$30 | W16: =1/(1+EXP(-V16)) | X16: =-IF(C16=1,LN(W16),LN(1-W16)) | Y16: =IF(W16>$AC$33,1,0) | Z16: =IF(Y16=C16,1,0) | AB16: cuota_pct_ingreso | AC16: 0.28721577 | AD16: 0.085070087 | AE16: =ABS(AC16) | AH16: total | AJ16: =AJ14+AJ15 | AK16: =AK14+AK15 | AL16: =AL14+AL15
A17: ='1 datos preparados'!A10 | B17: ='1 datos preparados'!U10 | C17: ='1 datos preparados'!B10 | D17: ='1 datos preparados'!C10 | E17: ='1 datos preparados'!D10 | F17: ='1 datos preparados'!E10 | G17: ='1 datos preparados'!F10 | H17: ='1 datos preparados'!G10 | I17: ='1 datos preparados'!H10 | J17: ='1 datos preparados'!I10 | ... U17: ='1 datos preparados'!T10 | V17: =$AC$12+D17*$AC$13+E17*$AC$14+F17*$AC$15+G17*$AC$16+H17*$AC$17+I17*$AC$18+J17*$AC$19+K17*$AC$20+L17*$AC$21+M17*$AC$22+N17*$AC$23+O17*$AC$24+P17*$AC$25+Q17*$AC$26+R17*$AC$27+S17*$AC$28+T17*$AC$29+U17*$AC$30 | W17: =1/(1+EXP(-V17)) | X17: =-IF(C17=1,LN(W17),LN(1-W17)) | Y17: =IF(W17>$AC$33,1,0) | Z17: =IF(Y17=C17,1,0) | AB17: cta_negativa | AC17: 1.5464027 | AD17: 0.97455047 | AE17: =ABS(AC17)
A18: ='1 datos preparados'!A11 | B18: ='1 datos preparados'!U11 | C18: ='1 datos preparados'!B11 | D18: ='1 datos preparados'!C11 | E18: ='1 datos preparados'!D11 | F18: ='1 datos preparados'!E11 | G18: ='1 datos preparados'!F11 | H18: ='1 datos preparados'!G11 | I18: ='1 datos preparados'!H11 | J18: ='1 datos preparados'!I11 | ... U18: ='1 datos preparados'!T11 | V18: =$AC$12+D18*$AC$13+E18*$AC$14+F18*$AC$15+G18*$AC$16+H18*$AC$17+I18*$AC$18+J18*$AC$19+K18*$AC$20+L18*$AC$21+M18*$AC$22+N18*$AC$23+O18*$AC$24+P18*$AC$25+Q18*$AC$26+R18*$AC$27+S18*$AC$28+T18*$AC$29+U18*$AC$30 | W18: =1/(1+EXP(-V18)) | X18: =-IF(C18=1,LN(W18),LN(1-W18)) | Y18: =IF(W18>$AC$33,1,0) | Z18: =IF(Y18=C18,1,0) | AB18: cta_0_200 | AC18: 1.2949978 | AD18: 0.60995409 | AE18: =ABS(AC18) | AI18: precision | AJ18: recall | AK18: f1-score | AL18: support
A19: ='1 datos preparados'!A12 | B19: ='1 datos preparados'!U12 | C19: ='1 datos preparados'!B12 | D19: ='1 datos preparados'!C12 | E19: ='1 datos preparados'!D12 | F19: ='1 datos preparados'!E12 | G19: ='1 datos preparados'!F12 | H19: ='1 datos preparados'!G12 | I19: ='1 datos preparados'!H12 | J19: ='1 datos preparados'!I12 | ... U19: ='1 datos preparados'!T12 | V19: =$AC$12+D19*$AC$13+E19*$AC$14+F19*$AC$15+G19*$AC$16+H19*$AC$17+I19*$AC$18+J19*$AC$19+K19*$AC$20+L19*$AC$21+M19*$AC$22+N19*$AC$23+O19*$AC$24+P19*$AC$25+Q19*$AC$26+R19*$AC$27+S19*$AC$28+T19*$AC$29+U19*$AC$30 | W19: =1/(1+EXP(-V19)) | X19: =-IF(C19=1,LN(W19),LN(1-W19)) | Y19: =IF(W19>$AC$33,1,0) | Z19: =IF(Y19=C19,1,0) | AB19: cta_sobre_200 | AC19: 0.66836159 | AD19: 0 | AE19: =ABS(AC19) | AH19: clase 0 (paga) | AI19: =IF(AJ14+AJ15=0,0,AJ14/(AJ14+AJ15)) | AJ19: =IF(AJ14+AK14=0,0,AJ14/(AJ14+AK14)) | AK19: =IF(AI19+AJ19=0,0,2*AI19*AJ19/(AI19+AJ19)) | AL19: =AL14
A20: ='1 datos preparados'!A13 | B20: ='1 datos preparados'!U13 | C20: ='1 datos preparados'!B13 | D20: ='1 datos preparados'!C13 | E20: ='1 datos preparados'!D13 | F20: ='1 datos preparados'!E13 | G20: ='1 datos preparados'!F13 | H20: ='1 datos preparados'!G13 | I20: ='1 datos preparados'!H13 | J20: ='1 datos preparados'!I13 | ... U20: ='1 datos preparados'!T13 | V20: =$AC$12+D20*$AC$13+E20*$AC$14+F20*$AC$15+G20*$AC$16+H20*$AC$17+I20*$AC$18+J20*$AC$19+K20*$AC$20+L20*$AC$21+M20*$AC$22+N20*$AC$23+O20*$AC$24+P20*$AC$25+Q20*$AC$26+R20*$AC$27+S20*$AC$28+T20*$AC$29+U20*$AC$30 | W20: =1/(1+EXP(-V20)) | X20: =-IF(C20=1,LN(W20),LN(1-W20)) | Y20: =IF(W20>$AC$33,1,0) | Z20: =IF(Y20=C20,1,0) | AB20: hist_critico | AC20: -0.65734494 | AD20: -0.35469615 | AE20: =ABS(AC20) | AH20: clase 1 (no paga) | AI20: =IF(AK15+AK14=0,0,AK15/(AK15+AK14)) | AJ20: =IF(AK15+AJ15=0,0,AK15/(AK15+AJ15)) | AK20: =IF(AI20+AJ20=0,0,2*AI20*AJ20/(AI20+AJ20)) | AL20: =AL15
A21: ='1 datos preparados'!A14 | B21: ='1 datos preparados'!U14 | C21: ='1 datos preparados'!B14 | D21: ='1 datos preparados'!C14 | E21: ='1 datos preparados'!D14 | F21: ='1 datos preparados'!E14 | G21: ='1 datos preparados'!F14 | H21: ='1 datos preparados'!G14 | I21: ='1 datos preparados'!H14 | J21: ='1 datos preparados'!I14 | ... U21: ='1 datos preparados'!T14 | V21: =$AC$12+D21*$AC$13+E21*$AC$14+F21*$AC$15+G21*$AC$16+H21*$AC$17+I21*$AC$18+J21*$AC$19+K21*$AC$20+L21*$AC$21+M21*$AC$22+N21*$AC$23+O21*$AC$24+P21*$AC$25+Q21*$AC$26+R21*$AC$27+S21*$AC$28+T21*$AC$29+U21*$AC$30 | W21: =1/(1+EXP(-V21)) | X21: =-IF(C21=1,LN(W21),LN(1-W21)) | Y21: =IF(W21>$AC$33,1,0) | Z21: =IF(Y21=C21,1,0) | AB21: hist_atrasos | AC21: -0.040195519 | AD21: 0 | AE21: =ABS(AC21) | AH21: accuracy | AK21: =(AK15+AJ14)/AL16
A22: ='1 datos preparados'!A15 | B22: ='1 datos preparados'!U15 | C22: ='1 datos preparados'!B15 | D22: ='1 datos preparados'!C15 | E22: ='1 datos preparados'!D15 | F22: ='1 datos preparados'!E15 | G22: ='1 datos preparados'!F15 | H22: ='1 datos preparados'!G15 | I22: ='1 datos preparados'!H15 | J22: ='1 datos preparados'!I15 | ... U22: ='1 datos preparados'!T15 | V22: =$AC$12+D22*$AC$13+E22*$AC$14+F22*$AC$15+G22*$AC$16+H22*$AC$17+I22*$AC$18+J22*$AC$19+K22*$AC$20+L22*$AC$21+M22*$AC$22+N22*$AC$23+O22*$AC$24+P22*$AC$25+Q22*$AC$26+R22*$AC$27+S22*$AC$28+T22*$AC$29+U22*$AC$30 | W22: =1/(1+EXP(-V22)) | X22: =-IF(C22=1,LN(W22),LN(1-W22)) | Y22: =IF(W22>$AC$33,1,0) | Z22: =IF(Y22=C22,1,0) | AB22: hist_sin_creditos | AC22: 0.66906563 | AD22: 0.15570542 | AE22: =ABS(AC22)
A23: ='1 datos preparados'!A16 | B23: ='1 datos preparados'!U16 | C23: ='1 datos preparados'!B16 | D23: ='1 datos preparados'!C16 | E23: ='1 datos preparados'!D16 | F23: ='1 datos preparados'!E16 | G23: ='1 datos preparados'!F16 | H23: ='1 datos preparados'!G16 | I23: ='1 datos preparados'!H16 | J23: ='1 datos preparados'!I16 | ... U23: ='1 datos preparados'!T16 | V23: =$AC$12+D23*$AC$13+E23*$AC$14+F23*$AC$15+G23*$AC$16+H23*$AC$17+I23*$AC$18+J23*$AC$19+K23*$AC$20+L23*$AC$21+M23*$AC$22+N23*$AC$23+O23*$AC$24+P23*$AC$25+Q23*$AC$26+R23*$AC$27+S23*$AC$28+T23*$AC$29+U23*$AC$30 | W23: =1/(1+EXP(-V23)) | X23: =-IF(C23=1,LN(W23),LN(1-W23)) | Y23: =IF(W23>$AC$33,1,0) | Z23: =IF(Y23=C23,1,0) | AB23: ahorro_100_1000 | AC23: -0.38958343 | AD23: 0 | AE23: =ABS(AC23)
A24: ='1 datos preparados'!A17 | B24: ='1 datos preparados'!U17 | C24: ='1 datos preparados'!B17 | D24: ='1 datos preparados'!C17 | E24: ='1 datos preparados'!D17 | F24: ='1 datos preparados'!E17 | G24: ='1 datos preparados'!F17 | H24: ='1 datos preparados'!G17 | I24: ='1 datos preparados'!H17 | J24: ='1 datos preparados'!I17 | ... U24: ='1 datos preparados'!T17 | V24: =$AC$12+D24*$AC$13+E24*$AC$14+F24*$AC$15+G24*$AC$16+H24*$AC$17+I24*$AC$18+J24*$AC$19+K24*$AC$20+L24*$AC$21+M24*$AC$22+N24*$AC$23+O24*$AC$24+P24*$AC$25+Q24*$AC$26+R24*$AC$27+S24*$AC$28+T24*$AC$29+U24*$AC$30 | W24: =1/(1+EXP(-V24)) | X24: =-IF(C24=1,LN(W24),LN(1-W24)) | Y24: =IF(W24>$AC$33,1,0) | Z24: =IF(Y24=C24,1,0) | AB24: ahorro_sobre_1000 | AC24: -0.88922386 | AD24: 0 | AE24: =ABS(AC24)
A25: ='1 datos preparados'!A18 | B25: ='1 datos preparados'!U18 | C25: ='1 datos preparados'!B18 | D25: ='1 datos preparados'!C18 | E25: ='1 datos preparados'!D18 | F25: ='1 datos preparados'!E18 | G25: ='1 datos preparados'!F18 | H25: ='1 datos preparados'!G18 | I25: ='1 datos preparados'!H18 | J25: ='1 datos preparados'!I18 | ... U25: ='1 datos preparados'!T18 | V25: =$AC$12+D25*$AC$13+E25*$AC$14+F25*$AC$15+G25*$AC$16+H25*$AC$17+I25*$AC$18+J25*$AC$19+K25*$AC$20+L25*$AC$21+M25*$AC$22+N25*$AC$23+O25*$AC$24+P25*$AC$25+Q25*$AC$26+R25*$AC$27+S25*$AC$28+T25*$AC$29+U25*$AC$30 | W25: =1/(1+EXP(-V25)) | X25: =-IF(C25=1,LN(W25),LN(1-W25)) | Y25: =IF(W25>$AC$33,1,0) | Z25: =IF(Y25=C25,1,0) | AB25: ahorro_desconocido | AC25: -1.0760929 | AD25: -0.23308747 | AE25: =ABS(AC25)
A26: ='1 datos preparados'!A19 | B26: ='1 datos preparados'!U19 | C26: ='1 datos preparados'!B19 | D26: ='1 datos preparados'!C19 | E26: ='1 datos preparados'!D19 | F26: ='1 datos preparados'!E19 | G26: ='1 datos preparados'!F19 | H26: ='1 datos preparados'!G19 | I26: ='1 datos preparados'!H19 | J26: ='1 datos preparados'!I19 | ... U26: ='1 datos preparados'!T19 | V26: =$AC$12+D26*$AC$13+E26*$AC$14+F26*$AC$15+G26*$AC$16+H26*$AC$17+I26*$AC$18+J26*$AC$19+K26*$AC$20+L26*$AC$21+M26*$AC$22+N26*$AC$23+O26*$AC$24+P26*$AC$25+Q26*$AC$26+R26*$AC$27+S26*$AC$28+T26*$AC$29+U26*$AC$30 | W26: =1/(1+EXP(-V26)) | X26: =-IF(C26=1,LN(W26),LN(1-W26)) | Y26: =IF(W26>$AC$33,1,0) | Z26: =IF(Y26=C26,1,0) | AB26: vivienda_arriendo | AC26: 0.65383718 | AD26: 0.084128659 | AE26: =ABS(AC26)
A27: ='1 datos preparados'!A20 | B27: ='1 datos preparados'!U20 | C27: ='1 datos preparados'!B20 | D27: ='1 datos preparados'!C20 | E27: ='1 datos preparados'!D20 | F27: ='1 datos preparados'!E20 | G27: ='1 datos preparados'!F20 | H27: ='1 datos preparados'!G20 | I27: ='1 datos preparados'!H20 | J27: ='1 datos preparados'!I20 | ... U27: ='1 datos preparados'!T20 | V27: =$AC$12+D27*$AC$13+E27*$AC$14+F27*$AC$15+G27*$AC$16+H27*$AC$17+I27*$AC$18+J27*$AC$19+K27*$AC$20+L27*$AC$21+M27*$AC$22+N27*$AC$23+O27*$AC$24+P27*$AC$25+Q27*$AC$26+R27*$AC$27+S27*$AC$28+T27*$AC$29+U27*$AC$30 | W27: =1/(1+EXP(-V27)) | X27: =-IF(C27=1,LN(W27),LN(1-W27)) | Y27: =IF(W27>$AC$33,1,0) | Z27: =IF(Y27=C27,1,0) | AB27: vivienda_gratis | AC27: 0.19536536 | AD27: 0 | AE27: =ABS(AC27)
A28: ='1 datos preparados'!A21 | B28: ='1 datos preparados'!U21 | C28: ='1 datos preparados'!B21 | D28: ='1 datos preparados'!C21 | E28: ='1 datos preparados'!D21 | F28: ='1 datos preparados'!E21 | G28: ='1 datos preparados'!F21 | H28: ='1 datos preparados'!G21 | I28: ='1 datos preparados'!H21 | J28: ='1 datos preparados'!I21 | ... U28: ='1 datos preparados'!T21 | V28: =$AC$12+D28*$AC$13+E28*$AC$14+F28*$AC$15+G28*$AC$16+H28*$AC$17+I28*$AC$18+J28*$AC$19+K28*$AC$20+L28*$AC$21+M28*$AC$22+N28*$AC$23+O28*$AC$24+P28*$AC$25+Q28*$AC$26+R28*$AC$27+S28*$AC$28+T28*$AC$29+U28*$AC$30 | W28: =1/(1+EXP(-V28)) | X28: =-IF(C28=1,LN(W28),LN(1-W28)) | Y28: =IF(W28>$AC$33,1,0) | Z28: =IF(Y28=C28,1,0) | AB28: proposito_auto | AC28: -0.080165476 | AD28: 0 | AE28: =ABS(AC28)
A29: ='1 datos preparados'!A22 | B29: ='1 datos preparados'!U22 | C29: ='1 datos preparados'!B22 | D29: ='1 datos preparados'!C22 | E29: ='1 datos preparados'!D22 | F29: ='1 datos preparados'!E22 | G29: ='1 datos preparados'!F22 | H29: ='1 datos preparados'!G22 | I29: ='1 datos preparados'!H22 | J29: ='1 datos preparados'!I22 | ... U29: ='1 datos preparados'!T22 | V29: =$AC$12+D29*$AC$13+E29*$AC$14+F29*$AC$15+G29*$AC$16+H29*$AC$17+I29*$AC$18+J29*$AC$19+K29*$AC$20+L29*$AC$21+M29*$AC$22+N29*$AC$23+O29*$AC$24+P29*$AC$25+Q29*$AC$26+R29*$AC$27+S29*$AC$28+T29*$AC$29+U29*$AC$30 | W29: =1/(1+EXP(-V29)) | X29: =-IF(C29=1,LN(W29),LN(1-W29)) | Y29: =IF(W29>$AC$33,1,0) | Z29: =IF(Y29=C29,1,0) | AB29: proposito_radio_tv | AC29: -0.52021065 | AD29: -0.064936381 | AE29: =ABS(AC29)
A30: ='1 datos preparados'!A23 | B30: ='1 datos preparados'!U23 | C30: ='1 datos preparados'!B23 | D30: ='1 datos preparados'!C23 | E30: ='1 datos preparados'!D23 | F30: ='1 datos preparados'!E23 | G30: ='1 datos preparados'!F23 | H30: ='1 datos preparados'!G23 | I30: ='1 datos preparados'!H23 | J30: ='1 datos preparados'!I23 | ... U30: ='1 datos preparados'!T23 | V30: =$AC$12+D30*$AC$13+E30*$AC$14+F30*$AC$15+G30*$AC$16+H30*$AC$17+I30*$AC$18+J30*$AC$19+K30*$AC$20+L30*$AC$21+M30*$AC$22+N30*$AC$23+O30*$AC$24+P30*$AC$25+Q30*$AC$26+R30*$AC$27+S30*$AC$28+T30*$AC$29+U30*$AC$30 | W30: =1/(1+EXP(-V30)) | X30: =-IF(C30=1,LN(W30),LN(1-W30)) | Y30: =IF(W30>$AC$33,1,0) | Z30: =IF(Y30=C30,1,0) | AB30: proposito_muebles | AC30: -0.28180274 | AD30: 0 | AE30: =ABS(AC30)
A31: ='1 datos preparados'!A24 | B31: ='1 datos preparados'!U24 | C31: ='1 datos preparados'!B24 | D31: ='1 datos preparados'!C24 | E31: ='1 datos preparados'!D24 | F31: ='1 datos preparados'!E24 | G31: ='1 datos preparados'!F24 | H31: ='1 datos preparados'!G24 | I31: ='1 datos preparados'!H24 | J31: ='1 datos preparados'!I24 | ... U31: ='1 datos preparados'!T24 | V31: =$AC$12+D31*$AC$13+E31*$AC$14+F31*$AC$15+G31*$AC$16+H31*$AC$17+I31*$AC$18+J31*$AC$19+K31*$AC$20+L31*$AC$21+M31*$AC$22+N31*$AC$23+O31*$AC$24+P31*$AC$25+Q31*$AC$26+R31*$AC$27+S31*$AC$28+T31*$AC$29+U31*$AC$30 | W31: =1/(1+EXP(-V31)) | X31: =-IF(C31=1,LN(W31),LN(1-W31)) | Y31: =IF(W31>$AC$33,1,0) | Z31: =IF(Y31=C31,1,0)
A32: ='1 datos preparados'!A25 | B32: ='1 datos preparados'!U25 | C32: ='1 datos preparados'!B25 | D32: ='1 datos preparados'!C25 | E32: ='1 datos preparados'!D25 | F32: ='1 datos preparados'!E25 | G32: ='1 datos preparados'!F25 | H32: ='1 datos preparados'!G25 | I32: ='1 datos preparados'!H25 | J32: ='1 datos preparados'!I25 | ... U32: ='1 datos preparados'!T25 | V32: =$AC$12+D32*$AC$13+E32*$AC$14+F32*$AC$15+G32*$AC$16+H32*$AC$17+I32*$AC$18+J32*$AC$19+K32*$AC$20+L32*$AC$21+M32*$AC$22+N32*$AC$23+O32*$AC$24+P32*$AC$25+Q32*$AC$26+R32*$AC$27+S32*$AC$28+T32*$AC$29+U32*$AC$30 | W32: =1/(1+EXP(-V32)) | X32: =-IF(C32=1,LN(W32),LN(1-W32)) | Y32: =IF(W32>$AC$33,1,0) | Z32: =IF(Y32=C32,1,0) | AB32: λ (lambda): cuánto cuesta el tamaño de los pesos | AC32: 10
A33: ='1 datos preparados'!A26 | B33: ='1 datos preparados'!U26 | C33: ='1 datos preparados'!B26 | D33: ='1 datos preparados'!C26 | E33: ='1 datos preparados'!D26 | F33: ='1 datos preparados'!E26 | G33: ='1 datos preparados'!F26 | H33: ='1 datos preparados'!G26 | I33: ='1 datos preparados'!H26 | J33: ='1 datos preparados'!I26 | ... U33: ='1 datos preparados'!T26 | V33: =$AC$12+D33*$AC$13+E33*$AC$14+F33*$AC$15+G33*$AC$16+H33*$AC$17+I33*$AC$18+J33*$AC$19+K33*$AC$20+L33*$AC$21+M33*$AC$22+N33*$AC$23+O33*$AC$24+P33*$AC$25+Q33*$AC$26+R33*$AC$27+S33*$AC$28+T33*$AC$29+U33*$AC$30 | W33: =1/(1+EXP(-V33)) | X33: =-IF(C33=1,LN(W33),LN(1-W33)) | Y33: =IF(W33>$AC$33,1,0) | Z33: =IF(Y33=C33,1,0) | AB33: umbral | AC33: 0.5
A34: ='1 datos preparados'!A27 | B34: ='1 datos preparados'!U27 | C34: ='1 datos preparados'!B27 | D34: ='1 datos preparados'!C27 | E34: ='1 datos preparados'!D27 | F34: ='1 datos preparados'!E27 | G34: ='1 datos preparados'!F27 | H34: ='1 datos preparados'!G27 | I34: ='1 datos preparados'!H27 | J34: ='1 datos preparados'!I27 | ... U34: ='1 datos preparados'!T27 | V34: =$AC$12+D34*$AC$13+E34*$AC$14+F34*$AC$15+G34*$AC$16+H34*$AC$17+I34*$AC$18+J34*$AC$19+K34*$AC$20+L34*$AC$21+M34*$AC$22+N34*$AC$23+O34*$AC$24+P34*$AC$25+Q34*$AC$26+R34*$AC$27+S34*$AC$28+T34*$AC$29+U34*$AC$30 | W34: =1/(1+EXP(-V34)) | X34: =-IF(C34=1,LN(W34),LN(1-W34)) | Y34: =IF(W34>$AC$33,1,0) | Z34: =IF(Y34=C34,1,0)
A35: ='1 datos preparados'!A28 | B35: ='1 datos preparados'!U28 | C35: ='1 datos preparados'!B28 | D35: ='1 datos preparados'!C28 | E35: ='1 datos preparados'!D28 | F35: ='1 datos preparados'!E28 | G35: ='1 datos preparados'!F28 | H35: ='1 datos preparados'!G28 | I35: ='1 datos preparados'!H28 | J35: ='1 datos preparados'!I28 | ... U35: ='1 datos preparados'!T28 | V35: =$AC$12+D35*$AC$13+E35*$AC$14+F35*$AC$15+G35*$AC$16+H35*$AC$17+I35*$AC$18+J35*$AC$19+K35*$AC$20+L35*$AC$21+M35*$AC$22+N35*$AC$23+O35*$AC$24+P35*$AC$25+Q35*$AC$26+R35*$AC$27+S35*$AC$28+T35*$AC$29+U35*$AC$30 | W35: =1/(1+EXP(-V35)) | X35: =-IF(C35=1,LN(W35),LN(1-W35)) | Y35: =IF(W35>$AC$33,1,0) | Z35: =IF(Y35=C35,1,0) | AB35: RESULTADOS
A36: ='1 datos preparados'!A29 | B36: ='1 datos preparados'!U29 | C36: ='1 datos preparados'!B29 | D36: ='1 datos preparados'!C29 | E36: ='1 datos preparados'!D29 | F36: ='1 datos preparados'!E29 | G36: ='1 datos preparados'!F29 | H36: ='1 datos preparados'!G29 | I36: ='1 datos preparados'!H29 | J36: ='1 datos preparados'!I29 | ... U36: ='1 datos preparados'!T29 | V36: =$AC$12+D36*$AC$13+E36*$AC$14+F36*$AC$15+G36*$AC$16+H36*$AC$17+I36*$AC$18+J36*$AC$19+K36*$AC$20+L36*$AC$21+M36*$AC$22+N36*$AC$23+O36*$AC$24+P36*$AC$25+Q36*$AC$26+R36*$AC$27+S36*$AC$28+T36*$AC$29+U36*$AC$30 | W36: =1/(1+EXP(-V36)) | X36: =-IF(C36=1,LN(W36),LN(1-W36)) | Y36: =IF(W36>$AC$33,1,0) | Z36: =IF(Y36=C36,1,0) | AB36: suma de pérdidas en training | AC36: =SUMPRODUCT(($B$12:$B$1011="training")*$X$12:$X$1011)
A37: ='1 datos preparados'!A30 | B37: ='1 datos preparados'!U30 | C37: ='1 datos preparados'!B30 | D37: ='1 datos preparados'!C30 | E37: ='1 datos preparados'!D30 | F37: ='1 datos preparados'!E30 | G37: ='1 datos preparados'!F30 | H37: ='1 datos preparados'!G30 | I37: ='1 datos preparados'!H30 | J37: ='1 datos preparados'!I30 | ... U37: ='1 datos preparados'!T30 | V37: =$AC$12+D37*$AC$13+E37*$AC$14+F37*$AC$15+G37*$AC$16+H37*$AC$17+I37*$AC$18+J37*$AC$19+K37*$AC$20+L37*$AC$21+M37*$AC$22+N37*$AC$23+O37*$AC$24+P37*$AC$25+Q37*$AC$26+R37*$AC$27+S37*$AC$28+T37*$AC$29+U37*$AC$30 | W37: =1/(1+EXP(-V37)) | X37: =-IF(C37=1,LN(W37),LN(1-W37)) | Y37: =IF(W37>$AC$33,1,0) | Z37: =IF(Y37=C37,1,0) | AB37: penalización L1 = λ · Σ |theta| | AC37: =$AC$32*SUM($AE$13:$AE$30)
A38: ='1 datos preparados'!A31 | B38: ='1 datos preparados'!U31 | C38: ='1 datos preparados'!B31 | D38: ='1 datos preparados'!C31 | E38: ='1 datos preparados'!D31 | F38: ='1 datos preparados'!E31 | G38: ='1 datos preparados'!F31 | H38: ='1 datos preparados'!G31 | I38: ='1 datos preparados'!H31 | J38: ='1 datos preparados'!I31 | ... U38: ='1 datos preparados'!T31 | V38: =$AC$12+D38*$AC$13+E38*$AC$14+F38*$AC$15+G38*$AC$16+H38*$AC$17+I38*$AC$18+J38*$AC$19+K38*$AC$20+L38*$AC$21+M38*$AC$22+N38*$AC$23+O38*$AC$24+P38*$AC$25+Q38*$AC$26+R38*$AC$27+S38*$AC$28+T38*$AC$29+U38*$AC$30 | W38: =1/(1+EXP(-V38)) | X38: =-IF(C38=1,LN(W38),LN(1-W38)) | Y38: =IF(W38>$AC$33,1,0) | Z38: =IF(Y38=C38,1,0) | AB38: J = suma de pérdidas + penalización (OBJETIVO DE SOLVER) | AC38: =AC36+AC37
A39: ='1 datos preparados'!A32 | B39: ='1 datos preparados'!U32 | C39: ='1 datos preparados'!B32 | D39: ='1 datos preparados'!C32 | E39: ='1 datos preparados'!D32 | F39: ='1 datos preparados'!E32 | G39: ='1 datos preparados'!F32 | H39: ='1 datos preparados'!G32 | I39: ='1 datos preparados'!H32 | J39: ='1 datos preparados'!I32 | ... U39: ='1 datos preparados'!T32 | V39: =$AC$12+D39*$AC$13+E39*$AC$14+F39*$AC$15+G39*$AC$16+H39*$AC$17+I39*$AC$18+J39*$AC$19+K39*$AC$20+L39*$AC$21+M39*$AC$22+N39*$AC$23+O39*$AC$24+P39*$AC$25+Q39*$AC$26+R39*$AC$27+S39*$AC$28+T39*$AC$29+U39*$AC$30 | W39: =1/(1+EXP(-V39)) | X39: =-IF(C39=1,LN(W39),LN(1-W39)) | Y39: =IF(W39>$AC$33,1,0) | Z39: =IF(Y39=C39,1,0) | AB39: pérdida promedio training | AC39: =AC36/COUNTIF($B$12:$B$1011,"training")
A40: ='1 datos preparados'!A33 | B40: ='1 datos preparados'!U33 | C40: ='1 datos preparados'!B33 | D40: ='1 datos preparados'!C33 | E40: ='1 datos preparados'!D33 | F40: ='1 datos preparados'!E33 | G40: ='1 datos preparados'!F33 | H40: ='1 datos preparados'!G33 | I40: ='1 datos preparados'!H33 | J40: ='1 datos preparados'!I33 | ... U40: ='1 datos preparados'!T33 | V40: =$AC$12+D40*$AC$13+E40*$AC$14+F40*$AC$15+G40*$AC$16+H40*$AC$17+I40*$AC$18+J40*$AC$19+K40*$AC$20+L40*$AC$21+M40*$AC$22+N40*$AC$23+O40*$AC$24+P40*$AC$25+Q40*$AC$26+R40*$AC$27+S40*$AC$28+T40*$AC$29+U40*$AC$30 | W40: =1/(1+EXP(-V40)) | X40: =-IF(C40=1,LN(W40),LN(1-W40)) | Y40: =IF(W40>$AC$33,1,0) | Z40: =IF(Y40=C40,1,0) | AB40: pérdida promedio testing | AC40: =SUMPRODUCT(($B$12:$B$1011="testing")*$X$12:$X$1011)/COUNTIF($B$12:$B$1011,"testing")
A41: ='1 datos preparados'!A34 | B41: ='1 datos preparados'!U34 | C41: ='1 datos preparados'!B34 | D41: ='1 datos preparados'!C34 | E41: ='1 datos preparados'!D34 | F41: ='1 datos preparados'!E34 | G41: ='1 datos preparados'!F34 | H41: ='1 datos preparados'!G34 | I41: ='1 datos preparados'!H34 | J41: ='1 datos preparados'!I34 | ... U41: ='1 datos preparados'!T34 | V41: =$AC$12+D41*$AC$13+E41*$AC$14+F41*$AC$15+G41*$AC$16+H41*$AC$17+I41*$AC$18+J41*$AC$19+K41*$AC$20+L41*$AC$21+M41*$AC$22+N41*$AC$23+O41*$AC$24+P41*$AC$25+Q41*$AC$26+R41*$AC$27+S41*$AC$28+T41*$AC$29+U41*$AC$30 | W41: =1/(1+EXP(-V41)) | X41: =-IF(C41=1,LN(W41),LN(1-W41)) | Y41: =IF(W41>$AC$33,1,0) | Z41: =IF(Y41=C41,1,0) | AB41: acierto testing | AC41: =SUMPRODUCT(($B$12:$B$1011="testing")*$Z$12:$Z$1011)/COUNTIF($B$12:$B$1011,"testing")
A42: ='1 datos preparados'!A35 | B42: ='1 datos preparados'!U35 | C42: ='1 datos preparados'!B35 | D42: ='1 datos preparados'!C35 | E42: ='1 datos preparados'!D35 | F42: ='1 datos preparados'!E35 | G42: ='1 datos preparados'!F35 | H42: ='1 datos preparados'!G35 | I42: ='1 datos preparados'!H35 | J42: ='1 datos preparados'!I35 | ... U42: ='1 datos preparados'!T35 | V42: =$AC$12+D42*$AC$13+E42*$AC$14+F42*$AC$15+G42*$AC$16+H42*$AC$17+I42*$AC$18+J42*$AC$19+K42*$AC$20+L42*$AC$21+M42*$AC$22+N42*$AC$23+O42*$AC$24+P42*$AC$25+Q42*$AC$26+R42*$AC$27+S42*$AC$28+T42*$AC$29+U42*$AC$30 | W42: =1/(1+EXP(-V42)) | X42: =-IF(C42=1,LN(W42),LN(1-W42)) | Y42: =IF(W42>$AC$33,1,0) | Z42: =IF(Y42=C42,1,0) | AB42: pesos (sin intercepto) con |theta| < 0,01 | AC42: =COUNTIF(AC13:AC30,"<0.01")-COUNTIF(AC13:AC30,"<-0.01")
A43: ='1 datos preparados'!A36 | B43: ='1 datos preparados'!U36 | C43: ='1 datos preparados'!B36 | D43: ='1 datos preparados'!C36 | E43: ='1 datos preparados'!D36 | F43: ='1 datos preparados'!E36 | G43: ='1 datos preparados'!F36 | H43: ='1 datos preparados'!G36 | I43: ='1 datos preparados'!H36 | J43: ='1 datos preparados'!I36 | ... U43: ='1 datos preparados'!T36 | V43: =$AC$12+D43*$AC$13+E43*$AC$14+F43*$AC$15+G43*$AC$16+H43*$AC$17+I43*$AC$18+J43*$AC$19+K43*$AC$20+L43*$AC$21+M43*$AC$22+N43*$AC$23+O43*$AC$24+P43*$AC$25+Q43*$AC$26+R43*$AC$27+S43*$AC$28+T43*$AC$29+U43*$AC$30 | W43: =1/(1+EXP(-V43)) | X43: =-IF(C43=1,LN(W43),LN(1-W43)) | Y43: =IF(W43>$AC$33,1,0) | Z43: =IF(Y43=C43,1,0) | AB43: referencia scikit-learn (λ = 10): J | AC43: 401.67357
A44: ='1 datos preparados'!A37 | B44: ='1 datos preparados'!U37 | C44: ='1 datos preparados'!B37 | D44: ='1 datos preparados'!C37 | E44: ='1 datos preparados'!D37 | F44: ='1 datos preparados'!E37 | G44: ='1 datos preparados'!F37 | H44: ='1 datos preparados'!G37 | I44: ='1 datos preparados'!H37 | J44: ='1 datos preparados'!I37 | ... U44: ='1 datos preparados'!T37 | V44: =$AC$12+D44*$AC$13+E44*$AC$14+F44*$AC$15+G44*$AC$16+H44*$AC$17+I44*$AC$18+J44*$AC$19+K44*$AC$20+L44*$AC$21+M44*$AC$22+N44*$AC$23+O44*$AC$24+P44*$AC$25+Q44*$AC$26+R44*$AC$27+S44*$AC$28+T44*$AC$29+U44*$AC$30 | W44: =1/(1+EXP(-V44)) | X44: =-IF(C44=1,LN(W44),LN(1-W44)) | Y44: =IF(W44>$AC$33,1,0) | Z44: =IF(Y44=C44,1,0) | AB44: referencia scikit-learn (λ = 10): pérdida promedio testing | AC44: 0.50707619
A45: ='1 datos preparados'!A38 | B45: ='1 datos preparados'!U38 | C45: ='1 datos preparados'!B38 | D45: ='1 datos preparados'!C38 | E45: ='1 datos preparados'!D38 | F45: ='1 datos preparados'!E38 | G45: ='1 datos preparados'!F38 | H45: ='1 datos preparados'!G38 | I45: ='1 datos preparados'!H38 | J45: ='1 datos preparados'!I38 | ... U45: ='1 datos preparados'!T38 | V45: =$AC$12+D45*$AC$13+E45*$AC$14+F45*$AC$15+G45*$AC$16+H45*$AC$17+I45*$AC$18+J45*$AC$19+K45*$AC$20+L45*$AC$21+M45*$AC$22+N45*$AC$23+O45*$AC$24+P45*$AC$25+Q45*$AC$26+R45*$AC$27+S45*$AC$28+T45*$AC$29+U45*$AC$30 | W45: =1/(1+EXP(-V45)) | X45: =-IF(C45=1,LN(W45),LN(1-W45)) | Y45: =IF(W45>$AC$33,1,0) | Z45: =IF(Y45=C45,1,0) | AB45: referencia scikit-learn (λ = 10): pesos en cero | AC45: 7
A46: ='1 datos preparados'!A39 | B46: ='1 datos preparados'!U39 | C46: ='1 datos preparados'!B39 | D46: ='1 datos preparados'!C39 | E46: ='1 datos preparados'!D39 | F46: ='1 datos preparados'!E39 | G46: ='1 datos preparados'!F39 | H46: ='1 datos preparados'!G39 | I46: ='1 datos preparados'!H39 | J46: ='1 datos preparados'!I39 | ... U46: ='1 datos preparados'!T39 | V46: =$AC$12+D46*$AC$13+E46*$AC$14+F46*$AC$15+G46*$AC$16+H46*$AC$17+I46*$AC$18+J46*$AC$19+K46*$AC$20+L46*$AC$21+M46*$AC$22+N46*$AC$23+O46*$AC$24+P46*$AC$25+Q46*$AC$26+R46*$AC$27+S46*$AC$28+T46*$AC$29+U46*$AC$30 | W46: =1/(1+EXP(-V46)) | X46: =-IF(C46=1,LN(W46),LN(1-W46)) | Y46: =IF(W46>$AC$33,1,0) | Z46: =IF(Y46=C46,1,0) | AB46: referencia sin regularizar (Excel base): pérdida promedio testing | AC46: 0.46905992
A47: ='1 datos preparados'!A40 | B47: ='1 datos preparados'!U40 | C47: ='1 datos preparados'!B40 | D47: ='1 datos preparados'!C40 | E47: ='1 datos preparados'!D40 | F47: ='1 datos preparados'!E40 | G47: ='1 datos preparados'!F40 | H47: ='1 datos preparados'!G40 | I47: ='1 datos preparados'!H40 | J47: ='1 datos preparados'!I40 | ... U47: ='1 datos preparados'!T40 | V47: =$AC$12+D47*$AC$13+E47*$AC$14+F47*$AC$15+G47*$AC$16+H47*$AC$17+I47*$AC$18+J47*$AC$19+K47*$AC$20+L47*$AC$21+M47*$AC$22+N47*$AC$23+O47*$AC$24+P47*$AC$25+Q47*$AC$26+R47*$AC$27+S47*$AC$28+T47*$AC$29+U47*$AC$30 | W47: =1/(1+EXP(-V47)) | X47: =-IF(C47=1,LN(W47),LN(1-W47)) | Y47: =IF(W47>$AC$33,1,0) | Z47: =IF(Y47=C47,1,0)
A48: ='1 datos preparados'!A41 | B48: ='1 datos preparados'!U41 | C48: ='1 datos preparados'!B41 | D48: ='1 datos preparados'!C41 | E48: ='1 datos preparados'!D41 | F48: ='1 datos preparados'!E41 | G48: ='1 datos preparados'!F41 | H48: ='1 datos preparados'!G41 | I48: ='1 datos preparados'!H41 | J48: ='1 datos preparados'!I41 | ... U48: ='1 datos preparados'!T41 | V48: =$AC$12+D48*$AC$13+E48*$AC$14+F48*$AC$15+G48*$AC$16+H48*$AC$17+I48*$AC$18+J48*$AC$19+K48*$AC$20+L48*$AC$21+M48*$AC$22+N48*$AC$23+O48*$AC$24+P48*$AC$25+Q48*$AC$26+R48*$AC$27+S48*$AC$28+T48*$AC$29+U48*$AC$30 | W48: =1/(1+EXP(-V48)) | X48: =-IF(C48=1,LN(W48),LN(1-W48)) | Y48: =IF(W48>$AC$33,1,0) | Z48: =IF(Y48=C48,1,0) | AB48: Solver: minimizar J (celda del objetivo) cambiando las celdas celestes de los pesos, GRG no lineal, derivadas centrales, convergencia 0,000001, sin restricciones y con la casilla 'Convertir variables sin restricciones en no negativas' DESMARCADA. Correr dos veces si se detiene antes.
A49: ='1 datos preparados'!A42 | B49: ='1 datos preparados'!U42 | C49: ='1 datos preparados'!B42 | D49: ='1 datos preparados'!C42 | E49: ='1 datos preparados'!D42 | F49: ='1 datos preparados'!E42 | G49: ='1 datos preparados'!F42 | H49: ='1 datos preparados'!G42 | I49: ='1 datos preparados'!H42 | J49: ='1 datos preparados'!I42 | ... U49: ='1 datos preparados'!T42 | V49: =$AC$12+D49*$AC$13+E49*$AC$14+F49*$AC$15+G49*$AC$16+H49*$AC$17+I49*$AC$18+J49*$AC$19+K49*$AC$20+L49*$AC$21+M49*$AC$22+N49*$AC$23+O49*$AC$24+P49*$AC$25+Q49*$AC$26+R49*$AC$27+S49*$AC$28+T49*$AC$29+U49*$AC$30 | W49: =1/(1+EXP(-V49)) | X49: =-IF(C49=1,LN(W49),LN(1-W49)) | Y49: =IF(W49>$AC$33,1,0) | Z49: =IF(Y49=C49,1,0) | AB49: Con L1 el valor absoluto no tiene derivada en cero y GRG puede dejar pesos en 0,003 en vez de 0: léelos como cero. scikit-learn usa un algoritmo (saga) que sí los deja exactamente en cero.
A50: ='1 datos preparados'!A43 | B50: ='1 datos preparados'!U43 | C50: ='1 datos preparados'!B43 | D50: ='1 datos preparados'!C43 | E50: ='1 datos preparados'!D43 | F50: ='1 datos preparados'!E43 | G50: ='1 datos preparados'!F43 | H50: ='1 datos preparados'!G43 | I50: ='1 datos preparados'!H43 | J50: ='1 datos preparados'!I43 | ... U50: ='1 datos preparados'!T43 | V50: =$AC$12+D50*$AC$13+E50*$AC$14+F50*$AC$15+G50*$AC$16+H50*$AC$17+I50*$AC$18+J50*$AC$19+K50*$AC$20+L50*$AC$21+M50*$AC$22+N50*$AC$23+O50*$AC$24+P50*$AC$25+Q50*$AC$26+R50*$AC$27+S50*$AC$28+T50*$AC$29+U50*$AC$30 | W50: =1/(1+EXP(-V50)) | X50: =-IF(C50=1,LN(W50),LN(1-W50)) | Y50: =IF(W50>$AC$33,1,0) | Z50: =IF(Y50=C50,1,0)
A51: ='1 datos preparados'!A44 | B51: ='1 datos preparados'!U44 | C51: ='1 datos preparados'!B44 | D51: ='1 datos preparados'!C44 | E51: ='1 datos preparados'!D44 | F51: ='1 datos preparados'!E44 | G51: ='1 datos preparados'!F44 | H51: ='1 datos preparados'!G44 | I51: ='1 datos preparados'!H44 | J51: ='1 datos preparados'!I44 | ... U51: ='1 datos preparados'!T44 | V51: =$AC$12+D51*$AC$13+E51*$AC$14+F51*$AC$15+G51*$AC$16+H51*$AC$17+I51*$AC$18+J51*$AC$19+K51*$AC$20+L51*$AC$21+M51*$AC$22+N51*$AC$23+O51*$AC$24+P51*$AC$25+Q51*$AC$26+R51*$AC$27+S51*$AC$28+T51*$AC$29+U51*$AC$30 | W51: =1/(1+EXP(-V51)) | X51: =-IF(C51=1,LN(W51),LN(1-W51)) | Y51: =IF(W51>$AC$33,1,0) | Z51: =IF(Y51=C51,1,0)
A52: ='1 datos preparados'!A45 | B52: ='1 datos preparados'!U45 | C52: ='1 datos preparados'!B45 | D52: ='1 datos preparados'!C45 | E52: ='1 datos preparados'!D45 | F52: ='1 datos preparados'!E45 | G52: ='1 datos preparados'!F45 | H52: ='1 datos preparados'!G45 | I52: ='1 datos preparados'!H45 | J52: ='1 datos preparados'!I45 | ... U52: ='1 datos preparados'!T45 | V52: =$AC$12+D52*$AC$13+E52*$AC$14+F52*$AC$15+G52*$AC$16+H52*$AC$17+I52*$AC$18+J52*$AC$19+K52*$AC$20+L52*$AC$21+M52*$AC$22+N52*$AC$23+O52*$AC$24+P52*$AC$25+Q52*$AC$26+R52*$AC$27+S52*$AC$28+T52*$AC$29+U52*$AC$30 | W52: =1/(1+EXP(-V52)) | X52: =-IF(C52=1,LN(W52),LN(1-W52)) | Y52: =IF(W52>$AC$33,1,0) | Z52: =IF(Y52=C52,1,0)
A53: ='1 datos preparados'!A46 | B53: ='1 datos preparados'!U46 | C53: ='1 datos preparados'!B46 | D53: ='1 datos preparados'!C46 | E53: ='1 datos preparados'!D46 | F53: ='1 datos preparados'!E46 | G53: ='1 datos preparados'!F46 | H53: ='1 datos preparados'!G46 | I53: ='1 datos preparados'!H46 | J53: ='1 datos preparados'!I46 | ... U53: ='1 datos preparados'!T46 | V53: =$AC$12+D53*$AC$13+E53*$AC$14+F53*$AC$15+G53*$AC$16+H53*$AC$17+I53*$AC$18+J53*$AC$19+K53*$AC$20+L53*$AC$21+M53*$AC$22+N53*$AC$23+O53*$AC$24+P53*$AC$25+Q53*$AC$26+R53*$AC$27+S53*$AC$28+T53*$AC$29+U53*$AC$30 | W53: =1/(1+EXP(-V53)) | X53: =-IF(C53=1,LN(W53),LN(1-W53)) | Y53: =IF(W53>$AC$33,1,0) | Z53: =IF(Y53=C53,1,0)
A54: ='1 datos preparados'!A47 | B54: ='1 datos preparados'!U47 | C54: ='1 datos preparados'!B47 | D54: ='1 datos preparados'!C47 | E54: ='1 datos preparados'!D47 | F54: ='1 datos preparados'!E47 | G54: ='1 datos preparados'!F47 | H54: ='1 datos preparados'!G47 | I54: ='1 datos preparados'!H47 | J54: ='1 datos preparados'!I47 | ... U54: ='1 datos preparados'!T47 | V54: =$AC$12+D54*$AC$13+E54*$AC$14+F54*$AC$15+G54*$AC$16+H54*$AC$17+I54*$AC$18+J54*$AC$19+K54*$AC$20+L54*$AC$21+M54*$AC$22+N54*$AC$23+O54*$AC$24+P54*$AC$25+Q54*$AC$26+R54*$AC$27+S54*$AC$28+T54*$AC$29+U54*$AC$30 | W54: =1/(1+EXP(-V54)) | X54: =-IF(C54=1,LN(W54),LN(1-W54)) | Y54: =IF(W54>$AC$33,1,0) | Z54: =IF(Y54=C54,1,0)
A55: ='1 datos preparados'!A48 | B55: ='1 datos preparados'!U48 | C55: ='1 datos preparados'!B48 | D55: ='1 datos preparados'!C48 | E55: ='1 datos preparados'!D48 | F55: ='1 datos preparados'!E48 | G55: ='1 datos preparados'!F48 | H55: ='1 datos preparados'!G48 | I55: ='1 datos preparados'!H48 | J55: ='1 datos preparados'!I48 | ... U55: ='1 datos preparados'!T48 | V55: =$AC$12+D55*$AC$13+E55*$AC$14+F55*$AC$15+G55*$AC$16+H55*$AC$17+I55*$AC$18+J55*$AC$19+K55*$AC$20+L55*$AC$21+M55*$AC$22+N55*$AC$23+O55*$AC$24+P55*$AC$25+Q55*$AC$26+R55*$AC$27+S55*$AC$28+T55*$AC$29+U55*$AC$30 | W55: =1/(1+EXP(-V55)) | X55: =-IF(C55=1,LN(W55),LN(1-W55)) | Y55: =IF(W55>$AC$33,1,0) | Z55: =IF(Y55=C55,1,0)
A56: ='1 datos preparados'!A49 | B56: ='1 datos preparados'!U49 | C56: ='1 datos preparados'!B49 | D56: ='1 datos preparados'!C49 | E56: ='1 datos preparados'!D49 | F56: ='1 datos preparados'!E49 | G56: ='1 datos preparados'!F49 | H56: ='1 datos preparados'!G49 | I56: ='1 datos preparados'!H49 | J56: ='1 datos preparados'!I49 | ... U56: ='1 datos preparados'!T49 | V56: =$AC$12+D56*$AC$13+E56*$AC$14+F56*$AC$15+G56*$AC$16+H56*$AC$17+I56*$AC$18+J56*$AC$19+K56*$AC$20+L56*$AC$21+M56*$AC$22+N56*$AC$23+O56*$AC$24+P56*$AC$25+Q56*$AC$26+R56*$AC$27+S56*$AC$28+T56*$AC$29+U56*$AC$30 | W56: =1/(1+EXP(-V56)) | X56: =-IF(C56=1,LN(W56),LN(1-W56)) | Y56: =IF(W56>$AC$33,1,0) | Z56: =IF(Y56=C56,1,0)
A57: ='1 datos preparados'!A50 | B57: ='1 datos preparados'!U50 | C57: ='1 datos preparados'!B50 | D57: ='1 datos preparados'!C50 | E57: ='1 datos preparados'!D50 | F57: ='1 datos preparados'!E50 | G57: ='1 datos preparados'!F50 | H57: ='1 datos preparados'!G50 | I57: ='1 datos preparados'!H50 | J57: ='1 datos preparados'!I50 | ... U57: ='1 datos preparados'!T50 | V57: =$AC$12+D57*$AC$13+E57*$AC$14+F57*$AC$15+G57*$AC$16+H57*$AC$17+I57*$AC$18+J57*$AC$19+K57*$AC$20+L57*$AC$21+M57*$AC$22+N57*$AC$23+O57*$AC$24+P57*$AC$25+Q57*$AC$26+R57*$AC$27+S57*$AC$28+T57*$AC$29+U57*$AC$30 | W57: =1/(1+EXP(-V57)) | X57: =-IF(C57=1,LN(W57),LN(1-W57)) | Y57: =IF(W57>$AC$33,1,0) | Z57: =IF(Y57=C57,1,0)
A58: ='1 datos preparados'!A51 | B58: ='1 datos preparados'!U51 | C58: ='1 datos preparados'!B51 | D58: ='1 datos preparados'!C51 | E58: ='1 datos preparados'!D51 | F58: ='1 datos preparados'!E51 | G58: ='1 datos preparados'!F51 | H58: ='1 datos preparados'!G51 | I58: ='1 datos preparados'!H51 | J58: ='1 datos preparados'!I51 | ... U58: ='1 datos preparados'!T51 | V58: =$AC$12+D58*$AC$13+E58*$AC$14+F58*$AC$15+G58*$AC$16+H58*$AC$17+I58*$AC$18+J58*$AC$19+K58*$AC$20+L58*$AC$21+M58*$AC$22+N58*$AC$23+O58*$AC$24+P58*$AC$25+Q58*$AC$26+R58*$AC$27+S58*$AC$28+T58*$AC$29+U58*$AC$30 | W58: =1/(1+EXP(-V58)) | X58: =-IF(C58=1,LN(W58),LN(1-W58)) | Y58: =IF(W58>$AC$33,1,0) | Z58: =IF(Y58=C58,1,0)
A59: ='1 datos preparados'!A52 | B59: ='1 datos preparados'!U52 | C59: ='1 datos preparados'!B52 | D59: ='1 datos preparados'!C52 | E59: ='1 datos preparados'!D52 | F59: ='1 datos preparados'!E52 | G59: ='1 datos preparados'!F52 | H59: ='1 datos preparados'!G52 | I59: ='1 datos preparados'!H52 | J59: ='1 datos preparados'!I52 | ... U59: ='1 datos preparados'!T52 | V59: =$AC$12+D59*$AC$13+E59*$AC$14+F59*$AC$15+G59*$AC$16+H59*$AC$17+I59*$AC$18+J59*$AC$19+K59*$AC$20+L59*$AC$21+M59*$AC$22+N59*$AC$23+O59*$AC$24+P59*$AC$25+Q59*$AC$26+R59*$AC$27+S59*$AC$28+T59*$AC$29+U59*$AC$30 | W59: =1/(1+EXP(-V59)) | X59: =-IF(C59=1,LN(W59),LN(1-W59)) | Y59: =IF(W59>$AC$33,1,0) | Z59: =IF(Y59=C59,1,0)
A60: ='1 datos preparados'!A53 | B60: ='1 datos preparados'!U53 | C60: ='1 datos preparados'!B53 | D60: ='1 datos preparados'!C53 | E60: ='1 datos preparados'!D53 | F60: ='1 datos preparados'!E53 | G60: ='1 datos preparados'!F53 | H60: ='1 datos preparados'!G53 | I60: ='1 datos preparados'!H53 | J60: ='1 datos preparados'!I53 | ... U60: ='1 datos preparados'!T53 | V60: =$AC$12+D60*$AC$13+E60*$AC$14+F60*$AC$15+G60*$AC$16+H60*$AC$17+I60*$AC$18+J60*$AC$19+K60*$AC$20+L60*$AC$21+M60*$AC$22+N60*$AC$23+O60*$AC$24+P60*$AC$25+Q60*$AC$26+R60*$AC$27+S60*$AC$28+T60*$AC$29+U60*$AC$30 | W60: =1/(1+EXP(-V60)) | X60: =-IF(C60=1,LN(W60),LN(1-W60)) | Y60: =IF(W60>$AC$33,1,0) | Z60: =IF(Y60=C60,1,0)
A61: ='1 datos preparados'!A54 | B61: ='1 datos preparados'!U54 | C61: ='1 datos preparados'!B54 | D61: ='1 datos preparados'!C54 | E61: ='1 datos preparados'!D54 | F61: ='1 datos preparados'!E54 | G61: ='1 datos preparados'!F54 | H61: ='1 datos preparados'!G54 | I61: ='1 datos preparados'!H54 | J61: ='1 datos preparados'!I54 | ... U61: ='1 datos preparados'!T54 | V61: =$AC$12+D61*$AC$13+E61*$AC$14+F61*$AC$15+G61*$AC$16+H61*$AC$17+I61*$AC$18+J61*$AC$19+K61*$AC$20+L61*$AC$21+M61*$AC$22+N61*$AC$23+O61*$AC$24+P61*$AC$25+Q61*$AC$26+R61*$AC$27+S61*$AC$28+T61*$AC$29+U61*$AC$30 | W61: =1/(1+EXP(-V61)) | X61: =-IF(C61=1,LN(W61),LN(1-W61)) | Y61: =IF(W61>$AC$33,1,0) | Z61: =IF(Y61=C61,1,0)
... A1011: ='1 datos preparados'!A1004 | B1011: ='1 datos preparados'!U1004 | C1011: ='1 datos preparados'!B1004 | D1011: ='1 datos preparados'!C1004 | E1011: ='1 datos preparados'!D1004 | F1011: ='1 datos preparados'!E1004 | G1011: ='1 datos preparados'!F1004 | H1011: ='1 datos preparados'!G1004 | I1011: ='1 datos preparados'!H1004 | J1011: ='1 datos preparados'!I1004 | ... U1011: ='1 datos preparados'!T1004 | V1011: =$AC$12+D1011*$AC$13+E1011*$AC$14+F1011*$AC$15+G1011*$AC$16+H1011*$AC$17+I1011*$AC$18+J1011*$AC$19+K1011*$AC$20+L1011*$AC$21+M1011*$AC$22+N1011*$AC$23+O1011*$AC$24+P1011*$AC$25+Q1011*$AC$26+R1011*$AC$27+S1011*$AC$28+T1011*$AC$29+U1011*$AC$30 | W1011: =1/(1+EXP(-V1011)) | X1011: =-IF(C1011=1,LN(W1011),LN(1-W1011)) | Y1011: =IF(W1011>$AC$33,1,0) | Z1011: =IF(Y1011=C1011,1,0)

Sheet 4 elastic net
A1: Elastic net: una mezcla de las dos, con α para repartir
A2: Elastic net. J = Σ pérdidas + λ · [α Σ|theta| + (1 − α)/2 Σ theta²]: una mezcla de las dos anteriores, donde α dice qué fracción del castigo es L1. Con α = 1 es lasso, con α = 0 es ridge; el valor 0,5 reparte. Por qué existe: lasso, cuando dos variables están muy correlacionadas, tiende a quedarse con una y botar la otra al azar; el pedazo L2 las hace compartir el peso. Y ridge nunca elimina; el pedazo L1 sí. En scikit-learn es penalty='elasticnet' con l1_ratio = α y C = 1/λ.
A3: Las columnas amarillas son |theta| y theta², una para cada pedazo del castigo. Juega con λ y α y observa dos cosas: cuántos pesos se van a cero (eso lo gobierna α) y cuánto se encogen los que quedan (eso lo gobierna λ).
AB10: Pesos (theta): parten de la solución sin regularizar del Excel base | AH10: EVALUACIÓN EN TESTING (con el umbral celeste)
A11: id | B11: conjunto | C11: y | D11: duracion | E11: monto | F11: edad | G11: cuota_pct_ingreso | H11: cta_negativa | I11: cta_0_200 | J11: cta_sobre_200 | K11: hist_critico | L11: hist_atrasos | M11: hist_sin_creditos | N11: ahorro_100_1000 | O11: ahorro_sobre_1000 | P11: ahorro_desconocido | Q11: vivienda_arriendo | R11: vivienda_gratis | S11: proposito_auto | T11: proposito_radio_tv | U11: proposito_muebles | V11: Z (recta) | W11: p (logística) | X11: pérdida | Y11: predicción | Z11: acierto | AB11: variable | AC11: theta (celeste) | AD11: referencia scikit-learn, λ = 10 | AE11: |theta| | AF11: theta²
A12: ='1 datos preparados'!A5 | B12: ='1 datos preparados'!U5 | C12: ='1 datos preparados'!B5 | D12: ='1 datos preparados'!C5 | E12: ='1 datos preparados'!D5 | F12: ='1 datos preparados'!E5 | G12: ='1 datos preparados'!F5 | H12: ='1 datos preparados'!G5 | I12: ='1 datos preparados'!H5 | J12: ='1 datos preparados'!I5 | ... U12: ='1 datos preparados'!T5 | V12: =$AC$12+D12*$AC$13+E12*$AC$14+F12*$AC$15+G12*$AC$16+H12*$AC$17+I12*$AC$18+J12*$AC$19+K12*$AC$20+L12*$AC$21+M12*$AC$22+N12*$AC$23+O12*$AC$24+P12*$AC$25+Q12*$AC$26+R12*$AC$27+S12*$AC$28+T12*$AC$29+U12*$AC$30 | W12: =1/(1+EXP(-V12)) | X12: =-IF(C12=1,LN(W12),LN(1-W12)) | Y12: =IF(W12>$AC$34,1,0) | Z12: =IF(Y12=C12,1,0) | AB12: intercepto | AC12: -1.341271 | AD12: -1.1647085 | AE12: (no se penaliza)
A13: ='1 datos preparados'!A6 | B13: ='1 datos preparados'!U6 | C13: ='1 datos preparados'!B6 | D13: ='1 datos preparados'!C6 | E13: ='1 datos preparados'!D6 | F13: ='1 datos preparados'!E6 | G13: ='1 datos preparados'!F6 | H13: ='1 datos preparados'!G6 | I13: ='1 datos preparados'!H6 | J13: ='1 datos preparados'!I6 | ... U13: ='1 datos preparados'!T6 | V13: =$AC$12+D13*$AC$13+E13*$AC$14+F13*$AC$15+G13*$AC$16+H13*$AC$17+I13*$AC$18+J13*$AC$19+K13*$AC$20+L13*$AC$21+M13*$AC$22+N13*$AC$23+O13*$AC$24+P13*$AC$25+Q13*$AC$26+R13*$AC$27+S13*$AC$28+T13*$AC$29+U13*$AC$30 | W13: =1/(1+EXP(-V13)) | X13: =-IF(C13=1,LN(W13),LN(1-W13)) | Y13: =IF(W13>$AC$34,1,0) | Z13: =IF(Y13=C13,1,0) | AB13: duracion | AC13: 0.32470125 | AD13: 0.28832639 | AE13: =ABS(AC13) | AF13: =AC13^2 | AJ13: predicho 0 | AK13: predicho 1 | AL13: total
A14: ='1 datos preparados'!A7 | B14: ='1 datos preparados'!U7 | C14: ='1 datos preparados'!B7 | D14: ='1 datos preparados'!C7 | E14: ='1 datos preparados'!D7 | F14: ='1 datos preparados'!E7 | G14: ='1 datos preparados'!F7 | H14: ='1 datos preparados'!G7 | I14: ='1 datos preparados'!H7 | J14: ='1 datos preparados'!I7 | ... U14: ='1 datos preparados'!T7 | V14: =$AC$12+D14*$AC$13+E14*$AC$14+F14*$AC$15+G14*$AC$16+H14*$AC$17+I14*$AC$18+J14*$AC$19+K14*$AC$20+L14*$AC$21+M14*$AC$22+N14*$AC$23+O14*$AC$24+P14*$AC$25+Q14*$AC$26+R14*$AC$27+S14*$AC$28+T14*$AC$29+U14*$AC$30 | W14: =1/(1+EXP(-V14)) | X14: =-IF(C14=1,LN(W14),LN(1-W14)) | Y14: =IF(W14>$AC$34,1,0) | Z14: =IF(Y14=C14,1,0) | AB14: monto | AC14: 0.11635359 | AD14: 0.064499857 | AE14: =ABS(AC14) | AF14: =AC14^2 | AH14: real 0 (buen pagador) | AI14: TN | FP | AJ14: =COUNTIFS($B$12:$B$1011,"testing",$C$12:$C$1011,0,$Y$12:$Y$1011,0) | AK14: =COUNTIFS($B$12:$B$1011,"testing",$C$12:$C$1011,0,$Y$12:$Y$1011,1) | AL14: =AJ14+AK14
A15: ='1 datos preparados'!A8 | B15: ='1 datos preparados'!U8 | C15: ='1 datos preparados'!B8 | D15: ='1 datos preparados'!C8 | E15: ='1 datos preparados'!D8 | F15: ='1 datos preparados'!E8 | G15: ='1 datos preparados'!F8 | H15: ='1 datos preparados'!G8 | I15: ='1 datos preparados'!H8 | J15: ='1 datos preparados'!I8 | ... U15: ='1 datos preparados'!T8 | V15: =$AC$12+D15*$AC$13+E15*$AC$14+F15*$AC$15+G15*$AC$16+H15*$AC$17+I15*$AC$18+J15*$AC$19+K15*$AC$20+L15*$AC$21+M15*$AC$22+N15*$AC$23+O15*$AC$24+P15*$AC$25+Q15*$AC$26+R15*$AC$27+S15*$AC$28+T15*$AC$29+U15*$AC$30 | W15: =1/(1+EXP(-V15)) | X15: =-IF(C15=1,LN(W15),LN(1-W15)) | Y15: =IF(W15>$AC$34,1,0) | Z15: =IF(Y15=C15,1,0) | AB15: edad | AC15: -0.099145225 | AD15: -0.07104034 | AE15: =ABS(AC15) | AF15: =AC15^2 | AH15: real 1 (mal pagador) | AI15: FN | TP | AJ15: =COUNTIFS($B$12:$B$1011,"testing",$C$12:$C$1011,1,$Y$12:$Y$1011,0) | AK15: =COUNTIFS($B$12:$B$1011,"testing",$C$12:$C$1011,1,$Y$12:$Y$1011,1) | AL15: =AJ15+AK15
A16: ='1 datos preparados'!A9 | B16: ='1 datos preparados'!U9 | C16: ='1 datos preparados'!B9 | D16: ='1 datos preparados'!C9 | E16: ='1 datos preparados'!D9 | F16: ='1 datos preparados'!E9 | G16: ='1 datos preparados'!F9 | H16: ='1 datos preparados'!G9 | I16: ='1 datos preparados'!H9 | J16: ='1 datos preparados'!I9 | ... U16: ='1 datos preparados'!T9 | V16: =$AC$12+D16*$AC$13+E16*$AC$14+F16*$AC$15+G16*$AC$16+H16*$AC$17+I16*$AC$18+J16*$AC$19+K16*$AC$20+L16*$AC$21+M16*$AC$22+N16*$AC$23+O16*$AC$24+P16*$AC$25+Q16*$AC$26+R16*$AC$27+S16*$AC$28+T16*$AC$29+U16*$AC$30 | W16: =1/(1+EXP(-V16)) | X16: =-IF(C16=1,LN(W16),LN(1-W16)) | Y16: =IF(W16>$AC$34,1,0) | Z16: =IF(Y16=C16,1,0) | AB16: cuota_pct_ingreso | AC16: 0.28721577 | AD16: 0.16062402 | AE16: =ABS(AC16) | AF16: =AC16^2 | AH16: total | AJ16: =AJ14+AJ15 | AK16: =AK14+AK15 | AL16: =AL14+AL15
A17: ='1 datos preparados'!A10 | B17: ='1 datos preparados'!U10 | C17: ='1 datos preparados'!B10 | D17: ='1 datos preparados'!C10 | E17: ='1 datos preparados'!D10 | F17: ='1 datos preparados'!E10 | G17: ='1 datos preparados'!F10 | H17: ='1 datos preparados'!G10 | I17: ='1 datos preparados'!H10 | J17: ='1 datos preparados'!I10 | ... U17: ='1 datos preparados'!T10 | V17: =$AC$12+D17*$AC$13+E17*$AC$14+F17*$AC$15+G17*$AC$16+H17*$AC$17+I17*$AC$18+J17*$AC$19+K17*$AC$20+L17*$AC$21+M17*$AC$22+N17*$AC$23+O17*$AC$24+P17*$AC$25+Q17*$AC$26+R17*$AC$27+S17*$AC$28+T17*$AC$29+U17*$AC$30 | W17: =1/(1+EXP(-V17)) | X17: =-IF(C17=1,LN(W17),LN(1-W17)) | Y17: =IF(W17>$AC$34,1,0) | Z17: =IF(Y17=C17,1,0) | AB17: cta_negativa | AC17: 1.5464027 | AD17: 0.94729216 | AE17: =ABS(AC17) | AF17: =AC17^2
A18: ='1 datos preparados'!A11 | B18: ='1 datos preparados'!U11 | C18: ='1 datos preparados'!B11 | D18: ='1 datos preparados'!C11 | E18: ='1 datos preparados'!D11 | F18: ='1 datos preparados'!E11 | G18: ='1 datos preparados'!F11 | H18: ='1 datos preparados'!G11 | I18: ='1 datos preparados'!H11 | J18: ='1 datos preparados'!I11 | ... U18: ='1 datos preparados'!T11 | V18: =$AC$12+D18*$AC$13+E18*$AC$14+F18*$AC$15+G18*$AC$16+H18*$AC$17+I18*$AC$18+J18*$AC$19+K18*$AC$20+L18*$AC$21+M18*$AC$22+N18*$AC$23+O18*$AC$24+P18*$AC$25+Q18*$AC$26+R18*$AC$27+S18*$AC$28+T18*$AC$29+U18*$AC$30 | W18: =1/(1+EXP(-V18)) | X18: =-IF(C18=1,LN(W18),LN(1-W18)) | Y18: =IF(W18>$AC$34,1,0) | Z18: =IF(Y18=C18,1,0) | AB18: cta_0_200 | AC18: 1.2949978 | AD18: 0.64561916 | AE18: =ABS(AC18) | AF18: =AC18^2 | AI18: precision | AJ18: recall | AK18: f1-score | AL18: support
A19: ='1 datos preparados'!A12 | B19: ='1 datos preparados'!U12 | C19: ='1 datos preparados'!B12 | D19: ='1 datos preparados'!C12 | E19: ='1 datos preparados'!D12 | F19: ='1 datos preparados'!E12 | G19: ='1 datos preparados'!F12 | H19: ='1 datos preparados'!G12 | I19: ='1 datos preparados'!H12 | J19: ='1 datos preparados'!I12 | ... U19: ='1 datos preparados'!T12 | V19: =$AC$12+D19*$AC$13+E19*$AC$14+F19*$AC$15+G19*$AC$16+H19*$AC$17+I19*$AC$18+J19*$AC$19+K19*$AC$20+L19*$AC$21+M19*$AC$22+N19*$AC$23+O19*$AC$24+P19*$AC$25+Q19*$AC$26+R19*$AC$27+S19*$AC$28+T19*$AC$29+U19*$AC$30 | W19: =1/(1+EXP(-V19)) | X19: =-IF(C19=1,LN(W19),LN(1-W19)) | Y19: =IF(W19>$AC$34,1,0) | Z19: =IF(Y19=C19,1,0) | AB19: cta_sobre_200 | AC19: 0.66836159 | AD19: 0 | AE19: =ABS(AC19) | AF19: =AC19^2 | AH19: clase 0 (paga) | AI19: =IF(AJ14+AJ15=0,0,AJ14/(AJ14+AJ15)) | AJ19: =IF(AJ14+AK14=0,0,AJ14/(AJ14+AK14)) | AK19: =IF(AI19+AJ19=0,0,2*AI19*AJ19/(AI19+AJ19)) | AL19: =AL14
A20: ='1 datos preparados'!A13 | B20: ='1 datos preparados'!U13 | C20: ='1 datos preparados'!B13 | D20: ='1 datos preparados'!C13 | E20: ='1 datos preparados'!D13 | F20: ='1 datos preparados'!E13 | G20: ='1 datos preparados'!F13 | H20: ='1 datos preparados'!G13 | I20: ='1 datos preparados'!H13 | J20: ='1 datos preparados'!I13 | ... U20: ='1 datos preparados'!T13 | V20: =$AC$12+D20*$AC$13+E20*$AC$14+F20*$AC$15+G20*$AC$16+H20*$AC$17+I20*$AC$18+J20*$AC$19+K20*$AC$20+L20*$AC$21+M20*$AC$22+N20*$AC$23+O20*$AC$24+P20*$AC$25+Q20*$AC$26+R20*$AC$27+S20*$AC$28+T20*$AC$29+U20*$AC$30 | W20: =1/(1+EXP(-V20)) | X20: =-IF(C20=1,LN(W20),LN(1-W20)) | Y20: =IF(W20>$AC$34,1,0) | Z20: =IF(Y20=C20,1,0) | AB20: hist_critico | AC20: -0.65734494 | AD20: -0.43001654 | AE20: =ABS(AC20) | AF20: =AC20^2 | AH20: clase 1 (no paga) | AI20: =IF(AK15+AK14=0,0,AK15/(AK15+AK14)) | AJ20: =IF(AK15+AJ15=0,0,AK15/(AK15+AJ15)) | AK20: =IF(AI20+AJ20=0,0,2*AI20*AJ20/(AI20+AJ20)) | AL20: =AL15
A21: ='1 datos preparados'!A14 | B21: ='1 datos preparados'!U14 | C21: ='1 datos preparados'!B14 | D21: ='1 datos preparados'!C14 | E21: ='1 datos preparados'!D14 | F21: ='1 datos preparados'!E14 | G21: ='1 datos preparados'!F14 | H21: ='1 datos preparados'!G14 | I21: ='1 datos preparados'!H14 | J21: ='1 datos preparados'!I14 | ... U21: ='1 datos preparados'!T14 | V21: =$AC$12+D21*$AC$13+E21*$AC$14+F21*$AC$15+G21*$AC$16+H21*$AC$17+I21*$AC$18+J21*$AC$19+K21*$AC$20+L21*$AC$21+M21*$AC$22+N21*$AC$23+O21*$AC$24+P21*$AC$25+Q21*$AC$26+R21*$AC$27+S21*$AC$28+T21*$AC$29+U21*$AC$30 | W21: =1/(1+EXP(-V21)) | X21: =-IF(C21=1,LN(W21),LN(1-W21)) | Y21: =IF(W21>$AC$34,1,0) | Z21: =IF(Y21=C21,1,0) | AB21: hist_atrasos | AC21: -0.040195519 | AD21: 0 | AE21: =ABS(AC21) | AF21: =AC21^2 | AH21: accuracy | AK21: =(AK15+AJ14)/AL16
A22: ='1 datos preparados'!A15 | B22: ='1 datos preparados'!U15 | C22: ='1 datos preparados'!B15 | D22: ='1 datos preparados'!C15 | E22: ='1 datos preparados'!D15 | F22: ='1 datos preparados'!E15 | G22: ='1 datos preparados'!F15 | H22: ='1 datos preparados'!G15 | I22: ='1 datos preparados'!H15 | J22: ='1 datos preparados'!I15 | ... U22: ='1 datos preparados'!T15 | V22: =$AC$12+D22*$AC$13+E22*$AC$14+F22*$AC$15+G22*$AC$16+H22*$AC$17+I22*$AC$18+J22*$AC$19+K22*$AC$20+L22*$AC$21+M22*$AC$22+N22*$AC$23+O22*$AC$24+P22*$AC$25+Q22*$AC$26+R22*$AC$27+S22*$AC$28+T22*$AC$29+U22*$AC$30 | W22: =1/(1+EXP(-V22)) | X22: =-IF(C22=1,LN(W22),LN(1-W22)) | Y22: =IF(W22>$AC$34,1,0) | Z22: =IF(Y22=C22,1,0) | AB22: hist_sin_creditos | AC22: 0.66906563 | AD22: 0.3416637 | AE22: =ABS(AC22) | AF22: =AC22^2
A23: ='1 datos preparados'!A16 | B23: ='1 datos preparados'!U16 | C23: ='1 datos preparados'!B16 | D23: ='1 datos preparados'!C16 | E23: ='1 datos preparados'!D16 | F23: ='1 datos preparados'!E16 | G23: ='1 datos preparados'!F16 | H23: ='1 datos preparados'!G16 | I23: ='1 datos preparados'!H16 | J23: ='1 datos preparados'!I16 | ... U23: ='1 datos preparados'!T16 | V23: =$AC$12+D23*$AC$13+E23*$AC$14+F23*$AC$15+G23*$AC$16+H23*$AC$17+I23*$AC$18+J23*$AC$19+K23*$AC$20+L23*$AC$21+M23*$AC$22+N23*$AC$23+O23*$AC$24+P23*$AC$25+Q23*$AC$26+R23*$AC$27+S23*$AC$28+T23*$AC$29+U23*$AC$30 | W23: =1/(1+EXP(-V23)) | X23: =-IF(C23=1,LN(W23),LN(1-W23)) | Y23: =IF(W23>$AC$34,1,0) | Z23: =IF(Y23=C23,1,0) | AB23: ahorro_100_1000 | AC23: -0.38958343 | AD23: 0 | AE23: =ABS(AC23) | AF23: =AC23^2
A24: ='1 datos preparados'!A17 | B24: ='1 datos preparados'!U17 | C24: ='1 datos preparados'!B17 | D24: ='1 datos preparados'!C17 | E24: ='1 datos preparados'!D17 | F24: ='1 datos preparados'!E17 | G24: ='1 datos preparados'!F17 | H24: ='1 datos preparados'!G17 | I24: ='1 datos preparados'!H17 | J24: ='1 datos preparados'!I17 | ... U24: ='1 datos preparados'!T17 | V24: =$AC$12+D24*$AC$13+E24*$AC$14+F24*$AC$15+G24*$AC$16+H24*$AC$17+I24*$AC$18+J24*$AC$19+K24*$AC$20+L24*$AC$21+M24*$AC$22+N24*$AC$23+O24*$AC$24+P24*$AC$25+Q24*$AC$26+R24*$AC$27+S24*$AC$28+T24*$AC$29+U24*$AC$30 | W24: =1/(1+EXP(-V24)) | X24: =-IF(C24=1,LN(W24),LN(1-W24)) | Y24: =IF(W24>$AC$34,1,0) | Z24: =IF(Y24=C24,1,0) | AB24: ahorro_sobre_1000 | AC24: -0.88922386 | AD24: 0 | AE24: =ABS(AC24) | AF24: =AC24^2
A25: ='1 datos preparados'!A18 | B25: ='1 datos preparados'!U18 | C25: ='1 datos preparados'!B18 | D25: ='1 datos preparados'!C18 | E25: ='1 datos preparados'!D18 | F25: ='1 datos preparados'!E18 | G25: ='1 datos preparados'!F18 | H25: ='1 datos preparados'!G18 | I25: ='1 datos preparados'!H18 | J25: ='1 datos preparados'!I18 | ... U25: ='1 datos preparados'!T18 | V25: =$AC$12+D25*$AC$13+E25*$AC$14+F25*$AC$15+G25*$AC$16+H25*$AC$17+I25*$AC$18+J25*$AC$19+K25*$AC$20+L25*$AC$21+M25*$AC$22+N25*$AC$23+O25*$AC$24+P25*$AC$25+Q25*$AC$26+R25*$AC$27+S25*$AC$28+T25*$AC$29+U25*$AC$30 | W25: =1/(1+EXP(-V25)) | X25: =-IF(C25=1,LN(W25),LN(1-W25)) | Y25: =IF(W25>$AC$34,1,0) | Z25: =IF(Y25=C25,1,0) | AB25: ahorro_desconocido | AC25: -1.0760929 | AD25: -0.42068937 | AE25: =ABS(AC25) | AF25: =AC25^2
A26: ='1 datos preparados'!A19 | B26: ='1 datos preparados'!U19 | C26: ='1 datos preparados'!B19 | D26: ='1 datos preparados'!C19 | E26: ='1 datos preparados'!D19 | F26: ='1 datos preparados'!E19 | G26: ='1 datos preparados'!F19 | H26: ='1 datos preparados'!G19 | I26: ='1 datos preparados'!H19 | J26: ='1 datos preparados'!I19 | ... U26: ='1 datos preparados'!T19 | V26: =$AC$12+D26*$AC$13+E26*$AC$14+F26*$AC$15+G26*$AC$16+H26*$AC$17+I26*$AC$18+J26*$AC$19+K26*$AC$20+L26*$AC$21+M26*$AC$22+N26*$AC$23+O26*$AC$24+P26*$AC$25+Q26*$AC$26+R26*$AC$27+S26*$AC$28+T26*$AC$29+U26*$AC$30 | W26: =1/(1+EXP(-V26)) | X26: =-IF(C26=1,LN(W26),LN(1-W26)) | Y26: =IF(W26>$AC$34,1,0) | Z26: =IF(Y26=C26,1,0) | AB26: vivienda_arriendo | AC26: 0.65383718 | AD26: 0.25233397 | AE26: =ABS(AC26) | AF26: =AC26^2
A27: ='1 datos preparados'!A20 | B27: ='1 datos preparados'!U20 | C27: ='1 datos preparados'!B20 | D27: ='1 datos preparados'!C20 | E27: ='1 datos preparados'!D20 | F27: ='1 datos preparados'!E20 | G27: ='1 datos preparados'!F20 | H27: ='1 datos preparados'!G20 | I27: ='1 datos preparados'!H20 | J27: ='1 datos preparados'!I20 | ... U27: ='1 datos preparados'!T20 | V27: =$AC$12+D27*$AC$13+E27*$AC$14+F27*$AC$15+G27*$AC$16+H27*$AC$17+I27*$AC$18+J27*$AC$19+K27*$AC$20+L27*$AC$21+M27*$AC$22+N27*$AC$23+O27*$AC$24+P27*$AC$25+Q27*$AC$26+R27*$AC$27+S27*$AC$28+T27*$AC$29+U27*$AC$30 | W27: =1/(1+EXP(-V27)) | X27: =-IF(C27=1,LN(W27),LN(1-W27)) | Y27: =IF(W27>$AC$34,1,0) | Z27: =IF(Y27=C27,1,0) | AB27: vivienda_gratis | AC27: 0.19536536 | AD27: 0 | AE27: =ABS(AC27) | AF27: =AC27^2
A28: ='1 datos preparados'!A21 | B28: ='1 datos preparados'!U21 | C28: ='1 datos preparados'!B21 | D28: ='1 datos preparados'!C21 | E28: ='1 datos preparados'!D21 | F28: ='1 datos preparados'!E21 | G28: ='1 datos preparados'!F21 | H28: ='1 datos preparados'!G21 | I28: ='1 datos preparados'!H21 | J28: ='1 datos preparados'!I21 | ... U28: ='1 datos preparados'!T21 | V28: =$AC$12+D28*$AC$13+E28*$AC$14+F28*$AC$15+G28*$AC$16+H28*$AC$17+I28*$AC$18+J28*$AC$19+K28*$AC$20+L28*$AC$21+M28*$AC$22+N28*$AC$23+O28*$AC$24+P28*$AC$25+Q28*$AC$26+R28*$AC$27+S28*$AC$28+T28*$AC$29+U28*$AC$30 | W28: =1/(1+EXP(-V28)) | X28: =-IF(C28=1,LN(W28),LN(1-W28)) | Y28: =IF(W28>$AC$34,1,0) | Z28: =IF(Y28=C28,1,0) | AB28: proposito_auto | AC28: -0.080165476 | AD28: 0 | AE28: =ABS(AC28) | AF28: =AC28^2
A29: ='1 datos preparados'!A22 | B29: ='1 datos preparados'!U22 | C29: ='1 datos preparados'!B22 | D29: ='1 datos preparados'!C22 | E29: ='1 datos preparados'!D22 | F29: ='1 datos preparados'!E22 | G29: ='1 datos preparados'!F22 | H29: ='1 datos preparados'!G22 | I29: ='1 datos preparados'!H22 | J29: ='1 datos preparados'!I22 | ... U29: ='1 datos preparados'!T22 | V29: =$AC$12+D29*$AC$13+E29*$AC$14+F29*$AC$15+G29*$AC$16+H29*$AC$17+I29*$AC$18+J29*$AC$19+K29*$AC$20+L29*$AC$21+M29*$AC$22+N29*$AC$23+O29*$AC$24+P29*$AC$25+Q29*$AC$26+R29*$AC$27+S29*$AC$28+T29*$AC$29+U29*$AC$30 | W29: =1/(1+EXP(-V29)) | X29: =-IF(C29=1,LN(W29),LN(1-W29)) | Y29: =IF(W29>$AC$34,1,0) | Z29: =IF(Y29=C29,1,0) | AB29: proposito_radio_tv | AC29: -0.52021065 | AD29: -0.20474311 | AE29: =ABS(AC29) | AF29: =AC29^2
A30: ='1 datos preparados'!A23 | B30: ='1 datos preparados'!U23 | C30: ='1 datos preparados'!B23 | D30: ='1 datos preparados'!C23 | E30: ='1 datos preparados'!D23 | F30: ='1 datos preparados'!E23 | G30: ='1 datos preparados'!F23 | H30: ='1 datos preparados'!G23 | I30: ='1 datos preparados'!H23 | J30: ='1 datos preparados'!I23 | ... U30: ='1 datos preparados'!T23 | V30: =$AC$12+D30*$AC$13+E30*$AC$14+F30*$AC$15+G30*$AC$16+H30*$AC$17+I30*$AC$18+J30*$AC$19+K30*$AC$20+L30*$AC$21+M30*$AC$22+N30*$AC$23+O30*$AC$24+P30*$AC$25+Q30*$AC$26+R30*$AC$27+S30*$AC$28+T30*$AC$29+U30*$AC$30 | W30: =1/(1+EXP(-V30)) | X30: =-IF(C30=1,LN(W30),LN(1-W30)) | Y30: =IF(W30>$AC$34,1,0) | Z30: =IF(Y30=C30,1,0) | AB30: proposito_muebles | AC30: -0.28180274 | AD30: 0 | AE30: =ABS(AC30) | AF30: =AC30^2
A31: ='1 datos preparados'!A24 | B31: ='1 datos preparados'!U24 | C31: ='1 datos preparados'!B24 | D31: ='1 datos preparados'!C24 | E31: ='1 datos preparados'!D24 | F31: ='1 datos preparados'!E24 | G31: ='1 datos preparados'!F24 | H31: ='1 datos preparados'!G24 | I31: ='1 datos preparados'!H24 | J31: ='1 datos preparados'!I24 | ... U31: ='1 datos preparados'!T24 | V31: =$AC$12+D31*$AC$13+E31*$AC$14+F31*$AC$15+G31*$AC$16+H31*$AC$17+I31*$AC$18+J31*$AC$19+K31*$AC$20+L31*$AC$21+M31*$AC$22+N31*$AC$23+O31*$AC$24+P31*$AC$25+Q31*$AC$26+R31*$AC$27+S31*$AC$28+T31*$AC$29+U31*$AC$30 | W31: =1/(1+EXP(-V31)) | X31: =-IF(C31=1,LN(W31),LN(1-W31)) | Y31: =IF(W31>$AC$34,1,0) | Z31: =IF(Y31=C31,1,0)
A32: ='1 datos preparados'!A25 | B32: ='1 datos preparados'!U25 | C32: ='1 datos preparados'!B25 | D32: ='1 datos preparados'!C25 | E32: ='1 datos preparados'!D25 | F32: ='1 datos preparados'!E25 | G32: ='1 datos preparados'!F25 | H32: ='1 datos preparados'!G25 | I32: ='1 datos preparados'!H25 | J32: ='1 datos preparados'!I25 | ... U32: ='1 datos preparados'!T25 | V32: =$AC$12+D32*$AC$13+E32*$AC$14+F32*$AC$15+G32*$AC$16+H32*$AC$17+I32*$AC$18+J32*$AC$19+K32*$AC$20+L32*$AC$21+M32*$AC$22+N32*$AC$23+O32*$AC$24+P32*$AC$25+Q32*$AC$26+R32*$AC$27+S32*$AC$28+T32*$AC$29+U32*$AC$30 | W32: =1/(1+EXP(-V32)) | X32: =-IF(C32=1,LN(W32),LN(1-W32)) | Y32: =IF(W32>$AC$34,1,0) | Z32: =IF(Y32=C32,1,0) | AB32: λ (lambda): cuánto cuesta el tamaño de los pesos | AC32: 10
A33: ='1 datos preparados'!A26 | B33: ='1 datos preparados'!U26 | C33: ='1 datos preparados'!B26 | D33: ='1 datos preparados'!C26 | E33: ='1 datos preparados'!D26 | F33: ='1 datos preparados'!E26 | G33: ='1 datos preparados'!F26 | H33: ='1 datos preparados'!G26 | I33: ='1 datos preparados'!H26 | J33: ='1 datos preparados'!I26 | ... U33: ='1 datos preparados'!T26 | V33: =$AC$12+D33*$AC$13+E33*$AC$14+F33*$AC$15+G33*$AC$16+H33*$AC$17+I33*$AC$18+J33*$AC$19+K33*$AC$20+L33*$AC$21+M33*$AC$22+N33*$AC$23+O33*$AC$24+P33*$AC$25+Q33*$AC$26+R33*$AC$27+S33*$AC$28+T33*$AC$29+U33*$AC$30 | W33: =1/(1+EXP(-V33)) | X33: =-IF(C33=1,LN(W33),LN(1-W33)) | Y33: =IF(W33>$AC$34,1,0) | Z33: =IF(Y33=C33,1,0) | AB33: α (alpha): fracción L1 de la mezcla (0 = ridge puro, 1 = lasso puro) | AC33: 0.5
A34: ='1 datos preparados'!A27 | B34: ='1 datos preparados'!U27 | C34: ='1 datos preparados'!B27 | D34: ='1 datos preparados'!C27 | E34: ='1 datos preparados'!D27 | F34: ='1 datos preparados'!E27 | G34: ='1 datos preparados'!F27 | H34: ='1 datos preparados'!G27 | I34: ='1 datos preparados'!H27 | J34: ='1 datos preparados'!I27 | ... U34: ='1 datos preparados'!T27 | V34: =$AC$12+D34*$AC$13+E34*$AC$14+F34*$AC$15+G34*$AC$16+H34*$AC$17+I34*$AC$18+J34*$AC$19+K34*$AC$20+L34*$AC$21+M34*$AC$22+N34*$AC$23+O34*$AC$24+P34*$AC$25+Q34*$AC$26+R34*$AC$27+S34*$AC$28+T34*$AC$29+U34*$AC$30 | W34: =1/(1+EXP(-V34)) | X34: =-IF(C34=1,LN(W34),LN(1-W34)) | Y34: =IF(W34>$AC$34,1,0) | Z34: =IF(Y34=C34,1,0) | AB34: umbral | AC34: 0.5
A35: ='1 datos preparados'!A28 | B35: ='1 datos preparados'!U28 | C35: ='1 datos preparados'!B28 | D35: ='1 datos preparados'!C28 | E35: ='1 datos preparados'!D28 | F35: ='1 datos preparados'!E28 | G35: ='1 datos preparados'!F28 | H35: ='1 datos preparados'!G28 | I35: ='1 datos preparados'!H28 | J35: ='1 datos preparados'!I28 | ... U35: ='1 datos preparados'!T28 | V35: =$AC$12+D35*$AC$13+E35*$AC$14+F35*$AC$15+G35*$AC$16+H35*$AC$17+I35*$AC$18+J35*$AC$19+K35*$AC$20+L35*$AC$21+M35*$AC$22+N35*$AC$23+O35*$AC$24+P35*$AC$25+Q35*$AC$26+R35*$AC$27+S35*$AC$28+T35*$AC$29+U35*$AC$30 | W35: =1/(1+EXP(-V35)) | X35: =-IF(C35=1,LN(W35),LN(1-W35)) | Y35: =IF(W35>$AC$34,1,0) | Z35: =IF(Y35=C35,1,0)
A36: ='1 datos preparados'!A29 | B36: ='1 datos preparados'!U29 | C36: ='1 datos preparados'!B29 | D36: ='1 datos preparados'!C29 | E36: ='1 datos preparados'!D29 | F36: ='1 datos preparados'!E29 | G36: ='1 datos preparados'!F29 | H36: ='1 datos preparados'!G29 | I36: ='1 datos preparados'!H29 | J36: ='1 datos preparados'!I29 | ... U36: ='1 datos preparados'!T29 | V36: =$AC$12+D36*$AC$13+E36*$AC$14+F36*$AC$15+G36*$AC$16+H36*$AC$17+I36*$AC$18+J36*$AC$19+K36*$AC$20+L36*$AC$21+M36*$AC$22+N36*$AC$23+O36*$AC$24+P36*$AC$25+Q36*$AC$26+R36*$AC$27+S36*$AC$28+T36*$AC$29+U36*$AC$30 | W36: =1/(1+EXP(-V36)) | X36: =-IF(C36=1,LN(W36),LN(1-W36)) | Y36: =IF(W36>$AC$34,1,0) | Z36: =IF(Y36=C36,1,0) | AB36: RESULTADOS
A37: ='1 datos preparados'!A30 | B37: ='1 datos preparados'!U30 | C37: ='1 datos preparados'!B30 | D37: ='1 datos preparados'!C30 | E37: ='1 datos preparados'!D30 | F37: ='1 datos preparados'!E30 | G37: ='1 datos preparados'!F30 | H37: ='1 datos preparados'!G30 | I37: ='1 datos preparados'!H30 | J37: ='1 datos preparados'!I30 | ... U37: ='1 datos preparados'!T30 | V37: =$AC$12+D37*$AC$13+E37*$AC$14+F37*$AC$15+G37*$AC$16+H37*$AC$17+I37*$AC$18+J37*$AC$19+K37*$AC$20+L37*$AC$21+M37*$AC$22+N37*$AC$23+O37*$AC$24+P37*$AC$25+Q37*$AC$26+R37*$AC$27+S37*$AC$28+T37*$AC$29+U37*$AC$30 | W37: =1/(1+EXP(-V37)) | X37: =-IF(C37=1,LN(W37),LN(1-W37)) | Y37: =IF(W37>$AC$34,1,0) | Z37: =IF(Y37=C37,1,0) | AB37: suma de pérdidas en training | AC37: =SUMPRODUCT(($B$12:$B$1011="training")*$X$12:$X$1011)
A38: ='1 datos preparados'!A31 | B38: ='1 datos preparados'!U31 | C38: ='1 datos preparados'!B31 | D38: ='1 datos preparados'!C31 | E38: ='1 datos preparados'!D31 | F38: ='1 datos preparados'!E31 | G38: ='1 datos preparados'!F31 | H38: ='1 datos preparados'!G31 | I38: ='1 datos preparados'!H31 | J38: ='1 datos preparados'!I31 | ... U38: ='1 datos preparados'!T31 | V38: =$AC$12+D38*$AC$13+E38*$AC$14+F38*$AC$15+G38*$AC$16+H38*$AC$17+I38*$AC$18+J38*$AC$19+K38*$AC$20+L38*$AC$21+M38*$AC$22+N38*$AC$23+O38*$AC$24+P38*$AC$25+Q38*$AC$26+R38*$AC$27+S38*$AC$28+T38*$AC$29+U38*$AC$30 | W38: =1/(1+EXP(-V38)) | X38: =-IF(C38=1,LN(W38),LN(1-W38)) | Y38: =IF(W38>$AC$34,1,0) | Z38: =IF(Y38=C38,1,0) | AB38: penalización elastic net = λ · [α Σ|theta| + (1 − α)/2 Σ theta²] | AC38: =$AC$32*($AC$33*SUM($AE$13:$AE$30)+(1-$AC$33)/2*SUM($AF$13:$AF$30))
A39: ='1 datos preparados'!A32 | B39: ='1 datos preparados'!U32 | C39: ='1 datos preparados'!B32 | D39: ='1 datos preparados'!C32 | E39: ='1 datos preparados'!D32 | F39: ='1 datos preparados'!E32 | G39: ='1 datos preparados'!F32 | H39: ='1 datos preparados'!G32 | I39: ='1 datos preparados'!H32 | J39: ='1 datos preparados'!I32 | ... U39: ='1 datos preparados'!T32 | V39: =$AC$12+D39*$AC$13+E39*$AC$14+F39*$AC$15+G39*$AC$16+H39*$AC$17+I39*$AC$18+J39*$AC$19+K39*$AC$20+L39*$AC$21+M39*$AC$22+N39*$AC$23+O39*$AC$24+P39*$AC$25+Q39*$AC$26+R39*$AC$27+S39*$AC$28+T39*$AC$29+U39*$AC$30 | W39: =1/(1+EXP(-V39)) | X39: =-IF(C39=1,LN(W39),LN(1-W39)) | Y39: =IF(W39>$AC$34,1,0) | Z39: =IF(Y39=C39,1,0) | AB39: J = suma de pérdidas + penalización (OBJETIVO DE SOLVER) | AC39: =AC37+AC38
A40: ='1 datos preparados'!A33 | B40: ='1 datos preparados'!U33 | C40: ='1 datos preparados'!B33 | D40: ='1 datos preparados'!C33 | E40: ='1 datos preparados'!D33 | F40: ='1 datos preparados'!E33 | G40: ='1 datos preparados'!F33 | H40: ='1 datos preparados'!G33 | I40: ='1 datos preparados'!H33 | J40: ='1 datos preparados'!I33 | ... U40: ='1 datos preparados'!T33 | V40: =$AC$12+D40*$AC$13+E40*$AC$14+F40*$AC$15+G40*$AC$16+H40*$AC$17+I40*$AC$18+J40*$AC$19+K40*$AC$20+L40*$AC$21+M40*$AC$22+N40*$AC$23+O40*$AC$24+P40*$AC$25+Q40*$AC$26+R40*$AC$27+S40*$AC$28+T40*$AC$29+U40*$AC$30 | W40: =1/(1+EXP(-V40)) | X40: =-IF(C40=1,LN(W40),LN(1-W40)) | Y40: =IF(W40>$AC$34,1,0) | Z40: =IF(Y40=C40,1,0) | AB40: pérdida promedio training | AC40: =AC37/COUNTIF($B$12:$B$1011,"training")
A41: ='1 datos preparados'!A34 | B41: ='1 datos preparados'!U34 | C41: ='1 datos preparados'!B34 | D41: ='1 datos preparados'!C34 | E41: ='1 datos preparados'!D34 | F41: ='1 datos preparados'!E34 | G41: ='1 datos preparados'!F34 | H41: ='1 datos preparados'!G34 | I41: ='1 datos preparados'!H34 | J41: ='1 datos preparados'!I34 | ... U41: ='1 datos preparados'!T34 | V41: =$AC$12+D41*$AC$13+E41*$AC$14+F41*$AC$15+G41*$AC$16+H41*$AC$17+I41*$AC$18+J41*$AC$19+K41*$AC$20+L41*$AC$21+M41*$AC$22+N41*$AC$23+O41*$AC$24+P41*$AC$25+Q41*$AC$26+R41*$AC$27+S41*$AC$28+T41*$AC$29+U41*$AC$30 | W41: =1/(1+EXP(-V41)) | X41: =-IF(C41=1,LN(W41),LN(1-W41)) | Y41: =IF(W41>$AC$34,1,0) | Z41: =IF(Y41=C41,1,0) | AB41: pérdida promedio testing | AC41: =SUMPRODUCT(($B$12:$B$1011="testing")*$X$12:$X$1011)/COUNTIF($B$12:$B$1011,"testing")
A42: ='1 datos preparados'!A35 | B42: ='1 datos preparados'!U35 | C42: ='1 datos preparados'!B35 | D42: ='1 datos preparados'!C35 | E42: ='1 datos preparados'!D35 | F42: ='1 datos preparados'!E35 | G42: ='1 datos preparados'!F35 | H42: ='1 datos preparados'!G35 | I42: ='1 datos preparados'!H35 | J42: ='1 datos preparados'!I35 | ... U42: ='1 datos preparados'!T35 | V42: =$AC$12+D42*$AC$13+E42*$AC$14+F42*$AC$15+G42*$AC$16+H42*$AC$17+I42*$AC$18+J42*$AC$19+K42*$AC$20+L42*$AC$21+M42*$AC$22+N42*$AC$23+O42*$AC$24+P42*$AC$25+Q42*$AC$26+R42*$AC$27+S42*$AC$28+T42*$AC$29+U42*$AC$30 | W42: =1/(1+EXP(-V42)) | X42: =-IF(C42=1,LN(W42),LN(1-W42)) | Y42: =IF(W42>$AC$34,1,0) | Z42: =IF(Y42=C42,1,0) | AB42: acierto testing | AC42: =SUMPRODUCT(($B$12:$B$1011="testing")*$Z$12:$Z$1011)/COUNTIF($B$12:$B$1011,"testing")
A43: ='1 datos preparados'!A36 | B43: ='1 datos preparados'!U36 | C43: ='1 datos preparados'!B36 | D43: ='1 datos preparados'!C36 | E43: ='1 datos preparados'!D36 | F43: ='1 datos preparados'!E36 | G43: ='1 datos preparados'!F36 | H43: ='1 datos preparados'!G36 | I43: ='1 datos preparados'!H36 | J43: ='1 datos preparados'!I36 | ... U43: ='1 datos preparados'!T36 | V43: =$AC$12+D43*$AC$13+E43*$AC$14+F43*$AC$15+G43*$AC$16+H43*$AC$17+I43*$AC$18+J43*$AC$19+K43*$AC$20+L43*$AC$21+M43*$AC$22+N43*$AC$23+O43*$AC$24+P43*$AC$25+Q43*$AC$26+R43*$AC$27+S43*$AC$28+T43*$AC$29+U43*$AC$30 | W43: =1/(1+EXP(-V43)) | X43: =-IF(C43=1,LN(W43),LN(1-W43)) | Y43: =IF(W43>$AC$34,1,0) | Z43: =IF(Y43=C43,1,0) | AB43: pesos (sin intercepto) con |theta| < 0,01 | AC43: =COUNTIF(AC13:AC30,"<0.01")-COUNTIF(AC13:AC30,"<-0.01")
A44: ='1 datos preparados'!A37 | B44: ='1 datos preparados'!U37 | C44: ='1 datos preparados'!B37 | D44: ='1 datos preparados'!C37 | E44: ='1 datos preparados'!D37 | F44: ='1 datos preparados'!E37 | G44: ='1 datos preparados'!F37 | H44: ='1 datos preparados'!G37 | I44: ='1 datos preparados'!H37 | J44: ='1 datos preparados'!I37 | ... U44: ='1 datos preparados'!T37 | V44: =$AC$12+D44*$AC$13+E44*$AC$14+F44*$AC$15+G44*$AC$16+H44*$AC$17+I44*$AC$18+J44*$AC$19+K44*$AC$20+L44*$AC$21+M44*$AC$22+N44*$AC$23+O44*$AC$24+P44*$AC$25+Q44*$AC$26+R44*$AC$27+S44*$AC$28+T44*$AC$29+U44*$AC$30 | W44: =1/(1+EXP(-V44)) | X44: =-IF(C44=1,LN(W44),LN(1-W44)) | Y44: =IF(W44>$AC$34,1,0) | Z44: =IF(Y44=C44,1,0) | AB44: referencia scikit-learn (λ = 10): J | AC44: 389.23498
A45: ='1 datos preparados'!A38 | B45: ='1 datos preparados'!U38 | C45: ='1 datos preparados'!B38 | D45: ='1 datos preparados'!C38 | E45: ='1 datos preparados'!D38 | F45: ='1 datos preparados'!E38 | G45: ='1 datos preparados'!F38 | H45: ='1 datos preparados'!G38 | I45: ='1 datos preparados'!H38 | J45: ='1 datos preparados'!I38 | ... U45: ='1 datos preparados'!T38 | V45: =$AC$12+D45*$AC$13+E45*$AC$14+F45*$AC$15+G45*$AC$16+H45*$AC$17+I45*$AC$18+J45*$AC$19+K45*$AC$20+L45*$AC$21+M45*$AC$22+N45*$AC$23+O45*$AC$24+P45*$AC$25+Q45*$AC$26+R45*$AC$27+S45*$AC$28+T45*$AC$29+U45*$AC$30 | W45: =1/(1+EXP(-V45)) | X45: =-IF(C45=1,LN(W45),LN(1-W45)) | Y45: =IF(W45>$AC$34,1,0) | Z45: =IF(Y45=C45,1,0) | AB45: referencia scikit-learn (λ = 10): pérdida promedio testing | AC45: 0.49526354
A46: ='1 datos preparados'!A39 | B46: ='1 datos preparados'!U39 | C46: ='1 datos preparados'!B39 | D46: ='1 datos preparados'!C39 | E46: ='1 datos preparados'!D39 | F46: ='1 datos preparados'!E39 | G46: ='1 datos preparados'!F39 | H46: ='1 datos preparados'!G39 | I46: ='1 datos preparados'!H39 | J46: ='1 datos preparados'!I39 | ... U46: ='1 datos preparados'!T39 | V46: =$AC$12+D46*$AC$13+E46*$AC$14+F46*$AC$15+G46*$AC$16+H46*$AC$17+I46*$AC$18+J46*$AC$19+K46*$AC$20+L46*$AC$21+M46*$AC$22+N46*$AC$23+O46*$AC$24+P46*$AC$25+Q46*$AC$26+R46*$AC$27+S46*$AC$28+T46*$AC$29+U46*$AC$30 | W46: =1/(1+EXP(-V46)) | X46: =-IF(C46=1,LN(W46),LN(1-W46)) | Y46: =IF(W46>$AC$34,1,0) | Z46: =IF(Y46=C46,1,0) | AB46: referencia scikit-learn (λ = 10): pesos en cero | AC46: 7
A47: ='1 datos preparados'!A40 | B47: ='1 datos preparados'!U40 | C47: ='1 datos preparados'!B40 | D47: ='1 datos preparados'!C40 | E47: ='1 datos preparados'!D40 | F47: ='1 datos preparados'!E40 | G47: ='1 datos preparados'!F40 | H47: ='1 datos preparados'!G40 | I47: ='1 datos preparados'!H40 | J47: ='1 datos preparados'!I40 | ... U47: ='1 datos preparados'!T40 | V47: =$AC$12+D47*$AC$13+E47*$AC$14+F47*$AC$15+G47*$AC$16+H47*$AC$17+I47*$AC$18+J47*$AC$19+K47*$AC$20+L47*$AC$21+M47*$AC$22+N47*$AC$23+O47*$AC$24+P47*$AC$25+Q47*$AC$26+R47*$AC$27+S47*$AC$28+T47*$AC$29+U47*$AC$30 | W47: =1/(1+EXP(-V47)) | X47: =-IF(C47=1,LN(W47),LN(1-W47)) | Y47: =IF(W47>$AC$34,1,0) | Z47: =IF(Y47=C47,1,0) | AB47: referencia sin regularizar (Excel base): pérdida promedio testing | AC47: 0.46905992
A48: ='1 datos preparados'!A41 | B48: ='1 datos preparados'!U41 | C48: ='1 datos preparados'!B41 | D48: ='1 datos preparados'!C41 | E48: ='1 datos preparados'!D41 | F48: ='1 datos preparados'!E41 | G48: ='1 datos preparados'!F41 | H48: ='1 datos preparados'!G41 | I48: ='1 datos preparados'!H41 | J48: ='1 datos preparados'!I41 | ... U48: ='1 datos preparados'!T41 | V48: =$AC$12+D48*$AC$13+E48*$AC$14+F48*$AC$15+G48*$AC$16+H48*$AC$17+I48*$AC$18+J48*$AC$19+K48*$AC$20+L48*$AC$21+M48*$AC$22+N48*$AC$23+O48*$AC$24+P48*$AC$25+Q48*$AC$26+R48*$AC$27+S48*$AC$28+T48*$AC$29+U48*$AC$30 | W48: =1/(1+EXP(-V48)) | X48: =-IF(C48=1,LN(W48),LN(1-W48)) | Y48: =IF(W48>$AC$34,1,0) | Z48: =IF(Y48=C48,1,0)
A49: ='1 datos preparados'!A42 | B49: ='1 datos preparados'!U42 | C49: ='1 datos preparados'!B42 | D49: ='1 datos preparados'!C42 | E49: ='1 datos preparados'!D42 | F49: ='1 datos preparados'!E42 | G49: ='1 datos preparados'!F42 | H49: ='1 datos preparados'!G42 | I49: ='1 datos preparados'!H42 | J49: ='1 datos preparados'!I42 | ... U49: ='1 datos preparados'!T42 | V49: =$AC$12+D49*$AC$13+E49*$AC$14+F49*$AC$15+G49*$AC$16+H49*$AC$17+I49*$AC$18+J49*$AC$19+K49*$AC$20+L49*$AC$21+M49*$AC$22+N49*$AC$23+O49*$AC$24+P49*$AC$25+Q49*$AC$26+R49*$AC$27+S49*$AC$28+T49*$AC$29+U49*$AC$30 | W49: =1/(1+EXP(-V49)) | X49: =-IF(C49=1,LN(W49),LN(1-W49)) | Y49: =IF(W49>$AC$34,1,0) | Z49: =IF(Y49=C49,1,0) | AB49: Solver: minimizar J (celda del objetivo) cambiando las celdas celestes de los pesos, GRG no lineal, derivadas centrales, convergencia 0,000001, sin restricciones y con la casilla 'Convertir variables sin restricciones en no negativas' DESMARCADA. Correr dos veces si se detiene antes.
A50: ='1 datos preparados'!A43 | B50: ='1 datos preparados'!U43 | C50: ='1 datos preparados'!B43 | D50: ='1 datos preparados'!C43 | E50: ='1 datos preparados'!D43 | F50: ='1 datos preparados'!E43 | G50: ='1 datos preparados'!F43 | H50: ='1 datos preparados'!G43 | I50: ='1 datos preparados'!H43 | J50: ='1 datos preparados'!I43 | ... U50: ='1 datos preparados'!T43 | V50: =$AC$12+D50*$AC$13+E50*$AC$14+F50*$AC$15+G50*$AC$16+H50*$AC$17+I50*$AC$18+J50*$AC$19+K50*$AC$20+L50*$AC$21+M50*$AC$22+N50*$AC$23+O50*$AC$24+P50*$AC$25+Q50*$AC$26+R50*$AC$27+S50*$AC$28+T50*$AC$29+U50*$AC$30 | W50: =1/(1+EXP(-V50)) | X50: =-IF(C50=1,LN(W50),LN(1-W50)) | Y50: =IF(W50>$AC$34,1,0) | Z50: =IF(Y50=C50,1,0) | AB50: Con L1 el valor absoluto no tiene derivada en cero y GRG puede dejar pesos en 0,003 en vez de 0: léelos como cero. scikit-learn usa un algoritmo (saga) que sí los deja exactamente en cero.
A51: ='1 datos preparados'!A44 | B51: ='1 datos preparados'!U44 | C51: ='1 datos preparados'!B44 | D51: ='1 datos preparados'!C44 | E51: ='1 datos preparados'!D44 | F51: ='1 datos preparados'!E44 | G51: ='1 datos preparados'!F44 | H51: ='1 datos preparados'!G44 | I51: ='1 datos preparados'!H44 | J51: ='1 datos preparados'!I44 | ... U51: ='1 datos preparados'!T44 | V51: =$AC$12+D51*$AC$13+E51*$AC$14+F51*$AC$15+G51*$AC$16+H51*$AC$17+I51*$AC$18+J51*$AC$19+K51*$AC$20+L51*$AC$21+M51*$AC$22+N51*$AC$23+O51*$AC$24+P51*$AC$25+Q51*$AC$26+R51*$AC$27+S51*$AC$28+T51*$AC$29+U51*$AC$30 | W51: =1/(1+EXP(-V51)) | X51: =-IF(C51=1,LN(W51),LN(1-W51)) | Y51: =IF(W51>$AC$34,1,0) | Z51: =IF(Y51=C51,1,0)
A52: ='1 datos preparados'!A45 | B52: ='1 datos preparados'!U45 | C52: ='1 datos preparados'!B45 | D52: ='1 datos preparados'!C45 | E52: ='1 datos preparados'!D45 | F52: ='1 datos preparados'!E45 | G52: ='1 datos preparados'!F45 | H52: ='1 datos preparados'!G45 | I52: ='1 datos preparados'!H45 | J52: ='1 datos preparados'!I45 | ... U52: ='1 datos preparados'!T45 | V52: =$AC$12+D52*$AC$13+E52*$AC$14+F52*$AC$15+G52*$AC$16+H52*$AC$17+I52*$AC$18+J52*$AC$19+K52*$AC$20+L52*$AC$21+M52*$AC$22+N52*$AC$23+O52*$AC$24+P52*$AC$25+Q52*$AC$26+R52*$AC$27+S52*$AC$28+T52*$AC$29+U52*$AC$30 | W52: =1/(1+EXP(-V52)) | X52: =-IF(C52=1,LN(W52),LN(1-W52)) | Y52: =IF(W52>$AC$34,1,0) | Z52: =IF(Y52=C52,1,0)
A53: ='1 datos preparados'!A46 | B53: ='1 datos preparados'!U46 | C53: ='1 datos preparados'!B46 | D53: ='1 datos preparados'!C46 | E53: ='1 datos preparados'!D46 | F53: ='1 datos preparados'!E46 | G53: ='1 datos preparados'!F46 | H53: ='1 datos preparados'!G46 | I53: ='1 datos preparados'!H46 | J53: ='1 datos preparados'!I46 | ... U53: ='1 datos preparados'!T46 | V53: =$AC$12+D53*$AC$13+E53*$AC$14+F53*$AC$15+G53*$AC$16+H53*$AC$17+I53*$AC$18+J53*$AC$19+K53*$AC$20+L53*$AC$21+M53*$AC$22+N53*$AC$23+O53*$AC$24+P53*$AC$25+Q53*$AC$26+R53*$AC$27+S53*$AC$28+T53*$AC$29+U53*$AC$30 | W53: =1/(1+EXP(-V53)) | X53: =-IF(C53=1,LN(W53),LN(1-W53)) | Y53: =IF(W53>$AC$34,1,0) | Z53: =IF(Y53=C53,1,0)
A54: ='1 datos preparados'!A47 | B54: ='1 datos preparados'!U47 | C54: ='1 datos preparados'!B47 | D54: ='1 datos preparados'!C47 | E54: ='1 datos preparados'!D47 | F54: ='1 datos preparados'!E47 | G54: ='1 datos preparados'!F47 | H54: ='1 datos preparados'!G47 | I54: ='1 datos preparados'!H47 | J54: ='1 datos preparados'!I47 | ... U54: ='1 datos preparados'!T47 | V54: =$AC$12+D54*$AC$13+E54*$AC$14+F54*$AC$15+G54*$AC$16+H54*$AC$17+I54*$AC$18+J54*$AC$19+K54*$AC$20+L54*$AC$21+M54*$AC$22+N54*$AC$23+O54*$AC$24+P54*$AC$25+Q54*$AC$26+R54*$AC$27+S54*$AC$28+T54*$AC$29+U54*$AC$30 | W54: =1/(1+EXP(-V54)) | X54: =-IF(C54=1,LN(W54),LN(1-W54)) | Y54: =IF(W54>$AC$34,1,0) | Z54: =IF(Y54=C54,1,0)
A55: ='1 datos preparados'!A48 | B55: ='1 datos preparados'!U48 | C55: ='1 datos preparados'!B48 | D55: ='1 datos preparados'!C48 | E55: ='1 datos preparados'!D48 | F55: ='1 datos preparados'!E48 | G55: ='1 datos preparados'!F48 | H55: ='1 datos preparados'!G48 | I55: ='1 datos preparados'!H48 | J55: ='1 datos preparados'!I48 | ... U55: ='1 datos preparados'!T48 | V55: =$AC$12+D55*$AC$13+E55*$AC$14+F55*$AC$15+G55*$AC$16+H55*$AC$17+I55*$AC$18+J55*$AC$19+K55*$AC$20+L55*$AC$21+M55*$AC$22+N55*$AC$23+O55*$AC$24+P55*$AC$25+Q55*$AC$26+R55*$AC$27+S55*$AC$28+T55*$AC$29+U55*$AC$30 | W55: =1/(1+EXP(-V55)) | X55: =-IF(C55=1,LN(W55),LN(1-W55)) | Y55: =IF(W55>$AC$34,1,0) | Z55: =IF(Y55=C55,1,0)
A56: ='1 datos preparados'!A49 | B56: ='1 datos preparados'!U49 | C56: ='1 datos preparados'!B49 | D56: ='1 datos preparados'!C49 | E56: ='1 datos preparados'!D49 | F56: ='1 datos preparados'!E49 | G56: ='1 datos preparados'!F49 | H56: ='1 datos preparados'!G49 | I56: ='1 datos preparados'!H49 | J56: ='1 datos preparados'!I49 | ... U56: ='1 datos preparados'!T49 | V56: =$AC$12+D56*$AC$13+E56*$AC$14+F56*$AC$15+G56*$AC$16+H56*$AC$17+I56*$AC$18+J56*$AC$19+K56*$AC$20+L56*$AC$21+M56*$AC$22+N56*$AC$23+O56*$AC$24+P56*$AC$25+Q56*$AC$26+R56*$AC$27+S56*$AC$28+T56*$AC$29+U56*$AC$30 | W56: =1/(1+EXP(-V56)) | X56: =-IF(C56=1,LN(W56),LN(1-W56)) | Y56: =IF(W56>$AC$34,1,0) | Z56: =IF(Y56=C56,1,0)
A57: ='1 datos preparados'!A50 | B57: ='1 datos preparados'!U50 | C57: ='1 datos preparados'!B50 | D57: ='1 datos preparados'!C50 | E57: ='1 datos preparados'!D50 | F57: ='1 datos preparados'!E50 | G57: ='1 datos preparados'!F50 | H57: ='1 datos preparados'!G50 | I57: ='1 datos preparados'!H50 | J57: ='1 datos preparados'!I50 | ... U57: ='1 datos preparados'!T50 | V57: =$AC$12+D57*$AC$13+E57*$AC$14+F57*$AC$15+G57*$AC$16+H57*$AC$17+I57*$AC$18+J57*$AC$19+K57*$AC$20+L57*$AC$21+M57*$AC$22+N57*$AC$23+O57*$AC$24+P57*$AC$25+Q57*$AC$26+R57*$AC$27+S57*$AC$28+T57*$AC$29+U57*$AC$30 | W57: =1/(1+EXP(-V57)) | X57: =-IF(C57=1,LN(W57),LN(1-W57)) | Y57: =IF(W57>$AC$34,1,0) | Z57: =IF(Y57=C57,1,0)
A58: ='1 datos preparados'!A51 | B58: ='1 datos preparados'!U51 | C58: ='1 datos preparados'!B51 | D58: ='1 datos preparados'!C51 | E58: ='1 datos preparados'!D51 | F58: ='1 datos preparados'!E51 | G58: ='1 datos preparados'!F51 | H58: ='1 datos preparados'!G51 | I58: ='1 datos preparados'!H51 | J58: ='1 datos preparados'!I51 | ... U58: ='1 datos preparados'!T51 | V58: =$AC$12+D58*$AC$13+E58*$AC$14+F58*$AC$15+G58*$AC$16+H58*$AC$17+I58*$AC$18+J58*$AC$19+K58*$AC$20+L58*$AC$21+M58*$AC$22+N58*$AC$23+O58*$AC$24+P58*$AC$25+Q58*$AC$26+R58*$AC$27+S58*$AC$28+T58*$AC$29+U58*$AC$30 | W58: =1/(1+EXP(-V58)) | X58: =-IF(C58=1,LN(W58),LN(1-W58)) | Y58: =IF(W58>$AC$34,1,0) | Z58: =IF(Y58=C58,1,0)
A59: ='1 datos preparados'!A52 | B59: ='1 datos preparados'!U52 | C59: ='1 datos preparados'!B52 | D59: ='1 datos preparados'!C52 | E59: ='1 datos preparados'!D52 | F59: ='1 datos preparados'!E52 | G59: ='1 datos preparados'!F52 | H59: ='1 datos preparados'!G52 | I59: ='1 datos preparados'!H52 | J59: ='1 datos preparados'!I52 | ... U59: ='1 datos preparados'!T52 | V59: =$AC$12+D59*$AC$13+E59*$AC$14+F59*$AC$15+G59*$AC$16+H59*$AC$17+I59*$AC$18+J59*$AC$19+K59*$AC$20+L59*$AC$21+M59*$AC$22+N59*$AC$23+O59*$AC$24+P59*$AC$25+Q59*$AC$26+R59*$AC$27+S59*$AC$28+T59*$AC$29+U59*$AC$30 | W59: =1/(1+EXP(-V59)) | X59: =-IF(C59=1,LN(W59),LN(1-W59)) | Y59: =IF(W59>$AC$34,1,0) | Z59: =IF(Y59=C59,1,0)
A60: ='1 datos preparados'!A53 | B60: ='1 datos preparados'!U53 | C60: ='1 datos preparados'!B53 | D60: ='1 datos preparados'!C53 | E60: ='1 datos preparados'!D53 | F60: ='1 datos preparados'!E53 | G60: ='1 datos preparados'!F53 | H60: ='1 datos preparados'!G53 | I60: ='1 datos preparados'!H53 | J60: ='1 datos preparados'!I53 | ... U60: ='1 datos preparados'!T53 | V60: =$AC$12+D60*$AC$13+E60*$AC$14+F60*$AC$15+G60*$AC$16+H60*$AC$17+I60*$AC$18+J60*$AC$19+K60*$AC$20+L60*$AC$21+M60*$AC$22+N60*$AC$23+O60*$AC$24+P60*$AC$25+Q60*$AC$26+R60*$AC$27+S60*$AC$28+T60*$AC$29+U60*$AC$30 | W60: =1/(1+EXP(-V60)) | X60: =-IF(C60=1,LN(W60),LN(1-W60)) | Y60: =IF(W60>$AC$34,1,0) | Z60: =IF(Y60=C60,1,0)
A61: ='1 datos preparados'!A54 | B61: ='1 datos preparados'!U54 | C61: ='1 datos preparados'!B54 | D61: ='1 datos preparados'!C54 | E61: ='1 datos preparados'!D54 | F61: ='1 datos preparados'!E54 | G61: ='1 datos preparados'!F54 | H61: ='1 datos preparados'!G54 | I61: ='1 datos preparados'!H54 | J61: ='1 datos preparados'!I54 | ... U61: ='1 datos preparados'!T54 | V61: =$AC$12+D61*$AC$13+E61*$AC$14+F61*$AC$15+G61*$AC$16+H61*$AC$17+I61*$AC$18+J61*$AC$19+K61*$AC$20+L61*$AC$21+M61*$AC$22+N61*$AC$23+O61*$AC$24+P61*$AC$25+Q61*$AC$26+R61*$AC$27+S61*$AC$28+T61*$AC$29+U61*$AC$30 | W61: =1/(1+EXP(-V61)) | X61: =-IF(C61=1,LN(W61),LN(1-W61)) | Y61: =IF(W61>$AC$34,1,0) | Z61: =IF(Y61=C61,1,0)
A62: ='1 datos preparados'!A55 | B62: ='1 datos preparados'!U55 | C62: ='1 datos preparados'!B55 | D62: ='1 datos preparados'!C55 | E62: ='1 datos preparados'!D55 | F62: ='1 datos preparados'!E55 | G62: ='1 datos preparados'!F55 | H62: ='1 datos preparados'!G55 | I62: ='1 datos preparados'!H55 | J62: ='1 datos preparados'!I55 | ... U62: ='1 datos preparados'!T55 | V62: =$AC$12+D62*$AC$13+E62*$AC$14+F62*$AC$15+G62*$AC$16+H62*$AC$17+I62*$AC$18+J62*$AC$19+K62*$AC$20+L62*$AC$21+M62*$AC$22+N62*$AC$23+O62*$AC$24+P62*$AC$25+Q62*$AC$26+R62*$AC$27+S62*$AC$28+T62*$AC$29+U62*$AC$30 | W62: =1/(1+EXP(-V62)) | X62: =-IF(C62=1,LN(W62),LN(1-W62)) | Y62: =IF(W62>$AC$34,1,0) | Z62: =IF(Y62=C62,1,0)
... A1011: ='1 datos preparados'!A1004 | B1011: ='1 datos preparados'!U1004 | C1011: ='1 datos preparados'!B1004 | D1011: ='1 datos preparados'!C1004 | E1011: ='1 datos preparados'!D1004 | F1011: ='1 datos preparados'!E1004 | G1011: ='1 datos preparados'!F1004 | H1011: ='1 datos preparados'!G1004 | I1011: ='1 datos preparados'!H1004 | J1011: ='1 datos preparados'!I1004 | ... U1011: ='1 datos preparados'!T1004 | V1011: =$AC$12+D1011*$AC$13+E1011*$AC$14+F1011*$AC$15+G1011*$AC$16+H1011*$AC$17+I1011*$AC$18+J1011*$AC$19+K1011*$AC$20+L1011*$AC$21+M1011*$AC$22+N1011*$AC$23+O1011*$AC$24+P1011*$AC$25+Q1011*$AC$26+R1011*$AC$27+S1011*$AC$28+T1011*$AC$29+U1011*$AC$30 | W1011: =1/(1+EXP(-V1011)) | X1011: =-IF(C1011=1,LN(W1011),LN(1-W1011)) | Y1011: =IF(W1011>$AC$34,1,0) | Z1011: =IF(Y1011=C1011,1,0)

Sheet 5 comparación según λ
A1: Los tres métodos para varios λ (calculado en Python con scikit-learn): trayectoria de los pesos, pérdida y AUC
A2: Cada bloque muestra, para λ en 0, 1, 3, 10, 30, 100 y 300, los 18 pesos y el desempeño en training y testing. Con λ = 0 los tres métodos son el mismo modelo (el Excel base). A medida que λ crece, ridge encoge todos los pesos sin anularlos, lasso los va apagando uno a uno (la fila 'pesos en cero' lo cuenta) y elastic net queda entre medio. Los gráficos de la derecha dibujan la trayectoria de cada peso: es el gráfico clásico de regularización, y se lee de izquierda a derecha como 'qué variable sobrevive más tiempo'.
A3: Lectura honesta de las filas de desempeño: la pérdida en training sube con λ (obligatorio, el modelo tiene menos libertad) y la pérdida en testing también sube, en vez de bajar. El AUC de testing se mantiene hasta λ = 10 y después cae. Es decir, en esta base regularizar no mejora la predicción: el modelo sin regularizar no sobreajustaba. Lo que la regularización sí entrega aquí es un modelo más chico (lasso con λ = 10 usa 11 variables en vez de 18 y pierde una centésima de AUC) y pesos más estables ante cambios de muestra, que es el tema del notebook. Cuando hay muchas más variables que filas, o polinomios de grado alto, la historia cambia y regularizar sí mejora testing.
A5: Ridge (L2)
A6: λ | B6: 0 | C6: 1 | D6: 3 | E6: 10 | F6: 30 | G6: 100 | H6: 300
A7: intercepto | B7: -1.341271 | C7: -1.3037349 | D7: -1.2450742 | E7: -1.1287862 | F7: -1.0019537 | G7: -0.90564825 | H7: -0.86696544
A8: duracion | B8: 0.32470125 | C8: 0.3194672 | D8: 0.30966209 | E8: 0.28934872 | F8: 0.25371273 | G8: 0.18960559 | H8: 0.11445758
A9: monto | B9: 0.11635359 | C9: 0.11100442 | D9: 0.10648268 | E9: 0.10179157 | F9: 0.10200918 | G9: 0.094134248 | H9: 0.06637981
A10: edad | B10: -0.099145225 | C10: -0.10320878 | D10: -0.10800895 | E10: -0.11532177 | F10: -0.11551139 | G10: -0.091087692 | H10: -0.052320669
A11: cuota_pct_ingreso | B11: 0.28721577 | C11: 0.27435892 | D11: 0.25703446 | E11: 0.22222887 | F11: 0.17445283 | G11: 0.10775919 | H11: 0.05251597
A12: cta_negativa | B12: 1.5464027 | C12: 1.4190705 | D12: 1.2435685 | E12: 0.92017635 | F12: 0.56521237 | G12: 0.2527726 | H12: 0.099626263
A13: cta_0_200 | B13: 1.2949978 | C13: 1.170329 | D13: 1.0000498 | E13: 0.69158747 | F13: 0.3819001 | G13: 0.15267328 | H13: 0.057717139
A14: cta_sobre_200 | B14: 0.66836159 | C14: 0.49189636 | D14: 0.30118403 | E14: 0.082674509 | F14: -0.0072730207 | G14: -0.017841912 | H14: -0.0097380491
A15: hist_critico | B15: -0.65734494 | C15: -0.63704268 | D15: -0.60145215 | E15: -0.50285706 | F15: -0.34836022 | G15: -0.17333283 | H15: -0.072882843
A16: hist_atrasos | B16: -0.040195519 | C16: -0.043566669 | D16: -0.041509611 | E16: -0.032989077 | F16: -0.017197087 | G16: -0.0038329351 | H16: 0.00054442235
A17: hist_sin_creditos | B17: 0.66906563 | C17: 0.63884235 | D17: 0.5857694 | E17: 0.45665963 | F17: 0.28782133 | G17: 0.12992753 | H17: 0.051890506
A18: ahorro_100_1000 | B18: -0.38958343 | C18: -0.35028069 | D18: -0.29367745 | E18: -0.19262314 | F18: -0.10030325 | G18: -0.038776976 | H18: -0.014253448
... A32: Σ |theta| | B32: 9.7900656 | C32: 8.7415741 | D32: 7.4292127 | E32: 5.3535306 | F32: 3.4053844 | G32: 1.7306763 | H32: 0.78289791
A35: Lasso (L1)
A36: λ | B36: 0 | C36: 1 | D36: 3 | E36: 10 | F36: 30 | G36: 100 | H36: 300
A37: intercepto | B37: -1.341271 | C37: -1.368574 | D37: -1.318226 | E37: -1.1904713 | F37: -0.8798692 | G37: -0.84952151 | H37: -0.95335221
A38: duracion | B38: 0.32470125 | C38: 0.32187309 | D38: 0.3150188 | E38: 0.29144233 | F38: 0.19204372 | G38: 0 | H38: 0
A39: monto | B39: 0.11635359 | C39: 0.10019713 | D39: 0.077136944 | E39: 0.014975721 | F39: 0 | G39: 0 | H39: 0
A40: edad | B40: -0.099145225 | C40: -0.087357398 | D40: -0.066025076 | E40: -0.044617042 | F40: 0 | G40: 0 | H40: 0
A41: cuota_pct_ingreso | B41: 0.28721577 | C41: 0.26136425 | D41: 0.21365206 | E41: 0.085070091 | F41: 0 | G41: 0 | H41: 0
A42: cta_negativa | B42: 1.5464027 | C42: 1.4420214 | D42: 1.2882136 | E42: 0.97455046 | F42: 0.10166166 | G42: 0 | H42: 0
A43: cta_0_200 | B43: 1.2949978 | C43: 1.1815185 | D43: 0.99283677 | E43: 0.60995409 | F43: 0 | G43: 0 | H43: 0
A44: cta_sobre_200 | B44: 0.66836159 | C44: 0.41907559 | D44: 0 | E44: 0 | F44: 0 | G44: 0 | H44: 0
A45: hist_critico | B45: -0.65734494 | C45: -0.61551717 | D45: -0.55091194 | E45: -0.35469614 | F45: 0 | G45: 0 | H45: 0
A46: hist_atrasos | B46: -0.040195519 | C46: 0 | D46: 0 | E46: 0 | F46: 0 | G46: 0 | H46: 0
A47: hist_sin_creditos | B47: 0.66906563 | C47: 0.62799598 | D47: 0.52321088 | E47: 0.15570541 | F47: 0 | G47: 0 | H47: 0
A48: ahorro_100_1000 | B48: -0.38958343 | C48: -0.2965886 | D48: -0.1286577 | E48: 0 | F48: 0 | G48: 0 | H48: 0
... A62: Σ |theta| | B62: 9.7900656 | C62: 8.1069474 | D62: 5.7055812 | E62: 2.9131638 | F62: 0.29370538 | G62: 0 | H62: 0
A65: Elastic net (α = 0,5)
A66: λ | B66: 0 | C66: 1 | D66: 3 | E66: 10 | F66: 30 | G66: 100 | H66: 300
A67: intercepto | B67: -1.341271 | C67: -1.3527098 | D67: -1.2897819 | E67: -1.1647085 | F67: -0.96618866 | G67: -0.84772912 | H67: -0.8356643
A68: duracion | B68: 0.32470125 | C68: 0.32059432 | D68: 0.31203282 | E68: 0.2883264 | F68: 0.25055441 | G68: 0.046709549 | H68: 0
A69: monto | B69: 0.11635359 | C69: 0.10485719 | D69: 0.091106991 | E69: 0.064499857 | F69: 0.0038124674 | G69: 0 | H69: 0
A70: edad | B70: -0.099145225 | C70: -0.096276647 | D70: -0.086688739 | E70: -0.071040343 | F70: -0.035457259 | G70: 0 | H70: 0
A71: cuota_pct_ingreso | B71: 0.28721577 | C71: 0.26846234 | D71: 0.23621086 | E71: 0.16062401 | F71: 0.024142266 | G71: 0 | H71: 0
A72: cta_negativa | B72: 1.5464027 | C72: 1.4303341 | D72: 1.2597845 | E72: 0.94729216 | F72: 0.44056725 | G72: 0 | H72: 0
A73: cta_0_200 | B73: 1.2949978 | C73: 1.1759196 | D73: 0.99560575 | E73: 0.64561917 | F73: 0.16076697 | G73: 0 | H73: 0
A74: cta_sobre_200 | B74: 0.66836159 | C74: 0.45924526 | D74: 0.1578929 | E74: 0 | F74: 0 | G74: 0 | H74: 0
A75: hist_critico | B75: -0.65734494 | C75: -0.62343002 | D75: -0.57196029 | E75: -0.43001654 | F75: -0.18134615 | G75: 0 | H75: 0
A76: hist_atrasos | B76: -0.040195519 | C76: 0 | D76: 0 | E76: 0 | F76: 0 | G76: 0 | H76: 0
A77: hist_sin_creditos | B77: 0.66906563 | C77: 0.63987204 | D77: 0.55975811 | E77: 0.3416637 | F77: 0 | G77: 0 | H77: 0
A78: ahorro_100_1000 | B78: -0.38958343 | C78: -0.32405555 | D78: -0.21905788 | E78: 0 | F78: 0 | G78: 0 | H78: 0
... A92: Σ |theta| | B92: 9.7900656 | C92: 8.3708516 | D92: 6.575776 | E92: 3.8268486 | F92: 1.113405 | G92: 0.046709549 | H92: 0
