Workbook

Sheet 0 logic
A1: Logistic regression with class imbalance: what it causes and how it is corrected (class weights, undersampling, oversampling, SMOTE)
A2: Prepared by David Díaz, with assistance from Claude (Anthropic).
A4: This workbook is the class imbalance variant of the base workbook (logistic_01_german_credit_EN.xlsx): same 1,000 customers, same 18 prepared columns, same 700 training / 300 testing split, and no regularization. Sheet 1 brings in the data as values.
A5: The problem. In German Credit 30% of customers default and 70% pay. Cross-entropy adds up each customer's error equally, so the uncorrected model cares more about getting the 490 good payers in training right than the 210 defaulters: sheet 2 shows it with the classification report, where the recall of class 0 is 87% and that of class 1, the one that matters, 57%. In more imbalanced datasets (fraud with 1% of cases, churn with 5%) the effect is worse: the model learns to always say 'no' and is 99% accurate.
A6: The fixes change one of two things: how much each customer weighs in the cost function, or which customers enter training. Class weights (sheet 3) multiplies each row's loss by a weight that depends on its class, typically n / (2 · n_class) so that the two classes add up to the same total; that is what class_weight='balanced' does in scikit-learn. Undersampling (sheet 4) randomly drops good payers until they match the defaulters, and trains on fewer rows. Oversampling (sheet 5) repeats the rows of the minority class, which in the cost function is identical to giving them an integer weight. SMOTE (sheet 6) does not repeat: it invents new defaulters by interpolating between pairs of neighboring defaulters. In Excel, the first three are done with Solver, because they all reduce to a 'row weight' column that multiplies the loss; SMOTE is shown with its synthetic rows and its result computed in Python.
A7: Sheet 7 compares the four methods on testing, and adds a row worth looking at carefully: the unbalanced model, but with threshold 0.30 instead of 0.50. Its recall and precision are almost the same as those of the class weights model. That is no coincidence: for a logistic, weighting the classes shifts the line in a way that is almost equivalent to moving the threshold, so balancing and moving the threshold are two roads to the same place. The practical difference is that the threshold can be chosen with costs (base workbook, sheet 6) without retraining, whereas balancing changes the probabilities the model delivers (it is no longer calibrated: the average p on testing rises from 0.33 to 0.48 when the actual rate is 0.30). That is why, for a logistic, the honest recommendation is to balance only when the imbalance is severe or when the algorithm does not allow moving the threshold; with a 30% minority, moving the threshold is enough.
A8: Colors: light blue cells are parameters (model weights, class weights, repetitions, threshold), yellow cells are intermediate calculations, green cells are results, gray cells are values that come from Python.

Sheet 1 prepared data
A1: The 1,000 customers already transformed and scaled (values; the preparation is in the base workbook, sheets 2 and 3)
A2: Same columns and same split as logistic_01_german_credit_EN.xlsx. The column 'use in undersampling' comes from Python: it equals 1 for the 210 training defaulters and for 210 good payers chosen at random (fixed seed), 0 for the rest of training; it does not apply to testing (evaluation uses all 300).
A4: id | B4: y | C4: duration | D4: amount | E4: age | F4: installment_pct_income | G4: chk_negative | H4: chk_0_200 | I4: chk_over_200 | J4: hist_critical | K4: hist_delays | L4: hist_no_credits | M4: sav_100_1000 | N4: sav_over_1000 | O4: sav_unknown | P4: housing_rent | Q4: housing_free | R4: purpose_car | S4: purpose_radio_tv | T4: purpose_furniture | U4: set | V4: use in undersampling
A5: 1 | B5: 0 | C5: -1.2412547 | D5: -0.72837022 | E5: 2.7361712 | F5: 0.91854372 | G5: 1 | H5: 0 | I5: 0 | J5: 1 | K5: 0 | L5: 0 | M5: 0 | N5: 0 | O5: 1 | P5: 0 | Q5: 0 | R5: 0 | S5: 1 | T5: 0 | U5: training | V5: 0
A6: 2 | B6: 1 | C6: 2.2976212 | D6: 0.94481687 | E6: -1.1776147 | F6: -0.88504844 | G6: 0 | H6: 1 | I6: 0 | J6: 0 | K6: 0 | L6: 0 | M6: 0 | N6: 0 | O6: 0 | P6: 0 | Q6: 0 | R6: 0 | S6: 1 | T6: 0 | U6: training | V6: 1
A7: 3 | B7: 0 | C7: -0.73570101 | D7: -0.40401965 | E7: 1.1706569 | F7: -0.88504844 | G7: 0 | H7: 0 | I7: 0 | J7: 1 | K7: 0 | L7: 0 | M7: 0 | N7: 0 | O7: 0 | P7: 0 | Q7: 0 | R7: 0 | S7: 0 | T7: 0 | U7: training | V7: 1
A8: 4 | B8: 0 | C8: 1.7920675 | D8: 1.6204598 | E8: 0.82276478 | F8: -0.88504844 | G8: 1 | H8: 0 | I8: 0 | J8: 0 | K8: 0 | L8: 0 | M8: 0 | N8: 0 | O8: 0 | P8: 0 | Q8: 1 | R8: 0 | S8: 0 | T8: 1 | U8: testing | V8: 0
A9: 5 | B9: 1 | C9: 0.2754064 | D9: 0.56658282 | E9: 1.5185489 | F9: 0.016747641 | G9: 1 | H9: 0 | I9: 0 | J9: 0 | K9: 1 | L9: 0 | M9: 0 | N9: 0 | O9: 0 | P9: 0 | Q9: 1 | R9: 1 | S9: 0 | T9: 0 | U9: training | V9: 1
A10: 6 | B10: 0 | C10: 1.2865138 | D10: 2.0308839 | E10: -0.046965431 | F10: -0.88504844 | G10: 0 | H10: 0 | I10: 0 | J10: 0 | K10: 0 | L10: 0 | M10: 0 | N10: 0 | O10: 1 | P10: 0 | Q10: 1 | R10: 0 | S10: 0 | T10: 0 | U10: testing | V10: 0
A11: 7 | B11: 0 | C11: 0.2754064 | D11: -0.14544891 | E11: 1.5185489 | F11: 0.016747641 | G11: 0 | H11: 0 | I11: 0 | J11: 0 | K11: 0 | L11: 0 | M11: 1 | N11: 0 | O11: 0 | P11: 0 | Q11: 0 | R11: 0 | S11: 0 | T11: 1 | U11: training | V11: 0
A12: 8 | B12: 0 | C12: 1.2865138 | D12: 1.2936599 | E12: -0.046965431 | F12: -0.88504844 | G12: 0 | H12: 1 | I12: 0 | J12: 0 | K12: 0 | L12: 0 | M12: 0 | N12: 0 | O12: 0 | P12: 1 | Q12: 0 | R12: 1 | S12: 0 | T12: 0 | U12: training | V12: 1
A13: 9 | B13: 0 | C13: -0.73570101 | D13: -0.067072939 | E13: 2.2143331 | F13: -0.88504844 | G13: 0 | H13: 0 | I13: 0 | J13: 0 | K13: 0 | L13: 0 | M13: 0 | N13: 1 | O13: 0 | P13: 0 | Q13: 0 | R13: 0 | S13: 1 | T13: 0 | U13: training | V13: 0
A14: 10 | B14: 1 | C14: 0.78096011 | D14: 0.69394377 | E14: -0.65577658 | F14: 0.91854372 | G14: 0 | H14: 1 | I14: 0 | J14: 1 | K14: 0 | L14: 0 | M14: 0 | N14: 0 | O14: 0 | P14: 0 | Q14: 0 | R14: 1 | S14: 0 | T14: 0 | U14: training | V14: 1
A15: 11 | B15: 1 | C15: -0.73570101 | D15: -0.68428374 | E15: -0.91669564 | F15: 0.016747641 | G15: 0 | H15: 1 | I15: 0 | J15: 0 | K15: 0 | L15: 0 | M15: 0 | N15: 0 | O15: 0 | P15: 1 | Q15: 0 | R15: 1 | S15: 0 | T15: 0 | U15: training | V15: 1
A16: 12 | B16: 1 | C16: 2.2976212 | D16: 0.3699431 | E16: -1.0036687 | F16: 0.016747641 | G16: 1 | H16: 0 | I16: 0 | J16: 0 | K16: 0 | L16: 0 | M16: 0 | N16: 0 | O16: 0 | P16: 1 | Q16: 0 | R16: 0 | S16: 0 | T16: 0 | U16: training | V16: 1
... A1004: 1000 | B1004: 0 | C1004: 2.0448444 | D1004: 0.46371435 | E1004: -0.7427496 | F1004: 0.016747641 | G1004: 0 | H1004: 1 | I1004: 0 | J1004: 1 | K1004: 0 | L1004: 0 | M1004: 1 | N1004: 0 | O1004: 0 | P1004: 0 | Q1004: 0 | R1004: 1 | S1004: 0 | T1004: 0 | U1004: training | V1004: 0

Sheet 2 the problem
A1: Without correcting anything: the base workbook model and what class imbalance does to the recall of class 1
A2: Training has 210 defaulters and 490 good payers. Cross-entropy adds up each customer's loss equally (column 'row weight' at 1), so reducing the error on the 490 good payers is worth more than on the 210 defaulters, and the model accommodates them. Look at the report on the right with the weights already trained (gray column, or Solver): class 0 has recall 0.87 and class 1 only 0.57. The overall accuracy, 78%, hides the fact that the model lets 4 out of every 10 defaulters through.
A3: This sheet is the point of comparison for the ones that follow. Also note the average p on testing: 0.33, very close to the actual rate of 0.30. That means the probabilities are calibrated, and it is something the balancing methods are going to break.
AD10: Model weights (theta): start from the unbalanced solution | AI10: EVALUATION ON TESTING (with the light blue threshold)
A11: id | B11: set | C11: y | D11: duration | E11: amount | F11: age | G11: installment_pct_income | H11: chk_negative | I11: chk_0_200 | J11: chk_over_200 | K11: hist_critical | L11: hist_delays | M11: hist_no_credits | N11: sav_100_1000 | O11: sav_over_1000 | P11: sav_unknown | Q11: housing_rent | R11: housing_free | S11: purpose_car | T11: purpose_radio_tv | U11: purpose_furniture | V11: Z (line) | W11: p (logistic) | X11: loss | Y11: row weight | Z11: weighted loss | AA11: prediction | AB11: correct | AD11: variable | AE11: theta (light blue) | AF11: scikit-learn reference for this variant
A12: ='1 prepared data'!A5 | B12: ='1 prepared data'!U5 | C12: ='1 prepared data'!B5 | D12: ='1 prepared data'!C5 | E12: ='1 prepared data'!D5 | F12: ='1 prepared data'!E5 | G12: ='1 prepared data'!F5 | H12: ='1 prepared data'!G5 | I12: ='1 prepared data'!H5 | J12: ='1 prepared data'!I5 | ... U12: ='1 prepared data'!T5 | V12: =$AE$12+D12*$AE$13+E12*$AE$14+F12*$AE$15+G12*$AE$16+H12*$AE$17+I12*$AE$18+J12*$AE$19+K12*$AE$20+L12*$AE$21+M12*$AE$22+N12*$AE$23+O12*$AE$24+P12*$AE$25+Q12*$AE$26+R12*$AE$27+S12*$AE$28+T12*$AE$29+U12*$AE$30 | W12: =1/(1+EXP(-V12)) | X12: =-IF(C12=1,LN(W12),LN(1-W12)) | Y12: =1 | Z12: =Y12*X12 | AA12: =IF(W12>$AE$32,1,0) | AB12: =IF(AA12=C12,1,0) | AD12: intercept | AE12: -1.341271 | AF12: -1.341271
A13: ='1 prepared data'!A6 | B13: ='1 prepared data'!U6 | C13: ='1 prepared data'!B6 | D13: ='1 prepared data'!C6 | E13: ='1 prepared data'!D6 | F13: ='1 prepared data'!E6 | G13: ='1 prepared data'!F6 | H13: ='1 prepared data'!G6 | I13: ='1 prepared data'!H6 | J13: ='1 prepared data'!I6 | ... U13: ='1 prepared data'!T6 | V13: =$AE$12+D13*$AE$13+E13*$AE$14+F13*$AE$15+G13*$AE$16+H13*$AE$17+I13*$AE$18+J13*$AE$19+K13*$AE$20+L13*$AE$21+M13*$AE$22+N13*$AE$23+O13*$AE$24+P13*$AE$25+Q13*$AE$26+R13*$AE$27+S13*$AE$28+T13*$AE$29+U13*$AE$30 | W13: =1/(1+EXP(-V13)) | X13: =-IF(C13=1,LN(W13),LN(1-W13)) | Y13: =1 | Z13: =Y13*X13 | AA13: =IF(W13>$AE$32,1,0) | AB13: =IF(AA13=C13,1,0) | AD13: duration | AE13: 0.32470125 | AF13: 0.32470125 | AK13: predicted 0 | AL13: predicted 1 | AM13: total
A14: ='1 prepared data'!A7 | B14: ='1 prepared data'!U7 | C14: ='1 prepared data'!B7 | D14: ='1 prepared data'!C7 | E14: ='1 prepared data'!D7 | F14: ='1 prepared data'!E7 | G14: ='1 prepared data'!F7 | H14: ='1 prepared data'!G7 | I14: ='1 prepared data'!H7 | J14: ='1 prepared data'!I7 | ... U14: ='1 prepared data'!T7 | V14: =$AE$12+D14*$AE$13+E14*$AE$14+F14*$AE$15+G14*$AE$16+H14*$AE$17+I14*$AE$18+J14*$AE$19+K14*$AE$20+L14*$AE$21+M14*$AE$22+N14*$AE$23+O14*$AE$24+P14*$AE$25+Q14*$AE$26+R14*$AE$27+S14*$AE$28+T14*$AE$29+U14*$AE$30 | W14: =1/(1+EXP(-V14)) | X14: =-IF(C14=1,LN(W14),LN(1-W14)) | Y14: =1 | Z14: =Y14*X14 | AA14: =IF(W14>$AE$32,1,0) | AB14: =IF(AA14=C14,1,0) | AD14: amount | AE14: 0.11635359 | AF14: 0.11635359 | AI14: actual 0 (good payer) | AJ14: TN | FP | AK14: =COUNTIFS($B$12:$B$1011,"testing",$C$12:$C$1011,0,$AA$12:$AA$1011,0) | AL14: =COUNTIFS($B$12:$B$1011,"testing",$C$12:$C$1011,0,$AA$12:$AA$1011,1) | AM14: =AK14+AL14
A15: ='1 prepared data'!A8 | B15: ='1 prepared data'!U8 | C15: ='1 prepared data'!B8 | D15: ='1 prepared data'!C8 | E15: ='1 prepared data'!D8 | F15: ='1 prepared data'!E8 | G15: ='1 prepared data'!F8 | H15: ='1 prepared data'!G8 | I15: ='1 prepared data'!H8 | J15: ='1 prepared data'!I8 | ... U15: ='1 prepared data'!T8 | V15: =$AE$12+D15*$AE$13+E15*$AE$14+F15*$AE$15+G15*$AE$16+H15*$AE$17+I15*$AE$18+J15*$AE$19+K15*$AE$20+L15*$AE$21+M15*$AE$22+N15*$AE$23+O15*$AE$24+P15*$AE$25+Q15*$AE$26+R15*$AE$27+S15*$AE$28+T15*$AE$29+U15*$AE$30 | W15: =1/(1+EXP(-V15)) | X15: =-IF(C15=1,LN(W15),LN(1-W15)) | Y15: =1 | Z15: =Y15*X15 | AA15: =IF(W15>$AE$32,1,0) | AB15: =IF(AA15=C15,1,0) | AD15: age | AE15: -0.099145225 | AF15: -0.099145225 | AI15: actual 1 (defaulter) | AJ15: FN | TP | AK15: =COUNTIFS($B$12:$B$1011,"testing",$C$12:$C$1011,1,$AA$12:$AA$1011,0) | AL15: =COUNTIFS($B$12:$B$1011,"testing",$C$12:$C$1011,1,$AA$12:$AA$1011,1) | AM15: =AK15+AL15
A16: ='1 prepared data'!A9 | B16: ='1 prepared data'!U9 | C16: ='1 prepared data'!B9 | D16: ='1 prepared data'!C9 | E16: ='1 prepared data'!D9 | F16: ='1 prepared data'!E9 | G16: ='1 prepared data'!F9 | H16: ='1 prepared data'!G9 | I16: ='1 prepared data'!H9 | J16: ='1 prepared data'!I9 | ... U16: ='1 prepared data'!T9 | V16: =$AE$12+D16*$AE$13+E16*$AE$14+F16*$AE$15+G16*$AE$16+H16*$AE$17+I16*$AE$18+J16*$AE$19+K16*$AE$20+L16*$AE$21+M16*$AE$22+N16*$AE$23+O16*$AE$24+P16*$AE$25+Q16*$AE$26+R16*$AE$27+S16*$AE$28+T16*$AE$29+U16*$AE$30 | W16: =1/(1+EXP(-V16)) | X16: =-IF(C16=1,LN(W16),LN(1-W16)) | Y16: =1 | Z16: =Y16*X16 | AA16: =IF(W16>$AE$32,1,0) | AB16: =IF(AA16=C16,1,0) | AD16: installment_pct_income | AE16: 0.28721577 | AF16: 0.28721577 | AI16: total | AK16: =AK14+AK15 | AL16: =AL14+AL15 | AM16: =AM14+AM15
A17: ='1 prepared data'!A10 | B17: ='1 prepared data'!U10 | C17: ='1 prepared data'!B10 | D17: ='1 prepared data'!C10 | E17: ='1 prepared data'!D10 | F17: ='1 prepared data'!E10 | G17: ='1 prepared data'!F10 | H17: ='1 prepared data'!G10 | I17: ='1 prepared data'!H10 | J17: ='1 prepared data'!I10 | ... U17: ='1 prepared data'!T10 | V17: =$AE$12+D17*$AE$13+E17*$AE$14+F17*$AE$15+G17*$AE$16+H17*$AE$17+I17*$AE$18+J17*$AE$19+K17*$AE$20+L17*$AE$21+M17*$AE$22+N17*$AE$23+O17*$AE$24+P17*$AE$25+Q17*$AE$26+R17*$AE$27+S17*$AE$28+T17*$AE$29+U17*$AE$30 | W17: =1/(1+EXP(-V17)) | X17: =-IF(C17=1,LN(W17),LN(1-W17)) | Y17: =1 | Z17: =Y17*X17 | AA17: =IF(W17>$AE$32,1,0) | AB17: =IF(AA17=C17,1,0) | AD17: chk_negative | AE17: 1.5464027 | AF17: 1.5464027
A18: ='1 prepared data'!A11 | B18: ='1 prepared data'!U11 | C18: ='1 prepared data'!B11 | D18: ='1 prepared data'!C11 | E18: ='1 prepared data'!D11 | F18: ='1 prepared data'!E11 | G18: ='1 prepared data'!F11 | H18: ='1 prepared data'!G11 | I18: ='1 prepared data'!H11 | J18: ='1 prepared data'!I11 | ... U18: ='1 prepared data'!T11 | V18: =$AE$12+D18*$AE$13+E18*$AE$14+F18*$AE$15+G18*$AE$16+H18*$AE$17+I18*$AE$18+J18*$AE$19+K18*$AE$20+L18*$AE$21+M18*$AE$22+N18*$AE$23+O18*$AE$24+P18*$AE$25+Q18*$AE$26+R18*$AE$27+S18*$AE$28+T18*$AE$29+U18*$AE$30 | W18: =1/(1+EXP(-V18)) | X18: =-IF(C18=1,LN(W18),LN(1-W18)) | Y18: =1 | Z18: =Y18*X18 | AA18: =IF(W18>$AE$32,1,0) | AB18: =IF(AA18=C18,1,0) | AD18: chk_0_200 | AE18: 1.2949978 | AF18: 1.2949978 | AJ18: precision | AK18: recall | AL18: f1-score | AM18: support
A19: ='1 prepared data'!A12 | B19: ='1 prepared data'!U12 | C19: ='1 prepared data'!B12 | D19: ='1 prepared data'!C12 | E19: ='1 prepared data'!D12 | F19: ='1 prepared data'!E12 | G19: ='1 prepared data'!F12 | H19: ='1 prepared data'!G12 | I19: ='1 prepared data'!H12 | J19: ='1 prepared data'!I12 | ... U19: ='1 prepared data'!T12 | V19: =$AE$12+D19*$AE$13+E19*$AE$14+F19*$AE$15+G19*$AE$16+H19*$AE$17+I19*$AE$18+J19*$AE$19+K19*$AE$20+L19*$AE$21+M19*$AE$22+N19*$AE$23+O19*$AE$24+P19*$AE$25+Q19*$AE$26+R19*$AE$27+S19*$AE$28+T19*$AE$29+U19*$AE$30 | W19: =1/(1+EXP(-V19)) | X19: =-IF(C19=1,LN(W19),LN(1-W19)) | Y19: =1 | Z19: =Y19*X19 | AA19: =IF(W19>$AE$32,1,0) | AB19: =IF(AA19=C19,1,0) | AD19: chk_over_200 | AE19: 0.66836159 | AF19: 0.66836159 | AI19: class 0 (pays) | AJ19: =IF(AK14+AK15=0,0,AK14/(AK14+AK15)) | AK19: =IF(AK14+AL14=0,0,AK14/(AK14+AL14)) | AL19: =IF(AJ19+AK19=0,0,2*AJ19*AK19/(AJ19+AK19)) | AM19: =AM14
A20: ='1 prepared data'!A13 | B20: ='1 prepared data'!U13 | C20: ='1 prepared data'!B13 | D20: ='1 prepared data'!C13 | E20: ='1 prepared data'!D13 | F20: ='1 prepared data'!E13 | G20: ='1 prepared data'!F13 | H20: ='1 prepared data'!G13 | I20: ='1 prepared data'!H13 | J20: ='1 prepared data'!I13 | ... U20: ='1 prepared data'!T13 | V20: =$AE$12+D20*$AE$13+E20*$AE$14+F20*$AE$15+G20*$AE$16+H20*$AE$17+I20*$AE$18+J20*$AE$19+K20*$AE$20+L20*$AE$21+M20*$AE$22+N20*$AE$23+O20*$AE$24+P20*$AE$25+Q20*$AE$26+R20*$AE$27+S20*$AE$28+T20*$AE$29+U20*$AE$30 | W20: =1/(1+EXP(-V20)) | X20: =-IF(C20=1,LN(W20),LN(1-W20)) | Y20: =1 | Z20: =Y20*X20 | AA20: =IF(W20>$AE$32,1,0) | AB20: =IF(AA20=C20,1,0) | AD20: hist_critical | AE20: -0.65734494 | AF20: -0.65734494 | AI20: class 1 (defaults) | AJ20: =IF(AL15+AL14=0,0,AL15/(AL15+AL14)) | AK20: =IF(AL15+AK15=0,0,AL15/(AL15+AK15)) | AL20: =IF(AJ20+AK20=0,0,2*AJ20*AK20/(AJ20+AK20)) | AM20: =AM15
A21: ='1 prepared data'!A14 | B21: ='1 prepared data'!U14 | C21: ='1 prepared data'!B14 | D21: ='1 prepared data'!C14 | E21: ='1 prepared data'!D14 | F21: ='1 prepared data'!E14 | G21: ='1 prepared data'!F14 | H21: ='1 prepared data'!G14 | I21: ='1 prepared data'!H14 | J21: ='1 prepared data'!I14 | ... U21: ='1 prepared data'!T14 | V21: =$AE$12+D21*$AE$13+E21*$AE$14+F21*$AE$15+G21*$AE$16+H21*$AE$17+I21*$AE$18+J21*$AE$19+K21*$AE$20+L21*$AE$21+M21*$AE$22+N21*$AE$23+O21*$AE$24+P21*$AE$25+Q21*$AE$26+R21*$AE$27+S21*$AE$28+T21*$AE$29+U21*$AE$30 | W21: =1/(1+EXP(-V21)) | X21: =-IF(C21=1,LN(W21),LN(1-W21)) | Y21: =1 | Z21: =Y21*X21 | AA21: =IF(W21>$AE$32,1,0) | AB21: =IF(AA21=C21,1,0) | AD21: hist_delays | AE21: -0.040195519 | AF21: -0.040195519 | AI21: accuracy | AL21: =(AL15+AK14)/AM16
A22: ='1 prepared data'!A15 | B22: ='1 prepared data'!U15 | C22: ='1 prepared data'!B15 | D22: ='1 prepared data'!C15 | E22: ='1 prepared data'!D15 | F22: ='1 prepared data'!E15 | G22: ='1 prepared data'!F15 | H22: ='1 prepared data'!G15 | I22: ='1 prepared data'!H15 | J22: ='1 prepared data'!I15 | ... U22: ='1 prepared data'!T15 | V22: =$AE$12+D22*$AE$13+E22*$AE$14+F22*$AE$15+G22*$AE$16+H22*$AE$17+I22*$AE$18+J22*$AE$19+K22*$AE$20+L22*$AE$21+M22*$AE$22+N22*$AE$23+O22*$AE$24+P22*$AE$25+Q22*$AE$26+R22*$AE$27+S22*$AE$28+T22*$AE$29+U22*$AE$30 | W22: =1/(1+EXP(-V22)) | X22: =-IF(C22=1,LN(W22),LN(1-W22)) | Y22: =1 | Z22: =Y22*X22 | AA22: =IF(W22>$AE$32,1,0) | AB22: =IF(AA22=C22,1,0) | AD22: hist_no_credits | AE22: 0.66906563 | AF22: 0.66906563
A23: ='1 prepared data'!A16 | B23: ='1 prepared data'!U16 | C23: ='1 prepared data'!B16 | D23: ='1 prepared data'!C16 | E23: ='1 prepared data'!D16 | F23: ='1 prepared data'!E16 | G23: ='1 prepared data'!F16 | H23: ='1 prepared data'!G16 | I23: ='1 prepared data'!H16 | J23: ='1 prepared data'!I16 | ... U23: ='1 prepared data'!T16 | V23: =$AE$12+D23*$AE$13+E23*$AE$14+F23*$AE$15+G23*$AE$16+H23*$AE$17+I23*$AE$18+J23*$AE$19+K23*$AE$20+L23*$AE$21+M23*$AE$22+N23*$AE$23+O23*$AE$24+P23*$AE$25+Q23*$AE$26+R23*$AE$27+S23*$AE$28+T23*$AE$29+U23*$AE$30 | W23: =1/(1+EXP(-V23)) | X23: =-IF(C23=1,LN(W23),LN(1-W23)) | Y23: =1 | Z23: =Y23*X23 | AA23: =IF(W23>$AE$32,1,0) | AB23: =IF(AA23=C23,1,0) | AD23: sav_100_1000 | AE23: -0.38958343 | AF23: -0.38958343
A24: ='1 prepared data'!A17 | B24: ='1 prepared data'!U17 | C24: ='1 prepared data'!B17 | D24: ='1 prepared data'!C17 | E24: ='1 prepared data'!D17 | F24: ='1 prepared data'!E17 | G24: ='1 prepared data'!F17 | H24: ='1 prepared data'!G17 | I24: ='1 prepared data'!H17 | J24: ='1 prepared data'!I17 | ... U24: ='1 prepared data'!T17 | V24: =$AE$12+D24*$AE$13+E24*$AE$14+F24*$AE$15+G24*$AE$16+H24*$AE$17+I24*$AE$18+J24*$AE$19+K24*$AE$20+L24*$AE$21+M24*$AE$22+N24*$AE$23+O24*$AE$24+P24*$AE$25+Q24*$AE$26+R24*$AE$27+S24*$AE$28+T24*$AE$29+U24*$AE$30 | W24: =1/(1+EXP(-V24)) | X24: =-IF(C24=1,LN(W24),LN(1-W24)) | Y24: =1 | Z24: =Y24*X24 | AA24: =IF(W24>$AE$32,1,0) | AB24: =IF(AA24=C24,1,0) | AD24: sav_over_1000 | AE24: -0.88922386 | AF24: -0.88922386
A25: ='1 prepared data'!A18 | B25: ='1 prepared data'!U18 | C25: ='1 prepared data'!B18 | D25: ='1 prepared data'!C18 | E25: ='1 prepared data'!D18 | F25: ='1 prepared data'!E18 | G25: ='1 prepared data'!F18 | H25: ='1 prepared data'!G18 | I25: ='1 prepared data'!H18 | J25: ='1 prepared data'!I18 | ... U25: ='1 prepared data'!T18 | V25: =$AE$12+D25*$AE$13+E25*$AE$14+F25*$AE$15+G25*$AE$16+H25*$AE$17+I25*$AE$18+J25*$AE$19+K25*$AE$20+L25*$AE$21+M25*$AE$22+N25*$AE$23+O25*$AE$24+P25*$AE$25+Q25*$AE$26+R25*$AE$27+S25*$AE$28+T25*$AE$29+U25*$AE$30 | W25: =1/(1+EXP(-V25)) | X25: =-IF(C25=1,LN(W25),LN(1-W25)) | Y25: =1 | Z25: =Y25*X25 | AA25: =IF(W25>$AE$32,1,0) | AB25: =IF(AA25=C25,1,0) | AD25: sav_unknown | AE25: -1.0760929 | AF25: -1.0760929
A26: ='1 prepared data'!A19 | B26: ='1 prepared data'!U19 | C26: ='1 prepared data'!B19 | D26: ='1 prepared data'!C19 | E26: ='1 prepared data'!D19 | F26: ='1 prepared data'!E19 | G26: ='1 prepared data'!F19 | H26: ='1 prepared data'!G19 | I26: ='1 prepared data'!H19 | J26: ='1 prepared data'!I19 | ... U26: ='1 prepared data'!T19 | V26: =$AE$12+D26*$AE$13+E26*$AE$14+F26*$AE$15+G26*$AE$16+H26*$AE$17+I26*$AE$18+J26*$AE$19+K26*$AE$20+L26*$AE$21+M26*$AE$22+N26*$AE$23+O26*$AE$24+P26*$AE$25+Q26*$AE$26+R26*$AE$27+S26*$AE$28+T26*$AE$29+U26*$AE$30 | W26: =1/(1+EXP(-V26)) | X26: =-IF(C26=1,LN(W26),LN(1-W26)) | Y26: =1 | Z26: =Y26*X26 | AA26: =IF(W26>$AE$32,1,0) | AB26: =IF(AA26=C26,1,0) | AD26: housing_rent | AE26: 0.65383718 | AF26: 0.65383718
A27: ='1 prepared data'!A20 | B27: ='1 prepared data'!U20 | C27: ='1 prepared data'!B20 | D27: ='1 prepared data'!C20 | E27: ='1 prepared data'!D20 | F27: ='1 prepared data'!E20 | G27: ='1 prepared data'!F20 | H27: ='1 prepared data'!G20 | I27: ='1 prepared data'!H20 | J27: ='1 prepared data'!I20 | ... U27: ='1 prepared data'!T20 | V27: =$AE$12+D27*$AE$13+E27*$AE$14+F27*$AE$15+G27*$AE$16+H27*$AE$17+I27*$AE$18+J27*$AE$19+K27*$AE$20+L27*$AE$21+M27*$AE$22+N27*$AE$23+O27*$AE$24+P27*$AE$25+Q27*$AE$26+R27*$AE$27+S27*$AE$28+T27*$AE$29+U27*$AE$30 | W27: =1/(1+EXP(-V27)) | X27: =-IF(C27=1,LN(W27),LN(1-W27)) | Y27: =1 | Z27: =Y27*X27 | AA27: =IF(W27>$AE$32,1,0) | AB27: =IF(AA27=C27,1,0) | AD27: housing_free | AE27: 0.19536536 | AF27: 0.19536536
A28: ='1 prepared data'!A21 | B28: ='1 prepared data'!U21 | C28: ='1 prepared data'!B21 | D28: ='1 prepared data'!C21 | E28: ='1 prepared data'!D21 | F28: ='1 prepared data'!E21 | G28: ='1 prepared data'!F21 | H28: ='1 prepared data'!G21 | I28: ='1 prepared data'!H21 | J28: ='1 prepared data'!I21 | ... U28: ='1 prepared data'!T21 | V28: =$AE$12+D28*$AE$13+E28*$AE$14+F28*$AE$15+G28*$AE$16+H28*$AE$17+I28*$AE$18+J28*$AE$19+K28*$AE$20+L28*$AE$21+M28*$AE$22+N28*$AE$23+O28*$AE$24+P28*$AE$25+Q28*$AE$26+R28*$AE$27+S28*$AE$28+T28*$AE$29+U28*$AE$30 | W28: =1/(1+EXP(-V28)) | X28: =-IF(C28=1,LN(W28),LN(1-W28)) | Y28: =1 | Z28: =Y28*X28 | AA28: =IF(W28>$AE$32,1,0) | AB28: =IF(AA28=C28,1,0) | AD28: purpose_car | AE28: -0.080165476 | AF28: -0.080165476
A29: ='1 prepared data'!A22 | B29: ='1 prepared data'!U22 | C29: ='1 prepared data'!B22 | D29: ='1 prepared data'!C22 | E29: ='1 prepared data'!D22 | F29: ='1 prepared data'!E22 | G29: ='1 prepared data'!F22 | H29: ='1 prepared data'!G22 | I29: ='1 prepared data'!H22 | J29: ='1 prepared data'!I22 | ... U29: ='1 prepared data'!T22 | V29: =$AE$12+D29*$AE$13+E29*$AE$14+F29*$AE$15+G29*$AE$16+H29*$AE$17+I29*$AE$18+J29*$AE$19+K29*$AE$20+L29*$AE$21+M29*$AE$22+N29*$AE$23+O29*$AE$24+P29*$AE$25+Q29*$AE$26+R29*$AE$27+S29*$AE$28+T29*$AE$29+U29*$AE$30 | W29: =1/(1+EXP(-V29)) | X29: =-IF(C29=1,LN(W29),LN(1-W29)) | Y29: =1 | Z29: =Y29*X29 | AA29: =IF(W29>$AE$32,1,0) | AB29: =IF(AA29=C29,1,0) | AD29: purpose_radio_tv | AE29: -0.52021065 | AF29: -0.52021065
A30: ='1 prepared data'!A23 | B30: ='1 prepared data'!U23 | C30: ='1 prepared data'!B23 | D30: ='1 prepared data'!C23 | E30: ='1 prepared data'!D23 | F30: ='1 prepared data'!E23 | G30: ='1 prepared data'!F23 | H30: ='1 prepared data'!G23 | I30: ='1 prepared data'!H23 | J30: ='1 prepared data'!I23 | ... U30: ='1 prepared data'!T23 | V30: =$AE$12+D30*$AE$13+E30*$AE$14+F30*$AE$15+G30*$AE$16+H30*$AE$17+I30*$AE$18+J30*$AE$19+K30*$AE$20+L30*$AE$21+M30*$AE$22+N30*$AE$23+O30*$AE$24+P30*$AE$25+Q30*$AE$26+R30*$AE$27+S30*$AE$28+T30*$AE$29+U30*$AE$30 | W30: =1/(1+EXP(-V30)) | X30: =-IF(C30=1,LN(W30),LN(1-W30)) | Y30: =1 | Z30: =Y30*X30 | AA30: =IF(W30>$AE$32,1,0) | AB30: =IF(AA30=C30,1,0) | AD30: purpose_furniture | AE30: -0.28180274 | AF30: -0.28180274
A31: ='1 prepared data'!A24 | B31: ='1 prepared data'!U24 | C31: ='1 prepared data'!B24 | D31: ='1 prepared data'!C24 | E31: ='1 prepared data'!D24 | F31: ='1 prepared data'!E24 | G31: ='1 prepared data'!F24 | H31: ='1 prepared data'!G24 | I31: ='1 prepared data'!H24 | J31: ='1 prepared data'!I24 | ... U31: ='1 prepared data'!T24 | V31: =$AE$12+D31*$AE$13+E31*$AE$14+F31*$AE$15+G31*$AE$16+H31*$AE$17+I31*$AE$18+J31*$AE$19+K31*$AE$20+L31*$AE$21+M31*$AE$22+N31*$AE$23+O31*$AE$24+P31*$AE$25+Q31*$AE$26+R31*$AE$27+S31*$AE$28+T31*$AE$29+U31*$AE$30 | W31: =1/(1+EXP(-V31)) | X31: =-IF(C31=1,LN(W31),LN(1-W31)) | Y31: =1 | Z31: =Y31*X31 | AA31: =IF(W31>$AE$32,1,0) | AB31: =IF(AA31=C31,1,0)
A32: ='1 prepared data'!A25 | B32: ='1 prepared data'!U25 | C32: ='1 prepared data'!B25 | D32: ='1 prepared data'!C25 | E32: ='1 prepared data'!D25 | F32: ='1 prepared data'!E25 | G32: ='1 prepared data'!F25 | H32: ='1 prepared data'!G25 | I32: ='1 prepared data'!H25 | J32: ='1 prepared data'!I25 | ... U32: ='1 prepared data'!T25 | V32: =$AE$12+D32*$AE$13+E32*$AE$14+F32*$AE$15+G32*$AE$16+H32*$AE$17+I32*$AE$18+J32*$AE$19+K32*$AE$20+L32*$AE$21+M32*$AE$22+N32*$AE$23+O32*$AE$24+P32*$AE$25+Q32*$AE$26+R32*$AE$27+S32*$AE$28+T32*$AE$29+U32*$AE$30 | W32: =1/(1+EXP(-V32)) | X32: =-IF(C32=1,LN(W32),LN(1-W32)) | Y32: =1 | Z32: =Y32*X32 | AA32: =IF(W32>$AE$32,1,0) | AB32: =IF(AA32=C32,1,0) | AD32: threshold | AE32: 0.5
A33: ='1 prepared data'!A26 | B33: ='1 prepared data'!U26 | C33: ='1 prepared data'!B26 | D33: ='1 prepared data'!C26 | E33: ='1 prepared data'!D26 | F33: ='1 prepared data'!E26 | G33: ='1 prepared data'!F26 | H33: ='1 prepared data'!G26 | I33: ='1 prepared data'!H26 | J33: ='1 prepared data'!I26 | ... U33: ='1 prepared data'!T26 | V33: =$AE$12+D33*$AE$13+E33*$AE$14+F33*$AE$15+G33*$AE$16+H33*$AE$17+I33*$AE$18+J33*$AE$19+K33*$AE$20+L33*$AE$21+M33*$AE$22+N33*$AE$23+O33*$AE$24+P33*$AE$25+Q33*$AE$26+R33*$AE$27+S33*$AE$28+T33*$AE$29+U33*$AE$30 | W33: =1/(1+EXP(-V33)) | X33: =-IF(C33=1,LN(W33),LN(1-W33)) | Y33: =1 | Z33: =Y33*X33 | AA33: =IF(W33>$AE$32,1,0) | AB33: =IF(AA33=C33,1,0)
A34: ='1 prepared data'!A27 | B34: ='1 prepared data'!U27 | C34: ='1 prepared data'!B27 | D34: ='1 prepared data'!C27 | E34: ='1 prepared data'!D27 | F34: ='1 prepared data'!E27 | G34: ='1 prepared data'!F27 | H34: ='1 prepared data'!G27 | I34: ='1 prepared data'!H27 | J34: ='1 prepared data'!I27 | ... U34: ='1 prepared data'!T27 | V34: =$AE$12+D34*$AE$13+E34*$AE$14+F34*$AE$15+G34*$AE$16+H34*$AE$17+I34*$AE$18+J34*$AE$19+K34*$AE$20+L34*$AE$21+M34*$AE$22+N34*$AE$23+O34*$AE$24+P34*$AE$25+Q34*$AE$26+R34*$AE$27+S34*$AE$28+T34*$AE$29+U34*$AE$30 | W34: =1/(1+EXP(-V34)) | X34: =-IF(C34=1,LN(W34),LN(1-W34)) | Y34: =1 | Z34: =Y34*X34 | AA34: =IF(W34>$AE$32,1,0) | AB34: =IF(AA34=C34,1,0) | AD34: RESULTS
A35: ='1 prepared data'!A28 | B35: ='1 prepared data'!U28 | C35: ='1 prepared data'!B28 | D35: ='1 prepared data'!C28 | E35: ='1 prepared data'!D28 | F35: ='1 prepared data'!E28 | G35: ='1 prepared data'!F28 | H35: ='1 prepared data'!G28 | I35: ='1 prepared data'!H28 | J35: ='1 prepared data'!I28 | ... U35: ='1 prepared data'!T28 | V35: =$AE$12+D35*$AE$13+E35*$AE$14+F35*$AE$15+G35*$AE$16+H35*$AE$17+I35*$AE$18+J35*$AE$19+K35*$AE$20+L35*$AE$21+M35*$AE$22+N35*$AE$23+O35*$AE$24+P35*$AE$25+Q35*$AE$26+R35*$AE$27+S35*$AE$28+T35*$AE$29+U35*$AE$30 | W35: =1/(1+EXP(-V35)) | X35: =-IF(C35=1,LN(W35),LN(1-W35)) | Y35: =1 | Z35: =Y35*X35 | AA35: =IF(W35>$AE$32,1,0) | AB35: =IF(AA35=C35,1,0) | AD35: J = sum of weighted training losses (SOLVER OBJECTIVE) | AE35: =SUMPRODUCT(($B$12:$B$1011="training")*$Z$12:$Z$1011)
A36: ='1 prepared data'!A29 | B36: ='1 prepared data'!U29 | C36: ='1 prepared data'!B29 | D36: ='1 prepared data'!C29 | E36: ='1 prepared data'!D29 | F36: ='1 prepared data'!E29 | G36: ='1 prepared data'!F29 | H36: ='1 prepared data'!G29 | I36: ='1 prepared data'!H29 | J36: ='1 prepared data'!I29 | ... U36: ='1 prepared data'!T29 | V36: =$AE$12+D36*$AE$13+E36*$AE$14+F36*$AE$15+G36*$AE$16+H36*$AE$17+I36*$AE$18+J36*$AE$19+K36*$AE$20+L36*$AE$21+M36*$AE$22+N36*$AE$23+O36*$AE$24+P36*$AE$25+Q36*$AE$26+R36*$AE$27+S36*$AE$28+T36*$AE$29+U36*$AE$30 | W36: =1/(1+EXP(-V36)) | X36: =-IF(C36=1,LN(W36),LN(1-W36)) | Y36: =1 | Z36: =Y36*X36 | AA36: =IF(W36>$AE$32,1,0) | AB36: =IF(AA36=C36,1,0) | AD36: sum of row weights in training | AE36: =SUMPRODUCT(($B$12:$B$1011="training")*$Y$12:$Y$1011)
A37: ='1 prepared data'!A30 | B37: ='1 prepared data'!U30 | C37: ='1 prepared data'!B30 | D37: ='1 prepared data'!C30 | E37: ='1 prepared data'!D30 | F37: ='1 prepared data'!E30 | G37: ='1 prepared data'!F30 | H37: ='1 prepared data'!G30 | I37: ='1 prepared data'!H30 | J37: ='1 prepared data'!I30 | ... U37: ='1 prepared data'!T30 | V37: =$AE$12+D37*$AE$13+E37*$AE$14+F37*$AE$15+G37*$AE$16+H37*$AE$17+I37*$AE$18+J37*$AE$19+K37*$AE$20+L37*$AE$21+M37*$AE$22+N37*$AE$23+O37*$AE$24+P37*$AE$25+Q37*$AE$26+R37*$AE$27+S37*$AE$28+T37*$AE$29+U37*$AE$30 | W37: =1/(1+EXP(-V37)) | X37: =-IF(C37=1,LN(W37),LN(1-W37)) | Y37: =1 | Z37: =Y37*X37 | AA37: =IF(W37>$AE$32,1,0) | AB37: =IF(AA37=C37,1,0) | AD37: of which, class 1 | AE37: =SUMPRODUCT(($B$12:$B$1011="training")*($C$12:$C$1011=1)*$Y$12:$Y$1011)
A38: ='1 prepared data'!A31 | B38: ='1 prepared data'!U31 | C38: ='1 prepared data'!B31 | D38: ='1 prepared data'!C31 | E38: ='1 prepared data'!D31 | F38: ='1 prepared data'!E31 | G38: ='1 prepared data'!F31 | H38: ='1 prepared data'!G31 | I38: ='1 prepared data'!H31 | J38: ='1 prepared data'!I31 | ... U38: ='1 prepared data'!T31 | V38: =$AE$12+D38*$AE$13+E38*$AE$14+F38*$AE$15+G38*$AE$16+H38*$AE$17+I38*$AE$18+J38*$AE$19+K38*$AE$20+L38*$AE$21+M38*$AE$22+N38*$AE$23+O38*$AE$24+P38*$AE$25+Q38*$AE$26+R38*$AE$27+S38*$AE$28+T38*$AE$29+U38*$AE$30 | W38: =1/(1+EXP(-V38)) | X38: =-IF(C38=1,LN(W38),LN(1-W38)) | Y38: =1 | Z38: =Y38*X38 | AA38: =IF(W38>$AE$32,1,0) | AB38: =IF(AA38=C38,1,0) | AD38: of which, class 0 | AE38: =SUMPRODUCT(($B$12:$B$1011="training")*($C$12:$C$1011=0)*$Y$12:$Y$1011)
A39: ='1 prepared data'!A32 | B39: ='1 prepared data'!U32 | C39: ='1 prepared data'!B32 | D39: ='1 prepared data'!C32 | E39: ='1 prepared data'!D32 | F39: ='1 prepared data'!E32 | G39: ='1 prepared data'!F32 | H39: ='1 prepared data'!G32 | I39: ='1 prepared data'!H32 | J39: ='1 prepared data'!I32 | ... U39: ='1 prepared data'!T32 | V39: =$AE$12+D39*$AE$13+E39*$AE$14+F39*$AE$15+G39*$AE$16+H39*$AE$17+I39*$AE$18+J39*$AE$19+K39*$AE$20+L39*$AE$21+M39*$AE$22+N39*$AE$23+O39*$AE$24+P39*$AE$25+Q39*$AE$26+R39*$AE$27+S39*$AE$28+T39*$AE$29+U39*$AE$30 | W39: =1/(1+EXP(-V39)) | X39: =-IF(C39=1,LN(W39),LN(1-W39)) | Y39: =1 | Z39: =Y39*X39 | AA39: =IF(W39>$AE$32,1,0) | AB39: =IF(AA39=C39,1,0) | AD39: average testing loss (unweighted) | AE39: =SUMPRODUCT(($B$12:$B$1011="testing")*$X$12:$X$1011)/COUNTIF($B$12:$B$1011,"testing")
A40: ='1 prepared data'!A33 | B40: ='1 prepared data'!U33 | C40: ='1 prepared data'!B33 | D40: ='1 prepared data'!C33 | E40: ='1 prepared data'!D33 | F40: ='1 prepared data'!E33 | G40: ='1 prepared data'!F33 | H40: ='1 prepared data'!G33 | I40: ='1 prepared data'!H33 | J40: ='1 prepared data'!I33 | ... U40: ='1 prepared data'!T33 | V40: =$AE$12+D40*$AE$13+E40*$AE$14+F40*$AE$15+G40*$AE$16+H40*$AE$17+I40*$AE$18+J40*$AE$19+K40*$AE$20+L40*$AE$21+M40*$AE$22+N40*$AE$23+O40*$AE$24+P40*$AE$25+Q40*$AE$26+R40*$AE$27+S40*$AE$28+T40*$AE$29+U40*$AE$30 | W40: =1/(1+EXP(-V40)) | X40: =-IF(C40=1,LN(W40),LN(1-W40)) | Y40: =1 | Z40: =Y40*X40 | AA40: =IF(W40>$AE$32,1,0) | AB40: =IF(AA40=C40,1,0) | AD40: average p on testing (the actual rate is 0.300) | AE40: =SUMPRODUCT(($B$12:$B$1011="testing")*$W$12:$W$1011)/COUNTIF($B$12:$B$1011,"testing")
A41: ='1 prepared data'!A34 | B41: ='1 prepared data'!U34 | C41: ='1 prepared data'!B34 | D41: ='1 prepared data'!C34 | E41: ='1 prepared data'!D34 | F41: ='1 prepared data'!E34 | G41: ='1 prepared data'!F34 | H41: ='1 prepared data'!G34 | I41: ='1 prepared data'!H34 | J41: ='1 prepared data'!I34 | ... U41: ='1 prepared data'!T34 | V41: =$AE$12+D41*$AE$13+E41*$AE$14+F41*$AE$15+G41*$AE$16+H41*$AE$17+I41*$AE$18+J41*$AE$19+K41*$AE$20+L41*$AE$21+M41*$AE$22+N41*$AE$23+O41*$AE$24+P41*$AE$25+Q41*$AE$26+R41*$AE$27+S41*$AE$28+T41*$AE$29+U41*$AE$30 | W41: =1/(1+EXP(-V41)) | X41: =-IF(C41=1,LN(W41),LN(1-W41)) | Y41: =1 | Z41: =Y41*X41 | AA41: =IF(W41>$AE$32,1,0) | AB41: =IF(AA41=C41,1,0) | AD41: testing accuracy | AE41: =SUMPRODUCT(($B$12:$B$1011="testing")*$AB$12:$AB$1011)/COUNTIF($B$12:$B$1011,"testing")
A42: ='1 prepared data'!A35 | B42: ='1 prepared data'!U35 | C42: ='1 prepared data'!B35 | D42: ='1 prepared data'!C35 | E42: ='1 prepared data'!D35 | F42: ='1 prepared data'!E35 | G42: ='1 prepared data'!F35 | H42: ='1 prepared data'!G35 | I42: ='1 prepared data'!H35 | J42: ='1 prepared data'!I35 | ... U42: ='1 prepared data'!T35 | V42: =$AE$12+D42*$AE$13+E42*$AE$14+F42*$AE$15+G42*$AE$16+H42*$AE$17+I42*$AE$18+J42*$AE$19+K42*$AE$20+L42*$AE$21+M42*$AE$22+N42*$AE$23+O42*$AE$24+P42*$AE$25+Q42*$AE$26+R42*$AE$27+S42*$AE$28+T42*$AE$29+U42*$AE$30 | W42: =1/(1+EXP(-V42)) | X42: =-IF(C42=1,LN(W42),LN(1-W42)) | Y42: =1 | Z42: =Y42*X42 | AA42: =IF(W42>$AE$32,1,0) | AB42: =IF(AA42=C42,1,0) | AD42: scikit-learn reference: class 1 recall on testing (threshold 0.5) | AE42: 0.56666667
A43: ='1 prepared data'!A36 | B43: ='1 prepared data'!U36 | C43: ='1 prepared data'!B36 | D43: ='1 prepared data'!C36 | E43: ='1 prepared data'!D36 | F43: ='1 prepared data'!E36 | G43: ='1 prepared data'!F36 | H43: ='1 prepared data'!G36 | I43: ='1 prepared data'!H36 | J43: ='1 prepared data'!I36 | ... U43: ='1 prepared data'!T36 | V43: =$AE$12+D43*$AE$13+E43*$AE$14+F43*$AE$15+G43*$AE$16+H43*$AE$17+I43*$AE$18+J43*$AE$19+K43*$AE$20+L43*$AE$21+M43*$AE$22+N43*$AE$23+O43*$AE$24+P43*$AE$25+Q43*$AE$26+R43*$AE$27+S43*$AE$28+T43*$AE$29+U43*$AE$30 | W43: =1/(1+EXP(-V43)) | X43: =-IF(C43=1,LN(W43),LN(1-W43)) | Y43: =1 | Z43: =Y43*X43 | AA43: =IF(W43>$AE$32,1,0) | AB43: =IF(AA43=C43,1,0) | AD43: scikit-learn reference: class 1 precision on testing | AE43: 0.65384615
A44: ='1 prepared data'!A37 | B44: ='1 prepared data'!U37 | C44: ='1 prepared data'!B37 | D44: ='1 prepared data'!C37 | E44: ='1 prepared data'!D37 | F44: ='1 prepared data'!E37 | G44: ='1 prepared data'!F37 | H44: ='1 prepared data'!G37 | I44: ='1 prepared data'!H37 | J44: ='1 prepared data'!I37 | ... U44: ='1 prepared data'!T37 | V44: =$AE$12+D44*$AE$13+E44*$AE$14+F44*$AE$15+G44*$AE$16+H44*$AE$17+I44*$AE$18+J44*$AE$19+K44*$AE$20+L44*$AE$21+M44*$AE$22+N44*$AE$23+O44*$AE$24+P44*$AE$25+Q44*$AE$26+R44*$AE$27+S44*$AE$28+T44*$AE$29+U44*$AE$30 | W44: =1/(1+EXP(-V44)) | X44: =-IF(C44=1,LN(W44),LN(1-W44)) | Y44: =1 | Z44: =Y44*X44 | AA44: =IF(W44>$AE$32,1,0) | AB44: =IF(AA44=C44,1,0) | AD44: scikit-learn reference: testing AUC | AE44: 0.82169312
A45: ='1 prepared data'!A38 | B45: ='1 prepared data'!U38 | C45: ='1 prepared data'!B38 | D45: ='1 prepared data'!C38 | E45: ='1 prepared data'!D38 | F45: ='1 prepared data'!E38 | G45: ='1 prepared data'!F38 | H45: ='1 prepared data'!G38 | I45: ='1 prepared data'!H38 | J45: ='1 prepared data'!I38 | ... U45: ='1 prepared data'!T38 | V45: =$AE$12+D45*$AE$13+E45*$AE$14+F45*$AE$15+G45*$AE$16+H45*$AE$17+I45*$AE$18+J45*$AE$19+K45*$AE$20+L45*$AE$21+M45*$AE$22+N45*$AE$23+O45*$AE$24+P45*$AE$25+Q45*$AE$26+R45*$AE$27+S45*$AE$28+T45*$AE$29+U45*$AE$30 | W45: =1/(1+EXP(-V45)) | X45: =-IF(C45=1,LN(W45),LN(1-W45)) | Y45: =1 | Z45: =Y45*X45 | AA45: =IF(W45>$AE$32,1,0) | AB45: =IF(AA45=C45,1,0)
A46: ='1 prepared data'!A39 | B46: ='1 prepared data'!U39 | C46: ='1 prepared data'!B39 | D46: ='1 prepared data'!C39 | E46: ='1 prepared data'!D39 | F46: ='1 prepared data'!E39 | G46: ='1 prepared data'!F39 | H46: ='1 prepared data'!G39 | I46: ='1 prepared data'!H39 | J46: ='1 prepared data'!I39 | ... U46: ='1 prepared data'!T39 | V46: =$AE$12+D46*$AE$13+E46*$AE$14+F46*$AE$15+G46*$AE$16+H46*$AE$17+I46*$AE$18+J46*$AE$19+K46*$AE$20+L46*$AE$21+M46*$AE$22+N46*$AE$23+O46*$AE$24+P46*$AE$25+Q46*$AE$26+R46*$AE$27+S46*$AE$28+T46*$AE$29+U46*$AE$30 | W46: =1/(1+EXP(-V46)) | X46: =-IF(C46=1,LN(W46),LN(1-W46)) | Y46: =1 | Z46: =Y46*X46 | AA46: =IF(W46>$AE$32,1,0) | AB46: =IF(AA46=C46,1,0) | AD46: Solver: minimize J by changing the light blue model weight cells (not the class weight cells), GRG Nonlinear, central derivatives, convergence 0.000001, no constraints and with 'Make Unconstrained Variables Non-Negative' UNTICKED. Run twice if it stops early.
A47: ='1 prepared data'!A40 | B47: ='1 prepared data'!U40 | C47: ='1 prepared data'!B40 | D47: ='1 prepared data'!C40 | E47: ='1 prepared data'!D40 | F47: ='1 prepared data'!E40 | G47: ='1 prepared data'!F40 | H47: ='1 prepared data'!G40 | I47: ='1 prepared data'!H40 | J47: ='1 prepared data'!I40 | ... U47: ='1 prepared data'!T40 | V47: =$AE$12+D47*$AE$13+E47*$AE$14+F47*$AE$15+G47*$AE$16+H47*$AE$17+I47*$AE$18+J47*$AE$19+K47*$AE$20+L47*$AE$21+M47*$AE$22+N47*$AE$23+O47*$AE$24+P47*$AE$25+Q47*$AE$26+R47*$AE$27+S47*$AE$28+T47*$AE$29+U47*$AE$30 | W47: =1/(1+EXP(-V47)) | X47: =-IF(C47=1,LN(W47),LN(1-W47)) | Y47: =1 | Z47: =Y47*X47 | AA47: =IF(W47>$AE$32,1,0) | AB47: =IF(AA47=C47,1,0)
A48: ='1 prepared data'!A41 | B48: ='1 prepared data'!U41 | C48: ='1 prepared data'!B41 | D48: ='1 prepared data'!C41 | E48: ='1 prepared data'!D41 | F48: ='1 prepared data'!E41 | G48: ='1 prepared data'!F41 | H48: ='1 prepared data'!G41 | I48: ='1 prepared data'!H41 | J48: ='1 prepared data'!I41 | ... U48: ='1 prepared data'!T41 | V48: =$AE$12+D48*$AE$13+E48*$AE$14+F48*$AE$15+G48*$AE$16+H48*$AE$17+I48*$AE$18+J48*$AE$19+K48*$AE$20+L48*$AE$21+M48*$AE$22+N48*$AE$23+O48*$AE$24+P48*$AE$25+Q48*$AE$26+R48*$AE$27+S48*$AE$28+T48*$AE$29+U48*$AE$30 | W48: =1/(1+EXP(-V48)) | X48: =-IF(C48=1,LN(W48),LN(1-W48)) | Y48: =1 | Z48: =Y48*X48 | AA48: =IF(W48>$AE$32,1,0) | AB48: =IF(AA48=C48,1,0)
A49: ='1 prepared data'!A42 | B49: ='1 prepared data'!U42 | C49: ='1 prepared data'!B42 | D49: ='1 prepared data'!C42 | E49: ='1 prepared data'!D42 | F49: ='1 prepared data'!E42 | G49: ='1 prepared data'!F42 | H49: ='1 prepared data'!G42 | I49: ='1 prepared data'!H42 | J49: ='1 prepared data'!I42 | ... U49: ='1 prepared data'!T42 | V49: =$AE$12+D49*$AE$13+E49*$AE$14+F49*$AE$15+G49*$AE$16+H49*$AE$17+I49*$AE$18+J49*$AE$19+K49*$AE$20+L49*$AE$21+M49*$AE$22+N49*$AE$23+O49*$AE$24+P49*$AE$25+Q49*$AE$26+R49*$AE$27+S49*$AE$28+T49*$AE$29+U49*$AE$30 | W49: =1/(1+EXP(-V49)) | X49: =-IF(C49=1,LN(W49),LN(1-W49)) | Y49: =1 | Z49: =Y49*X49 | AA49: =IF(W49>$AE$32,1,0) | AB49: =IF(AA49=C49,1,0)
A50: ='1 prepared data'!A43 | B50: ='1 prepared data'!U43 | C50: ='1 prepared data'!B43 | D50: ='1 prepared data'!C43 | E50: ='1 prepared data'!D43 | F50: ='1 prepared data'!E43 | G50: ='1 prepared data'!F43 | H50: ='1 prepared data'!G43 | I50: ='1 prepared data'!H43 | J50: ='1 prepared data'!I43 | ... U50: ='1 prepared data'!T43 | V50: =$AE$12+D50*$AE$13+E50*$AE$14+F50*$AE$15+G50*$AE$16+H50*$AE$17+I50*$AE$18+J50*$AE$19+K50*$AE$20+L50*$AE$21+M50*$AE$22+N50*$AE$23+O50*$AE$24+P50*$AE$25+Q50*$AE$26+R50*$AE$27+S50*$AE$28+T50*$AE$29+U50*$AE$30 | W50: =1/(1+EXP(-V50)) | X50: =-IF(C50=1,LN(W50),LN(1-W50)) | Y50: =1 | Z50: =Y50*X50 | AA50: =IF(W50>$AE$32,1,0) | AB50: =IF(AA50=C50,1,0)
A51: ='1 prepared data'!A44 | B51: ='1 prepared data'!U44 | C51: ='1 prepared data'!B44 | D51: ='1 prepared data'!C44 | E51: ='1 prepared data'!D44 | F51: ='1 prepared data'!E44 | G51: ='1 prepared data'!F44 | H51: ='1 prepared data'!G44 | I51: ='1 prepared data'!H44 | J51: ='1 prepared data'!I44 | ... U51: ='1 prepared data'!T44 | V51: =$AE$12+D51*$AE$13+E51*$AE$14+F51*$AE$15+G51*$AE$16+H51*$AE$17+I51*$AE$18+J51*$AE$19+K51*$AE$20+L51*$AE$21+M51*$AE$22+N51*$AE$23+O51*$AE$24+P51*$AE$25+Q51*$AE$26+R51*$AE$27+S51*$AE$28+T51*$AE$29+U51*$AE$30 | W51: =1/(1+EXP(-V51)) | X51: =-IF(C51=1,LN(W51),LN(1-W51)) | Y51: =1 | Z51: =Y51*X51 | AA51: =IF(W51>$AE$32,1,0) | AB51: =IF(AA51=C51,1,0)
A52: ='1 prepared data'!A45 | B52: ='1 prepared data'!U45 | C52: ='1 prepared data'!B45 | D52: ='1 prepared data'!C45 | E52: ='1 prepared data'!D45 | F52: ='1 prepared data'!E45 | G52: ='1 prepared data'!F45 | H52: ='1 prepared data'!G45 | I52: ='1 prepared data'!H45 | J52: ='1 prepared data'!I45 | ... U52: ='1 prepared data'!T45 | V52: =$AE$12+D52*$AE$13+E52*$AE$14+F52*$AE$15+G52*$AE$16+H52*$AE$17+I52*$AE$18+J52*$AE$19+K52*$AE$20+L52*$AE$21+M52*$AE$22+N52*$AE$23+O52*$AE$24+P52*$AE$25+Q52*$AE$26+R52*$AE$27+S52*$AE$28+T52*$AE$29+U52*$AE$30 | W52: =1/(1+EXP(-V52)) | X52: =-IF(C52=1,LN(W52),LN(1-W52)) | Y52: =1 | Z52: =Y52*X52 | AA52: =IF(W52>$AE$32,1,0) | AB52: =IF(AA52=C52,1,0)
A53: ='1 prepared data'!A46 | B53: ='1 prepared data'!U46 | C53: ='1 prepared data'!B46 | D53: ='1 prepared data'!C46 | E53: ='1 prepared data'!D46 | F53: ='1 prepared data'!E46 | G53: ='1 prepared data'!F46 | H53: ='1 prepared data'!G46 | I53: ='1 prepared data'!H46 | J53: ='1 prepared data'!I46 | ... U53: ='1 prepared data'!T46 | V53: =$AE$12+D53*$AE$13+E53*$AE$14+F53*$AE$15+G53*$AE$16+H53*$AE$17+I53*$AE$18+J53*$AE$19+K53*$AE$20+L53*$AE$21+M53*$AE$22+N53*$AE$23+O53*$AE$24+P53*$AE$25+Q53*$AE$26+R53*$AE$27+S53*$AE$28+T53*$AE$29+U53*$AE$30 | W53: =1/(1+EXP(-V53)) | X53: =-IF(C53=1,LN(W53),LN(1-W53)) | Y53: =1 | Z53: =Y53*X53 | AA53: =IF(W53>$AE$32,1,0) | AB53: =IF(AA53=C53,1,0)
A54: ='1 prepared data'!A47 | B54: ='1 prepared data'!U47 | C54: ='1 prepared data'!B47 | D54: ='1 prepared data'!C47 | E54: ='1 prepared data'!D47 | F54: ='1 prepared data'!E47 | G54: ='1 prepared data'!F47 | H54: ='1 prepared data'!G47 | I54: ='1 prepared data'!H47 | J54: ='1 prepared data'!I47 | ... U54: ='1 prepared data'!T47 | V54: =$AE$12+D54*$AE$13+E54*$AE$14+F54*$AE$15+G54*$AE$16+H54*$AE$17+I54*$AE$18+J54*$AE$19+K54*$AE$20+L54*$AE$21+M54*$AE$22+N54*$AE$23+O54*$AE$24+P54*$AE$25+Q54*$AE$26+R54*$AE$27+S54*$AE$28+T54*$AE$29+U54*$AE$30 | W54: =1/(1+EXP(-V54)) | X54: =-IF(C54=1,LN(W54),LN(1-W54)) | Y54: =1 | Z54: =Y54*X54 | AA54: =IF(W54>$AE$32,1,0) | AB54: =IF(AA54=C54,1,0)
A55: ='1 prepared data'!A48 | B55: ='1 prepared data'!U48 | C55: ='1 prepared data'!B48 | D55: ='1 prepared data'!C48 | E55: ='1 prepared data'!D48 | F55: ='1 prepared data'!E48 | G55: ='1 prepared data'!F48 | H55: ='1 prepared data'!G48 | I55: ='1 prepared data'!H48 | J55: ='1 prepared data'!I48 | ... U55: ='1 prepared data'!T48 | V55: =$AE$12+D55*$AE$13+E55*$AE$14+F55*$AE$15+G55*$AE$16+H55*$AE$17+I55*$AE$18+J55*$AE$19+K55*$AE$20+L55*$AE$21+M55*$AE$22+N55*$AE$23+O55*$AE$24+P55*$AE$25+Q55*$AE$26+R55*$AE$27+S55*$AE$28+T55*$AE$29+U55*$AE$30 | W55: =1/(1+EXP(-V55)) | X55: =-IF(C55=1,LN(W55),LN(1-W55)) | Y55: =1 | Z55: =Y55*X55 | AA55: =IF(W55>$AE$32,1,0) | AB55: =IF(AA55=C55,1,0)
A56: ='1 prepared data'!A49 | B56: ='1 prepared data'!U49 | C56: ='1 prepared data'!B49 | D56: ='1 prepared data'!C49 | E56: ='1 prepared data'!D49 | F56: ='1 prepared data'!E49 | G56: ='1 prepared data'!F49 | H56: ='1 prepared data'!G49 | I56: ='1 prepared data'!H49 | J56: ='1 prepared data'!I49 | ... U56: ='1 prepared data'!T49 | V56: =$AE$12+D56*$AE$13+E56*$AE$14+F56*$AE$15+G56*$AE$16+H56*$AE$17+I56*$AE$18+J56*$AE$19+K56*$AE$20+L56*$AE$21+M56*$AE$22+N56*$AE$23+O56*$AE$24+P56*$AE$25+Q56*$AE$26+R56*$AE$27+S56*$AE$28+T56*$AE$29+U56*$AE$30 | W56: =1/(1+EXP(-V56)) | X56: =-IF(C56=1,LN(W56),LN(1-W56)) | Y56: =1 | Z56: =Y56*X56 | AA56: =IF(W56>$AE$32,1,0) | AB56: =IF(AA56=C56,1,0)
A57: ='1 prepared data'!A50 | B57: ='1 prepared data'!U50 | C57: ='1 prepared data'!B50 | D57: ='1 prepared data'!C50 | E57: ='1 prepared data'!D50 | F57: ='1 prepared data'!E50 | G57: ='1 prepared data'!F50 | H57: ='1 prepared data'!G50 | I57: ='1 prepared data'!H50 | J57: ='1 prepared data'!I50 | ... U57: ='1 prepared data'!T50 | V57: =$AE$12+D57*$AE$13+E57*$AE$14+F57*$AE$15+G57*$AE$16+H57*$AE$17+I57*$AE$18+J57*$AE$19+K57*$AE$20+L57*$AE$21+M57*$AE$22+N57*$AE$23+O57*$AE$24+P57*$AE$25+Q57*$AE$26+R57*$AE$27+S57*$AE$28+T57*$AE$29+U57*$AE$30 | W57: =1/(1+EXP(-V57)) | X57: =-IF(C57=1,LN(W57),LN(1-W57)) | Y57: =1 | Z57: =Y57*X57 | AA57: =IF(W57>$AE$32,1,0) | AB57: =IF(AA57=C57,1,0)
A58: ='1 prepared data'!A51 | B58: ='1 prepared data'!U51 | C58: ='1 prepared data'!B51 | D58: ='1 prepared data'!C51 | E58: ='1 prepared data'!D51 | F58: ='1 prepared data'!E51 | G58: ='1 prepared data'!F51 | H58: ='1 prepared data'!G51 | I58: ='1 prepared data'!H51 | J58: ='1 prepared data'!I51 | ... U58: ='1 prepared data'!T51 | V58: =$AE$12+D58*$AE$13+E58*$AE$14+F58*$AE$15+G58*$AE$16+H58*$AE$17+I58*$AE$18+J58*$AE$19+K58*$AE$20+L58*$AE$21+M58*$AE$22+N58*$AE$23+O58*$AE$24+P58*$AE$25+Q58*$AE$26+R58*$AE$27+S58*$AE$28+T58*$AE$29+U58*$AE$30 | W58: =1/(1+EXP(-V58)) | X58: =-IF(C58=1,LN(W58),LN(1-W58)) | Y58: =1 | Z58: =Y58*X58 | AA58: =IF(W58>$AE$32,1,0) | AB58: =IF(AA58=C58,1,0)
... A1011: ='1 prepared data'!A1004 | B1011: ='1 prepared data'!U1004 | C1011: ='1 prepared data'!B1004 | D1011: ='1 prepared data'!C1004 | E1011: ='1 prepared data'!D1004 | F1011: ='1 prepared data'!E1004 | G1011: ='1 prepared data'!F1004 | H1011: ='1 prepared data'!G1004 | I1011: ='1 prepared data'!H1004 | J1011: ='1 prepared data'!I1004 | ... U1011: ='1 prepared data'!T1004 | V1011: =$AE$12+D1011*$AE$13+E1011*$AE$14+F1011*$AE$15+G1011*$AE$16+H1011*$AE$17+I1011*$AE$18+J1011*$AE$19+K1011*$AE$20+L1011*$AE$21+M1011*$AE$22+N1011*$AE$23+O1011*$AE$24+P1011*$AE$25+Q1011*$AE$26+R1011*$AE$27+S1011*$AE$28+T1011*$AE$29+U1011*$AE$30 | W1011: =1/(1+EXP(-V1011)) | X1011: =-IF(C1011=1,LN(W1011),LN(1-W1011)) | Y1011: =1 | Z1011: =Y1011*X1011 | AA1011: =IF(W1011>$AE$32,1,0) | AB1011: =IF(AA1011=C1011,1,0)

Sheet 3 class weights
A1: Class weights: each customer weighs according to its class, and the two classes add up to the same total
A2: The most direct fix: instead of adding up each row's loss, we add up the loss multiplied by a weight that depends on the class. With w1 = n / (2 · n1) = 1.667 for the defaulters and w0 = n / (2 · n0) = 0.714 for the good payers, each class contributes exactly 350 to the total, as if there were 350 and 350. The model can no longer ignore the minority class. In scikit-learn it is class_weight='balanced'; in any other library it is sample_weight.
A3: Run Solver and look at the report: the recall of class 1 rises from 0.57 to 0.86, and precision falls from 0.65 to 0.53: it catches more defaulters at the cost of flagging more good payers. It is the same trade-off as always. And look at the average p on testing: it rises to 0.48 when the actual rate is 0.30. The weighted model no longer delivers calibrated probabilities; it delivers higher scores for everyone. Compare with sheet 7: the unbalanced model, with threshold 0.30, reaches almost the same recall and precision.
AD10: Model weights (theta): start from the unbalanced solution | AI10: EVALUATION ON TESTING (with the light blue threshold)
A11: id | B11: set | C11: y | D11: duration | E11: amount | F11: age | G11: installment_pct_income | H11: chk_negative | I11: chk_0_200 | J11: chk_over_200 | K11: hist_critical | L11: hist_delays | M11: hist_no_credits | N11: sav_100_1000 | O11: sav_over_1000 | P11: sav_unknown | Q11: housing_rent | R11: housing_free | S11: purpose_car | T11: purpose_radio_tv | U11: purpose_furniture | V11: Z (line) | W11: p (logistic) | X11: loss | Y11: row weight | Z11: weighted loss | AA11: prediction | AB11: correct | AD11: variable | AE11: theta (light blue) | AF11: scikit-learn reference for this variant
A12: ='1 prepared data'!A5 | B12: ='1 prepared data'!U5 | C12: ='1 prepared data'!B5 | D12: ='1 prepared data'!C5 | E12: ='1 prepared data'!D5 | F12: ='1 prepared data'!E5 | G12: ='1 prepared data'!F5 | H12: ='1 prepared data'!G5 | I12: ='1 prepared data'!H5 | J12: ='1 prepared data'!I5 | ... U12: ='1 prepared data'!T5 | V12: =$AE$12+D12*$AE$13+E12*$AE$14+F12*$AE$15+G12*$AE$16+H12*$AE$17+I12*$AE$18+J12*$AE$19+K12*$AE$20+L12*$AE$21+M12*$AE$22+N12*$AE$23+O12*$AE$24+P12*$AE$25+Q12*$AE$26+R12*$AE$27+S12*$AE$28+T12*$AE$29+U12*$AE$30 | W12: =1/(1+EXP(-V12)) | X12: =-IF(C12=1,LN(W12),LN(1-W12)) | Y12: =IF(C12=1,$AE$32,$AE$33) | Z12: =Y12*X12 | AA12: =IF(W12>$AE$34,1,0) | AB12: =IF(AA12=C12,1,0) | AD12: intercept | AE12: -1.341271 | AF12: -0.48796379
A13: ='1 prepared data'!A6 | B13: ='1 prepared data'!U6 | C13: ='1 prepared data'!B6 | D13: ='1 prepared data'!C6 | E13: ='1 prepared data'!D6 | F13: ='1 prepared data'!E6 | G13: ='1 prepared data'!F6 | H13: ='1 prepared data'!G6 | I13: ='1 prepared data'!H6 | J13: ='1 prepared data'!I6 | ... U13: ='1 prepared data'!T6 | V13: =$AE$12+D13*$AE$13+E13*$AE$14+F13*$AE$15+G13*$AE$16+H13*$AE$17+I13*$AE$18+J13*$AE$19+K13*$AE$20+L13*$AE$21+M13*$AE$22+N13*$AE$23+O13*$AE$24+P13*$AE$25+Q13*$AE$26+R13*$AE$27+S13*$AE$28+T13*$AE$29+U13*$AE$30 | W13: =1/(1+EXP(-V13)) | X13: =-IF(C13=1,LN(W13),LN(1-W13)) | Y13: =IF(C13=1,$AE$32,$AE$33) | Z13: =Y13*X13 | AA13: =IF(W13>$AE$34,1,0) | AB13: =IF(AA13=C13,1,0) | AD13: duration | AE13: 0.32470125 | AF13: 0.2913039 | AK13: predicted 0 | AL13: predicted 1 | AM13: total
A14: ='1 prepared data'!A7 | B14: ='1 prepared data'!U7 | C14: ='1 prepared data'!B7 | D14: ='1 prepared data'!C7 | E14: ='1 prepared data'!D7 | F14: ='1 prepared data'!E7 | G14: ='1 prepared data'!F7 | H14: ='1 prepared data'!G7 | I14: ='1 prepared data'!H7 | J14: ='1 prepared data'!I7 | ... U14: ='1 prepared data'!T7 | V14: =$AE$12+D14*$AE$13+E14*$AE$14+F14*$AE$15+G14*$AE$16+H14*$AE$17+I14*$AE$18+J14*$AE$19+K14*$AE$20+L14*$AE$21+M14*$AE$22+N14*$AE$23+O14*$AE$24+P14*$AE$25+Q14*$AE$26+R14*$AE$27+S14*$AE$28+T14*$AE$29+U14*$AE$30 | W14: =1/(1+EXP(-V14)) | X14: =-IF(C14=1,LN(W14),LN(1-W14)) | Y14: =IF(C14=1,$AE$32,$AE$33) | Z14: =Y14*X14 | AA14: =IF(W14>$AE$34,1,0) | AB14: =IF(AA14=C14,1,0) | AD14: amount | AE14: 0.11635359 | AF14: 0.16069038 | AI14: actual 0 (good payer) | AJ14: TN | FP | AK14: =COUNTIFS($B$12:$B$1011,"testing",$C$12:$C$1011,0,$AA$12:$AA$1011,0) | AL14: =COUNTIFS($B$12:$B$1011,"testing",$C$12:$C$1011,0,$AA$12:$AA$1011,1) | AM14: =AK14+AL14
A15: ='1 prepared data'!A8 | B15: ='1 prepared data'!U8 | C15: ='1 prepared data'!B8 | D15: ='1 prepared data'!C8 | E15: ='1 prepared data'!D8 | F15: ='1 prepared data'!E8 | G15: ='1 prepared data'!F8 | H15: ='1 prepared data'!G8 | I15: ='1 prepared data'!H8 | J15: ='1 prepared data'!I8 | ... U15: ='1 prepared data'!T8 | V15: =$AE$12+D15*$AE$13+E15*$AE$14+F15*$AE$15+G15*$AE$16+H15*$AE$17+I15*$AE$18+J15*$AE$19+K15*$AE$20+L15*$AE$21+M15*$AE$22+N15*$AE$23+O15*$AE$24+P15*$AE$25+Q15*$AE$26+R15*$AE$27+S15*$AE$28+T15*$AE$29+U15*$AE$30 | W15: =1/(1+EXP(-V15)) | X15: =-IF(C15=1,LN(W15),LN(1-W15)) | Y15: =IF(C15=1,$AE$32,$AE$33) | Z15: =Y15*X15 | AA15: =IF(W15>$AE$34,1,0) | AB15: =IF(AA15=C15,1,0) | AD15: age | AE15: -0.099145225 | AF15: -0.1278058 | AI15: actual 1 (defaulter) | AJ15: FN | TP | AK15: =COUNTIFS($B$12:$B$1011,"testing",$C$12:$C$1011,1,$AA$12:$AA$1011,0) | AL15: =COUNTIFS($B$12:$B$1011,"testing",$C$12:$C$1011,1,$AA$12:$AA$1011,1) | AM15: =AK15+AL15
A16: ='1 prepared data'!A9 | B16: ='1 prepared data'!U9 | C16: ='1 prepared data'!B9 | D16: ='1 prepared data'!C9 | E16: ='1 prepared data'!D9 | F16: ='1 prepared data'!E9 | G16: ='1 prepared data'!F9 | H16: ='1 prepared data'!G9 | I16: ='1 prepared data'!H9 | J16: ='1 prepared data'!I9 | ... U16: ='1 prepared data'!T9 | V16: =$AE$12+D16*$AE$13+E16*$AE$14+F16*$AE$15+G16*$AE$16+H16*$AE$17+I16*$AE$18+J16*$AE$19+K16*$AE$20+L16*$AE$21+M16*$AE$22+N16*$AE$23+O16*$AE$24+P16*$AE$25+Q16*$AE$26+R16*$AE$27+S16*$AE$28+T16*$AE$29+U16*$AE$30 | W16: =1/(1+EXP(-V16)) | X16: =-IF(C16=1,LN(W16),LN(1-W16)) | Y16: =IF(C16=1,$AE$32,$AE$33) | Z16: =Y16*X16 | AA16: =IF(W16>$AE$34,1,0) | AB16: =IF(AA16=C16,1,0) | AD16: installment_pct_income | AE16: 0.28721577 | AF16: 0.28614887 | AI16: total | AK16: =AK14+AK15 | AL16: =AL14+AL15 | AM16: =AM14+AM15
A17: ='1 prepared data'!A10 | B17: ='1 prepared data'!U10 | C17: ='1 prepared data'!B10 | D17: ='1 prepared data'!C10 | E17: ='1 prepared data'!D10 | F17: ='1 prepared data'!E10 | G17: ='1 prepared data'!F10 | H17: ='1 prepared data'!G10 | I17: ='1 prepared data'!H10 | J17: ='1 prepared data'!I10 | ... U17: ='1 prepared data'!T10 | V17: =$AE$12+D17*$AE$13+E17*$AE$14+F17*$AE$15+G17*$AE$16+H17*$AE$17+I17*$AE$18+J17*$AE$19+K17*$AE$20+L17*$AE$21+M17*$AE$22+N17*$AE$23+O17*$AE$24+P17*$AE$25+Q17*$AE$26+R17*$AE$27+S17*$AE$28+T17*$AE$29+U17*$AE$30 | W17: =1/(1+EXP(-V17)) | X17: =-IF(C17=1,LN(W17),LN(1-W17)) | Y17: =IF(C17=1,$AE$32,$AE$33) | Z17: =Y17*X17 | AA17: =IF(W17>$AE$34,1,0) | AB17: =IF(AA17=C17,1,0) | AD17: chk_negative | AE17: 1.5464027 | AF17: 1.5734261
A18: ='1 prepared data'!A11 | B18: ='1 prepared data'!U11 | C18: ='1 prepared data'!B11 | D18: ='1 prepared data'!C11 | E18: ='1 prepared data'!D11 | F18: ='1 prepared data'!E11 | G18: ='1 prepared data'!F11 | H18: ='1 prepared data'!G11 | I18: ='1 prepared data'!H11 | J18: ='1 prepared data'!I11 | ... U18: ='1 prepared data'!T11 | V18: =$AE$12+D18*$AE$13+E18*$AE$14+F18*$AE$15+G18*$AE$16+H18*$AE$17+I18*$AE$18+J18*$AE$19+K18*$AE$20+L18*$AE$21+M18*$AE$22+N18*$AE$23+O18*$AE$24+P18*$AE$25+Q18*$AE$26+R18*$AE$27+S18*$AE$28+T18*$AE$29+U18*$AE$30 | W18: =1/(1+EXP(-V18)) | X18: =-IF(C18=1,LN(W18),LN(1-W18)) | Y18: =IF(C18=1,$AE$32,$AE$33) | Z18: =Y18*X18 | AA18: =IF(W18>$AE$34,1,0) | AB18: =IF(AA18=C18,1,0) | AD18: chk_0_200 | AE18: 1.2949978 | AF18: 1.339005 | AJ18: precision | AK18: recall | AL18: f1-score | AM18: support
A19: ='1 prepared data'!A12 | B19: ='1 prepared data'!U12 | C19: ='1 prepared data'!B12 | D19: ='1 prepared data'!C12 | E19: ='1 prepared data'!D12 | F19: ='1 prepared data'!E12 | G19: ='1 prepared data'!F12 | H19: ='1 prepared data'!G12 | I19: ='1 prepared data'!H12 | J19: ='1 prepared data'!I12 | ... U19: ='1 prepared data'!T12 | V19: =$AE$12+D19*$AE$13+E19*$AE$14+F19*$AE$15+G19*$AE$16+H19*$AE$17+I19*$AE$18+J19*$AE$19+K19*$AE$20+L19*$AE$21+M19*$AE$22+N19*$AE$23+O19*$AE$24+P19*$AE$25+Q19*$AE$26+R19*$AE$27+S19*$AE$28+T19*$AE$29+U19*$AE$30 | W19: =1/(1+EXP(-V19)) | X19: =-IF(C19=1,LN(W19),LN(1-W19)) | Y19: =IF(C19=1,$AE$32,$AE$33) | Z19: =Y19*X19 | AA19: =IF(W19>$AE$34,1,0) | AB19: =IF(AA19=C19,1,0) | AD19: chk_over_200 | AE19: 0.66836159 | AF19: 0.74810039 | AI19: class 0 (pays) | AJ19: =IF(AK14+AK15=0,0,AK14/(AK14+AK15)) | AK19: =IF(AK14+AL14=0,0,AK14/(AK14+AL14)) | AL19: =IF(AJ19+AK19=0,0,2*AJ19*AK19/(AJ19+AK19)) | AM19: =AM14
A20: ='1 prepared data'!A13 | B20: ='1 prepared data'!U13 | C20: ='1 prepared data'!B13 | D20: ='1 prepared data'!C13 | E20: ='1 prepared data'!D13 | F20: ='1 prepared data'!E13 | G20: ='1 prepared data'!F13 | H20: ='1 prepared data'!G13 | I20: ='1 prepared data'!H13 | J20: ='1 prepared data'!I13 | ... U20: ='1 prepared data'!T13 | V20: =$AE$12+D20*$AE$13+E20*$AE$14+F20*$AE$15+G20*$AE$16+H20*$AE$17+I20*$AE$18+J20*$AE$19+K20*$AE$20+L20*$AE$21+M20*$AE$22+N20*$AE$23+O20*$AE$24+P20*$AE$25+Q20*$AE$26+R20*$AE$27+S20*$AE$28+T20*$AE$29+U20*$AE$30 | W20: =1/(1+EXP(-V20)) | X20: =-IF(C20=1,LN(W20),LN(1-W20)) | Y20: =IF(C20=1,$AE$32,$AE$33) | Z20: =Y20*X20 | AA20: =IF(W20>$AE$34,1,0) | AB20: =IF(AA20=C20,1,0) | AD20: hist_critical | AE20: -0.65734494 | AF20: -0.65746629 | AI20: class 1 (defaults) | AJ20: =IF(AL15+AL14=0,0,AL15/(AL15+AL14)) | AK20: =IF(AL15+AK15=0,0,AL15/(AL15+AK15)) | AL20: =IF(AJ20+AK20=0,0,2*AJ20*AK20/(AJ20+AK20)) | AM20: =AM15
A21: ='1 prepared data'!A14 | B21: ='1 prepared data'!U14 | C21: ='1 prepared data'!B14 | D21: ='1 prepared data'!C14 | E21: ='1 prepared data'!D14 | F21: ='1 prepared data'!E14 | G21: ='1 prepared data'!F14 | H21: ='1 prepared data'!G14 | I21: ='1 prepared data'!H14 | J21: ='1 prepared data'!I14 | ... U21: ='1 prepared data'!T14 | V21: =$AE$12+D21*$AE$13+E21*$AE$14+F21*$AE$15+G21*$AE$16+H21*$AE$17+I21*$AE$18+J21*$AE$19+K21*$AE$20+L21*$AE$21+M21*$AE$22+N21*$AE$23+O21*$AE$24+P21*$AE$25+Q21*$AE$26+R21*$AE$27+S21*$AE$28+T21*$AE$29+U21*$AE$30 | W21: =1/(1+EXP(-V21)) | X21: =-IF(C21=1,LN(W21),LN(1-W21)) | Y21: =IF(C21=1,$AE$32,$AE$33) | Z21: =Y21*X21 | AA21: =IF(W21>$AE$34,1,0) | AB21: =IF(AA21=C21,1,0) | AD21: hist_delays | AE21: -0.040195519 | AF21: -0.014564057 | AI21: accuracy | AL21: =(AL15+AK14)/AM16
A22: ='1 prepared data'!A15 | B22: ='1 prepared data'!U15 | C22: ='1 prepared data'!B15 | D22: ='1 prepared data'!C15 | E22: ='1 prepared data'!D15 | F22: ='1 prepared data'!E15 | G22: ='1 prepared data'!F15 | H22: ='1 prepared data'!G15 | I22: ='1 prepared data'!H15 | J22: ='1 prepared data'!I15 | ... U22: ='1 prepared data'!T15 | V22: =$AE$12+D22*$AE$13+E22*$AE$14+F22*$AE$15+G22*$AE$16+H22*$AE$17+I22*$AE$18+J22*$AE$19+K22*$AE$20+L22*$AE$21+M22*$AE$22+N22*$AE$23+O22*$AE$24+P22*$AE$25+Q22*$AE$26+R22*$AE$27+S22*$AE$28+T22*$AE$29+U22*$AE$30 | W22: =1/(1+EXP(-V22)) | X22: =-IF(C22=1,LN(W22),LN(1-W22)) | Y22: =IF(C22=1,$AE$32,$AE$33) | Z22: =Y22*X22 | AA22: =IF(W22>$AE$34,1,0) | AB22: =IF(AA22=C22,1,0) | AD22: hist_no_credits | AE22: 0.66906563 | AF22: 0.61576668
A23: ='1 prepared data'!A16 | B23: ='1 prepared data'!U16 | C23: ='1 prepared data'!B16 | D23: ='1 prepared data'!C16 | E23: ='1 prepared data'!D16 | F23: ='1 prepared data'!E16 | G23: ='1 prepared data'!F16 | H23: ='1 prepared data'!G16 | I23: ='1 prepared data'!H16 | J23: ='1 prepared data'!I16 | ... U23: ='1 prepared data'!T16 | V23: =$AE$12+D23*$AE$13+E23*$AE$14+F23*$AE$15+G23*$AE$16+H23*$AE$17+I23*$AE$18+J23*$AE$19+K23*$AE$20+L23*$AE$21+M23*$AE$22+N23*$AE$23+O23*$AE$24+P23*$AE$25+Q23*$AE$26+R23*$AE$27+S23*$AE$28+T23*$AE$29+U23*$AE$30 | W23: =1/(1+EXP(-V23)) | X23: =-IF(C23=1,LN(W23),LN(1-W23)) | Y23: =IF(C23=1,$AE$32,$AE$33) | Z23: =Y23*X23 | AA23: =IF(W23>$AE$34,1,0) | AB23: =IF(AA23=C23,1,0) | AD23: sav_100_1000 | AE23: -0.38958343 | AF23: -0.33206733
A24: ='1 prepared data'!A17 | B24: ='1 prepared data'!U17 | C24: ='1 prepared data'!B17 | D24: ='1 prepared data'!C17 | E24: ='1 prepared data'!D17 | F24: ='1 prepared data'!E17 | G24: ='1 prepared data'!F17 | H24: ='1 prepared data'!G17 | I24: ='1 prepared data'!H17 | J24: ='1 prepared data'!I17 | ... U24: ='1 prepared data'!T17 | V24: =$AE$12+D24*$AE$13+E24*$AE$14+F24*$AE$15+G24*$AE$16+H24*$AE$17+I24*$AE$18+J24*$AE$19+K24*$AE$20+L24*$AE$21+M24*$AE$22+N24*$AE$23+O24*$AE$24+P24*$AE$25+Q24*$AE$26+R24*$AE$27+S24*$AE$28+T24*$AE$29+U24*$AE$30 | W24: =1/(1+EXP(-V24)) | X24: =-IF(C24=1,LN(W24),LN(1-W24)) | Y24: =IF(C24=1,$AE$32,$AE$33) | Z24: =Y24*X24 | AA24: =IF(W24>$AE$34,1,0) | AB24: =IF(AA24=C24,1,0) | AD24: sav_over_1000 | AE24: -0.88922386 | AF24: -0.7786412
A25: ='1 prepared data'!A18 | B25: ='1 prepared data'!U18 | C25: ='1 prepared data'!B18 | D25: ='1 prepared data'!C18 | E25: ='1 prepared data'!D18 | F25: ='1 prepared data'!E18 | G25: ='1 prepared data'!F18 | H25: ='1 prepared data'!G18 | I25: ='1 prepared data'!H18 | J25: ='1 prepared data'!I18 | ... U25: ='1 prepared data'!T18 | V25: =$AE$12+D25*$AE$13+E25*$AE$14+F25*$AE$15+G25*$AE$16+H25*$AE$17+I25*$AE$18+J25*$AE$19+K25*$AE$20+L25*$AE$21+M25*$AE$22+N25*$AE$23+O25*$AE$24+P25*$AE$25+Q25*$AE$26+R25*$AE$27+S25*$AE$28+T25*$AE$29+U25*$AE$30 | W25: =1/(1+EXP(-V25)) | X25: =-IF(C25=1,LN(W25),LN(1-W25)) | Y25: =IF(C25=1,$AE$32,$AE$33) | Z25: =Y25*X25 | AA25: =IF(W25>$AE$34,1,0) | AB25: =IF(AA25=C25,1,0) | AD25: sav_unknown | AE25: -1.0760929 | AF25: -0.97455632
A26: ='1 prepared data'!A19 | B26: ='1 prepared data'!U19 | C26: ='1 prepared data'!B19 | D26: ='1 prepared data'!C19 | E26: ='1 prepared data'!D19 | F26: ='1 prepared data'!E19 | G26: ='1 prepared data'!F19 | H26: ='1 prepared data'!G19 | I26: ='1 prepared data'!H19 | J26: ='1 prepared data'!I19 | ... U26: ='1 prepared data'!T19 | V26: =$AE$12+D26*$AE$13+E26*$AE$14+F26*$AE$15+G26*$AE$16+H26*$AE$17+I26*$AE$18+J26*$AE$19+K26*$AE$20+L26*$AE$21+M26*$AE$22+N26*$AE$23+O26*$AE$24+P26*$AE$25+Q26*$AE$26+R26*$AE$27+S26*$AE$28+T26*$AE$29+U26*$AE$30 | W26: =1/(1+EXP(-V26)) | X26: =-IF(C26=1,LN(W26),LN(1-W26)) | Y26: =IF(C26=1,$AE$32,$AE$33) | Z26: =Y26*X26 | AA26: =IF(W26>$AE$34,1,0) | AB26: =IF(AA26=C26,1,0) | AD26: housing_rent | AE26: 0.65383718 | AF26: 0.61873534
A27: ='1 prepared data'!A20 | B27: ='1 prepared data'!U20 | C27: ='1 prepared data'!B20 | D27: ='1 prepared data'!C20 | E27: ='1 prepared data'!D20 | F27: ='1 prepared data'!E20 | G27: ='1 prepared data'!F20 | H27: ='1 prepared data'!G20 | I27: ='1 prepared data'!H20 | J27: ='1 prepared data'!I20 | ... U27: ='1 prepared data'!T20 | V27: =$AE$12+D27*$AE$13+E27*$AE$14+F27*$AE$15+G27*$AE$16+H27*$AE$17+I27*$AE$18+J27*$AE$19+K27*$AE$20+L27*$AE$21+M27*$AE$22+N27*$AE$23+O27*$AE$24+P27*$AE$25+Q27*$AE$26+R27*$AE$27+S27*$AE$28+T27*$AE$29+U27*$AE$30 | W27: =1/(1+EXP(-V27)) | X27: =-IF(C27=1,LN(W27),LN(1-W27)) | Y27: =IF(C27=1,$AE$32,$AE$33) | Z27: =Y27*X27 | AA27: =IF(W27>$AE$34,1,0) | AB27: =IF(AA27=C27,1,0) | AD27: housing_free | AE27: 0.19536536 | AF27: 0.23105196
A28: ='1 prepared data'!A21 | B28: ='1 prepared data'!U21 | C28: ='1 prepared data'!B21 | D28: ='1 prepared data'!C21 | E28: ='1 prepared data'!D21 | F28: ='1 prepared data'!E21 | G28: ='1 prepared data'!F21 | H28: ='1 prepared data'!G21 | I28: ='1 prepared data'!H21 | J28: ='1 prepared data'!I21 | ... U28: ='1 prepared data'!T21 | V28: =$AE$12+D28*$AE$13+E28*$AE$14+F28*$AE$15+G28*$AE$16+H28*$AE$17+I28*$AE$18+J28*$AE$19+K28*$AE$20+L28*$AE$21+M28*$AE$22+N28*$AE$23+O28*$AE$24+P28*$AE$25+Q28*$AE$26+R28*$AE$27+S28*$AE$28+T28*$AE$29+U28*$AE$30 | W28: =1/(1+EXP(-V28)) | X28: =-IF(C28=1,LN(W28),LN(1-W28)) | Y28: =IF(C28=1,$AE$32,$AE$33) | Z28: =Y28*X28 | AA28: =IF(W28>$AE$34,1,0) | AB28: =IF(AA28=C28,1,0) | AD28: purpose_car | AE28: -0.080165476 | AF28: -0.16596788
A29: ='1 prepared data'!A22 | B29: ='1 prepared data'!U22 | C29: ='1 prepared data'!B22 | D29: ='1 prepared data'!C22 | E29: ='1 prepared data'!D22 | F29: ='1 prepared data'!E22 | G29: ='1 prepared data'!F22 | H29: ='1 prepared data'!G22 | I29: ='1 prepared data'!H22 | J29: ='1 prepared data'!I22 | ... U29: ='1 prepared data'!T22 | V29: =$AE$12+D29*$AE$13+E29*$AE$14+F29*$AE$15+G29*$AE$16+H29*$AE$17+I29*$AE$18+J29*$AE$19+K29*$AE$20+L29*$AE$21+M29*$AE$22+N29*$AE$23+O29*$AE$24+P29*$AE$25+Q29*$AE$26+R29*$AE$27+S29*$AE$28+T29*$AE$29+U29*$AE$30 | W29: =1/(1+EXP(-V29)) | X29: =-IF(C29=1,LN(W29),LN(1-W29)) | Y29: =IF(C29=1,$AE$32,$AE$33) | Z29: =Y29*X29 | AA29: =IF(W29>$AE$34,1,0) | AB29: =IF(AA29=C29,1,0) | AD29: purpose_radio_tv | AE29: -0.52021065 | AF29: -0.59893576
A30: ='1 prepared data'!A23 | B30: ='1 prepared data'!U23 | C30: ='1 prepared data'!B23 | D30: ='1 prepared data'!C23 | E30: ='1 prepared data'!D23 | F30: ='1 prepared data'!E23 | G30: ='1 prepared data'!F23 | H30: ='1 prepared data'!G23 | I30: ='1 prepared data'!H23 | J30: ='1 prepared data'!I23 | ... U30: ='1 prepared data'!T23 | V30: =$AE$12+D30*$AE$13+E30*$AE$14+F30*$AE$15+G30*$AE$16+H30*$AE$17+I30*$AE$18+J30*$AE$19+K30*$AE$20+L30*$AE$21+M30*$AE$22+N30*$AE$23+O30*$AE$24+P30*$AE$25+Q30*$AE$26+R30*$AE$27+S30*$AE$28+T30*$AE$29+U30*$AE$30 | W30: =1/(1+EXP(-V30)) | X30: =-IF(C30=1,LN(W30),LN(1-W30)) | Y30: =IF(C30=1,$AE$32,$AE$33) | Z30: =Y30*X30 | AA30: =IF(W30>$AE$34,1,0) | AB30: =IF(AA30=C30,1,0) | AD30: purpose_furniture | AE30: -0.28180274 | AF30: -0.3109583
A31: ='1 prepared data'!A24 | B31: ='1 prepared data'!U24 | C31: ='1 prepared data'!B24 | D31: ='1 prepared data'!C24 | E31: ='1 prepared data'!D24 | F31: ='1 prepared data'!E24 | G31: ='1 prepared data'!F24 | H31: ='1 prepared data'!G24 | I31: ='1 prepared data'!H24 | J31: ='1 prepared data'!I24 | ... U31: ='1 prepared data'!T24 | V31: =$AE$12+D31*$AE$13+E31*$AE$14+F31*$AE$15+G31*$AE$16+H31*$AE$17+I31*$AE$18+J31*$AE$19+K31*$AE$20+L31*$AE$21+M31*$AE$22+N31*$AE$23+O31*$AE$24+P31*$AE$25+Q31*$AE$26+R31*$AE$27+S31*$AE$28+T31*$AE$29+U31*$AE$30 | W31: =1/(1+EXP(-V31)) | X31: =-IF(C31=1,LN(W31),LN(1-W31)) | Y31: =IF(C31=1,$AE$32,$AE$33) | Z31: =Y31*X31 | AA31: =IF(W31>$AE$34,1,0) | AB31: =IF(AA31=C31,1,0)
A32: ='1 prepared data'!A25 | B32: ='1 prepared data'!U25 | C32: ='1 prepared data'!B25 | D32: ='1 prepared data'!C25 | E32: ='1 prepared data'!D25 | F32: ='1 prepared data'!E25 | G32: ='1 prepared data'!F25 | H32: ='1 prepared data'!G25 | I32: ='1 prepared data'!H25 | J32: ='1 prepared data'!I25 | ... U32: ='1 prepared data'!T25 | V32: =$AE$12+D32*$AE$13+E32*$AE$14+F32*$AE$15+G32*$AE$16+H32*$AE$17+I32*$AE$18+J32*$AE$19+K32*$AE$20+L32*$AE$21+M32*$AE$22+N32*$AE$23+O32*$AE$24+P32*$AE$25+Q32*$AE$26+R32*$AE$27+S32*$AE$28+T32*$AE$29+U32*$AE$30 | W32: =1/(1+EXP(-V32)) | X32: =-IF(C32=1,LN(W32),LN(1-W32)) | Y32: =IF(C32=1,$AE$32,$AE$33) | Z32: =Y32*X32 | AA32: =IF(W32>$AE$34,1,0) | AB32: =IF(AA32=C32,1,0) | AD32: weight of class 1 (defaulter), w1 | AE32: =700/(2*210)
A33: ='1 prepared data'!A26 | B33: ='1 prepared data'!U26 | C33: ='1 prepared data'!B26 | D33: ='1 prepared data'!C26 | E33: ='1 prepared data'!D26 | F33: ='1 prepared data'!E26 | G33: ='1 prepared data'!F26 | H33: ='1 prepared data'!G26 | I33: ='1 prepared data'!H26 | J33: ='1 prepared data'!I26 | ... U33: ='1 prepared data'!T26 | V33: =$AE$12+D33*$AE$13+E33*$AE$14+F33*$AE$15+G33*$AE$16+H33*$AE$17+I33*$AE$18+J33*$AE$19+K33*$AE$20+L33*$AE$21+M33*$AE$22+N33*$AE$23+O33*$AE$24+P33*$AE$25+Q33*$AE$26+R33*$AE$27+S33*$AE$28+T33*$AE$29+U33*$AE$30 | W33: =1/(1+EXP(-V33)) | X33: =-IF(C33=1,LN(W33),LN(1-W33)) | Y33: =IF(C33=1,$AE$32,$AE$33) | Z33: =Y33*X33 | AA33: =IF(W33>$AE$34,1,0) | AB33: =IF(AA33=C33,1,0) | AD33: weight of class 0 (good payer), w0 | AE33: =700/(2*490)
A34: ='1 prepared data'!A27 | B34: ='1 prepared data'!U27 | C34: ='1 prepared data'!B27 | D34: ='1 prepared data'!C27 | E34: ='1 prepared data'!D27 | F34: ='1 prepared data'!E27 | G34: ='1 prepared data'!F27 | H34: ='1 prepared data'!G27 | I34: ='1 prepared data'!H27 | J34: ='1 prepared data'!I27 | ... U34: ='1 prepared data'!T27 | V34: =$AE$12+D34*$AE$13+E34*$AE$14+F34*$AE$15+G34*$AE$16+H34*$AE$17+I34*$AE$18+J34*$AE$19+K34*$AE$20+L34*$AE$21+M34*$AE$22+N34*$AE$23+O34*$AE$24+P34*$AE$25+Q34*$AE$26+R34*$AE$27+S34*$AE$28+T34*$AE$29+U34*$AE$30 | W34: =1/(1+EXP(-V34)) | X34: =-IF(C34=1,LN(W34),LN(1-W34)) | Y34: =IF(C34=1,$AE$32,$AE$33) | Z34: =Y34*X34 | AA34: =IF(W34>$AE$34,1,0) | AB34: =IF(AA34=C34,1,0) | AD34: threshold | AE34: 0.5
A35: ='1 prepared data'!A28 | B35: ='1 prepared data'!U28 | C35: ='1 prepared data'!B28 | D35: ='1 prepared data'!C28 | E35: ='1 prepared data'!D28 | F35: ='1 prepared data'!E28 | G35: ='1 prepared data'!F28 | H35: ='1 prepared data'!G28 | I35: ='1 prepared data'!H28 | J35: ='1 prepared data'!I28 | ... U35: ='1 prepared data'!T28 | V35: =$AE$12+D35*$AE$13+E35*$AE$14+F35*$AE$15+G35*$AE$16+H35*$AE$17+I35*$AE$18+J35*$AE$19+K35*$AE$20+L35*$AE$21+M35*$AE$22+N35*$AE$23+O35*$AE$24+P35*$AE$25+Q35*$AE$26+R35*$AE$27+S35*$AE$28+T35*$AE$29+U35*$AE$30 | W35: =1/(1+EXP(-V35)) | X35: =-IF(C35=1,LN(W35),LN(1-W35)) | Y35: =IF(C35=1,$AE$32,$AE$33) | Z35: =Y35*X35 | AA35: =IF(W35>$AE$34,1,0) | AB35: =IF(AA35=C35,1,0)
A36: ='1 prepared data'!A29 | B36: ='1 prepared data'!U29 | C36: ='1 prepared data'!B29 | D36: ='1 prepared data'!C29 | E36: ='1 prepared data'!D29 | F36: ='1 prepared data'!E29 | G36: ='1 prepared data'!F29 | H36: ='1 prepared data'!G29 | I36: ='1 prepared data'!H29 | J36: ='1 prepared data'!I29 | ... U36: ='1 prepared data'!T29 | V36: =$AE$12+D36*$AE$13+E36*$AE$14+F36*$AE$15+G36*$AE$16+H36*$AE$17+I36*$AE$18+J36*$AE$19+K36*$AE$20+L36*$AE$21+M36*$AE$22+N36*$AE$23+O36*$AE$24+P36*$AE$25+Q36*$AE$26+R36*$AE$27+S36*$AE$28+T36*$AE$29+U36*$AE$30 | W36: =1/(1+EXP(-V36)) | X36: =-IF(C36=1,LN(W36),LN(1-W36)) | Y36: =IF(C36=1,$AE$32,$AE$33) | Z36: =Y36*X36 | AA36: =IF(W36>$AE$34,1,0) | AB36: =IF(AA36=C36,1,0) | AD36: RESULTS
A37: ='1 prepared data'!A30 | B37: ='1 prepared data'!U30 | C37: ='1 prepared data'!B30 | D37: ='1 prepared data'!C30 | E37: ='1 prepared data'!D30 | F37: ='1 prepared data'!E30 | G37: ='1 prepared data'!F30 | H37: ='1 prepared data'!G30 | I37: ='1 prepared data'!H30 | J37: ='1 prepared data'!I30 | ... U37: ='1 prepared data'!T30 | V37: =$AE$12+D37*$AE$13+E37*$AE$14+F37*$AE$15+G37*$AE$16+H37*$AE$17+I37*$AE$18+J37*$AE$19+K37*$AE$20+L37*$AE$21+M37*$AE$22+N37*$AE$23+O37*$AE$24+P37*$AE$25+Q37*$AE$26+R37*$AE$27+S37*$AE$28+T37*$AE$29+U37*$AE$30 | W37: =1/(1+EXP(-V37)) | X37: =-IF(C37=1,LN(W37),LN(1-W37)) | Y37: =IF(C37=1,$AE$32,$AE$33) | Z37: =Y37*X37 | AA37: =IF(W37>$AE$34,1,0) | AB37: =IF(AA37=C37,1,0) | AD37: J = sum of weighted training losses (SOLVER OBJECTIVE) | AE37: =SUMPRODUCT(($B$12:$B$1011="training")*$Z$12:$Z$1011)
A38: ='1 prepared data'!A31 | B38: ='1 prepared data'!U31 | C38: ='1 prepared data'!B31 | D38: ='1 prepared data'!C31 | E38: ='1 prepared data'!D31 | F38: ='1 prepared data'!E31 | G38: ='1 prepared data'!F31 | H38: ='1 prepared data'!G31 | I38: ='1 prepared data'!H31 | J38: ='1 prepared data'!I31 | ... U38: ='1 prepared data'!T31 | V38: =$AE$12+D38*$AE$13+E38*$AE$14+F38*$AE$15+G38*$AE$16+H38*$AE$17+I38*$AE$18+J38*$AE$19+K38*$AE$20+L38*$AE$21+M38*$AE$22+N38*$AE$23+O38*$AE$24+P38*$AE$25+Q38*$AE$26+R38*$AE$27+S38*$AE$28+T38*$AE$29+U38*$AE$30 | W38: =1/(1+EXP(-V38)) | X38: =-IF(C38=1,LN(W38),LN(1-W38)) | Y38: =IF(C38=1,$AE$32,$AE$33) | Z38: =Y38*X38 | AA38: =IF(W38>$AE$34,1,0) | AB38: =IF(AA38=C38,1,0) | AD38: sum of row weights in training | AE38: =SUMPRODUCT(($B$12:$B$1011="training")*$Y$12:$Y$1011)
A39: ='1 prepared data'!A32 | B39: ='1 prepared data'!U32 | C39: ='1 prepared data'!B32 | D39: ='1 prepared data'!C32 | E39: ='1 prepared data'!D32 | F39: ='1 prepared data'!E32 | G39: ='1 prepared data'!F32 | H39: ='1 prepared data'!G32 | I39: ='1 prepared data'!H32 | J39: ='1 prepared data'!I32 | ... U39: ='1 prepared data'!T32 | V39: =$AE$12+D39*$AE$13+E39*$AE$14+F39*$AE$15+G39*$AE$16+H39*$AE$17+I39*$AE$18+J39*$AE$19+K39*$AE$20+L39*$AE$21+M39*$AE$22+N39*$AE$23+O39*$AE$24+P39*$AE$25+Q39*$AE$26+R39*$AE$27+S39*$AE$28+T39*$AE$29+U39*$AE$30 | W39: =1/(1+EXP(-V39)) | X39: =-IF(C39=1,LN(W39),LN(1-W39)) | Y39: =IF(C39=1,$AE$32,$AE$33) | Z39: =Y39*X39 | AA39: =IF(W39>$AE$34,1,0) | AB39: =IF(AA39=C39,1,0) | AD39: of which, class 1 | AE39: =SUMPRODUCT(($B$12:$B$1011="training")*($C$12:$C$1011=1)*$Y$12:$Y$1011)
A40: ='1 prepared data'!A33 | B40: ='1 prepared data'!U33 | C40: ='1 prepared data'!B33 | D40: ='1 prepared data'!C33 | E40: ='1 prepared data'!D33 | F40: ='1 prepared data'!E33 | G40: ='1 prepared data'!F33 | H40: ='1 prepared data'!G33 | I40: ='1 prepared data'!H33 | J40: ='1 prepared data'!I33 | ... U40: ='1 prepared data'!T33 | V40: =$AE$12+D40*$AE$13+E40*$AE$14+F40*$AE$15+G40*$AE$16+H40*$AE$17+I40*$AE$18+J40*$AE$19+K40*$AE$20+L40*$AE$21+M40*$AE$22+N40*$AE$23+O40*$AE$24+P40*$AE$25+Q40*$AE$26+R40*$AE$27+S40*$AE$28+T40*$AE$29+U40*$AE$30 | W40: =1/(1+EXP(-V40)) | X40: =-IF(C40=1,LN(W40),LN(1-W40)) | Y40: =IF(C40=1,$AE$32,$AE$33) | Z40: =Y40*X40 | AA40: =IF(W40>$AE$34,1,0) | AB40: =IF(AA40=C40,1,0) | AD40: of which, class 0 | AE40: =SUMPRODUCT(($B$12:$B$1011="training")*($C$12:$C$1011=0)*$Y$12:$Y$1011)
A41: ='1 prepared data'!A34 | B41: ='1 prepared data'!U34 | C41: ='1 prepared data'!B34 | D41: ='1 prepared data'!C34 | E41: ='1 prepared data'!D34 | F41: ='1 prepared data'!E34 | G41: ='1 prepared data'!F34 | H41: ='1 prepared data'!G34 | I41: ='1 prepared data'!H34 | J41: ='1 prepared data'!I34 | ... U41: ='1 prepared data'!T34 | V41: =$AE$12+D41*$AE$13+E41*$AE$14+F41*$AE$15+G41*$AE$16+H41*$AE$17+I41*$AE$18+J41*$AE$19+K41*$AE$20+L41*$AE$21+M41*$AE$22+N41*$AE$23+O41*$AE$24+P41*$AE$25+Q41*$AE$26+R41*$AE$27+S41*$AE$28+T41*$AE$29+U41*$AE$30 | W41: =1/(1+EXP(-V41)) | X41: =-IF(C41=1,LN(W41),LN(1-W41)) | Y41: =IF(C41=1,$AE$32,$AE$33) | Z41: =Y41*X41 | AA41: =IF(W41>$AE$34,1,0) | AB41: =IF(AA41=C41,1,0) | AD41: average testing loss (unweighted) | AE41: =SUMPRODUCT(($B$12:$B$1011="testing")*$X$12:$X$1011)/COUNTIF($B$12:$B$1011,"testing")
A42: ='1 prepared data'!A35 | B42: ='1 prepared data'!U35 | C42: ='1 prepared data'!B35 | D42: ='1 prepared data'!C35 | E42: ='1 prepared data'!D35 | F42: ='1 prepared data'!E35 | G42: ='1 prepared data'!F35 | H42: ='1 prepared data'!G35 | I42: ='1 prepared data'!H35 | J42: ='1 prepared data'!I35 | ... U42: ='1 prepared data'!T35 | V42: =$AE$12+D42*$AE$13+E42*$AE$14+F42*$AE$15+G42*$AE$16+H42*$AE$17+I42*$AE$18+J42*$AE$19+K42*$AE$20+L42*$AE$21+M42*$AE$22+N42*$AE$23+O42*$AE$24+P42*$AE$25+Q42*$AE$26+R42*$AE$27+S42*$AE$28+T42*$AE$29+U42*$AE$30 | W42: =1/(1+EXP(-V42)) | X42: =-IF(C42=1,LN(W42),LN(1-W42)) | Y42: =IF(C42=1,$AE$32,$AE$33) | Z42: =Y42*X42 | AA42: =IF(W42>$AE$34,1,0) | AB42: =IF(AA42=C42,1,0) | AD42: average p on testing (the actual rate is 0.300) | AE42: =SUMPRODUCT(($B$12:$B$1011="testing")*$W$12:$W$1011)/COUNTIF($B$12:$B$1011,"testing")
A43: ='1 prepared data'!A36 | B43: ='1 prepared data'!U36 | C43: ='1 prepared data'!B36 | D43: ='1 prepared data'!C36 | E43: ='1 prepared data'!D36 | F43: ='1 prepared data'!E36 | G43: ='1 prepared data'!F36 | H43: ='1 prepared data'!G36 | I43: ='1 prepared data'!H36 | J43: ='1 prepared data'!I36 | ... U43: ='1 prepared data'!T36 | V43: =$AE$12+D43*$AE$13+E43*$AE$14+F43*$AE$15+G43*$AE$16+H43*$AE$17+I43*$AE$18+J43*$AE$19+K43*$AE$20+L43*$AE$21+M43*$AE$22+N43*$AE$23+O43*$AE$24+P43*$AE$25+Q43*$AE$26+R43*$AE$27+S43*$AE$28+T43*$AE$29+U43*$AE$30 | W43: =1/(1+EXP(-V43)) | X43: =-IF(C43=1,LN(W43),LN(1-W43)) | Y43: =IF(C43=1,$AE$32,$AE$33) | Z43: =Y43*X43 | AA43: =IF(W43>$AE$34,1,0) | AB43: =IF(AA43=C43,1,0) | AD43: testing accuracy | AE43: =SUMPRODUCT(($B$12:$B$1011="testing")*$AB$12:$AB$1011)/COUNTIF($B$12:$B$1011,"testing")
A44: ='1 prepared data'!A37 | B44: ='1 prepared data'!U37 | C44: ='1 prepared data'!B37 | D44: ='1 prepared data'!C37 | E44: ='1 prepared data'!D37 | F44: ='1 prepared data'!E37 | G44: ='1 prepared data'!F37 | H44: ='1 prepared data'!G37 | I44: ='1 prepared data'!H37 | J44: ='1 prepared data'!I37 | ... U44: ='1 prepared data'!T37 | V44: =$AE$12+D44*$AE$13+E44*$AE$14+F44*$AE$15+G44*$AE$16+H44*$AE$17+I44*$AE$18+J44*$AE$19+K44*$AE$20+L44*$AE$21+M44*$AE$22+N44*$AE$23+O44*$AE$24+P44*$AE$25+Q44*$AE$26+R44*$AE$27+S44*$AE$28+T44*$AE$29+U44*$AE$30 | W44: =1/(1+EXP(-V44)) | X44: =-IF(C44=1,LN(W44),LN(1-W44)) | Y44: =IF(C44=1,$AE$32,$AE$33) | Z44: =Y44*X44 | AA44: =IF(W44>$AE$34,1,0) | AB44: =IF(AA44=C44,1,0) | AD44: scikit-learn reference: class 1 recall on testing (threshold 0.5) | AE44: 0.85555556
A45: ='1 prepared data'!A38 | B45: ='1 prepared data'!U38 | C45: ='1 prepared data'!B38 | D45: ='1 prepared data'!C38 | E45: ='1 prepared data'!D38 | F45: ='1 prepared data'!E38 | G45: ='1 prepared data'!F38 | H45: ='1 prepared data'!G38 | I45: ='1 prepared data'!H38 | J45: ='1 prepared data'!I38 | ... U45: ='1 prepared data'!T38 | V45: =$AE$12+D45*$AE$13+E45*$AE$14+F45*$AE$15+G45*$AE$16+H45*$AE$17+I45*$AE$18+J45*$AE$19+K45*$AE$20+L45*$AE$21+M45*$AE$22+N45*$AE$23+O45*$AE$24+P45*$AE$25+Q45*$AE$26+R45*$AE$27+S45*$AE$28+T45*$AE$29+U45*$AE$30 | W45: =1/(1+EXP(-V45)) | X45: =-IF(C45=1,LN(W45),LN(1-W45)) | Y45: =IF(C45=1,$AE$32,$AE$33) | Z45: =Y45*X45 | AA45: =IF(W45>$AE$34,1,0) | AB45: =IF(AA45=C45,1,0) | AD45: scikit-learn reference: class 1 precision on testing | AE45: 0.52739726
A46: ='1 prepared data'!A39 | B46: ='1 prepared data'!U39 | C46: ='1 prepared data'!B39 | D46: ='1 prepared data'!C39 | E46: ='1 prepared data'!D39 | F46: ='1 prepared data'!E39 | G46: ='1 prepared data'!F39 | H46: ='1 prepared data'!G39 | I46: ='1 prepared data'!H39 | J46: ='1 prepared data'!I39 | ... U46: ='1 prepared data'!T39 | V46: =$AE$12+D46*$AE$13+E46*$AE$14+F46*$AE$15+G46*$AE$16+H46*$AE$17+I46*$AE$18+J46*$AE$19+K46*$AE$20+L46*$AE$21+M46*$AE$22+N46*$AE$23+O46*$AE$24+P46*$AE$25+Q46*$AE$26+R46*$AE$27+S46*$AE$28+T46*$AE$29+U46*$AE$30 | W46: =1/(1+EXP(-V46)) | X46: =-IF(C46=1,LN(W46),LN(1-W46)) | Y46: =IF(C46=1,$AE$32,$AE$33) | Z46: =Y46*X46 | AA46: =IF(W46>$AE$34,1,0) | AB46: =IF(AA46=C46,1,0) | AD46: scikit-learn reference: testing AUC | AE46: 0.82391534
A47: ='1 prepared data'!A40 | B47: ='1 prepared data'!U40 | C47: ='1 prepared data'!B40 | D47: ='1 prepared data'!C40 | E47: ='1 prepared data'!D40 | F47: ='1 prepared data'!E40 | G47: ='1 prepared data'!F40 | H47: ='1 prepared data'!G40 | I47: ='1 prepared data'!H40 | J47: ='1 prepared data'!I40 | ... U47: ='1 prepared data'!T40 | V47: =$AE$12+D47*$AE$13+E47*$AE$14+F47*$AE$15+G47*$AE$16+H47*$AE$17+I47*$AE$18+J47*$AE$19+K47*$AE$20+L47*$AE$21+M47*$AE$22+N47*$AE$23+O47*$AE$24+P47*$AE$25+Q47*$AE$26+R47*$AE$27+S47*$AE$28+T47*$AE$29+U47*$AE$30 | W47: =1/(1+EXP(-V47)) | X47: =-IF(C47=1,LN(W47),LN(1-W47)) | Y47: =IF(C47=1,$AE$32,$AE$33) | Z47: =Y47*X47 | AA47: =IF(W47>$AE$34,1,0) | AB47: =IF(AA47=C47,1,0)
A48: ='1 prepared data'!A41 | B48: ='1 prepared data'!U41 | C48: ='1 prepared data'!B41 | D48: ='1 prepared data'!C41 | E48: ='1 prepared data'!D41 | F48: ='1 prepared data'!E41 | G48: ='1 prepared data'!F41 | H48: ='1 prepared data'!G41 | I48: ='1 prepared data'!H41 | J48: ='1 prepared data'!I41 | ... U48: ='1 prepared data'!T41 | V48: =$AE$12+D48*$AE$13+E48*$AE$14+F48*$AE$15+G48*$AE$16+H48*$AE$17+I48*$AE$18+J48*$AE$19+K48*$AE$20+L48*$AE$21+M48*$AE$22+N48*$AE$23+O48*$AE$24+P48*$AE$25+Q48*$AE$26+R48*$AE$27+S48*$AE$28+T48*$AE$29+U48*$AE$30 | W48: =1/(1+EXP(-V48)) | X48: =-IF(C48=1,LN(W48),LN(1-W48)) | Y48: =IF(C48=1,$AE$32,$AE$33) | Z48: =Y48*X48 | AA48: =IF(W48>$AE$34,1,0) | AB48: =IF(AA48=C48,1,0) | AD48: Solver: minimize J by changing the light blue model weight cells (not the class weight cells), GRG Nonlinear, central derivatives, convergence 0.000001, no constraints and with 'Make Unconstrained Variables Non-Negative' UNTICKED. Run twice if it stops early.
A49: ='1 prepared data'!A42 | B49: ='1 prepared data'!U42 | C49: ='1 prepared data'!B42 | D49: ='1 prepared data'!C42 | E49: ='1 prepared data'!D42 | F49: ='1 prepared data'!E42 | G49: ='1 prepared data'!F42 | H49: ='1 prepared data'!G42 | I49: ='1 prepared data'!H42 | J49: ='1 prepared data'!I42 | ... U49: ='1 prepared data'!T42 | V49: =$AE$12+D49*$AE$13+E49*$AE$14+F49*$AE$15+G49*$AE$16+H49*$AE$17+I49*$AE$18+J49*$AE$19+K49*$AE$20+L49*$AE$21+M49*$AE$22+N49*$AE$23+O49*$AE$24+P49*$AE$25+Q49*$AE$26+R49*$AE$27+S49*$AE$28+T49*$AE$29+U49*$AE$30 | W49: =1/(1+EXP(-V49)) | X49: =-IF(C49=1,LN(W49),LN(1-W49)) | Y49: =IF(C49=1,$AE$32,$AE$33) | Z49: =Y49*X49 | AA49: =IF(W49>$AE$34,1,0) | AB49: =IF(AA49=C49,1,0)
A50: ='1 prepared data'!A43 | B50: ='1 prepared data'!U43 | C50: ='1 prepared data'!B43 | D50: ='1 prepared data'!C43 | E50: ='1 prepared data'!D43 | F50: ='1 prepared data'!E43 | G50: ='1 prepared data'!F43 | H50: ='1 prepared data'!G43 | I50: ='1 prepared data'!H43 | J50: ='1 prepared data'!I43 | ... U50: ='1 prepared data'!T43 | V50: =$AE$12+D50*$AE$13+E50*$AE$14+F50*$AE$15+G50*$AE$16+H50*$AE$17+I50*$AE$18+J50*$AE$19+K50*$AE$20+L50*$AE$21+M50*$AE$22+N50*$AE$23+O50*$AE$24+P50*$AE$25+Q50*$AE$26+R50*$AE$27+S50*$AE$28+T50*$AE$29+U50*$AE$30 | W50: =1/(1+EXP(-V50)) | X50: =-IF(C50=1,LN(W50),LN(1-W50)) | Y50: =IF(C50=1,$AE$32,$AE$33) | Z50: =Y50*X50 | AA50: =IF(W50>$AE$34,1,0) | AB50: =IF(AA50=C50,1,0)
A51: ='1 prepared data'!A44 | B51: ='1 prepared data'!U44 | C51: ='1 prepared data'!B44 | D51: ='1 prepared data'!C44 | E51: ='1 prepared data'!D44 | F51: ='1 prepared data'!E44 | G51: ='1 prepared data'!F44 | H51: ='1 prepared data'!G44 | I51: ='1 prepared data'!H44 | J51: ='1 prepared data'!I44 | ... U51: ='1 prepared data'!T44 | V51: =$AE$12+D51*$AE$13+E51*$AE$14+F51*$AE$15+G51*$AE$16+H51*$AE$17+I51*$AE$18+J51*$AE$19+K51*$AE$20+L51*$AE$21+M51*$AE$22+N51*$AE$23+O51*$AE$24+P51*$AE$25+Q51*$AE$26+R51*$AE$27+S51*$AE$28+T51*$AE$29+U51*$AE$30 | W51: =1/(1+EXP(-V51)) | X51: =-IF(C51=1,LN(W51),LN(1-W51)) | Y51: =IF(C51=1,$AE$32,$AE$33) | Z51: =Y51*X51 | AA51: =IF(W51>$AE$34,1,0) | AB51: =IF(AA51=C51,1,0)
A52: ='1 prepared data'!A45 | B52: ='1 prepared data'!U45 | C52: ='1 prepared data'!B45 | D52: ='1 prepared data'!C45 | E52: ='1 prepared data'!D45 | F52: ='1 prepared data'!E45 | G52: ='1 prepared data'!F45 | H52: ='1 prepared data'!G45 | I52: ='1 prepared data'!H45 | J52: ='1 prepared data'!I45 | ... U52: ='1 prepared data'!T45 | V52: =$AE$12+D52*$AE$13+E52*$AE$14+F52*$AE$15+G52*$AE$16+H52*$AE$17+I52*$AE$18+J52*$AE$19+K52*$AE$20+L52*$AE$21+M52*$AE$22+N52*$AE$23+O52*$AE$24+P52*$AE$25+Q52*$AE$26+R52*$AE$27+S52*$AE$28+T52*$AE$29+U52*$AE$30 | W52: =1/(1+EXP(-V52)) | X52: =-IF(C52=1,LN(W52),LN(1-W52)) | Y52: =IF(C52=1,$AE$32,$AE$33) | Z52: =Y52*X52 | AA52: =IF(W52>$AE$34,1,0) | AB52: =IF(AA52=C52,1,0)
A53: ='1 prepared data'!A46 | B53: ='1 prepared data'!U46 | C53: ='1 prepared data'!B46 | D53: ='1 prepared data'!C46 | E53: ='1 prepared data'!D46 | F53: ='1 prepared data'!E46 | G53: ='1 prepared data'!F46 | H53: ='1 prepared data'!G46 | I53: ='1 prepared data'!H46 | J53: ='1 prepared data'!I46 | ... U53: ='1 prepared data'!T46 | V53: =$AE$12+D53*$AE$13+E53*$AE$14+F53*$AE$15+G53*$AE$16+H53*$AE$17+I53*$AE$18+J53*$AE$19+K53*$AE$20+L53*$AE$21+M53*$AE$22+N53*$AE$23+O53*$AE$24+P53*$AE$25+Q53*$AE$26+R53*$AE$27+S53*$AE$28+T53*$AE$29+U53*$AE$30 | W53: =1/(1+EXP(-V53)) | X53: =-IF(C53=1,LN(W53),LN(1-W53)) | Y53: =IF(C53=1,$AE$32,$AE$33) | Z53: =Y53*X53 | AA53: =IF(W53>$AE$34,1,0) | AB53: =IF(AA53=C53,1,0)
A54: ='1 prepared data'!A47 | B54: ='1 prepared data'!U47 | C54: ='1 prepared data'!B47 | D54: ='1 prepared data'!C47 | E54: ='1 prepared data'!D47 | F54: ='1 prepared data'!E47 | G54: ='1 prepared data'!F47 | H54: ='1 prepared data'!G47 | I54: ='1 prepared data'!H47 | J54: ='1 prepared data'!I47 | ... U54: ='1 prepared data'!T47 | V54: =$AE$12+D54*$AE$13+E54*$AE$14+F54*$AE$15+G54*$AE$16+H54*$AE$17+I54*$AE$18+J54*$AE$19+K54*$AE$20+L54*$AE$21+M54*$AE$22+N54*$AE$23+O54*$AE$24+P54*$AE$25+Q54*$AE$26+R54*$AE$27+S54*$AE$28+T54*$AE$29+U54*$AE$30 | W54: =1/(1+EXP(-V54)) | X54: =-IF(C54=1,LN(W54),LN(1-W54)) | Y54: =IF(C54=1,$AE$32,$AE$33) | Z54: =Y54*X54 | AA54: =IF(W54>$AE$34,1,0) | AB54: =IF(AA54=C54,1,0)
A55: ='1 prepared data'!A48 | B55: ='1 prepared data'!U48 | C55: ='1 prepared data'!B48 | D55: ='1 prepared data'!C48 | E55: ='1 prepared data'!D48 | F55: ='1 prepared data'!E48 | G55: ='1 prepared data'!F48 | H55: ='1 prepared data'!G48 | I55: ='1 prepared data'!H48 | J55: ='1 prepared data'!I48 | ... U55: ='1 prepared data'!T48 | V55: =$AE$12+D55*$AE$13+E55*$AE$14+F55*$AE$15+G55*$AE$16+H55*$AE$17+I55*$AE$18+J55*$AE$19+K55*$AE$20+L55*$AE$21+M55*$AE$22+N55*$AE$23+O55*$AE$24+P55*$AE$25+Q55*$AE$26+R55*$AE$27+S55*$AE$28+T55*$AE$29+U55*$AE$30 | W55: =1/(1+EXP(-V55)) | X55: =-IF(C55=1,LN(W55),LN(1-W55)) | Y55: =IF(C55=1,$AE$32,$AE$33) | Z55: =Y55*X55 | AA55: =IF(W55>$AE$34,1,0) | AB55: =IF(AA55=C55,1,0)
A56: ='1 prepared data'!A49 | B56: ='1 prepared data'!U49 | C56: ='1 prepared data'!B49 | D56: ='1 prepared data'!C49 | E56: ='1 prepared data'!D49 | F56: ='1 prepared data'!E49 | G56: ='1 prepared data'!F49 | H56: ='1 prepared data'!G49 | I56: ='1 prepared data'!H49 | J56: ='1 prepared data'!I49 | ... U56: ='1 prepared data'!T49 | V56: =$AE$12+D56*$AE$13+E56*$AE$14+F56*$AE$15+G56*$AE$16+H56*$AE$17+I56*$AE$18+J56*$AE$19+K56*$AE$20+L56*$AE$21+M56*$AE$22+N56*$AE$23+O56*$AE$24+P56*$AE$25+Q56*$AE$26+R56*$AE$27+S56*$AE$28+T56*$AE$29+U56*$AE$30 | W56: =1/(1+EXP(-V56)) | X56: =-IF(C56=1,LN(W56),LN(1-W56)) | Y56: =IF(C56=1,$AE$32,$AE$33) | Z56: =Y56*X56 | AA56: =IF(W56>$AE$34,1,0) | AB56: =IF(AA56=C56,1,0)
A57: ='1 prepared data'!A50 | B57: ='1 prepared data'!U50 | C57: ='1 prepared data'!B50 | D57: ='1 prepared data'!C50 | E57: ='1 prepared data'!D50 | F57: ='1 prepared data'!E50 | G57: ='1 prepared data'!F50 | H57: ='1 prepared data'!G50 | I57: ='1 prepared data'!H50 | J57: ='1 prepared data'!I50 | ... U57: ='1 prepared data'!T50 | V57: =$AE$12+D57*$AE$13+E57*$AE$14+F57*$AE$15+G57*$AE$16+H57*$AE$17+I57*$AE$18+J57*$AE$19+K57*$AE$20+L57*$AE$21+M57*$AE$22+N57*$AE$23+O57*$AE$24+P57*$AE$25+Q57*$AE$26+R57*$AE$27+S57*$AE$28+T57*$AE$29+U57*$AE$30 | W57: =1/(1+EXP(-V57)) | X57: =-IF(C57=1,LN(W57),LN(1-W57)) | Y57: =IF(C57=1,$AE$32,$AE$33) | Z57: =Y57*X57 | AA57: =IF(W57>$AE$34,1,0) | AB57: =IF(AA57=C57,1,0)
A58: ='1 prepared data'!A51 | B58: ='1 prepared data'!U51 | C58: ='1 prepared data'!B51 | D58: ='1 prepared data'!C51 | E58: ='1 prepared data'!D51 | F58: ='1 prepared data'!E51 | G58: ='1 prepared data'!F51 | H58: ='1 prepared data'!G51 | I58: ='1 prepared data'!H51 | J58: ='1 prepared data'!I51 | ... U58: ='1 prepared data'!T51 | V58: =$AE$12+D58*$AE$13+E58*$AE$14+F58*$AE$15+G58*$AE$16+H58*$AE$17+I58*$AE$18+J58*$AE$19+K58*$AE$20+L58*$AE$21+M58*$AE$22+N58*$AE$23+O58*$AE$24+P58*$AE$25+Q58*$AE$26+R58*$AE$27+S58*$AE$28+T58*$AE$29+U58*$AE$30 | W58: =1/(1+EXP(-V58)) | X58: =-IF(C58=1,LN(W58),LN(1-W58)) | Y58: =IF(C58=1,$AE$32,$AE$33) | Z58: =Y58*X58 | AA58: =IF(W58>$AE$34,1,0) | AB58: =IF(AA58=C58,1,0)
A59: ='1 prepared data'!A52 | B59: ='1 prepared data'!U52 | C59: ='1 prepared data'!B52 | D59: ='1 prepared data'!C52 | E59: ='1 prepared data'!D52 | F59: ='1 prepared data'!E52 | G59: ='1 prepared data'!F52 | H59: ='1 prepared data'!G52 | I59: ='1 prepared data'!H52 | J59: ='1 prepared data'!I52 | ... U59: ='1 prepared data'!T52 | V59: =$AE$12+D59*$AE$13+E59*$AE$14+F59*$AE$15+G59*$AE$16+H59*$AE$17+I59*$AE$18+J59*$AE$19+K59*$AE$20+L59*$AE$21+M59*$AE$22+N59*$AE$23+O59*$AE$24+P59*$AE$25+Q59*$AE$26+R59*$AE$27+S59*$AE$28+T59*$AE$29+U59*$AE$30 | W59: =1/(1+EXP(-V59)) | X59: =-IF(C59=1,LN(W59),LN(1-W59)) | Y59: =IF(C59=1,$AE$32,$AE$33) | Z59: =Y59*X59 | AA59: =IF(W59>$AE$34,1,0) | AB59: =IF(AA59=C59,1,0)
A60: ='1 prepared data'!A53 | B60: ='1 prepared data'!U53 | C60: ='1 prepared data'!B53 | D60: ='1 prepared data'!C53 | E60: ='1 prepared data'!D53 | F60: ='1 prepared data'!E53 | G60: ='1 prepared data'!F53 | H60: ='1 prepared data'!G53 | I60: ='1 prepared data'!H53 | J60: ='1 prepared data'!I53 | ... U60: ='1 prepared data'!T53 | V60: =$AE$12+D60*$AE$13+E60*$AE$14+F60*$AE$15+G60*$AE$16+H60*$AE$17+I60*$AE$18+J60*$AE$19+K60*$AE$20+L60*$AE$21+M60*$AE$22+N60*$AE$23+O60*$AE$24+P60*$AE$25+Q60*$AE$26+R60*$AE$27+S60*$AE$28+T60*$AE$29+U60*$AE$30 | W60: =1/(1+EXP(-V60)) | X60: =-IF(C60=1,LN(W60),LN(1-W60)) | Y60: =IF(C60=1,$AE$32,$AE$33) | Z60: =Y60*X60 | AA60: =IF(W60>$AE$34,1,0) | AB60: =IF(AA60=C60,1,0)
... A1011: ='1 prepared data'!A1004 | B1011: ='1 prepared data'!U1004 | C1011: ='1 prepared data'!B1004 | D1011: ='1 prepared data'!C1004 | E1011: ='1 prepared data'!D1004 | F1011: ='1 prepared data'!E1004 | G1011: ='1 prepared data'!F1004 | H1011: ='1 prepared data'!G1004 | I1011: ='1 prepared data'!H1004 | J1011: ='1 prepared data'!I1004 | ... U1011: ='1 prepared data'!T1004 | V1011: =$AE$12+D1011*$AE$13+E1011*$AE$14+F1011*$AE$15+G1011*$AE$16+H1011*$AE$17+I1011*$AE$18+J1011*$AE$19+K1011*$AE$20+L1011*$AE$21+M1011*$AE$22+N1011*$AE$23+O1011*$AE$24+P1011*$AE$25+Q1011*$AE$26+R1011*$AE$27+S1011*$AE$28+T1011*$AE$29+U1011*$AE$30 | W1011: =1/(1+EXP(-V1011)) | X1011: =-IF(C1011=1,LN(W1011),LN(1-W1011)) | Y1011: =IF(C1011=1,$AE$32,$AE$33) | Z1011: =Y1011*X1011 | AA1011: =IF(W1011>$AE$34,1,0) | AB1011: =IF(AA1011=C1011,1,0)

Sheet 4 undersampling
A1: Undersampling: randomly dropping good payers until they match the defaulters
A2: Instead of weighting, 280 of the 490 good payers are removed from training, chosen at random, and the model is trained on 210 and 210. The column 'row weight' equals 1 for the rows that stay and 0 for those that leave, so the discarded ones contribute nothing to J. Testing stays complete, with its 300 customers: the only sample that is touched is the training sample.
A3: It is the simplest fix and the cheapest to run, which is why it is used so much with huge datasets. Its cost is obvious: 280 real customers with information are thrown away. In this dataset it shows little (the recall of class 1 ends up similar to class weights) but the model is somewhat worse in AUC, and with fewer rows the result depends more on which good payers happened to be drawn. The notebook shows this by repeating the draw several times.
AD10: Model weights (theta): start from the unbalanced solution | AI10: EVALUATION ON TESTING (with the light blue threshold)
A11: id | B11: set | C11: y | D11: duration | E11: amount | F11: age | G11: installment_pct_income | H11: chk_negative | I11: chk_0_200 | J11: chk_over_200 | K11: hist_critical | L11: hist_delays | M11: hist_no_credits | N11: sav_100_1000 | O11: sav_over_1000 | P11: sav_unknown | Q11: housing_rent | R11: housing_free | S11: purpose_car | T11: purpose_radio_tv | U11: purpose_furniture | V11: Z (line) | W11: p (logistic) | X11: loss | Y11: row weight | Z11: weighted loss | AA11: prediction | AB11: correct | AD11: variable | AE11: theta (light blue) | AF11: scikit-learn reference for this variant
A12: ='1 prepared data'!A5 | B12: ='1 prepared data'!U5 | C12: ='1 prepared data'!B5 | D12: ='1 prepared data'!C5 | E12: ='1 prepared data'!D5 | F12: ='1 prepared data'!E5 | G12: ='1 prepared data'!F5 | H12: ='1 prepared data'!G5 | I12: ='1 prepared data'!H5 | J12: ='1 prepared data'!I5 | ... U12: ='1 prepared data'!T5 | V12: =$AE$12+D12*$AE$13+E12*$AE$14+F12*$AE$15+G12*$AE$16+H12*$AE$17+I12*$AE$18+J12*$AE$19+K12*$AE$20+L12*$AE$21+M12*$AE$22+N12*$AE$23+O12*$AE$24+P12*$AE$25+Q12*$AE$26+R12*$AE$27+S12*$AE$28+T12*$AE$29+U12*$AE$30 | W12: =1/(1+EXP(-V12)) | X12: =-IF(C12=1,LN(W12),LN(1-W12)) | Y12: ='1 prepared data'!V5 | Z12: =Y12*X12 | AA12: =IF(W12>$AE$33,1,0) | AB12: =IF(AA12=C12,1,0) | AD12: intercept | AE12: -1.341271 | AF12: -0.56426777
A13: ='1 prepared data'!A6 | B13: ='1 prepared data'!U6 | C13: ='1 prepared data'!B6 | D13: ='1 prepared data'!C6 | E13: ='1 prepared data'!D6 | F13: ='1 prepared data'!E6 | G13: ='1 prepared data'!F6 | H13: ='1 prepared data'!G6 | I13: ='1 prepared data'!H6 | J13: ='1 prepared data'!I6 | ... U13: ='1 prepared data'!T6 | V13: =$AE$12+D13*$AE$13+E13*$AE$14+F13*$AE$15+G13*$AE$16+H13*$AE$17+I13*$AE$18+J13*$AE$19+K13*$AE$20+L13*$AE$21+M13*$AE$22+N13*$AE$23+O13*$AE$24+P13*$AE$25+Q13*$AE$26+R13*$AE$27+S13*$AE$28+T13*$AE$29+U13*$AE$30 | W13: =1/(1+EXP(-V13)) | X13: =-IF(C13=1,LN(W13),LN(1-W13)) | Y13: ='1 prepared data'!V6 | Z13: =Y13*X13 | AA13: =IF(W13>$AE$33,1,0) | AB13: =IF(AA13=C13,1,0) | AD13: duration | AE13: 0.32470125 | AF13: 0.15390117 | AK13: predicted 0 | AL13: predicted 1 | AM13: total
A14: ='1 prepared data'!A7 | B14: ='1 prepared data'!U7 | C14: ='1 prepared data'!B7 | D14: ='1 prepared data'!C7 | E14: ='1 prepared data'!D7 | F14: ='1 prepared data'!E7 | G14: ='1 prepared data'!F7 | H14: ='1 prepared data'!G7 | I14: ='1 prepared data'!H7 | J14: ='1 prepared data'!I7 | ... U14: ='1 prepared data'!T7 | V14: =$AE$12+D14*$AE$13+E14*$AE$14+F14*$AE$15+G14*$AE$16+H14*$AE$17+I14*$AE$18+J14*$AE$19+K14*$AE$20+L14*$AE$21+M14*$AE$22+N14*$AE$23+O14*$AE$24+P14*$AE$25+Q14*$AE$26+R14*$AE$27+S14*$AE$28+T14*$AE$29+U14*$AE$30 | W14: =1/(1+EXP(-V14)) | X14: =-IF(C14=1,LN(W14),LN(1-W14)) | Y14: ='1 prepared data'!V7 | Z14: =Y14*X14 | AA14: =IF(W14>$AE$33,1,0) | AB14: =IF(AA14=C14,1,0) | AD14: amount | AE14: 0.11635359 | AF14: 0.23866207 | AI14: actual 0 (good payer) | AJ14: TN | FP | AK14: =COUNTIFS($B$12:$B$1011,"testing",$C$12:$C$1011,0,$AA$12:$AA$1011,0) | AL14: =COUNTIFS($B$12:$B$1011,"testing",$C$12:$C$1011,0,$AA$12:$AA$1011,1) | AM14: =AK14+AL14
A15: ='1 prepared data'!A8 | B15: ='1 prepared data'!U8 | C15: ='1 prepared data'!B8 | D15: ='1 prepared data'!C8 | E15: ='1 prepared data'!D8 | F15: ='1 prepared data'!E8 | G15: ='1 prepared data'!F8 | H15: ='1 prepared data'!G8 | I15: ='1 prepared data'!H8 | J15: ='1 prepared data'!I8 | ... U15: ='1 prepared data'!T8 | V15: =$AE$12+D15*$AE$13+E15*$AE$14+F15*$AE$15+G15*$AE$16+H15*$AE$17+I15*$AE$18+J15*$AE$19+K15*$AE$20+L15*$AE$21+M15*$AE$22+N15*$AE$23+O15*$AE$24+P15*$AE$25+Q15*$AE$26+R15*$AE$27+S15*$AE$28+T15*$AE$29+U15*$AE$30 | W15: =1/(1+EXP(-V15)) | X15: =-IF(C15=1,LN(W15),LN(1-W15)) | Y15: ='1 prepared data'!V8 | Z15: =Y15*X15 | AA15: =IF(W15>$AE$33,1,0) | AB15: =IF(AA15=C15,1,0) | AD15: age | AE15: -0.099145225 | AF15: -0.093410688 | AI15: actual 1 (defaulter) | AJ15: FN | TP | AK15: =COUNTIFS($B$12:$B$1011,"testing",$C$12:$C$1011,1,$AA$12:$AA$1011,0) | AL15: =COUNTIFS($B$12:$B$1011,"testing",$C$12:$C$1011,1,$AA$12:$AA$1011,1) | AM15: =AK15+AL15
A16: ='1 prepared data'!A9 | B16: ='1 prepared data'!U9 | C16: ='1 prepared data'!B9 | D16: ='1 prepared data'!C9 | E16: ='1 prepared data'!D9 | F16: ='1 prepared data'!E9 | G16: ='1 prepared data'!F9 | H16: ='1 prepared data'!G9 | I16: ='1 prepared data'!H9 | J16: ='1 prepared data'!I9 | ... U16: ='1 prepared data'!T9 | V16: =$AE$12+D16*$AE$13+E16*$AE$14+F16*$AE$15+G16*$AE$16+H16*$AE$17+I16*$AE$18+J16*$AE$19+K16*$AE$20+L16*$AE$21+M16*$AE$22+N16*$AE$23+O16*$AE$24+P16*$AE$25+Q16*$AE$26+R16*$AE$27+S16*$AE$28+T16*$AE$29+U16*$AE$30 | W16: =1/(1+EXP(-V16)) | X16: =-IF(C16=1,LN(W16),LN(1-W16)) | Y16: ='1 prepared data'!V9 | Z16: =Y16*X16 | AA16: =IF(W16>$AE$33,1,0) | AB16: =IF(AA16=C16,1,0) | AD16: installment_pct_income | AE16: 0.28721577 | AF16: 0.39151548 | AI16: total | AK16: =AK14+AK15 | AL16: =AL14+AL15 | AM16: =AM14+AM15
A17: ='1 prepared data'!A10 | B17: ='1 prepared data'!U10 | C17: ='1 prepared data'!B10 | D17: ='1 prepared data'!C10 | E17: ='1 prepared data'!D10 | F17: ='1 prepared data'!E10 | G17: ='1 prepared data'!F10 | H17: ='1 prepared data'!G10 | I17: ='1 prepared data'!H10 | J17: ='1 prepared data'!I10 | ... U17: ='1 prepared data'!T10 | V17: =$AE$12+D17*$AE$13+E17*$AE$14+F17*$AE$15+G17*$AE$16+H17*$AE$17+I17*$AE$18+J17*$AE$19+K17*$AE$20+L17*$AE$21+M17*$AE$22+N17*$AE$23+O17*$AE$24+P17*$AE$25+Q17*$AE$26+R17*$AE$27+S17*$AE$28+T17*$AE$29+U17*$AE$30 | W17: =1/(1+EXP(-V17)) | X17: =-IF(C17=1,LN(W17),LN(1-W17)) | Y17: ='1 prepared data'!V10 | Z17: =Y17*X17 | AA17: =IF(W17>$AE$33,1,0) | AB17: =IF(AA17=C17,1,0) | AD17: chk_negative | AE17: 1.5464027 | AF17: 1.7658144
A18: ='1 prepared data'!A11 | B18: ='1 prepared data'!U11 | C18: ='1 prepared data'!B11 | D18: ='1 prepared data'!C11 | E18: ='1 prepared data'!D11 | F18: ='1 prepared data'!E11 | G18: ='1 prepared data'!F11 | H18: ='1 prepared data'!G11 | I18: ='1 prepared data'!H11 | J18: ='1 prepared data'!I11 | ... U18: ='1 prepared data'!T11 | V18: =$AE$12+D18*$AE$13+E18*$AE$14+F18*$AE$15+G18*$AE$16+H18*$AE$17+I18*$AE$18+J18*$AE$19+K18*$AE$20+L18*$AE$21+M18*$AE$22+N18*$AE$23+O18*$AE$24+P18*$AE$25+Q18*$AE$26+R18*$AE$27+S18*$AE$28+T18*$AE$29+U18*$AE$30 | W18: =1/(1+EXP(-V18)) | X18: =-IF(C18=1,LN(W18),LN(1-W18)) | Y18: ='1 prepared data'!V11 | Z18: =Y18*X18 | AA18: =IF(W18>$AE$33,1,0) | AB18: =IF(AA18=C18,1,0) | AD18: chk_0_200 | AE18: 1.2949978 | AF18: 1.213918 | AJ18: precision | AK18: recall | AL18: f1-score | AM18: support
A19: ='1 prepared data'!A12 | B19: ='1 prepared data'!U12 | C19: ='1 prepared data'!B12 | D19: ='1 prepared data'!C12 | E19: ='1 prepared data'!D12 | F19: ='1 prepared data'!E12 | G19: ='1 prepared data'!F12 | H19: ='1 prepared data'!G12 | I19: ='1 prepared data'!H12 | J19: ='1 prepared data'!I12 | ... U19: ='1 prepared data'!T12 | V19: =$AE$12+D19*$AE$13+E19*$AE$14+F19*$AE$15+G19*$AE$16+H19*$AE$17+I19*$AE$18+J19*$AE$19+K19*$AE$20+L19*$AE$21+M19*$AE$22+N19*$AE$23+O19*$AE$24+P19*$AE$25+Q19*$AE$26+R19*$AE$27+S19*$AE$28+T19*$AE$29+U19*$AE$30 | W19: =1/(1+EXP(-V19)) | X19: =-IF(C19=1,LN(W19),LN(1-W19)) | Y19: ='1 prepared data'!V12 | Z19: =Y19*X19 | AA19: =IF(W19>$AE$33,1,0) | AB19: =IF(AA19=C19,1,0) | AD19: chk_over_200 | AE19: 0.66836159 | AF19: 0.91577306 | AI19: class 0 (pays) | AJ19: =IF(AK14+AK15=0,0,AK14/(AK14+AK15)) | AK19: =IF(AK14+AL14=0,0,AK14/(AK14+AL14)) | AL19: =IF(AJ19+AK19=0,0,2*AJ19*AK19/(AJ19+AK19)) | AM19: =AM14
A20: ='1 prepared data'!A13 | B20: ='1 prepared data'!U13 | C20: ='1 prepared data'!B13 | D20: ='1 prepared data'!C13 | E20: ='1 prepared data'!D13 | F20: ='1 prepared data'!E13 | G20: ='1 prepared data'!F13 | H20: ='1 prepared data'!G13 | I20: ='1 prepared data'!H13 | J20: ='1 prepared data'!I13 | ... U20: ='1 prepared data'!T13 | V20: =$AE$12+D20*$AE$13+E20*$AE$14+F20*$AE$15+G20*$AE$16+H20*$AE$17+I20*$AE$18+J20*$AE$19+K20*$AE$20+L20*$AE$21+M20*$AE$22+N20*$AE$23+O20*$AE$24+P20*$AE$25+Q20*$AE$26+R20*$AE$27+S20*$AE$28+T20*$AE$29+U20*$AE$30 | W20: =1/(1+EXP(-V20)) | X20: =-IF(C20=1,LN(W20),LN(1-W20)) | Y20: ='1 prepared data'!V13 | Z20: =Y20*X20 | AA20: =IF(W20>$AE$33,1,0) | AB20: =IF(AA20=C20,1,0) | AD20: hist_critical | AE20: -0.65734494 | AF20: -0.66399023 | AI20: class 1 (defaults) | AJ20: =IF(AL15+AL14=0,0,AL15/(AL15+AL14)) | AK20: =IF(AL15+AK15=0,0,AL15/(AL15+AK15)) | AL20: =IF(AJ20+AK20=0,0,2*AJ20*AK20/(AJ20+AK20)) | AM20: =AM15
A21: ='1 prepared data'!A14 | B21: ='1 prepared data'!U14 | C21: ='1 prepared data'!B14 | D21: ='1 prepared data'!C14 | E21: ='1 prepared data'!D14 | F21: ='1 prepared data'!E14 | G21: ='1 prepared data'!F14 | H21: ='1 prepared data'!G14 | I21: ='1 prepared data'!H14 | J21: ='1 prepared data'!I14 | ... U21: ='1 prepared data'!T14 | V21: =$AE$12+D21*$AE$13+E21*$AE$14+F21*$AE$15+G21*$AE$16+H21*$AE$17+I21*$AE$18+J21*$AE$19+K21*$AE$20+L21*$AE$21+M21*$AE$22+N21*$AE$23+O21*$AE$24+P21*$AE$25+Q21*$AE$26+R21*$AE$27+S21*$AE$28+T21*$AE$29+U21*$AE$30 | W21: =1/(1+EXP(-V21)) | X21: =-IF(C21=1,LN(W21),LN(1-W21)) | Y21: ='1 prepared data'!V14 | Z21: =Y21*X21 | AA21: =IF(W21>$AE$33,1,0) | AB21: =IF(AA21=C21,1,0) | AD21: hist_delays | AE21: -0.040195519 | AF21: 0.45882329 | AI21: accuracy | AL21: =(AL15+AK14)/AM16
A22: ='1 prepared data'!A15 | B22: ='1 prepared data'!U15 | C22: ='1 prepared data'!B15 | D22: ='1 prepared data'!C15 | E22: ='1 prepared data'!D15 | F22: ='1 prepared data'!E15 | G22: ='1 prepared data'!F15 | H22: ='1 prepared data'!G15 | I22: ='1 prepared data'!H15 | J22: ='1 prepared data'!I15 | ... U22: ='1 prepared data'!T15 | V22: =$AE$12+D22*$AE$13+E22*$AE$14+F22*$AE$15+G22*$AE$16+H22*$AE$17+I22*$AE$18+J22*$AE$19+K22*$AE$20+L22*$AE$21+M22*$AE$22+N22*$AE$23+O22*$AE$24+P22*$AE$25+Q22*$AE$26+R22*$AE$27+S22*$AE$28+T22*$AE$29+U22*$AE$30 | W22: =1/(1+EXP(-V22)) | X22: =-IF(C22=1,LN(W22),LN(1-W22)) | Y22: ='1 prepared data'!V15 | Z22: =Y22*X22 | AA22: =IF(W22>$AE$33,1,0) | AB22: =IF(AA22=C22,1,0) | AD22: hist_no_credits | AE22: 0.66906563 | AF22: 0.43261422
A23: ='1 prepared data'!A16 | B23: ='1 prepared data'!U16 | C23: ='1 prepared data'!B16 | D23: ='1 prepared data'!C16 | E23: ='1 prepared data'!D16 | F23: ='1 prepared data'!E16 | G23: ='1 prepared data'!F16 | H23: ='1 prepared data'!G16 | I23: ='1 prepared data'!H16 | J23: ='1 prepared data'!I16 | ... U23: ='1 prepared data'!T16 | V23: =$AE$12+D23*$AE$13+E23*$AE$14+F23*$AE$15+G23*$AE$16+H23*$AE$17+I23*$AE$18+J23*$AE$19+K23*$AE$20+L23*$AE$21+M23*$AE$22+N23*$AE$23+O23*$AE$24+P23*$AE$25+Q23*$AE$26+R23*$AE$27+S23*$AE$28+T23*$AE$29+U23*$AE$30 | W23: =1/(1+EXP(-V23)) | X23: =-IF(C23=1,LN(W23),LN(1-W23)) | Y23: ='1 prepared data'!V16 | Z23: =Y23*X23 | AA23: =IF(W23>$AE$33,1,0) | AB23: =IF(AA23=C23,1,0) | AD23: sav_100_1000 | AE23: -0.38958343 | AF23: -0.3133509
A24: ='1 prepared data'!A17 | B24: ='1 prepared data'!U17 | C24: ='1 prepared data'!B17 | D24: ='1 prepared data'!C17 | E24: ='1 prepared data'!D17 | F24: ='1 prepared data'!E17 | G24: ='1 prepared data'!F17 | H24: ='1 prepared data'!G17 | I24: ='1 prepared data'!H17 | J24: ='1 prepared data'!I17 | ... U24: ='1 prepared data'!T17 | V24: =$AE$12+D24*$AE$13+E24*$AE$14+F24*$AE$15+G24*$AE$16+H24*$AE$17+I24*$AE$18+J24*$AE$19+K24*$AE$20+L24*$AE$21+M24*$AE$22+N24*$AE$23+O24*$AE$24+P24*$AE$25+Q24*$AE$26+R24*$AE$27+S24*$AE$28+T24*$AE$29+U24*$AE$30 | W24: =1/(1+EXP(-V24)) | X24: =-IF(C24=1,LN(W24),LN(1-W24)) | Y24: ='1 prepared data'!V17 | Z24: =Y24*X24 | AA24: =IF(W24>$AE$33,1,0) | AB24: =IF(AA24=C24,1,0) | AD24: sav_over_1000 | AE24: -0.88922386 | AF24: -1.0683639
A25: ='1 prepared data'!A18 | B25: ='1 prepared data'!U18 | C25: ='1 prepared data'!B18 | D25: ='1 prepared data'!C18 | E25: ='1 prepared data'!D18 | F25: ='1 prepared data'!E18 | G25: ='1 prepared data'!F18 | H25: ='1 prepared data'!G18 | I25: ='1 prepared data'!H18 | J25: ='1 prepared data'!I18 | ... U25: ='1 prepared data'!T18 | V25: =$AE$12+D25*$AE$13+E25*$AE$14+F25*$AE$15+G25*$AE$16+H25*$AE$17+I25*$AE$18+J25*$AE$19+K25*$AE$20+L25*$AE$21+M25*$AE$22+N25*$AE$23+O25*$AE$24+P25*$AE$25+Q25*$AE$26+R25*$AE$27+S25*$AE$28+T25*$AE$29+U25*$AE$30 | W25: =1/(1+EXP(-V25)) | X25: =-IF(C25=1,LN(W25),LN(1-W25)) | Y25: ='1 prepared data'!V18 | Z25: =Y25*X25 | AA25: =IF(W25>$AE$33,1,0) | AB25: =IF(AA25=C25,1,0) | AD25: sav_unknown | AE25: -1.0760929 | AF25: -0.98496015
A26: ='1 prepared data'!A19 | B26: ='1 prepared data'!U19 | C26: ='1 prepared data'!B19 | D26: ='1 prepared data'!C19 | E26: ='1 prepared data'!D19 | F26: ='1 prepared data'!E19 | G26: ='1 prepared data'!F19 | H26: ='1 prepared data'!G19 | I26: ='1 prepared data'!H19 | J26: ='1 prepared data'!I19 | ... U26: ='1 prepared data'!T19 | V26: =$AE$12+D26*$AE$13+E26*$AE$14+F26*$AE$15+G26*$AE$16+H26*$AE$17+I26*$AE$18+J26*$AE$19+K26*$AE$20+L26*$AE$21+M26*$AE$22+N26*$AE$23+O26*$AE$24+P26*$AE$25+Q26*$AE$26+R26*$AE$27+S26*$AE$28+T26*$AE$29+U26*$AE$30 | W26: =1/(1+EXP(-V26)) | X26: =-IF(C26=1,LN(W26),LN(1-W26)) | Y26: ='1 prepared data'!V19 | Z26: =Y26*X26 | AA26: =IF(W26>$AE$33,1,0) | AB26: =IF(AA26=C26,1,0) | AD26: housing_rent | AE26: 0.65383718 | AF26: 0.72797987
A27: ='1 prepared data'!A20 | B27: ='1 prepared data'!U20 | C27: ='1 prepared data'!B20 | D27: ='1 prepared data'!C20 | E27: ='1 prepared data'!D20 | F27: ='1 prepared data'!E20 | G27: ='1 prepared data'!F20 | H27: ='1 prepared data'!G20 | I27: ='1 prepared data'!H20 | J27: ='1 prepared data'!I20 | ... U27: ='1 prepared data'!T20 | V27: =$AE$12+D27*$AE$13+E27*$AE$14+F27*$AE$15+G27*$AE$16+H27*$AE$17+I27*$AE$18+J27*$AE$19+K27*$AE$20+L27*$AE$21+M27*$AE$22+N27*$AE$23+O27*$AE$24+P27*$AE$25+Q27*$AE$26+R27*$AE$27+S27*$AE$28+T27*$AE$29+U27*$AE$30 | W27: =1/(1+EXP(-V27)) | X27: =-IF(C27=1,LN(W27),LN(1-W27)) | Y27: ='1 prepared data'!V20 | Z27: =Y27*X27 | AA27: =IF(W27>$AE$33,1,0) | AB27: =IF(AA27=C27,1,0) | AD27: housing_free | AE27: 0.19536536 | AF27: 0.41899346
A28: ='1 prepared data'!A21 | B28: ='1 prepared data'!U21 | C28: ='1 prepared data'!B21 | D28: ='1 prepared data'!C21 | E28: ='1 prepared data'!D21 | F28: ='1 prepared data'!E21 | G28: ='1 prepared data'!F21 | H28: ='1 prepared data'!G21 | I28: ='1 prepared data'!H21 | J28: ='1 prepared data'!I21 | ... U28: ='1 prepared data'!T21 | V28: =$AE$12+D28*$AE$13+E28*$AE$14+F28*$AE$15+G28*$AE$16+H28*$AE$17+I28*$AE$18+J28*$AE$19+K28*$AE$20+L28*$AE$21+M28*$AE$22+N28*$AE$23+O28*$AE$24+P28*$AE$25+Q28*$AE$26+R28*$AE$27+S28*$AE$28+T28*$AE$29+U28*$AE$30 | W28: =1/(1+EXP(-V28)) | X28: =-IF(C28=1,LN(W28),LN(1-W28)) | Y28: ='1 prepared data'!V21 | Z28: =Y28*X28 | AA28: =IF(W28>$AE$33,1,0) | AB28: =IF(AA28=C28,1,0) | AD28: purpose_car | AE28: -0.080165476 | AF28: -0.2854666
A29: ='1 prepared data'!A22 | B29: ='1 prepared data'!U22 | C29: ='1 prepared data'!B22 | D29: ='1 prepared data'!C22 | E29: ='1 prepared data'!D22 | F29: ='1 prepared data'!E22 | G29: ='1 prepared data'!F22 | H29: ='1 prepared data'!G22 | I29: ='1 prepared data'!H22 | J29: ='1 prepared data'!I22 | ... U29: ='1 prepared data'!T22 | V29: =$AE$12+D29*$AE$13+E29*$AE$14+F29*$AE$15+G29*$AE$16+H29*$AE$17+I29*$AE$18+J29*$AE$19+K29*$AE$20+L29*$AE$21+M29*$AE$22+N29*$AE$23+O29*$AE$24+P29*$AE$25+Q29*$AE$26+R29*$AE$27+S29*$AE$28+T29*$AE$29+U29*$AE$30 | W29: =1/(1+EXP(-V29)) | X29: =-IF(C29=1,LN(W29),LN(1-W29)) | Y29: ='1 prepared data'!V22 | Z29: =Y29*X29 | AA29: =IF(W29>$AE$33,1,0) | AB29: =IF(AA29=C29,1,0) | AD29: purpose_radio_tv | AE29: -0.52021065 | AF29: -0.52033388
A30: ='1 prepared data'!A23 | B30: ='1 prepared data'!U23 | C30: ='1 prepared data'!B23 | D30: ='1 prepared data'!C23 | E30: ='1 prepared data'!D23 | F30: ='1 prepared data'!E23 | G30: ='1 prepared data'!F23 | H30: ='1 prepared data'!G23 | I30: ='1 prepared data'!H23 | J30: ='1 prepared data'!I23 | ... U30: ='1 prepared data'!T23 | V30: =$AE$12+D30*$AE$13+E30*$AE$14+F30*$AE$15+G30*$AE$16+H30*$AE$17+I30*$AE$18+J30*$AE$19+K30*$AE$20+L30*$AE$21+M30*$AE$22+N30*$AE$23+O30*$AE$24+P30*$AE$25+Q30*$AE$26+R30*$AE$27+S30*$AE$28+T30*$AE$29+U30*$AE$30 | W30: =1/(1+EXP(-V30)) | X30: =-IF(C30=1,LN(W30),LN(1-W30)) | Y30: ='1 prepared data'!V23 | Z30: =Y30*X30 | AA30: =IF(W30>$AE$33,1,0) | AB30: =IF(AA30=C30,1,0) | AD30: purpose_furniture | AE30: -0.28180274 | AF30: -0.20496137
A31: ='1 prepared data'!A24 | B31: ='1 prepared data'!U24 | C31: ='1 prepared data'!B24 | D31: ='1 prepared data'!C24 | E31: ='1 prepared data'!D24 | F31: ='1 prepared data'!E24 | G31: ='1 prepared data'!F24 | H31: ='1 prepared data'!G24 | I31: ='1 prepared data'!H24 | J31: ='1 prepared data'!I24 | ... U31: ='1 prepared data'!T24 | V31: =$AE$12+D31*$AE$13+E31*$AE$14+F31*$AE$15+G31*$AE$16+H31*$AE$17+I31*$AE$18+J31*$AE$19+K31*$AE$20+L31*$AE$21+M31*$AE$22+N31*$AE$23+O31*$AE$24+P31*$AE$25+Q31*$AE$26+R31*$AE$27+S31*$AE$28+T31*$AE$29+U31*$AE$30 | W31: =1/(1+EXP(-V31)) | X31: =-IF(C31=1,LN(W31),LN(1-W31)) | Y31: ='1 prepared data'!V24 | Z31: =Y31*X31 | AA31: =IF(W31>$AE$33,1,0) | AB31: =IF(AA31=C31,1,0)
A32: ='1 prepared data'!A25 | B32: ='1 prepared data'!U25 | C32: ='1 prepared data'!B25 | D32: ='1 prepared data'!C25 | E32: ='1 prepared data'!D25 | F32: ='1 prepared data'!E25 | G32: ='1 prepared data'!F25 | H32: ='1 prepared data'!G25 | I32: ='1 prepared data'!H25 | J32: ='1 prepared data'!I25 | ... U32: ='1 prepared data'!T25 | V32: =$AE$12+D32*$AE$13+E32*$AE$14+F32*$AE$15+G32*$AE$16+H32*$AE$17+I32*$AE$18+J32*$AE$19+K32*$AE$20+L32*$AE$21+M32*$AE$22+N32*$AE$23+O32*$AE$24+P32*$AE$25+Q32*$AE$26+R32*$AE$27+S32*$AE$28+T32*$AE$29+U32*$AE$30 | W32: =1/(1+EXP(-V32)) | X32: =-IF(C32=1,LN(W32),LN(1-W32)) | Y32: ='1 prepared data'!V25 | Z32: =Y32*X32 | AA32: =IF(W32>$AE$33,1,0) | AB32: =IF(AA32=C32,1,0) | AD32: training rows used (use = 1) | AE32: =COUNTIFS('1 prepared data'!$U$5:$U$1004,"training",'1 prepared data'!$V$5:$V$1004,1)
A33: ='1 prepared data'!A26 | B33: ='1 prepared data'!U26 | C33: ='1 prepared data'!B26 | D33: ='1 prepared data'!C26 | E33: ='1 prepared data'!D26 | F33: ='1 prepared data'!E26 | G33: ='1 prepared data'!F26 | H33: ='1 prepared data'!G26 | I33: ='1 prepared data'!H26 | J33: ='1 prepared data'!I26 | ... U33: ='1 prepared data'!T26 | V33: =$AE$12+D33*$AE$13+E33*$AE$14+F33*$AE$15+G33*$AE$16+H33*$AE$17+I33*$AE$18+J33*$AE$19+K33*$AE$20+L33*$AE$21+M33*$AE$22+N33*$AE$23+O33*$AE$24+P33*$AE$25+Q33*$AE$26+R33*$AE$27+S33*$AE$28+T33*$AE$29+U33*$AE$30 | W33: =1/(1+EXP(-V33)) | X33: =-IF(C33=1,LN(W33),LN(1-W33)) | Y33: ='1 prepared data'!V26 | Z33: =Y33*X33 | AA33: =IF(W33>$AE$33,1,0) | AB33: =IF(AA33=C33,1,0) | AD33: threshold | AE33: 0.5
A34: ='1 prepared data'!A27 | B34: ='1 prepared data'!U27 | C34: ='1 prepared data'!B27 | D34: ='1 prepared data'!C27 | E34: ='1 prepared data'!D27 | F34: ='1 prepared data'!E27 | G34: ='1 prepared data'!F27 | H34: ='1 prepared data'!G27 | I34: ='1 prepared data'!H27 | J34: ='1 prepared data'!I27 | ... U34: ='1 prepared data'!T27 | V34: =$AE$12+D34*$AE$13+E34*$AE$14+F34*$AE$15+G34*$AE$16+H34*$AE$17+I34*$AE$18+J34*$AE$19+K34*$AE$20+L34*$AE$21+M34*$AE$22+N34*$AE$23+O34*$AE$24+P34*$AE$25+Q34*$AE$26+R34*$AE$27+S34*$AE$28+T34*$AE$29+U34*$AE$30 | W34: =1/(1+EXP(-V34)) | X34: =-IF(C34=1,LN(W34),LN(1-W34)) | Y34: ='1 prepared data'!V27 | Z34: =Y34*X34 | AA34: =IF(W34>$AE$33,1,0) | AB34: =IF(AA34=C34,1,0)
A35: ='1 prepared data'!A28 | B35: ='1 prepared data'!U28 | C35: ='1 prepared data'!B28 | D35: ='1 prepared data'!C28 | E35: ='1 prepared data'!D28 | F35: ='1 prepared data'!E28 | G35: ='1 prepared data'!F28 | H35: ='1 prepared data'!G28 | I35: ='1 prepared data'!H28 | J35: ='1 prepared data'!I28 | ... U35: ='1 prepared data'!T28 | V35: =$AE$12+D35*$AE$13+E35*$AE$14+F35*$AE$15+G35*$AE$16+H35*$AE$17+I35*$AE$18+J35*$AE$19+K35*$AE$20+L35*$AE$21+M35*$AE$22+N35*$AE$23+O35*$AE$24+P35*$AE$25+Q35*$AE$26+R35*$AE$27+S35*$AE$28+T35*$AE$29+U35*$AE$30 | W35: =1/(1+EXP(-V35)) | X35: =-IF(C35=1,LN(W35),LN(1-W35)) | Y35: ='1 prepared data'!V28 | Z35: =Y35*X35 | AA35: =IF(W35>$AE$33,1,0) | AB35: =IF(AA35=C35,1,0) | AD35: RESULTS
A36: ='1 prepared data'!A29 | B36: ='1 prepared data'!U29 | C36: ='1 prepared data'!B29 | D36: ='1 prepared data'!C29 | E36: ='1 prepared data'!D29 | F36: ='1 prepared data'!E29 | G36: ='1 prepared data'!F29 | H36: ='1 prepared data'!G29 | I36: ='1 prepared data'!H29 | J36: ='1 prepared data'!I29 | ... U36: ='1 prepared data'!T29 | V36: =$AE$12+D36*$AE$13+E36*$AE$14+F36*$AE$15+G36*$AE$16+H36*$AE$17+I36*$AE$18+J36*$AE$19+K36*$AE$20+L36*$AE$21+M36*$AE$22+N36*$AE$23+O36*$AE$24+P36*$AE$25+Q36*$AE$26+R36*$AE$27+S36*$AE$28+T36*$AE$29+U36*$AE$30 | W36: =1/(1+EXP(-V36)) | X36: =-IF(C36=1,LN(W36),LN(1-W36)) | Y36: ='1 prepared data'!V29 | Z36: =Y36*X36 | AA36: =IF(W36>$AE$33,1,0) | AB36: =IF(AA36=C36,1,0) | AD36: J = sum of weighted training losses (SOLVER OBJECTIVE) | AE36: =SUMPRODUCT(($B$12:$B$1011="training")*$Z$12:$Z$1011)
A37: ='1 prepared data'!A30 | B37: ='1 prepared data'!U30 | C37: ='1 prepared data'!B30 | D37: ='1 prepared data'!C30 | E37: ='1 prepared data'!D30 | F37: ='1 prepared data'!E30 | G37: ='1 prepared data'!F30 | H37: ='1 prepared data'!G30 | I37: ='1 prepared data'!H30 | J37: ='1 prepared data'!I30 | ... U37: ='1 prepared data'!T30 | V37: =$AE$12+D37*$AE$13+E37*$AE$14+F37*$AE$15+G37*$AE$16+H37*$AE$17+I37*$AE$18+J37*$AE$19+K37*$AE$20+L37*$AE$21+M37*$AE$22+N37*$AE$23+O37*$AE$24+P37*$AE$25+Q37*$AE$26+R37*$AE$27+S37*$AE$28+T37*$AE$29+U37*$AE$30 | W37: =1/(1+EXP(-V37)) | X37: =-IF(C37=1,LN(W37),LN(1-W37)) | Y37: ='1 prepared data'!V30 | Z37: =Y37*X37 | AA37: =IF(W37>$AE$33,1,0) | AB37: =IF(AA37=C37,1,0) | AD37: sum of row weights in training | AE37: =SUMPRODUCT(($B$12:$B$1011="training")*$Y$12:$Y$1011)
A38: ='1 prepared data'!A31 | B38: ='1 prepared data'!U31 | C38: ='1 prepared data'!B31 | D38: ='1 prepared data'!C31 | E38: ='1 prepared data'!D31 | F38: ='1 prepared data'!E31 | G38: ='1 prepared data'!F31 | H38: ='1 prepared data'!G31 | I38: ='1 prepared data'!H31 | J38: ='1 prepared data'!I31 | ... U38: ='1 prepared data'!T31 | V38: =$AE$12+D38*$AE$13+E38*$AE$14+F38*$AE$15+G38*$AE$16+H38*$AE$17+I38*$AE$18+J38*$AE$19+K38*$AE$20+L38*$AE$21+M38*$AE$22+N38*$AE$23+O38*$AE$24+P38*$AE$25+Q38*$AE$26+R38*$AE$27+S38*$AE$28+T38*$AE$29+U38*$AE$30 | W38: =1/(1+EXP(-V38)) | X38: =-IF(C38=1,LN(W38),LN(1-W38)) | Y38: ='1 prepared data'!V31 | Z38: =Y38*X38 | AA38: =IF(W38>$AE$33,1,0) | AB38: =IF(AA38=C38,1,0) | AD38: of which, class 1 | AE38: =SUMPRODUCT(($B$12:$B$1011="training")*($C$12:$C$1011=1)*$Y$12:$Y$1011)
A39: ='1 prepared data'!A32 | B39: ='1 prepared data'!U32 | C39: ='1 prepared data'!B32 | D39: ='1 prepared data'!C32 | E39: ='1 prepared data'!D32 | F39: ='1 prepared data'!E32 | G39: ='1 prepared data'!F32 | H39: ='1 prepared data'!G32 | I39: ='1 prepared data'!H32 | J39: ='1 prepared data'!I32 | ... U39: ='1 prepared data'!T32 | V39: =$AE$12+D39*$AE$13+E39*$AE$14+F39*$AE$15+G39*$AE$16+H39*$AE$17+I39*$AE$18+J39*$AE$19+K39*$AE$20+L39*$AE$21+M39*$AE$22+N39*$AE$23+O39*$AE$24+P39*$AE$25+Q39*$AE$26+R39*$AE$27+S39*$AE$28+T39*$AE$29+U39*$AE$30 | W39: =1/(1+EXP(-V39)) | X39: =-IF(C39=1,LN(W39),LN(1-W39)) | Y39: ='1 prepared data'!V32 | Z39: =Y39*X39 | AA39: =IF(W39>$AE$33,1,0) | AB39: =IF(AA39=C39,1,0) | AD39: of which, class 0 | AE39: =SUMPRODUCT(($B$12:$B$1011="training")*($C$12:$C$1011=0)*$Y$12:$Y$1011)
A40: ='1 prepared data'!A33 | B40: ='1 prepared data'!U33 | C40: ='1 prepared data'!B33 | D40: ='1 prepared data'!C33 | E40: ='1 prepared data'!D33 | F40: ='1 prepared data'!E33 | G40: ='1 prepared data'!F33 | H40: ='1 prepared data'!G33 | I40: ='1 prepared data'!H33 | J40: ='1 prepared data'!I33 | ... U40: ='1 prepared data'!T33 | V40: =$AE$12+D40*$AE$13+E40*$AE$14+F40*$AE$15+G40*$AE$16+H40*$AE$17+I40*$AE$18+J40*$AE$19+K40*$AE$20+L40*$AE$21+M40*$AE$22+N40*$AE$23+O40*$AE$24+P40*$AE$25+Q40*$AE$26+R40*$AE$27+S40*$AE$28+T40*$AE$29+U40*$AE$30 | W40: =1/(1+EXP(-V40)) | X40: =-IF(C40=1,LN(W40),LN(1-W40)) | Y40: ='1 prepared data'!V33 | Z40: =Y40*X40 | AA40: =IF(W40>$AE$33,1,0) | AB40: =IF(AA40=C40,1,0) | AD40: average testing loss (unweighted) | AE40: =SUMPRODUCT(($B$12:$B$1011="testing")*$X$12:$X$1011)/COUNTIF($B$12:$B$1011,"testing")
A41: ='1 prepared data'!A34 | B41: ='1 prepared data'!U34 | C41: ='1 prepared data'!B34 | D41: ='1 prepared data'!C34 | E41: ='1 prepared data'!D34 | F41: ='1 prepared data'!E34 | G41: ='1 prepared data'!F34 | H41: ='1 prepared data'!G34 | I41: ='1 prepared data'!H34 | J41: ='1 prepared data'!I34 | ... U41: ='1 prepared data'!T34 | V41: =$AE$12+D41*$AE$13+E41*$AE$14+F41*$AE$15+G41*$AE$16+H41*$AE$17+I41*$AE$18+J41*$AE$19+K41*$AE$20+L41*$AE$21+M41*$AE$22+N41*$AE$23+O41*$AE$24+P41*$AE$25+Q41*$AE$26+R41*$AE$27+S41*$AE$28+T41*$AE$29+U41*$AE$30 | W41: =1/(1+EXP(-V41)) | X41: =-IF(C41=1,LN(W41),LN(1-W41)) | Y41: ='1 prepared data'!V34 | Z41: =Y41*X41 | AA41: =IF(W41>$AE$33,1,0) | AB41: =IF(AA41=C41,1,0) | AD41: average p on testing (the actual rate is 0.300) | AE41: =SUMPRODUCT(($B$12:$B$1011="testing")*$W$12:$W$1011)/COUNTIF($B$12:$B$1011,"testing")
A42: ='1 prepared data'!A35 | B42: ='1 prepared data'!U35 | C42: ='1 prepared data'!B35 | D42: ='1 prepared data'!C35 | E42: ='1 prepared data'!D35 | F42: ='1 prepared data'!E35 | G42: ='1 prepared data'!F35 | H42: ='1 prepared data'!G35 | I42: ='1 prepared data'!H35 | J42: ='1 prepared data'!I35 | ... U42: ='1 prepared data'!T35 | V42: =$AE$12+D42*$AE$13+E42*$AE$14+F42*$AE$15+G42*$AE$16+H42*$AE$17+I42*$AE$18+J42*$AE$19+K42*$AE$20+L42*$AE$21+M42*$AE$22+N42*$AE$23+O42*$AE$24+P42*$AE$25+Q42*$AE$26+R42*$AE$27+S42*$AE$28+T42*$AE$29+U42*$AE$30 | W42: =1/(1+EXP(-V42)) | X42: =-IF(C42=1,LN(W42),LN(1-W42)) | Y42: ='1 prepared data'!V35 | Z42: =Y42*X42 | AA42: =IF(W42>$AE$33,1,0) | AB42: =IF(AA42=C42,1,0) | AD42: testing accuracy | AE42: =SUMPRODUCT(($B$12:$B$1011="testing")*$AB$12:$AB$1011)/COUNTIF($B$12:$B$1011,"testing")
A43: ='1 prepared data'!A36 | B43: ='1 prepared data'!U36 | C43: ='1 prepared data'!B36 | D43: ='1 prepared data'!C36 | E43: ='1 prepared data'!D36 | F43: ='1 prepared data'!E36 | G43: ='1 prepared data'!F36 | H43: ='1 prepared data'!G36 | I43: ='1 prepared data'!H36 | J43: ='1 prepared data'!I36 | ... U43: ='1 prepared data'!T36 | V43: =$AE$12+D43*$AE$13+E43*$AE$14+F43*$AE$15+G43*$AE$16+H43*$AE$17+I43*$AE$18+J43*$AE$19+K43*$AE$20+L43*$AE$21+M43*$AE$22+N43*$AE$23+O43*$AE$24+P43*$AE$25+Q43*$AE$26+R43*$AE$27+S43*$AE$28+T43*$AE$29+U43*$AE$30 | W43: =1/(1+EXP(-V43)) | X43: =-IF(C43=1,LN(W43),LN(1-W43)) | Y43: ='1 prepared data'!V36 | Z43: =Y43*X43 | AA43: =IF(W43>$AE$33,1,0) | AB43: =IF(AA43=C43,1,0) | AD43: scikit-learn reference: class 1 recall on testing (threshold 0.5) | AE43: 0.86666667
A44: ='1 prepared data'!A37 | B44: ='1 prepared data'!U37 | C44: ='1 prepared data'!B37 | D44: ='1 prepared data'!C37 | E44: ='1 prepared data'!D37 | F44: ='1 prepared data'!E37 | G44: ='1 prepared data'!F37 | H44: ='1 prepared data'!G37 | I44: ='1 prepared data'!H37 | J44: ='1 prepared data'!I37 | ... U44: ='1 prepared data'!T37 | V44: =$AE$12+D44*$AE$13+E44*$AE$14+F44*$AE$15+G44*$AE$16+H44*$AE$17+I44*$AE$18+J44*$AE$19+K44*$AE$20+L44*$AE$21+M44*$AE$22+N44*$AE$23+O44*$AE$24+P44*$AE$25+Q44*$AE$26+R44*$AE$27+S44*$AE$28+T44*$AE$29+U44*$AE$30 | W44: =1/(1+EXP(-V44)) | X44: =-IF(C44=1,LN(W44),LN(1-W44)) | Y44: ='1 prepared data'!V37 | Z44: =Y44*X44 | AA44: =IF(W44>$AE$33,1,0) | AB44: =IF(AA44=C44,1,0) | AD44: scikit-learn reference: class 1 precision on testing | AE44: 0.5
A45: ='1 prepared data'!A38 | B45: ='1 prepared data'!U38 | C45: ='1 prepared data'!B38 | D45: ='1 prepared data'!C38 | E45: ='1 prepared data'!D38 | F45: ='1 prepared data'!E38 | G45: ='1 prepared data'!F38 | H45: ='1 prepared data'!G38 | I45: ='1 prepared data'!H38 | J45: ='1 prepared data'!I38 | ... U45: ='1 prepared data'!T38 | V45: =$AE$12+D45*$AE$13+E45*$AE$14+F45*$AE$15+G45*$AE$16+H45*$AE$17+I45*$AE$18+J45*$AE$19+K45*$AE$20+L45*$AE$21+M45*$AE$22+N45*$AE$23+O45*$AE$24+P45*$AE$25+Q45*$AE$26+R45*$AE$27+S45*$AE$28+T45*$AE$29+U45*$AE$30 | W45: =1/(1+EXP(-V45)) | X45: =-IF(C45=1,LN(W45),LN(1-W45)) | Y45: ='1 prepared data'!V38 | Z45: =Y45*X45 | AA45: =IF(W45>$AE$33,1,0) | AB45: =IF(AA45=C45,1,0) | AD45: scikit-learn reference: testing AUC | AE45: 0.81338624
A46: ='1 prepared data'!A39 | B46: ='1 prepared data'!U39 | C46: ='1 prepared data'!B39 | D46: ='1 prepared data'!C39 | E46: ='1 prepared data'!D39 | F46: ='1 prepared data'!E39 | G46: ='1 prepared data'!F39 | H46: ='1 prepared data'!G39 | I46: ='1 prepared data'!H39 | J46: ='1 prepared data'!I39 | ... U46: ='1 prepared data'!T39 | V46: =$AE$12+D46*$AE$13+E46*$AE$14+F46*$AE$15+G46*$AE$16+H46*$AE$17+I46*$AE$18+J46*$AE$19+K46*$AE$20+L46*$AE$21+M46*$AE$22+N46*$AE$23+O46*$AE$24+P46*$AE$25+Q46*$AE$26+R46*$AE$27+S46*$AE$28+T46*$AE$29+U46*$AE$30 | W46: =1/(1+EXP(-V46)) | X46: =-IF(C46=1,LN(W46),LN(1-W46)) | Y46: ='1 prepared data'!V39 | Z46: =Y46*X46 | AA46: =IF(W46>$AE$33,1,0) | AB46: =IF(AA46=C46,1,0)
A47: ='1 prepared data'!A40 | B47: ='1 prepared data'!U40 | C47: ='1 prepared data'!B40 | D47: ='1 prepared data'!C40 | E47: ='1 prepared data'!D40 | F47: ='1 prepared data'!E40 | G47: ='1 prepared data'!F40 | H47: ='1 prepared data'!G40 | I47: ='1 prepared data'!H40 | J47: ='1 prepared data'!I40 | ... U47: ='1 prepared data'!T40 | V47: =$AE$12+D47*$AE$13+E47*$AE$14+F47*$AE$15+G47*$AE$16+H47*$AE$17+I47*$AE$18+J47*$AE$19+K47*$AE$20+L47*$AE$21+M47*$AE$22+N47*$AE$23+O47*$AE$24+P47*$AE$25+Q47*$AE$26+R47*$AE$27+S47*$AE$28+T47*$AE$29+U47*$AE$30 | W47: =1/(1+EXP(-V47)) | X47: =-IF(C47=1,LN(W47),LN(1-W47)) | Y47: ='1 prepared data'!V40 | Z47: =Y47*X47 | AA47: =IF(W47>$AE$33,1,0) | AB47: =IF(AA47=C47,1,0) | AD47: Solver: minimize J by changing the light blue model weight cells (not the class weight cells), GRG Nonlinear, central derivatives, convergence 0.000001, no constraints and with 'Make Unconstrained Variables Non-Negative' UNTICKED. Run twice if it stops early.
A48: ='1 prepared data'!A41 | B48: ='1 prepared data'!U41 | C48: ='1 prepared data'!B41 | D48: ='1 prepared data'!C41 | E48: ='1 prepared data'!D41 | F48: ='1 prepared data'!E41 | G48: ='1 prepared data'!F41 | H48: ='1 prepared data'!G41 | I48: ='1 prepared data'!H41 | J48: ='1 prepared data'!I41 | ... U48: ='1 prepared data'!T41 | V48: =$AE$12+D48*$AE$13+E48*$AE$14+F48*$AE$15+G48*$AE$16+H48*$AE$17+I48*$AE$18+J48*$AE$19+K48*$AE$20+L48*$AE$21+M48*$AE$22+N48*$AE$23+O48*$AE$24+P48*$AE$25+Q48*$AE$26+R48*$AE$27+S48*$AE$28+T48*$AE$29+U48*$AE$30 | W48: =1/(1+EXP(-V48)) | X48: =-IF(C48=1,LN(W48),LN(1-W48)) | Y48: ='1 prepared data'!V41 | Z48: =Y48*X48 | AA48: =IF(W48>$AE$33,1,0) | AB48: =IF(AA48=C48,1,0)
A49: ='1 prepared data'!A42 | B49: ='1 prepared data'!U42 | C49: ='1 prepared data'!B42 | D49: ='1 prepared data'!C42 | E49: ='1 prepared data'!D42 | F49: ='1 prepared data'!E42 | G49: ='1 prepared data'!F42 | H49: ='1 prepared data'!G42 | I49: ='1 prepared data'!H42 | J49: ='1 prepared data'!I42 | ... U49: ='1 prepared data'!T42 | V49: =$AE$12+D49*$AE$13+E49*$AE$14+F49*$AE$15+G49*$AE$16+H49*$AE$17+I49*$AE$18+J49*$AE$19+K49*$AE$20+L49*$AE$21+M49*$AE$22+N49*$AE$23+O49*$AE$24+P49*$AE$25+Q49*$AE$26+R49*$AE$27+S49*$AE$28+T49*$AE$29+U49*$AE$30 | W49: =1/(1+EXP(-V49)) | X49: =-IF(C49=1,LN(W49),LN(1-W49)) | Y49: ='1 prepared data'!V42 | Z49: =Y49*X49 | AA49: =IF(W49>$AE$33,1,0) | AB49: =IF(AA49=C49,1,0)
A50: ='1 prepared data'!A43 | B50: ='1 prepared data'!U43 | C50: ='1 prepared data'!B43 | D50: ='1 prepared data'!C43 | E50: ='1 prepared data'!D43 | F50: ='1 prepared data'!E43 | G50: ='1 prepared data'!F43 | H50: ='1 prepared data'!G43 | I50: ='1 prepared data'!H43 | J50: ='1 prepared data'!I43 | ... U50: ='1 prepared data'!T43 | V50: =$AE$12+D50*$AE$13+E50*$AE$14+F50*$AE$15+G50*$AE$16+H50*$AE$17+I50*$AE$18+J50*$AE$19+K50*$AE$20+L50*$AE$21+M50*$AE$22+N50*$AE$23+O50*$AE$24+P50*$AE$25+Q50*$AE$26+R50*$AE$27+S50*$AE$28+T50*$AE$29+U50*$AE$30 | W50: =1/(1+EXP(-V50)) | X50: =-IF(C50=1,LN(W50),LN(1-W50)) | Y50: ='1 prepared data'!V43 | Z50: =Y50*X50 | AA50: =IF(W50>$AE$33,1,0) | AB50: =IF(AA50=C50,1,0)
A51: ='1 prepared data'!A44 | B51: ='1 prepared data'!U44 | C51: ='1 prepared data'!B44 | D51: ='1 prepared data'!C44 | E51: ='1 prepared data'!D44 | F51: ='1 prepared data'!E44 | G51: ='1 prepared data'!F44 | H51: ='1 prepared data'!G44 | I51: ='1 prepared data'!H44 | J51: ='1 prepared data'!I44 | ... U51: ='1 prepared data'!T44 | V51: =$AE$12+D51*$AE$13+E51*$AE$14+F51*$AE$15+G51*$AE$16+H51*$AE$17+I51*$AE$18+J51*$AE$19+K51*$AE$20+L51*$AE$21+M51*$AE$22+N51*$AE$23+O51*$AE$24+P51*$AE$25+Q51*$AE$26+R51*$AE$27+S51*$AE$28+T51*$AE$29+U51*$AE$30 | W51: =1/(1+EXP(-V51)) | X51: =-IF(C51=1,LN(W51),LN(1-W51)) | Y51: ='1 prepared data'!V44 | Z51: =Y51*X51 | AA51: =IF(W51>$AE$33,1,0) | AB51: =IF(AA51=C51,1,0)
A52: ='1 prepared data'!A45 | B52: ='1 prepared data'!U45 | C52: ='1 prepared data'!B45 | D52: ='1 prepared data'!C45 | E52: ='1 prepared data'!D45 | F52: ='1 prepared data'!E45 | G52: ='1 prepared data'!F45 | H52: ='1 prepared data'!G45 | I52: ='1 prepared data'!H45 | J52: ='1 prepared data'!I45 | ... U52: ='1 prepared data'!T45 | V52: =$AE$12+D52*$AE$13+E52*$AE$14+F52*$AE$15+G52*$AE$16+H52*$AE$17+I52*$AE$18+J52*$AE$19+K52*$AE$20+L52*$AE$21+M52*$AE$22+N52*$AE$23+O52*$AE$24+P52*$AE$25+Q52*$AE$26+R52*$AE$27+S52*$AE$28+T52*$AE$29+U52*$AE$30 | W52: =1/(1+EXP(-V52)) | X52: =-IF(C52=1,LN(W52),LN(1-W52)) | Y52: ='1 prepared data'!V45 | Z52: =Y52*X52 | AA52: =IF(W52>$AE$33,1,0) | AB52: =IF(AA52=C52,1,0)
A53: ='1 prepared data'!A46 | B53: ='1 prepared data'!U46 | C53: ='1 prepared data'!B46 | D53: ='1 prepared data'!C46 | E53: ='1 prepared data'!D46 | F53: ='1 prepared data'!E46 | G53: ='1 prepared data'!F46 | H53: ='1 prepared data'!G46 | I53: ='1 prepared data'!H46 | J53: ='1 prepared data'!I46 | ... U53: ='1 prepared data'!T46 | V53: =$AE$12+D53*$AE$13+E53*$AE$14+F53*$AE$15+G53*$AE$16+H53*$AE$17+I53*$AE$18+J53*$AE$19+K53*$AE$20+L53*$AE$21+M53*$AE$22+N53*$AE$23+O53*$AE$24+P53*$AE$25+Q53*$AE$26+R53*$AE$27+S53*$AE$28+T53*$AE$29+U53*$AE$30 | W53: =1/(1+EXP(-V53)) | X53: =-IF(C53=1,LN(W53),LN(1-W53)) | Y53: ='1 prepared data'!V46 | Z53: =Y53*X53 | AA53: =IF(W53>$AE$33,1,0) | AB53: =IF(AA53=C53,1,0)
A54: ='1 prepared data'!A47 | B54: ='1 prepared data'!U47 | C54: ='1 prepared data'!B47 | D54: ='1 prepared data'!C47 | E54: ='1 prepared data'!D47 | F54: ='1 prepared data'!E47 | G54: ='1 prepared data'!F47 | H54: ='1 prepared data'!G47 | I54: ='1 prepared data'!H47 | J54: ='1 prepared data'!I47 | ... U54: ='1 prepared data'!T47 | V54: =$AE$12+D54*$AE$13+E54*$AE$14+F54*$AE$15+G54*$AE$16+H54*$AE$17+I54*$AE$18+J54*$AE$19+K54*$AE$20+L54*$AE$21+M54*$AE$22+N54*$AE$23+O54*$AE$24+P54*$AE$25+Q54*$AE$26+R54*$AE$27+S54*$AE$28+T54*$AE$29+U54*$AE$30 | W54: =1/(1+EXP(-V54)) | X54: =-IF(C54=1,LN(W54),LN(1-W54)) | Y54: ='1 prepared data'!V47 | Z54: =Y54*X54 | AA54: =IF(W54>$AE$33,1,0) | AB54: =IF(AA54=C54,1,0)
A55: ='1 prepared data'!A48 | B55: ='1 prepared data'!U48 | C55: ='1 prepared data'!B48 | D55: ='1 prepared data'!C48 | E55: ='1 prepared data'!D48 | F55: ='1 prepared data'!E48 | G55: ='1 prepared data'!F48 | H55: ='1 prepared data'!G48 | I55: ='1 prepared data'!H48 | J55: ='1 prepared data'!I48 | ... U55: ='1 prepared data'!T48 | V55: =$AE$12+D55*$AE$13+E55*$AE$14+F55*$AE$15+G55*$AE$16+H55*$AE$17+I55*$AE$18+J55*$AE$19+K55*$AE$20+L55*$AE$21+M55*$AE$22+N55*$AE$23+O55*$AE$24+P55*$AE$25+Q55*$AE$26+R55*$AE$27+S55*$AE$28+T55*$AE$29+U55*$AE$30 | W55: =1/(1+EXP(-V55)) | X55: =-IF(C55=1,LN(W55),LN(1-W55)) | Y55: ='1 prepared data'!V48 | Z55: =Y55*X55 | AA55: =IF(W55>$AE$33,1,0) | AB55: =IF(AA55=C55,1,0)
A56: ='1 prepared data'!A49 | B56: ='1 prepared data'!U49 | C56: ='1 prepared data'!B49 | D56: ='1 prepared data'!C49 | E56: ='1 prepared data'!D49 | F56: ='1 prepared data'!E49 | G56: ='1 prepared data'!F49 | H56: ='1 prepared data'!G49 | I56: ='1 prepared data'!H49 | J56: ='1 prepared data'!I49 | ... U56: ='1 prepared data'!T49 | V56: =$AE$12+D56*$AE$13+E56*$AE$14+F56*$AE$15+G56*$AE$16+H56*$AE$17+I56*$AE$18+J56*$AE$19+K56*$AE$20+L56*$AE$21+M56*$AE$22+N56*$AE$23+O56*$AE$24+P56*$AE$25+Q56*$AE$26+R56*$AE$27+S56*$AE$28+T56*$AE$29+U56*$AE$30 | W56: =1/(1+EXP(-V56)) | X56: =-IF(C56=1,LN(W56),LN(1-W56)) | Y56: ='1 prepared data'!V49 | Z56: =Y56*X56 | AA56: =IF(W56>$AE$33,1,0) | AB56: =IF(AA56=C56,1,0)
A57: ='1 prepared data'!A50 | B57: ='1 prepared data'!U50 | C57: ='1 prepared data'!B50 | D57: ='1 prepared data'!C50 | E57: ='1 prepared data'!D50 | F57: ='1 prepared data'!E50 | G57: ='1 prepared data'!F50 | H57: ='1 prepared data'!G50 | I57: ='1 prepared data'!H50 | J57: ='1 prepared data'!I50 | ... U57: ='1 prepared data'!T50 | V57: =$AE$12+D57*$AE$13+E57*$AE$14+F57*$AE$15+G57*$AE$16+H57*$AE$17+I57*$AE$18+J57*$AE$19+K57*$AE$20+L57*$AE$21+M57*$AE$22+N57*$AE$23+O57*$AE$24+P57*$AE$25+Q57*$AE$26+R57*$AE$27+S57*$AE$28+T57*$AE$29+U57*$AE$30 | W57: =1/(1+EXP(-V57)) | X57: =-IF(C57=1,LN(W57),LN(1-W57)) | Y57: ='1 prepared data'!V50 | Z57: =Y57*X57 | AA57: =IF(W57>$AE$33,1,0) | AB57: =IF(AA57=C57,1,0)
A58: ='1 prepared data'!A51 | B58: ='1 prepared data'!U51 | C58: ='1 prepared data'!B51 | D58: ='1 prepared data'!C51 | E58: ='1 prepared data'!D51 | F58: ='1 prepared data'!E51 | G58: ='1 prepared data'!F51 | H58: ='1 prepared data'!G51 | I58: ='1 prepared data'!H51 | J58: ='1 prepared data'!I51 | ... U58: ='1 prepared data'!T51 | V58: =$AE$12+D58*$AE$13+E58*$AE$14+F58*$AE$15+G58*$AE$16+H58*$AE$17+I58*$AE$18+J58*$AE$19+K58*$AE$20+L58*$AE$21+M58*$AE$22+N58*$AE$23+O58*$AE$24+P58*$AE$25+Q58*$AE$26+R58*$AE$27+S58*$AE$28+T58*$AE$29+U58*$AE$30 | W58: =1/(1+EXP(-V58)) | X58: =-IF(C58=1,LN(W58),LN(1-W58)) | Y58: ='1 prepared data'!V51 | Z58: =Y58*X58 | AA58: =IF(W58>$AE$33,1,0) | AB58: =IF(AA58=C58,1,0)
A59: ='1 prepared data'!A52 | B59: ='1 prepared data'!U52 | C59: ='1 prepared data'!B52 | D59: ='1 prepared data'!C52 | E59: ='1 prepared data'!D52 | F59: ='1 prepared data'!E52 | G59: ='1 prepared data'!F52 | H59: ='1 prepared data'!G52 | I59: ='1 prepared data'!H52 | J59: ='1 prepared data'!I52 | ... U59: ='1 prepared data'!T52 | V59: =$AE$12+D59*$AE$13+E59*$AE$14+F59*$AE$15+G59*$AE$16+H59*$AE$17+I59*$AE$18+J59*$AE$19+K59*$AE$20+L59*$AE$21+M59*$AE$22+N59*$AE$23+O59*$AE$24+P59*$AE$25+Q59*$AE$26+R59*$AE$27+S59*$AE$28+T59*$AE$29+U59*$AE$30 | W59: =1/(1+EXP(-V59)) | X59: =-IF(C59=1,LN(W59),LN(1-W59)) | Y59: ='1 prepared data'!V52 | Z59: =Y59*X59 | AA59: =IF(W59>$AE$33,1,0) | AB59: =IF(AA59=C59,1,0)
... A1011: ='1 prepared data'!A1004 | B1011: ='1 prepared data'!U1004 | C1011: ='1 prepared data'!B1004 | D1011: ='1 prepared data'!C1004 | E1011: ='1 prepared data'!D1004 | F1011: ='1 prepared data'!E1004 | G1011: ='1 prepared data'!F1004 | H1011: ='1 prepared data'!G1004 | I1011: ='1 prepared data'!H1004 | J1011: ='1 prepared data'!I1004 | ... U1011: ='1 prepared data'!T1004 | V1011: =$AE$12+D1011*$AE$13+E1011*$AE$14+F1011*$AE$15+G1011*$AE$16+H1011*$AE$17+I1011*$AE$18+J1011*$AE$19+K1011*$AE$20+L1011*$AE$21+M1011*$AE$22+N1011*$AE$23+O1011*$AE$24+P1011*$AE$25+Q1011*$AE$26+R1011*$AE$27+S1011*$AE$28+T1011*$AE$29+U1011*$AE$30 | W1011: =1/(1+EXP(-V1011)) | X1011: =-IF(C1011=1,LN(W1011),LN(1-W1011)) | Y1011: ='1 prepared data'!V1004 | Z1011: =Y1011*X1011 | AA1011: =IF(W1011>$AE$33,1,0) | AB1011: =IF(AA1011=C1011,1,0)

Sheet 5 oversampling
A1: Oversampling: repeating the defaulters
A2: The mirror-image fix: instead of removing good payers, the defaulters are repeated until the two classes weigh the same. In the general case the count is not an integer: with 490 good and 210 bad payers each defaulter would have to be repeated 490/210 = 2.33 times, and that is handled either by sampling 490 rows with replacement from the 210 defaulters (some come out twice, others three times; that is what RandomOverSampler in imbalanced-learn does) or by giving each defaulter weight 2.33 in the cost function. This sheet uses the second route and starts with a simple number: each defaulter appears twice (420 versus 490). There is no need to paste rows: repeating a row k times is exactly the same as multiplying its loss by k, which is what the column 'row weight' does, and k does not have to be an integer. That also shows that oversampling and class weights are the same idea in different clothes: with repetitions 2.333 and 1 (or 1.667 and 0.714) this sheet is identical to sheet 3.
A3: Oversampling by repetition carries a risk with flexible models (trees, neural networks): the same repeated row gets memorized. With a logistic nothing serious happens, because the line cannot memorize rows. That is why, for the logistic, the recommendation is class weights, which does the same thing without duplicating data.
AD10: Model weights (theta): start from the unbalanced solution | AI10: EVALUATION ON TESTING (with the light blue threshold)
A11: id | B11: set | C11: y | D11: duration | E11: amount | F11: age | G11: installment_pct_income | H11: chk_negative | I11: chk_0_200 | J11: chk_over_200 | K11: hist_critical | L11: hist_delays | M11: hist_no_credits | N11: sav_100_1000 | O11: sav_over_1000 | P11: sav_unknown | Q11: housing_rent | R11: housing_free | S11: purpose_car | T11: purpose_radio_tv | U11: purpose_furniture | V11: Z (line) | W11: p (logistic) | X11: loss | Y11: row weight | Z11: weighted loss | AA11: prediction | AB11: correct | AD11: variable | AE11: theta (light blue) | AF11: scikit-learn reference for this variant
A12: ='1 prepared data'!A5 | B12: ='1 prepared data'!U5 | C12: ='1 prepared data'!B5 | D12: ='1 prepared data'!C5 | E12: ='1 prepared data'!D5 | F12: ='1 prepared data'!E5 | G12: ='1 prepared data'!F5 | H12: ='1 prepared data'!G5 | I12: ='1 prepared data'!H5 | J12: ='1 prepared data'!I5 | ... U12: ='1 prepared data'!T5 | V12: =$AE$12+D12*$AE$13+E12*$AE$14+F12*$AE$15+G12*$AE$16+H12*$AE$17+I12*$AE$18+J12*$AE$19+K12*$AE$20+L12*$AE$21+M12*$AE$22+N12*$AE$23+O12*$AE$24+P12*$AE$25+Q12*$AE$26+R12*$AE$27+S12*$AE$28+T12*$AE$29+U12*$AE$30 | W12: =1/(1+EXP(-V12)) | X12: =-IF(C12=1,LN(W12),LN(1-W12)) | Y12: =IF(C12=1,$AE$32,$AE$33) | Z12: =Y12*X12 | AA12: =IF(W12>$AE$34,1,0) | AB12: =IF(AA12=C12,1,0) | AD12: intercept | AE12: -1.341271 | AF12: -0.64141731
A13: ='1 prepared data'!A6 | B13: ='1 prepared data'!U6 | C13: ='1 prepared data'!B6 | D13: ='1 prepared data'!C6 | E13: ='1 prepared data'!D6 | F13: ='1 prepared data'!E6 | G13: ='1 prepared data'!F6 | H13: ='1 prepared data'!G6 | I13: ='1 prepared data'!H6 | J13: ='1 prepared data'!I6 | ... U13: ='1 prepared data'!T6 | V13: =$AE$12+D13*$AE$13+E13*$AE$14+F13*$AE$15+G13*$AE$16+H13*$AE$17+I13*$AE$18+J13*$AE$19+K13*$AE$20+L13*$AE$21+M13*$AE$22+N13*$AE$23+O13*$AE$24+P13*$AE$25+Q13*$AE$26+R13*$AE$27+S13*$AE$28+T13*$AE$29+U13*$AE$30 | W13: =1/(1+EXP(-V13)) | X13: =-IF(C13=1,LN(W13),LN(1-W13)) | Y13: =IF(C13=1,$AE$32,$AE$33) | Z13: =Y13*X13 | AA13: =IF(W13>$AE$34,1,0) | AB13: =IF(AA13=C13,1,0) | AD13: duration | AE13: 0.32470125 | AF13: 0.29722551 | AK13: predicted 0 | AL13: predicted 1 | AM13: total
A14: ='1 prepared data'!A7 | B14: ='1 prepared data'!U7 | C14: ='1 prepared data'!B7 | D14: ='1 prepared data'!C7 | E14: ='1 prepared data'!D7 | F14: ='1 prepared data'!E7 | G14: ='1 prepared data'!F7 | H14: ='1 prepared data'!G7 | I14: ='1 prepared data'!H7 | J14: ='1 prepared data'!I7 | ... U14: ='1 prepared data'!T7 | V14: =$AE$12+D14*$AE$13+E14*$AE$14+F14*$AE$15+G14*$AE$16+H14*$AE$17+I14*$AE$18+J14*$AE$19+K14*$AE$20+L14*$AE$21+M14*$AE$22+N14*$AE$23+O14*$AE$24+P14*$AE$25+Q14*$AE$26+R14*$AE$27+S14*$AE$28+T14*$AE$29+U14*$AE$30 | W14: =1/(1+EXP(-V14)) | X14: =-IF(C14=1,LN(W14),LN(1-W14)) | Y14: =IF(C14=1,$AE$32,$AE$33) | Z14: =Y14*X14 | AA14: =IF(W14>$AE$34,1,0) | AB14: =IF(AA14=C14,1,0) | AD14: amount | AE14: 0.11635359 | AF14: 0.15259468 | AI14: actual 0 (good payer) | AJ14: TN | FP | AK14: =COUNTIFS($B$12:$B$1011,"testing",$C$12:$C$1011,0,$AA$12:$AA$1011,0) | AL14: =COUNTIFS($B$12:$B$1011,"testing",$C$12:$C$1011,0,$AA$12:$AA$1011,1) | AM14: =AK14+AL14
A15: ='1 prepared data'!A8 | B15: ='1 prepared data'!U8 | C15: ='1 prepared data'!B8 | D15: ='1 prepared data'!C8 | E15: ='1 prepared data'!D8 | F15: ='1 prepared data'!E8 | G15: ='1 prepared data'!F8 | H15: ='1 prepared data'!G8 | I15: ='1 prepared data'!H8 | J15: ='1 prepared data'!I8 | ... U15: ='1 prepared data'!T8 | V15: =$AE$12+D15*$AE$13+E15*$AE$14+F15*$AE$15+G15*$AE$16+H15*$AE$17+I15*$AE$18+J15*$AE$19+K15*$AE$20+L15*$AE$21+M15*$AE$22+N15*$AE$23+O15*$AE$24+P15*$AE$25+Q15*$AE$26+R15*$AE$27+S15*$AE$28+T15*$AE$29+U15*$AE$30 | W15: =1/(1+EXP(-V15)) | X15: =-IF(C15=1,LN(W15),LN(1-W15)) | Y15: =IF(C15=1,$AE$32,$AE$33) | Z15: =Y15*X15 | AA15: =IF(W15>$AE$34,1,0) | AB15: =IF(AA15=C15,1,0) | AD15: age | AE15: -0.099145225 | AF15: -0.12196678 | AI15: actual 1 (defaulter) | AJ15: FN | TP | AK15: =COUNTIFS($B$12:$B$1011,"testing",$C$12:$C$1011,1,$AA$12:$AA$1011,0) | AL15: =COUNTIFS($B$12:$B$1011,"testing",$C$12:$C$1011,1,$AA$12:$AA$1011,1) | AM15: =AK15+AL15
A16: ='1 prepared data'!A9 | B16: ='1 prepared data'!U9 | C16: ='1 prepared data'!B9 | D16: ='1 prepared data'!C9 | E16: ='1 prepared data'!D9 | F16: ='1 prepared data'!E9 | G16: ='1 prepared data'!F9 | H16: ='1 prepared data'!G9 | I16: ='1 prepared data'!H9 | J16: ='1 prepared data'!I9 | ... U16: ='1 prepared data'!T9 | V16: =$AE$12+D16*$AE$13+E16*$AE$14+F16*$AE$15+G16*$AE$16+H16*$AE$17+I16*$AE$18+J16*$AE$19+K16*$AE$20+L16*$AE$21+M16*$AE$22+N16*$AE$23+O16*$AE$24+P16*$AE$25+Q16*$AE$26+R16*$AE$27+S16*$AE$28+T16*$AE$29+U16*$AE$30 | W16: =1/(1+EXP(-V16)) | X16: =-IF(C16=1,LN(W16),LN(1-W16)) | Y16: =IF(C16=1,$AE$32,$AE$33) | Z16: =Y16*X16 | AA16: =IF(W16>$AE$34,1,0) | AB16: =IF(AA16=C16,1,0) | AD16: installment_pct_income | AE16: 0.28721577 | AF16: 0.28628195 | AI16: total | AK16: =AK14+AK15 | AL16: =AL14+AL15 | AM16: =AM14+AM15
A17: ='1 prepared data'!A10 | B17: ='1 prepared data'!U10 | C17: ='1 prepared data'!B10 | D17: ='1 prepared data'!C10 | E17: ='1 prepared data'!D10 | F17: ='1 prepared data'!E10 | G17: ='1 prepared data'!F10 | H17: ='1 prepared data'!G10 | I17: ='1 prepared data'!H10 | J17: ='1 prepared data'!I10 | ... U17: ='1 prepared data'!T10 | V17: =$AE$12+D17*$AE$13+E17*$AE$14+F17*$AE$15+G17*$AE$16+H17*$AE$17+I17*$AE$18+J17*$AE$19+K17*$AE$20+L17*$AE$21+M17*$AE$22+N17*$AE$23+O17*$AE$24+P17*$AE$25+Q17*$AE$26+R17*$AE$27+S17*$AE$28+T17*$AE$29+U17*$AE$30 | W17: =1/(1+EXP(-V17)) | X17: =-IF(C17=1,LN(W17),LN(1-W17)) | Y17: =IF(C17=1,$AE$32,$AE$33) | Z17: =Y17*X17 | AA17: =IF(W17>$AE$34,1,0) | AB17: =IF(AA17=C17,1,0) | AD17: chk_negative | AE17: 1.5464027 | AF17: 1.5670575
A18: ='1 prepared data'!A11 | B18: ='1 prepared data'!U11 | C18: ='1 prepared data'!B11 | D18: ='1 prepared data'!C11 | E18: ='1 prepared data'!D11 | F18: ='1 prepared data'!E11 | G18: ='1 prepared data'!F11 | H18: ='1 prepared data'!G11 | I18: ='1 prepared data'!H11 | J18: ='1 prepared data'!I11 | ... U18: ='1 prepared data'!T11 | V18: =$AE$12+D18*$AE$13+E18*$AE$14+F18*$AE$15+G18*$AE$16+H18*$AE$17+I18*$AE$18+J18*$AE$19+K18*$AE$20+L18*$AE$21+M18*$AE$22+N18*$AE$23+O18*$AE$24+P18*$AE$25+Q18*$AE$26+R18*$AE$27+S18*$AE$28+T18*$AE$29+U18*$AE$30 | W18: =1/(1+EXP(-V18)) | X18: =-IF(C18=1,LN(W18),LN(1-W18)) | Y18: =IF(C18=1,$AE$32,$AE$33) | Z18: =Y18*X18 | AA18: =IF(W18>$AE$34,1,0) | AB18: =IF(AA18=C18,1,0) | AD18: chk_0_200 | AE18: 1.2949978 | AF18: 1.3286433 | AJ18: precision | AK18: recall | AL18: f1-score | AM18: support
A19: ='1 prepared data'!A12 | B19: ='1 prepared data'!U12 | C19: ='1 prepared data'!B12 | D19: ='1 prepared data'!C12 | E19: ='1 prepared data'!D12 | F19: ='1 prepared data'!E12 | G19: ='1 prepared data'!F12 | H19: ='1 prepared data'!G12 | I19: ='1 prepared data'!H12 | J19: ='1 prepared data'!I12 | ... U19: ='1 prepared data'!T12 | V19: =$AE$12+D19*$AE$13+E19*$AE$14+F19*$AE$15+G19*$AE$16+H19*$AE$17+I19*$AE$18+J19*$AE$19+K19*$AE$20+L19*$AE$21+M19*$AE$22+N19*$AE$23+O19*$AE$24+P19*$AE$25+Q19*$AE$26+R19*$AE$27+S19*$AE$28+T19*$AE$29+U19*$AE$30 | W19: =1/(1+EXP(-V19)) | X19: =-IF(C19=1,LN(W19),LN(1-W19)) | Y19: =IF(C19=1,$AE$32,$AE$33) | Z19: =Y19*X19 | AA19: =IF(W19>$AE$34,1,0) | AB19: =IF(AA19=C19,1,0) | AD19: chk_over_200 | AE19: 0.66836159 | AF19: 0.72838905 | AI19: class 0 (pays) | AJ19: =IF(AK14+AK15=0,0,AK14/(AK14+AK15)) | AK19: =IF(AK14+AL14=0,0,AK14/(AK14+AL14)) | AL19: =IF(AJ19+AK19=0,0,2*AJ19*AK19/(AJ19+AK19)) | AM19: =AM14
A20: ='1 prepared data'!A13 | B20: ='1 prepared data'!U13 | C20: ='1 prepared data'!B13 | D20: ='1 prepared data'!C13 | E20: ='1 prepared data'!D13 | F20: ='1 prepared data'!E13 | G20: ='1 prepared data'!F13 | H20: ='1 prepared data'!G13 | I20: ='1 prepared data'!H13 | J20: ='1 prepared data'!I13 | ... U20: ='1 prepared data'!T13 | V20: =$AE$12+D20*$AE$13+E20*$AE$14+F20*$AE$15+G20*$AE$16+H20*$AE$17+I20*$AE$18+J20*$AE$19+K20*$AE$20+L20*$AE$21+M20*$AE$22+N20*$AE$23+O20*$AE$24+P20*$AE$25+Q20*$AE$26+R20*$AE$27+S20*$AE$28+T20*$AE$29+U20*$AE$30 | W20: =1/(1+EXP(-V20)) | X20: =-IF(C20=1,LN(W20),LN(1-W20)) | Y20: =IF(C20=1,$AE$32,$AE$33) | Z20: =Y20*X20 | AA20: =IF(W20>$AE$34,1,0) | AB20: =IF(AA20=C20,1,0) | AD20: hist_critical | AE20: -0.65734494 | AF20: -0.65739344 | AI20: class 1 (defaults) | AJ20: =IF(AL15+AL14=0,0,AL15/(AL15+AL14)) | AK20: =IF(AL15+AK15=0,0,AL15/(AL15+AK15)) | AL20: =IF(AJ20+AK20=0,0,2*AJ20*AK20/(AJ20+AK20)) | AM20: =AM15
A21: ='1 prepared data'!A14 | B21: ='1 prepared data'!U14 | C21: ='1 prepared data'!B14 | D21: ='1 prepared data'!C14 | E21: ='1 prepared data'!D14 | F21: ='1 prepared data'!E14 | G21: ='1 prepared data'!F14 | H21: ='1 prepared data'!G14 | I21: ='1 prepared data'!H14 | J21: ='1 prepared data'!I14 | ... U21: ='1 prepared data'!T14 | V21: =$AE$12+D21*$AE$13+E21*$AE$14+F21*$AE$15+G21*$AE$16+H21*$AE$17+I21*$AE$18+J21*$AE$19+K21*$AE$20+L21*$AE$21+M21*$AE$22+N21*$AE$23+O21*$AE$24+P21*$AE$25+Q21*$AE$26+R21*$AE$27+S21*$AE$28+T21*$AE$29+U21*$AE$30 | W21: =1/(1+EXP(-V21)) | X21: =-IF(C21=1,LN(W21),LN(1-W21)) | Y21: =IF(C21=1,$AE$32,$AE$33) | Z21: =Y21*X21 | AA21: =IF(W21>$AE$34,1,0) | AB21: =IF(AA21=C21,1,0) | AD21: hist_delays | AE21: -0.040195519 | AF21: -0.021182608 | AI21: accuracy | AL21: =(AL15+AK14)/AM16
A22: ='1 prepared data'!A15 | B22: ='1 prepared data'!U15 | C22: ='1 prepared data'!B15 | D22: ='1 prepared data'!C15 | E22: ='1 prepared data'!D15 | F22: ='1 prepared data'!E15 | G22: ='1 prepared data'!F15 | H22: ='1 prepared data'!G15 | I22: ='1 prepared data'!H15 | J22: ='1 prepared data'!I15 | ... U22: ='1 prepared data'!T15 | V22: =$AE$12+D22*$AE$13+E22*$AE$14+F22*$AE$15+G22*$AE$16+H22*$AE$17+I22*$AE$18+J22*$AE$19+K22*$AE$20+L22*$AE$21+M22*$AE$22+N22*$AE$23+O22*$AE$24+P22*$AE$25+Q22*$AE$26+R22*$AE$27+S22*$AE$28+T22*$AE$29+U22*$AE$30 | W22: =1/(1+EXP(-V22)) | X22: =-IF(C22=1,LN(W22),LN(1-W22)) | Y22: =IF(C22=1,$AE$32,$AE$33) | Z22: =Y22*X22 | AA22: =IF(W22>$AE$34,1,0) | AB22: =IF(AA22=C22,1,0) | AD22: hist_no_credits | AE22: 0.66906563 | AF22: 0.62467505
A23: ='1 prepared data'!A16 | B23: ='1 prepared data'!U16 | C23: ='1 prepared data'!B16 | D23: ='1 prepared data'!C16 | E23: ='1 prepared data'!D16 | F23: ='1 prepared data'!E16 | G23: ='1 prepared data'!F16 | H23: ='1 prepared data'!G16 | I23: ='1 prepared data'!H16 | J23: ='1 prepared data'!I16 | ... U23: ='1 prepared data'!T16 | V23: =$AE$12+D23*$AE$13+E23*$AE$14+F23*$AE$15+G23*$AE$16+H23*$AE$17+I23*$AE$18+J23*$AE$19+K23*$AE$20+L23*$AE$21+M23*$AE$22+N23*$AE$23+O23*$AE$24+P23*$AE$25+Q23*$AE$26+R23*$AE$27+S23*$AE$28+T23*$AE$29+U23*$AE$30 | W23: =1/(1+EXP(-V23)) | X23: =-IF(C23=1,LN(W23),LN(1-W23)) | Y23: =IF(C23=1,$AE$32,$AE$33) | Z23: =Y23*X23 | AA23: =IF(W23>$AE$34,1,0) | AB23: =IF(AA23=C23,1,0) | AD23: sav_100_1000 | AE23: -0.38958343 | AF23: -0.3441662
A24: ='1 prepared data'!A17 | B24: ='1 prepared data'!U17 | C24: ='1 prepared data'!B17 | D24: ='1 prepared data'!C17 | E24: ='1 prepared data'!D17 | F24: ='1 prepared data'!E17 | G24: ='1 prepared data'!F17 | H24: ='1 prepared data'!G17 | I24: ='1 prepared data'!H17 | J24: ='1 prepared data'!I17 | ... U24: ='1 prepared data'!T17 | V24: =$AE$12+D24*$AE$13+E24*$AE$14+F24*$AE$15+G24*$AE$16+H24*$AE$17+I24*$AE$18+J24*$AE$19+K24*$AE$20+L24*$AE$21+M24*$AE$22+N24*$AE$23+O24*$AE$24+P24*$AE$25+Q24*$AE$26+R24*$AE$27+S24*$AE$28+T24*$AE$29+U24*$AE$30 | W24: =1/(1+EXP(-V24)) | X24: =-IF(C24=1,LN(W24),LN(1-W24)) | Y24: =IF(C24=1,$AE$32,$AE$33) | Z24: =Y24*X24 | AA24: =IF(W24>$AE$34,1,0) | AB24: =IF(AA24=C24,1,0) | AD24: sav_over_1000 | AE24: -0.88922386 | AF24: -0.79783805
A25: ='1 prepared data'!A18 | B25: ='1 prepared data'!U18 | C25: ='1 prepared data'!B18 | D25: ='1 prepared data'!C18 | E25: ='1 prepared data'!D18 | F25: ='1 prepared data'!E18 | G25: ='1 prepared data'!F18 | H25: ='1 prepared data'!G18 | I25: ='1 prepared data'!H18 | J25: ='1 prepared data'!I18 | ... U25: ='1 prepared data'!T18 | V25: =$AE$12+D25*$AE$13+E25*$AE$14+F25*$AE$15+G25*$AE$16+H25*$AE$17+I25*$AE$18+J25*$AE$19+K25*$AE$20+L25*$AE$21+M25*$AE$22+N25*$AE$23+O25*$AE$24+P25*$AE$25+Q25*$AE$26+R25*$AE$27+S25*$AE$28+T25*$AE$29+U25*$AE$30 | W25: =1/(1+EXP(-V25)) | X25: =-IF(C25=1,LN(W25),LN(1-W25)) | Y25: =IF(C25=1,$AE$32,$AE$33) | Z25: =Y25*X25 | AA25: =IF(W25>$AE$34,1,0) | AB25: =IF(AA25=C25,1,0) | AD25: sav_unknown | AE25: -1.0760929 | AF25: -0.99414607
A26: ='1 prepared data'!A19 | B26: ='1 prepared data'!U19 | C26: ='1 prepared data'!B19 | D26: ='1 prepared data'!C19 | E26: ='1 prepared data'!D19 | F26: ='1 prepared data'!E19 | G26: ='1 prepared data'!F19 | H26: ='1 prepared data'!G19 | I26: ='1 prepared data'!H19 | J26: ='1 prepared data'!I19 | ... U26: ='1 prepared data'!T19 | V26: =$AE$12+D26*$AE$13+E26*$AE$14+F26*$AE$15+G26*$AE$16+H26*$AE$17+I26*$AE$18+J26*$AE$19+K26*$AE$20+L26*$AE$21+M26*$AE$22+N26*$AE$23+O26*$AE$24+P26*$AE$25+Q26*$AE$26+R26*$AE$27+S26*$AE$28+T26*$AE$29+U26*$AE$30 | W26: =1/(1+EXP(-V26)) | X26: =-IF(C26=1,LN(W26),LN(1-W26)) | Y26: =IF(C26=1,$AE$32,$AE$33) | Z26: =Y26*X26 | AA26: =IF(W26>$AE$34,1,0) | AB26: =IF(AA26=C26,1,0) | AD26: housing_rent | AE26: 0.65383718 | AF26: 0.62303989
A27: ='1 prepared data'!A20 | B27: ='1 prepared data'!U20 | C27: ='1 prepared data'!B20 | D27: ='1 prepared data'!C20 | E27: ='1 prepared data'!D20 | F27: ='1 prepared data'!E20 | G27: ='1 prepared data'!F20 | H27: ='1 prepared data'!G20 | I27: ='1 prepared data'!H20 | J27: ='1 prepared data'!I20 | ... U27: ='1 prepared data'!T20 | V27: =$AE$12+D27*$AE$13+E27*$AE$14+F27*$AE$15+G27*$AE$16+H27*$AE$17+I27*$AE$18+J27*$AE$19+K27*$AE$20+L27*$AE$21+M27*$AE$22+N27*$AE$23+O27*$AE$24+P27*$AE$25+Q27*$AE$26+R27*$AE$27+S27*$AE$28+T27*$AE$29+U27*$AE$30 | W27: =1/(1+EXP(-V27)) | X27: =-IF(C27=1,LN(W27),LN(1-W27)) | Y27: =IF(C27=1,$AE$32,$AE$33) | Z27: =Y27*X27 | AA27: =IF(W27>$AE$34,1,0) | AB27: =IF(AA27=C27,1,0) | AD27: housing_free | AE27: 0.19536536 | AF27: 0.22187124
A28: ='1 prepared data'!A21 | B28: ='1 prepared data'!U21 | C28: ='1 prepared data'!B21 | D28: ='1 prepared data'!C21 | E28: ='1 prepared data'!D21 | F28: ='1 prepared data'!E21 | G28: ='1 prepared data'!F21 | H28: ='1 prepared data'!G21 | I28: ='1 prepared data'!H21 | J28: ='1 prepared data'!I21 | ... U28: ='1 prepared data'!T21 | V28: =$AE$12+D28*$AE$13+E28*$AE$14+F28*$AE$15+G28*$AE$16+H28*$AE$17+I28*$AE$18+J28*$AE$19+K28*$AE$20+L28*$AE$21+M28*$AE$22+N28*$AE$23+O28*$AE$24+P28*$AE$25+Q28*$AE$26+R28*$AE$27+S28*$AE$28+T28*$AE$29+U28*$AE$30 | W28: =1/(1+EXP(-V28)) | X28: =-IF(C28=1,LN(W28),LN(1-W28)) | Y28: =IF(C28=1,$AE$32,$AE$33) | Z28: =Y28*X28 | AA28: =IF(W28>$AE$34,1,0) | AB28: =IF(AA28=C28,1,0) | AD28: purpose_car | AE28: -0.080165476 | AF28: -0.14918048
A29: ='1 prepared data'!A22 | B29: ='1 prepared data'!U22 | C29: ='1 prepared data'!B22 | D29: ='1 prepared data'!C22 | E29: ='1 prepared data'!D22 | F29: ='1 prepared data'!E22 | G29: ='1 prepared data'!F22 | H29: ='1 prepared data'!G22 | I29: ='1 prepared data'!H22 | J29: ='1 prepared data'!I22 | ... U29: ='1 prepared data'!T22 | V29: =$AE$12+D29*$AE$13+E29*$AE$14+F29*$AE$15+G29*$AE$16+H29*$AE$17+I29*$AE$18+J29*$AE$19+K29*$AE$20+L29*$AE$21+M29*$AE$22+N29*$AE$23+O29*$AE$24+P29*$AE$25+Q29*$AE$26+R29*$AE$27+S29*$AE$28+T29*$AE$29+U29*$AE$30 | W29: =1/(1+EXP(-V29)) | X29: =-IF(C29=1,LN(W29),LN(1-W29)) | Y29: =IF(C29=1,$AE$32,$AE$33) | Z29: =Y29*X29 | AA29: =IF(W29>$AE$34,1,0) | AB29: =IF(AA29=C29,1,0) | AD29: purpose_radio_tv | AE29: -0.52021065 | AF29: -0.58384072
A30: ='1 prepared data'!A23 | B30: ='1 prepared data'!U23 | C30: ='1 prepared data'!B23 | D30: ='1 prepared data'!C23 | E30: ='1 prepared data'!D23 | F30: ='1 prepared data'!E23 | G30: ='1 prepared data'!F23 | H30: ='1 prepared data'!G23 | I30: ='1 prepared data'!H23 | J30: ='1 prepared data'!I23 | ... U30: ='1 prepared data'!T23 | V30: =$AE$12+D30*$AE$13+E30*$AE$14+F30*$AE$15+G30*$AE$16+H30*$AE$17+I30*$AE$18+J30*$AE$19+K30*$AE$20+L30*$AE$21+M30*$AE$22+N30*$AE$23+O30*$AE$24+P30*$AE$25+Q30*$AE$26+R30*$AE$27+S30*$AE$28+T30*$AE$29+U30*$AE$30 | W30: =1/(1+EXP(-V30)) | X30: =-IF(C30=1,LN(W30),LN(1-W30)) | Y30: =IF(C30=1,$AE$32,$AE$33) | Z30: =Y30*X30 | AA30: =IF(W30>$AE$34,1,0) | AB30: =IF(AA30=C30,1,0) | AD30: purpose_furniture | AE30: -0.28180274 | AF30: -0.3042255
A31: ='1 prepared data'!A24 | B31: ='1 prepared data'!U24 | C31: ='1 prepared data'!B24 | D31: ='1 prepared data'!C24 | E31: ='1 prepared data'!D24 | F31: ='1 prepared data'!E24 | G31: ='1 prepared data'!F24 | H31: ='1 prepared data'!G24 | I31: ='1 prepared data'!H24 | J31: ='1 prepared data'!I24 | ... U31: ='1 prepared data'!T24 | V31: =$AE$12+D31*$AE$13+E31*$AE$14+F31*$AE$15+G31*$AE$16+H31*$AE$17+I31*$AE$18+J31*$AE$19+K31*$AE$20+L31*$AE$21+M31*$AE$22+N31*$AE$23+O31*$AE$24+P31*$AE$25+Q31*$AE$26+R31*$AE$27+S31*$AE$28+T31*$AE$29+U31*$AE$30 | W31: =1/(1+EXP(-V31)) | X31: =-IF(C31=1,LN(W31),LN(1-W31)) | Y31: =IF(C31=1,$AE$32,$AE$33) | Z31: =Y31*X31 | AA31: =IF(W31>$AE$34,1,0) | AB31: =IF(AA31=C31,1,0)
A32: ='1 prepared data'!A25 | B32: ='1 prepared data'!U25 | C32: ='1 prepared data'!B25 | D32: ='1 prepared data'!C25 | E32: ='1 prepared data'!D25 | F32: ='1 prepared data'!E25 | G32: ='1 prepared data'!F25 | H32: ='1 prepared data'!G25 | I32: ='1 prepared data'!H25 | J32: ='1 prepared data'!I25 | ... U32: ='1 prepared data'!T25 | V32: =$AE$12+D32*$AE$13+E32*$AE$14+F32*$AE$15+G32*$AE$16+H32*$AE$17+I32*$AE$18+J32*$AE$19+K32*$AE$20+L32*$AE$21+M32*$AE$22+N32*$AE$23+O32*$AE$24+P32*$AE$25+Q32*$AE$26+R32*$AE$27+S32*$AE$28+T32*$AE$29+U32*$AE$30 | W32: =1/(1+EXP(-V32)) | X32: =-IF(C32=1,LN(W32),LN(1-W32)) | Y32: =IF(C32=1,$AE$32,$AE$33) | Z32: =Y32*X32 | AA32: =IF(W32>$AE$34,1,0) | AB32: =IF(AA32=C32,1,0) | AD32: repetitions of each defaulter | AE32: 2
A33: ='1 prepared data'!A26 | B33: ='1 prepared data'!U26 | C33: ='1 prepared data'!B26 | D33: ='1 prepared data'!C26 | E33: ='1 prepared data'!D26 | F33: ='1 prepared data'!E26 | G33: ='1 prepared data'!F26 | H33: ='1 prepared data'!G26 | I33: ='1 prepared data'!H26 | J33: ='1 prepared data'!I26 | ... U33: ='1 prepared data'!T26 | V33: =$AE$12+D33*$AE$13+E33*$AE$14+F33*$AE$15+G33*$AE$16+H33*$AE$17+I33*$AE$18+J33*$AE$19+K33*$AE$20+L33*$AE$21+M33*$AE$22+N33*$AE$23+O33*$AE$24+P33*$AE$25+Q33*$AE$26+R33*$AE$27+S33*$AE$28+T33*$AE$29+U33*$AE$30 | W33: =1/(1+EXP(-V33)) | X33: =-IF(C33=1,LN(W33),LN(1-W33)) | Y33: =IF(C33=1,$AE$32,$AE$33) | Z33: =Y33*X33 | AA33: =IF(W33>$AE$34,1,0) | AB33: =IF(AA33=C33,1,0) | AD33: repetitions of each good payer | AE33: 1
A34: ='1 prepared data'!A27 | B34: ='1 prepared data'!U27 | C34: ='1 prepared data'!B27 | D34: ='1 prepared data'!C27 | E34: ='1 prepared data'!D27 | F34: ='1 prepared data'!E27 | G34: ='1 prepared data'!F27 | H34: ='1 prepared data'!G27 | I34: ='1 prepared data'!H27 | J34: ='1 prepared data'!I27 | ... U34: ='1 prepared data'!T27 | V34: =$AE$12+D34*$AE$13+E34*$AE$14+F34*$AE$15+G34*$AE$16+H34*$AE$17+I34*$AE$18+J34*$AE$19+K34*$AE$20+L34*$AE$21+M34*$AE$22+N34*$AE$23+O34*$AE$24+P34*$AE$25+Q34*$AE$26+R34*$AE$27+S34*$AE$28+T34*$AE$29+U34*$AE$30 | W34: =1/(1+EXP(-V34)) | X34: =-IF(C34=1,LN(W34),LN(1-W34)) | Y34: =IF(C34=1,$AE$32,$AE$33) | Z34: =Y34*X34 | AA34: =IF(W34>$AE$34,1,0) | AB34: =IF(AA34=C34,1,0) | AD34: threshold | AE34: 0.5
A35: ='1 prepared data'!A28 | B35: ='1 prepared data'!U28 | C35: ='1 prepared data'!B28 | D35: ='1 prepared data'!C28 | E35: ='1 prepared data'!D28 | F35: ='1 prepared data'!E28 | G35: ='1 prepared data'!F28 | H35: ='1 prepared data'!G28 | I35: ='1 prepared data'!H28 | J35: ='1 prepared data'!I28 | ... U35: ='1 prepared data'!T28 | V35: =$AE$12+D35*$AE$13+E35*$AE$14+F35*$AE$15+G35*$AE$16+H35*$AE$17+I35*$AE$18+J35*$AE$19+K35*$AE$20+L35*$AE$21+M35*$AE$22+N35*$AE$23+O35*$AE$24+P35*$AE$25+Q35*$AE$26+R35*$AE$27+S35*$AE$28+T35*$AE$29+U35*$AE$30 | W35: =1/(1+EXP(-V35)) | X35: =-IF(C35=1,LN(W35),LN(1-W35)) | Y35: =IF(C35=1,$AE$32,$AE$33) | Z35: =Y35*X35 | AA35: =IF(W35>$AE$34,1,0) | AB35: =IF(AA35=C35,1,0)
A36: ='1 prepared data'!A29 | B36: ='1 prepared data'!U29 | C36: ='1 prepared data'!B29 | D36: ='1 prepared data'!C29 | E36: ='1 prepared data'!D29 | F36: ='1 prepared data'!E29 | G36: ='1 prepared data'!F29 | H36: ='1 prepared data'!G29 | I36: ='1 prepared data'!H29 | J36: ='1 prepared data'!I29 | ... U36: ='1 prepared data'!T29 | V36: =$AE$12+D36*$AE$13+E36*$AE$14+F36*$AE$15+G36*$AE$16+H36*$AE$17+I36*$AE$18+J36*$AE$19+K36*$AE$20+L36*$AE$21+M36*$AE$22+N36*$AE$23+O36*$AE$24+P36*$AE$25+Q36*$AE$26+R36*$AE$27+S36*$AE$28+T36*$AE$29+U36*$AE$30 | W36: =1/(1+EXP(-V36)) | X36: =-IF(C36=1,LN(W36),LN(1-W36)) | Y36: =IF(C36=1,$AE$32,$AE$33) | Z36: =Y36*X36 | AA36: =IF(W36>$AE$34,1,0) | AB36: =IF(AA36=C36,1,0) | AD36: RESULTS
A37: ='1 prepared data'!A30 | B37: ='1 prepared data'!U30 | C37: ='1 prepared data'!B30 | D37: ='1 prepared data'!C30 | E37: ='1 prepared data'!D30 | F37: ='1 prepared data'!E30 | G37: ='1 prepared data'!F30 | H37: ='1 prepared data'!G30 | I37: ='1 prepared data'!H30 | J37: ='1 prepared data'!I30 | ... U37: ='1 prepared data'!T30 | V37: =$AE$12+D37*$AE$13+E37*$AE$14+F37*$AE$15+G37*$AE$16+H37*$AE$17+I37*$AE$18+J37*$AE$19+K37*$AE$20+L37*$AE$21+M37*$AE$22+N37*$AE$23+O37*$AE$24+P37*$AE$25+Q37*$AE$26+R37*$AE$27+S37*$AE$28+T37*$AE$29+U37*$AE$30 | W37: =1/(1+EXP(-V37)) | X37: =-IF(C37=1,LN(W37),LN(1-W37)) | Y37: =IF(C37=1,$AE$32,$AE$33) | Z37: =Y37*X37 | AA37: =IF(W37>$AE$34,1,0) | AB37: =IF(AA37=C37,1,0) | AD37: J = sum of weighted training losses (SOLVER OBJECTIVE) | AE37: =SUMPRODUCT(($B$12:$B$1011="training")*$Z$12:$Z$1011)
A38: ='1 prepared data'!A31 | B38: ='1 prepared data'!U31 | C38: ='1 prepared data'!B31 | D38: ='1 prepared data'!C31 | E38: ='1 prepared data'!D31 | F38: ='1 prepared data'!E31 | G38: ='1 prepared data'!F31 | H38: ='1 prepared data'!G31 | I38: ='1 prepared data'!H31 | J38: ='1 prepared data'!I31 | ... U38: ='1 prepared data'!T31 | V38: =$AE$12+D38*$AE$13+E38*$AE$14+F38*$AE$15+G38*$AE$16+H38*$AE$17+I38*$AE$18+J38*$AE$19+K38*$AE$20+L38*$AE$21+M38*$AE$22+N38*$AE$23+O38*$AE$24+P38*$AE$25+Q38*$AE$26+R38*$AE$27+S38*$AE$28+T38*$AE$29+U38*$AE$30 | W38: =1/(1+EXP(-V38)) | X38: =-IF(C38=1,LN(W38),LN(1-W38)) | Y38: =IF(C38=1,$AE$32,$AE$33) | Z38: =Y38*X38 | AA38: =IF(W38>$AE$34,1,0) | AB38: =IF(AA38=C38,1,0) | AD38: sum of row weights in training | AE38: =SUMPRODUCT(($B$12:$B$1011="training")*$Y$12:$Y$1011)
A39: ='1 prepared data'!A32 | B39: ='1 prepared data'!U32 | C39: ='1 prepared data'!B32 | D39: ='1 prepared data'!C32 | E39: ='1 prepared data'!D32 | F39: ='1 prepared data'!E32 | G39: ='1 prepared data'!F32 | H39: ='1 prepared data'!G32 | I39: ='1 prepared data'!H32 | J39: ='1 prepared data'!I32 | ... U39: ='1 prepared data'!T32 | V39: =$AE$12+D39*$AE$13+E39*$AE$14+F39*$AE$15+G39*$AE$16+H39*$AE$17+I39*$AE$18+J39*$AE$19+K39*$AE$20+L39*$AE$21+M39*$AE$22+N39*$AE$23+O39*$AE$24+P39*$AE$25+Q39*$AE$26+R39*$AE$27+S39*$AE$28+T39*$AE$29+U39*$AE$30 | W39: =1/(1+EXP(-V39)) | X39: =-IF(C39=1,LN(W39),LN(1-W39)) | Y39: =IF(C39=1,$AE$32,$AE$33) | Z39: =Y39*X39 | AA39: =IF(W39>$AE$34,1,0) | AB39: =IF(AA39=C39,1,0) | AD39: of which, class 1 | AE39: =SUMPRODUCT(($B$12:$B$1011="training")*($C$12:$C$1011=1)*$Y$12:$Y$1011)
A40: ='1 prepared data'!A33 | B40: ='1 prepared data'!U33 | C40: ='1 prepared data'!B33 | D40: ='1 prepared data'!C33 | E40: ='1 prepared data'!D33 | F40: ='1 prepared data'!E33 | G40: ='1 prepared data'!F33 | H40: ='1 prepared data'!G33 | I40: ='1 prepared data'!H33 | J40: ='1 prepared data'!I33 | ... U40: ='1 prepared data'!T33 | V40: =$AE$12+D40*$AE$13+E40*$AE$14+F40*$AE$15+G40*$AE$16+H40*$AE$17+I40*$AE$18+J40*$AE$19+K40*$AE$20+L40*$AE$21+M40*$AE$22+N40*$AE$23+O40*$AE$24+P40*$AE$25+Q40*$AE$26+R40*$AE$27+S40*$AE$28+T40*$AE$29+U40*$AE$30 | W40: =1/(1+EXP(-V40)) | X40: =-IF(C40=1,LN(W40),LN(1-W40)) | Y40: =IF(C40=1,$AE$32,$AE$33) | Z40: =Y40*X40 | AA40: =IF(W40>$AE$34,1,0) | AB40: =IF(AA40=C40,1,0) | AD40: of which, class 0 | AE40: =SUMPRODUCT(($B$12:$B$1011="training")*($C$12:$C$1011=0)*$Y$12:$Y$1011)
A41: ='1 prepared data'!A34 | B41: ='1 prepared data'!U34 | C41: ='1 prepared data'!B34 | D41: ='1 prepared data'!C34 | E41: ='1 prepared data'!D34 | F41: ='1 prepared data'!E34 | G41: ='1 prepared data'!F34 | H41: ='1 prepared data'!G34 | I41: ='1 prepared data'!H34 | J41: ='1 prepared data'!I34 | ... U41: ='1 prepared data'!T34 | V41: =$AE$12+D41*$AE$13+E41*$AE$14+F41*$AE$15+G41*$AE$16+H41*$AE$17+I41*$AE$18+J41*$AE$19+K41*$AE$20+L41*$AE$21+M41*$AE$22+N41*$AE$23+O41*$AE$24+P41*$AE$25+Q41*$AE$26+R41*$AE$27+S41*$AE$28+T41*$AE$29+U41*$AE$30 | W41: =1/(1+EXP(-V41)) | X41: =-IF(C41=1,LN(W41),LN(1-W41)) | Y41: =IF(C41=1,$AE$32,$AE$33) | Z41: =Y41*X41 | AA41: =IF(W41>$AE$34,1,0) | AB41: =IF(AA41=C41,1,0) | AD41: average testing loss (unweighted) | AE41: =SUMPRODUCT(($B$12:$B$1011="testing")*$X$12:$X$1011)/COUNTIF($B$12:$B$1011,"testing")
A42: ='1 prepared data'!A35 | B42: ='1 prepared data'!U35 | C42: ='1 prepared data'!B35 | D42: ='1 prepared data'!C35 | E42: ='1 prepared data'!D35 | F42: ='1 prepared data'!E35 | G42: ='1 prepared data'!F35 | H42: ='1 prepared data'!G35 | I42: ='1 prepared data'!H35 | J42: ='1 prepared data'!I35 | ... U42: ='1 prepared data'!T35 | V42: =$AE$12+D42*$AE$13+E42*$AE$14+F42*$AE$15+G42*$AE$16+H42*$AE$17+I42*$AE$18+J42*$AE$19+K42*$AE$20+L42*$AE$21+M42*$AE$22+N42*$AE$23+O42*$AE$24+P42*$AE$25+Q42*$AE$26+R42*$AE$27+S42*$AE$28+T42*$AE$29+U42*$AE$30 | W42: =1/(1+EXP(-V42)) | X42: =-IF(C42=1,LN(W42),LN(1-W42)) | Y42: =IF(C42=1,$AE$32,$AE$33) | Z42: =Y42*X42 | AA42: =IF(W42>$AE$34,1,0) | AB42: =IF(AA42=C42,1,0) | AD42: average p on testing (the actual rate is 0.300) | AE42: =SUMPRODUCT(($B$12:$B$1011="testing")*$W$12:$W$1011)/COUNTIF($B$12:$B$1011,"testing")
A43: ='1 prepared data'!A36 | B43: ='1 prepared data'!U36 | C43: ='1 prepared data'!B36 | D43: ='1 prepared data'!C36 | E43: ='1 prepared data'!D36 | F43: ='1 prepared data'!E36 | G43: ='1 prepared data'!F36 | H43: ='1 prepared data'!G36 | I43: ='1 prepared data'!H36 | J43: ='1 prepared data'!I36 | ... U43: ='1 prepared data'!T36 | V43: =$AE$12+D43*$AE$13+E43*$AE$14+F43*$AE$15+G43*$AE$16+H43*$AE$17+I43*$AE$18+J43*$AE$19+K43*$AE$20+L43*$AE$21+M43*$AE$22+N43*$AE$23+O43*$AE$24+P43*$AE$25+Q43*$AE$26+R43*$AE$27+S43*$AE$28+T43*$AE$29+U43*$AE$30 | W43: =1/(1+EXP(-V43)) | X43: =-IF(C43=1,LN(W43),LN(1-W43)) | Y43: =IF(C43=1,$AE$32,$AE$33) | Z43: =Y43*X43 | AA43: =IF(W43>$AE$34,1,0) | AB43: =IF(AA43=C43,1,0) | AD43: testing accuracy | AE43: =SUMPRODUCT(($B$12:$B$1011="testing")*$AB$12:$AB$1011)/COUNTIF($B$12:$B$1011,"testing")
A44: ='1 prepared data'!A37 | B44: ='1 prepared data'!U37 | C44: ='1 prepared data'!B37 | D44: ='1 prepared data'!C37 | E44: ='1 prepared data'!D37 | F44: ='1 prepared data'!E37 | G44: ='1 prepared data'!F37 | H44: ='1 prepared data'!G37 | I44: ='1 prepared data'!H37 | J44: ='1 prepared data'!I37 | ... U44: ='1 prepared data'!T37 | V44: =$AE$12+D44*$AE$13+E44*$AE$14+F44*$AE$15+G44*$AE$16+H44*$AE$17+I44*$AE$18+J44*$AE$19+K44*$AE$20+L44*$AE$21+M44*$AE$22+N44*$AE$23+O44*$AE$24+P44*$AE$25+Q44*$AE$26+R44*$AE$27+S44*$AE$28+T44*$AE$29+U44*$AE$30 | W44: =1/(1+EXP(-V44)) | X44: =-IF(C44=1,LN(W44),LN(1-W44)) | Y44: =IF(C44=1,$AE$32,$AE$33) | Z44: =Y44*X44 | AA44: =IF(W44>$AE$34,1,0) | AB44: =IF(AA44=C44,1,0) | AD44: scikit-learn reference: class 1 recall on testing (threshold 0.5) | AE44: 0.83333333
A45: ='1 prepared data'!A38 | B45: ='1 prepared data'!U38 | C45: ='1 prepared data'!B38 | D45: ='1 prepared data'!C38 | E45: ='1 prepared data'!D38 | F45: ='1 prepared data'!E38 | G45: ='1 prepared data'!F38 | H45: ='1 prepared data'!G38 | I45: ='1 prepared data'!H38 | J45: ='1 prepared data'!I38 | ... U45: ='1 prepared data'!T38 | V45: =$AE$12+D45*$AE$13+E45*$AE$14+F45*$AE$15+G45*$AE$16+H45*$AE$17+I45*$AE$18+J45*$AE$19+K45*$AE$20+L45*$AE$21+M45*$AE$22+N45*$AE$23+O45*$AE$24+P45*$AE$25+Q45*$AE$26+R45*$AE$27+S45*$AE$28+T45*$AE$29+U45*$AE$30 | W45: =1/(1+EXP(-V45)) | X45: =-IF(C45=1,LN(W45),LN(1-W45)) | Y45: =IF(C45=1,$AE$32,$AE$33) | Z45: =Y45*X45 | AA45: =IF(W45>$AE$34,1,0) | AB45: =IF(AA45=C45,1,0) | AD45: scikit-learn reference: class 1 precision on testing | AE45: 0.55970149
A46: ='1 prepared data'!A39 | B46: ='1 prepared data'!U39 | C46: ='1 prepared data'!B39 | D46: ='1 prepared data'!C39 | E46: ='1 prepared data'!D39 | F46: ='1 prepared data'!E39 | G46: ='1 prepared data'!F39 | H46: ='1 prepared data'!G39 | I46: ='1 prepared data'!H39 | J46: ='1 prepared data'!I39 | ... U46: ='1 prepared data'!T39 | V46: =$AE$12+D46*$AE$13+E46*$AE$14+F46*$AE$15+G46*$AE$16+H46*$AE$17+I46*$AE$18+J46*$AE$19+K46*$AE$20+L46*$AE$21+M46*$AE$22+N46*$AE$23+O46*$AE$24+P46*$AE$25+Q46*$AE$26+R46*$AE$27+S46*$AE$28+T46*$AE$29+U46*$AE$30 | W46: =1/(1+EXP(-V46)) | X46: =-IF(C46=1,LN(W46),LN(1-W46)) | Y46: =IF(C46=1,$AE$32,$AE$33) | Z46: =Y46*X46 | AA46: =IF(W46>$AE$34,1,0) | AB46: =IF(AA46=C46,1,0) | AD46: scikit-learn reference: testing AUC | AE46: 0.82349206
A47: ='1 prepared data'!A40 | B47: ='1 prepared data'!U40 | C47: ='1 prepared data'!B40 | D47: ='1 prepared data'!C40 | E47: ='1 prepared data'!D40 | F47: ='1 prepared data'!E40 | G47: ='1 prepared data'!F40 | H47: ='1 prepared data'!G40 | I47: ='1 prepared data'!H40 | J47: ='1 prepared data'!I40 | ... U47: ='1 prepared data'!T40 | V47: =$AE$12+D47*$AE$13+E47*$AE$14+F47*$AE$15+G47*$AE$16+H47*$AE$17+I47*$AE$18+J47*$AE$19+K47*$AE$20+L47*$AE$21+M47*$AE$22+N47*$AE$23+O47*$AE$24+P47*$AE$25+Q47*$AE$26+R47*$AE$27+S47*$AE$28+T47*$AE$29+U47*$AE$30 | W47: =1/(1+EXP(-V47)) | X47: =-IF(C47=1,LN(W47),LN(1-W47)) | Y47: =IF(C47=1,$AE$32,$AE$33) | Z47: =Y47*X47 | AA47: =IF(W47>$AE$34,1,0) | AB47: =IF(AA47=C47,1,0)
A48: ='1 prepared data'!A41 | B48: ='1 prepared data'!U41 | C48: ='1 prepared data'!B41 | D48: ='1 prepared data'!C41 | E48: ='1 prepared data'!D41 | F48: ='1 prepared data'!E41 | G48: ='1 prepared data'!F41 | H48: ='1 prepared data'!G41 | I48: ='1 prepared data'!H41 | J48: ='1 prepared data'!I41 | ... U48: ='1 prepared data'!T41 | V48: =$AE$12+D48*$AE$13+E48*$AE$14+F48*$AE$15+G48*$AE$16+H48*$AE$17+I48*$AE$18+J48*$AE$19+K48*$AE$20+L48*$AE$21+M48*$AE$22+N48*$AE$23+O48*$AE$24+P48*$AE$25+Q48*$AE$26+R48*$AE$27+S48*$AE$28+T48*$AE$29+U48*$AE$30 | W48: =1/(1+EXP(-V48)) | X48: =-IF(C48=1,LN(W48),LN(1-W48)) | Y48: =IF(C48=1,$AE$32,$AE$33) | Z48: =Y48*X48 | AA48: =IF(W48>$AE$34,1,0) | AB48: =IF(AA48=C48,1,0) | AD48: Solver: minimize J by changing the light blue model weight cells (not the class weight cells), GRG Nonlinear, central derivatives, convergence 0.000001, no constraints and with 'Make Unconstrained Variables Non-Negative' UNTICKED. Run twice if it stops early.
A49: ='1 prepared data'!A42 | B49: ='1 prepared data'!U42 | C49: ='1 prepared data'!B42 | D49: ='1 prepared data'!C42 | E49: ='1 prepared data'!D42 | F49: ='1 prepared data'!E42 | G49: ='1 prepared data'!F42 | H49: ='1 prepared data'!G42 | I49: ='1 prepared data'!H42 | J49: ='1 prepared data'!I42 | ... U49: ='1 prepared data'!T42 | V49: =$AE$12+D49*$AE$13+E49*$AE$14+F49*$AE$15+G49*$AE$16+H49*$AE$17+I49*$AE$18+J49*$AE$19+K49*$AE$20+L49*$AE$21+M49*$AE$22+N49*$AE$23+O49*$AE$24+P49*$AE$25+Q49*$AE$26+R49*$AE$27+S49*$AE$28+T49*$AE$29+U49*$AE$30 | W49: =1/(1+EXP(-V49)) | X49: =-IF(C49=1,LN(W49),LN(1-W49)) | Y49: =IF(C49=1,$AE$32,$AE$33) | Z49: =Y49*X49 | AA49: =IF(W49>$AE$34,1,0) | AB49: =IF(AA49=C49,1,0)
A50: ='1 prepared data'!A43 | B50: ='1 prepared data'!U43 | C50: ='1 prepared data'!B43 | D50: ='1 prepared data'!C43 | E50: ='1 prepared data'!D43 | F50: ='1 prepared data'!E43 | G50: ='1 prepared data'!F43 | H50: ='1 prepared data'!G43 | I50: ='1 prepared data'!H43 | J50: ='1 prepared data'!I43 | ... U50: ='1 prepared data'!T43 | V50: =$AE$12+D50*$AE$13+E50*$AE$14+F50*$AE$15+G50*$AE$16+H50*$AE$17+I50*$AE$18+J50*$AE$19+K50*$AE$20+L50*$AE$21+M50*$AE$22+N50*$AE$23+O50*$AE$24+P50*$AE$25+Q50*$AE$26+R50*$AE$27+S50*$AE$28+T50*$AE$29+U50*$AE$30 | W50: =1/(1+EXP(-V50)) | X50: =-IF(C50=1,LN(W50),LN(1-W50)) | Y50: =IF(C50=1,$AE$32,$AE$33) | Z50: =Y50*X50 | AA50: =IF(W50>$AE$34,1,0) | AB50: =IF(AA50=C50,1,0)
A51: ='1 prepared data'!A44 | B51: ='1 prepared data'!U44 | C51: ='1 prepared data'!B44 | D51: ='1 prepared data'!C44 | E51: ='1 prepared data'!D44 | F51: ='1 prepared data'!E44 | G51: ='1 prepared data'!F44 | H51: ='1 prepared data'!G44 | I51: ='1 prepared data'!H44 | J51: ='1 prepared data'!I44 | ... U51: ='1 prepared data'!T44 | V51: =$AE$12+D51*$AE$13+E51*$AE$14+F51*$AE$15+G51*$AE$16+H51*$AE$17+I51*$AE$18+J51*$AE$19+K51*$AE$20+L51*$AE$21+M51*$AE$22+N51*$AE$23+O51*$AE$24+P51*$AE$25+Q51*$AE$26+R51*$AE$27+S51*$AE$28+T51*$AE$29+U51*$AE$30 | W51: =1/(1+EXP(-V51)) | X51: =-IF(C51=1,LN(W51),LN(1-W51)) | Y51: =IF(C51=1,$AE$32,$AE$33) | Z51: =Y51*X51 | AA51: =IF(W51>$AE$34,1,0) | AB51: =IF(AA51=C51,1,0)
A52: ='1 prepared data'!A45 | B52: ='1 prepared data'!U45 | C52: ='1 prepared data'!B45 | D52: ='1 prepared data'!C45 | E52: ='1 prepared data'!D45 | F52: ='1 prepared data'!E45 | G52: ='1 prepared data'!F45 | H52: ='1 prepared data'!G45 | I52: ='1 prepared data'!H45 | J52: ='1 prepared data'!I45 | ... U52: ='1 prepared data'!T45 | V52: =$AE$12+D52*$AE$13+E52*$AE$14+F52*$AE$15+G52*$AE$16+H52*$AE$17+I52*$AE$18+J52*$AE$19+K52*$AE$20+L52*$AE$21+M52*$AE$22+N52*$AE$23+O52*$AE$24+P52*$AE$25+Q52*$AE$26+R52*$AE$27+S52*$AE$28+T52*$AE$29+U52*$AE$30 | W52: =1/(1+EXP(-V52)) | X52: =-IF(C52=1,LN(W52),LN(1-W52)) | Y52: =IF(C52=1,$AE$32,$AE$33) | Z52: =Y52*X52 | AA52: =IF(W52>$AE$34,1,0) | AB52: =IF(AA52=C52,1,0)
A53: ='1 prepared data'!A46 | B53: ='1 prepared data'!U46 | C53: ='1 prepared data'!B46 | D53: ='1 prepared data'!C46 | E53: ='1 prepared data'!D46 | F53: ='1 prepared data'!E46 | G53: ='1 prepared data'!F46 | H53: ='1 prepared data'!G46 | I53: ='1 prepared data'!H46 | J53: ='1 prepared data'!I46 | ... U53: ='1 prepared data'!T46 | V53: =$AE$12+D53*$AE$13+E53*$AE$14+F53*$AE$15+G53*$AE$16+H53*$AE$17+I53*$AE$18+J53*$AE$19+K53*$AE$20+L53*$AE$21+M53*$AE$22+N53*$AE$23+O53*$AE$24+P53*$AE$25+Q53*$AE$26+R53*$AE$27+S53*$AE$28+T53*$AE$29+U53*$AE$30 | W53: =1/(1+EXP(-V53)) | X53: =-IF(C53=1,LN(W53),LN(1-W53)) | Y53: =IF(C53=1,$AE$32,$AE$33) | Z53: =Y53*X53 | AA53: =IF(W53>$AE$34,1,0) | AB53: =IF(AA53=C53,1,0)
A54: ='1 prepared data'!A47 | B54: ='1 prepared data'!U47 | C54: ='1 prepared data'!B47 | D54: ='1 prepared data'!C47 | E54: ='1 prepared data'!D47 | F54: ='1 prepared data'!E47 | G54: ='1 prepared data'!F47 | H54: ='1 prepared data'!G47 | I54: ='1 prepared data'!H47 | J54: ='1 prepared data'!I47 | ... U54: ='1 prepared data'!T47 | V54: =$AE$12+D54*$AE$13+E54*$AE$14+F54*$AE$15+G54*$AE$16+H54*$AE$17+I54*$AE$18+J54*$AE$19+K54*$AE$20+L54*$AE$21+M54*$AE$22+N54*$AE$23+O54*$AE$24+P54*$AE$25+Q54*$AE$26+R54*$AE$27+S54*$AE$28+T54*$AE$29+U54*$AE$30 | W54: =1/(1+EXP(-V54)) | X54: =-IF(C54=1,LN(W54),LN(1-W54)) | Y54: =IF(C54=1,$AE$32,$AE$33) | Z54: =Y54*X54 | AA54: =IF(W54>$AE$34,1,0) | AB54: =IF(AA54=C54,1,0)
A55: ='1 prepared data'!A48 | B55: ='1 prepared data'!U48 | C55: ='1 prepared data'!B48 | D55: ='1 prepared data'!C48 | E55: ='1 prepared data'!D48 | F55: ='1 prepared data'!E48 | G55: ='1 prepared data'!F48 | H55: ='1 prepared data'!G48 | I55: ='1 prepared data'!H48 | J55: ='1 prepared data'!I48 | ... U55: ='1 prepared data'!T48 | V55: =$AE$12+D55*$AE$13+E55*$AE$14+F55*$AE$15+G55*$AE$16+H55*$AE$17+I55*$AE$18+J55*$AE$19+K55*$AE$20+L55*$AE$21+M55*$AE$22+N55*$AE$23+O55*$AE$24+P55*$AE$25+Q55*$AE$26+R55*$AE$27+S55*$AE$28+T55*$AE$29+U55*$AE$30 | W55: =1/(1+EXP(-V55)) | X55: =-IF(C55=1,LN(W55),LN(1-W55)) | Y55: =IF(C55=1,$AE$32,$AE$33) | Z55: =Y55*X55 | AA55: =IF(W55>$AE$34,1,0) | AB55: =IF(AA55=C55,1,0)
A56: ='1 prepared data'!A49 | B56: ='1 prepared data'!U49 | C56: ='1 prepared data'!B49 | D56: ='1 prepared data'!C49 | E56: ='1 prepared data'!D49 | F56: ='1 prepared data'!E49 | G56: ='1 prepared data'!F49 | H56: ='1 prepared data'!G49 | I56: ='1 prepared data'!H49 | J56: ='1 prepared data'!I49 | ... U56: ='1 prepared data'!T49 | V56: =$AE$12+D56*$AE$13+E56*$AE$14+F56*$AE$15+G56*$AE$16+H56*$AE$17+I56*$AE$18+J56*$AE$19+K56*$AE$20+L56*$AE$21+M56*$AE$22+N56*$AE$23+O56*$AE$24+P56*$AE$25+Q56*$AE$26+R56*$AE$27+S56*$AE$28+T56*$AE$29+U56*$AE$30 | W56: =1/(1+EXP(-V56)) | X56: =-IF(C56=1,LN(W56),LN(1-W56)) | Y56: =IF(C56=1,$AE$32,$AE$33) | Z56: =Y56*X56 | AA56: =IF(W56>$AE$34,1,0) | AB56: =IF(AA56=C56,1,0)
A57: ='1 prepared data'!A50 | B57: ='1 prepared data'!U50 | C57: ='1 prepared data'!B50 | D57: ='1 prepared data'!C50 | E57: ='1 prepared data'!D50 | F57: ='1 prepared data'!E50 | G57: ='1 prepared data'!F50 | H57: ='1 prepared data'!G50 | I57: ='1 prepared data'!H50 | J57: ='1 prepared data'!I50 | ... U57: ='1 prepared data'!T50 | V57: =$AE$12+D57*$AE$13+E57*$AE$14+F57*$AE$15+G57*$AE$16+H57*$AE$17+I57*$AE$18+J57*$AE$19+K57*$AE$20+L57*$AE$21+M57*$AE$22+N57*$AE$23+O57*$AE$24+P57*$AE$25+Q57*$AE$26+R57*$AE$27+S57*$AE$28+T57*$AE$29+U57*$AE$30 | W57: =1/(1+EXP(-V57)) | X57: =-IF(C57=1,LN(W57),LN(1-W57)) | Y57: =IF(C57=1,$AE$32,$AE$33) | Z57: =Y57*X57 | AA57: =IF(W57>$AE$34,1,0) | AB57: =IF(AA57=C57,1,0)
A58: ='1 prepared data'!A51 | B58: ='1 prepared data'!U51 | C58: ='1 prepared data'!B51 | D58: ='1 prepared data'!C51 | E58: ='1 prepared data'!D51 | F58: ='1 prepared data'!E51 | G58: ='1 prepared data'!F51 | H58: ='1 prepared data'!G51 | I58: ='1 prepared data'!H51 | J58: ='1 prepared data'!I51 | ... U58: ='1 prepared data'!T51 | V58: =$AE$12+D58*$AE$13+E58*$AE$14+F58*$AE$15+G58*$AE$16+H58*$AE$17+I58*$AE$18+J58*$AE$19+K58*$AE$20+L58*$AE$21+M58*$AE$22+N58*$AE$23+O58*$AE$24+P58*$AE$25+Q58*$AE$26+R58*$AE$27+S58*$AE$28+T58*$AE$29+U58*$AE$30 | W58: =1/(1+EXP(-V58)) | X58: =-IF(C58=1,LN(W58),LN(1-W58)) | Y58: =IF(C58=1,$AE$32,$AE$33) | Z58: =Y58*X58 | AA58: =IF(W58>$AE$34,1,0) | AB58: =IF(AA58=C58,1,0)
A59: ='1 prepared data'!A52 | B59: ='1 prepared data'!U52 | C59: ='1 prepared data'!B52 | D59: ='1 prepared data'!C52 | E59: ='1 prepared data'!D52 | F59: ='1 prepared data'!E52 | G59: ='1 prepared data'!F52 | H59: ='1 prepared data'!G52 | I59: ='1 prepared data'!H52 | J59: ='1 prepared data'!I52 | ... U59: ='1 prepared data'!T52 | V59: =$AE$12+D59*$AE$13+E59*$AE$14+F59*$AE$15+G59*$AE$16+H59*$AE$17+I59*$AE$18+J59*$AE$19+K59*$AE$20+L59*$AE$21+M59*$AE$22+N59*$AE$23+O59*$AE$24+P59*$AE$25+Q59*$AE$26+R59*$AE$27+S59*$AE$28+T59*$AE$29+U59*$AE$30 | W59: =1/(1+EXP(-V59)) | X59: =-IF(C59=1,LN(W59),LN(1-W59)) | Y59: =IF(C59=1,$AE$32,$AE$33) | Z59: =Y59*X59 | AA59: =IF(W59>$AE$34,1,0) | AB59: =IF(AA59=C59,1,0)
A60: ='1 prepared data'!A53 | B60: ='1 prepared data'!U53 | C60: ='1 prepared data'!B53 | D60: ='1 prepared data'!C53 | E60: ='1 prepared data'!D53 | F60: ='1 prepared data'!E53 | G60: ='1 prepared data'!F53 | H60: ='1 prepared data'!G53 | I60: ='1 prepared data'!H53 | J60: ='1 prepared data'!I53 | ... U60: ='1 prepared data'!T53 | V60: =$AE$12+D60*$AE$13+E60*$AE$14+F60*$AE$15+G60*$AE$16+H60*$AE$17+I60*$AE$18+J60*$AE$19+K60*$AE$20+L60*$AE$21+M60*$AE$22+N60*$AE$23+O60*$AE$24+P60*$AE$25+Q60*$AE$26+R60*$AE$27+S60*$AE$28+T60*$AE$29+U60*$AE$30 | W60: =1/(1+EXP(-V60)) | X60: =-IF(C60=1,LN(W60),LN(1-W60)) | Y60: =IF(C60=1,$AE$32,$AE$33) | Z60: =Y60*X60 | AA60: =IF(W60>$AE$34,1,0) | AB60: =IF(AA60=C60,1,0)
... A1011: ='1 prepared data'!A1004 | B1011: ='1 prepared data'!U1004 | C1011: ='1 prepared data'!B1004 | D1011: ='1 prepared data'!C1004 | E1011: ='1 prepared data'!D1004 | F1011: ='1 prepared data'!E1004 | G1011: ='1 prepared data'!F1004 | H1011: ='1 prepared data'!G1004 | I1011: ='1 prepared data'!H1004 | J1011: ='1 prepared data'!I1004 | ... U1011: ='1 prepared data'!T1004 | V1011: =$AE$12+D1011*$AE$13+E1011*$AE$14+F1011*$AE$15+G1011*$AE$16+H1011*$AE$17+I1011*$AE$18+J1011*$AE$19+K1011*$AE$20+L1011*$AE$21+M1011*$AE$22+N1011*$AE$23+O1011*$AE$24+P1011*$AE$25+Q1011*$AE$26+R1011*$AE$27+S1011*$AE$28+T1011*$AE$29+U1011*$AE$30 | W1011: =1/(1+EXP(-V1011)) | X1011: =-IF(C1011=1,LN(W1011),LN(1-W1011)) | Y1011: =IF(C1011=1,$AE$32,$AE$33) | Z1011: =Y1011*X1011 | AA1011: =IF(W1011>$AE$34,1,0) | AB1011: =IF(AA1011=C1011,1,0)

Sheet 6 SMOTE
A1: SMOTE: inventing new defaulters by interpolating between neighbors (computed in Python)
A2: SMOTE (Synthetic Minority Oversampling Technique, Chawla et al., 2002) answers the risk of oversampling by repetition: instead of duplicating a row, it creates new rows. It takes a defaulter at random, finds its 5 nearest neighbors among the defaulters (distance over the scaled columns), picks one of them and creates a synthetic customer at a random point on the segment joining them: x_new = x_a + u · (x_b − x_a), with u between 0 and 1. It repeats until the minority class matches the majority: here, 280 synthetic customers, to reach 490 and 490.
A3: Below, three examples with their two real parents (ids from sheet 1) and the cell u in light blue: move it and you will see the child slide between the two. An honest detail: the 0/1 columns become fractional (a synthetic customer can have 0.37 of 'renting'), which means nothing; there are variants (SMOTE-NC) that treat the categorical columns separately. It also shows why SMOTE is not magic: the synthetic rows live inside the cloud of defaulters that already existed, so the new information is limited; what it does is smooth the oversampling. In this dataset its testing result is practically that of class weights. SMOTE is in the imbalanced-learn library (imblearn) and is applied only to training, never to testing.
A5: Example 1: parent a = id 675, parent b = id 332 | C5: u = | D5: 0.808
B6: duration | C6: amount | D6: age | E6: installment_pct_income | F6: chk_negative | G6: chk_0_200 | H6: chk_over_200 | I6: hist_critical | J6: hist_delays | K6: hist_no_credits | L6: sav_100_1000 | M6: sav_over_1000 | N6: sav_unknown | O6: housing_rent | P6: housing_free | Q6: purpose_car | R6: purpose_radio_tv | S6: purpose_furniture
A7: parent a (real) | B7: 0.022629547 | C7: -0.23467156 | D7: 0.47487269 | E7: 0.91854372 | F7: 0 | G7: 0 | H7: 0 | I7: 0 | J7: 1 | K7: 0 | L7: 1 | M7: 0 | N7: 0 | O7: 0 | P7: 0 | Q7: 0 | R7: 0 | S7: 0
A8: parent b (real) | B8: -0.23014731 | C8: -0.48519477 | D8: -0.48183053 | E8: 0.91854372 | F8: 0 | G8: 0 | H8: 0 | I8: 1 | J8: 0 | K8: 0 | L8: 1 | M8: 0 | N8: 0 | O8: 0 | P8: 0 | Q8: 0 | R8: 0 | S8: 0
A9: synthetic child = a + u · (b − a) | B9: =B7+$D$5*(B8-B7) | C9: =C7+$D$5*(C8-C7) | D9: =D7+$D$5*(D8-D7) | E9: =E7+$D$5*(E8-E7) | F9: =F7+$D$5*(F8-F7) | G9: =G7+$D$5*(G8-G7) | H9: =H7+$D$5*(H8-H7) | I9: =I7+$D$5*(I8-I7) | ... S9: =S7+$D$5*(S8-S7)
A11: Example 2: parent a = id 501, parent b = id 723 | C11: u = | D11: 0.286
B12: duration | C12: amount | D12: age | E12: installment_pct_income | F12: chk_negative | G12: chk_0_200 | H12: chk_over_200 | I12: hist_critical | J12: hist_delays | K12: hist_no_credits | L12: sav_100_1000 | M12: sav_over_1000 | N12: sav_unknown | O12: housing_rent | P12: housing_free | Q12: purpose_car | R12: purpose_radio_tv | S12: purpose_furniture
A13: parent a (real) | B13: 0.2754064 | C13: -0.044679804 | D13: -0.7427496 | E13: 0.91854372 | F13: 1 | G13: 0 | H13: 0 | I13: 0 | J13: 0 | K13: 0 | L13: 0 | M13: 0 | N13: 0 | O13: 0 | P13: 0 | Q13: 1 | R13: 0 | S13: 0
A14: parent b (real) | B14: -0.73570101 | C14: -0.70772655 | D14: -1.0036687 | E14: 0.91854372 | F14: 1 | G14: 0 | H14: 0 | I14: 0 | J14: 0 | K14: 0 | L14: 0 | M14: 0 | N14: 0 | O14: 0 | P14: 0 | Q14: 1 | R14: 0 | S14: 0
A15: synthetic child = a + u · (b − a) | B15: =B13+$D$11*(B14-B13) | C15: =C13+$D$11*(C14-C13) | D15: =D13+$D$11*(D14-D13) | E15: =E13+$D$11*(E14-E13) | F15: =F13+$D$11*(F14-F13) | G15: =G13+$D$11*(G14-G13) | H15: =H13+$D$11*(H14-H13) | I15: =I13+$D$11*(I14-I13) | ... S15: =S13+$D$11*(S14-S13)
A17: Example 3: parent a = id 980, parent b = id 810 | C17: u = | D17: 0.383
B18: duration | C18: amount | D18: age | E18: installment_pct_income | F18: chk_negative | G18: chk_0_200 | H18: chk_over_200 | I18: hist_critical | J18: hist_delays | K18: hist_no_credits | L18: sav_100_1000 | M18: sav_over_1000 | N18: sav_unknown | O18: housing_rent | P18: housing_free | Q18: purpose_car | R18: purpose_radio_tv | S18: purpose_furniture
A19: parent a (real) | B19: -0.48292416 | C19: -0.69513041 | D19: -0.91669564 | E19: -0.88504844 | F19: 0 | G19: 1 | H19: 0 | I19: 0 | J19: 0 | K19: 1 | L19: 1 | M19: 0 | N19: 0 | O19: 1 | P19: 0 | Q19: 1 | R19: 0 | S19: 0
A20: parent b (real) | B20: -0.48292416 | C20: -0.51528554 | D20: -0.82972262 | E20: -0.88504844 | F20: 0 | G20: 1 | H20: 0 | I20: 0 | J20: 0 | K20: 1 | L20: 0 | M20: 0 | N20: 0 | O20: 1 | P20: 0 | Q20: 1 | R20: 0 | S20: 0
A21: synthetic child = a + u · (b − a) | B21: =B19+$D$17*(B20-B19) | C21: =C19+$D$17*(C20-C19) | D21: =D19+$D$17*(D20-D19) | E21: =E19+$D$17*(E20-E19) | F21: =F19+$D$17*(F20-F19) | G21: =G19+$D$17*(G20-G19) | H21: =H19+$D$17*(H20-H19) | I21: =I19+$D$17*(I20-I19) | ... S21: =S19+$D$17*(S20-S19)
A24: The first 40 of the 280 synthetic customers (values from Python)
A25: synthetic | B25: duration | C25: amount | D25: age | E25: installment_pct_income | F25: chk_negative | G25: chk_0_200 | H25: chk_over_200 | I25: hist_critical | J25: hist_delays | K25: hist_no_credits | L25: sav_100_1000 | M25: sav_over_1000 | N25: sav_unknown | O25: housing_rent | P25: housing_free | Q25: purpose_car | R25: purpose_radio_tv | S25: purpose_furniture
A26: 1 | B26: -0.18159918 | C26: -0.43707948 | D26: -0.29808687 | E26: 0.91854372 | F26: 0 | G26: 0 | H26: 0 | I26: 0.80794079 | J26: 0.19205921 | K26: 0 | L26: 1 | M26: 0 | N26: 0 | O26: 0 | P26: 0 | Q26: 0 | R26: 0 | S26: 0
A27: 2 | B27: -0.013569494 | C27: -0.23417948 | D27: -0.81732062 | E27: 0.91854372 | F27: 1 | G27: 0 | H27: 0 | I27: 0 | J27: 0 | K27: 0 | L27: 0 | M27: 0 | N27: 0 | O27: 0 | P27: 0 | Q27: 1 | R27: 0 | S27: 0
A28: 3 | B28: -0.48292416 | C28: -0.62618348 | D28: -0.88335289 | E28: -0.88504844 | F28: 0 | G28: 1 | H28: 0 | I28: 0 | J28: 0 | K28: 1 | L28: 0.61663112 | M28: 0 | N28: 0 | O28: 1 | P28: 0 | Q28: 1 | R28: 0 | S28: 0
A29: 4 | B29: 0.2754064 | C29: -0.66187614 | D29: 0.36821107 | E29: 0.91854372 | F29: 1 | G29: 0 | H29: 0 | I29: 0 | J29: 0 | K29: 0.95472481 | L29: 0 | M29: 0 | N29: 1 | O29: 0 | P29: 0 | Q29: 0.045275194 | R29: 0 | S29: 0
A30: 5 | B30: 1.5399154 | C30: 0.58891952 | D30: -0.91691061 | E30: -0.88504844 | F30: 0 | G30: 1 | H30: 0 | I30: 0.99917612 | J30: 0 | K30: 0 | L30: 0 | M30: 0 | N30: 0 | O30: 0 | P30: 0 | Q30: 0 | R30: 1 | S30: 0
A31: 6 | B31: 0.1568489 | C31: 0.43400799 | D31: 1.2383929 | E31: -0.88504844 | F31: 0 | G31: 0 | H31: 0 | I31: 0 | J31: 0 | K31: 0.2345102 | L31: 0 | M31: 0.7654898 | N31: 0 | O31: 0 | P31: 0 | Q31: 0 | R31: 0 | S31: 0
A32: 7 | B32: 1.2865138 | C32: 1.752431 | D32: -0.82523241 | E32: -0.90832723 | F32: 0.97418619 | G32: 0.025813807 | H32: 0 | I32: 0 | J32: 0 | K32: 0 | L32: 0 | M32: 0 | N32: 0 | O32: 0.025813807 | P32: 0 | Q32: 1 | R32: 0 | S32: 0
A33: 8 | B33: -0.65695144 | C33: -0.90046028 | D33: -0.40054435 | E33: 0.91854372 | F33: 0 | G33: 1 | H33: 0 | I33: 0.15576896 | J33: 0 | K33: 0 | L33: 0 | M33: 0 | N33: 0 | O33: 0 | P33: 0 | Q33: 0.15576896 | R33: 0 | S33: 0
A34: 9 | B34: -0.10199526 | C34: -0.26159714 | D34: -0.95957534 | E34: -0.42785858 | F34: 1 | G34: 0 | H34: 0 | I34: 0 | J34: 0 | K34: 0 | L34: 0 | M34: 0 | N34: 0 | O34: 0 | P34: 0 | Q34: 0 | R34: 1 | S34: 0
A35: 10 | B35: -0.67422294 | C35: -0.81247111 | D35: -1.0800653 | E35: 0.91854372 | F35: 1 | G35: 0 | H35: 0 | I35: 0 | J35: 0 | K35: 0 | L35: 0 | M35: 0 | N35: 1 | O35: 0.060802713 | P35: 0 | Q35: 1 | R35: 0 | S35: 0
A36: 11 | B36: 0.069556353 | C36: -0.0872788 | D36: 0.071079399 | E36: 0.016747641 | F36: 0 | G36: 0 | H36: 0 | I36: 0 | J36: 0 | K36: 0 | L36: 1 | M36: 0 | N36: 0 | O36: 0 | P36: 0 | Q36: 0 | R36: 0.7285484 | S36: 0
A37: 12 | B37: 1.3514415 | C37: 0.39265363 | D37: -0.81855277 | E37: 0.91854372 | F37: 0 | G37: 0.064214437 | H37: 0 | I37: 0 | J37: 0.93578556 | K37: 0 | L37: 0 | M37: 0 | N37: 0 | O37: 0 | P37: 0 | Q37: 0 | R37: 1 | S37: 0
... A65: 40 | B65: 2.2976212 | C65: 1.3709074 | D65: -0.045856116 | E65: -0.74719536 | F65: 1 | G65: 0 | H65: 0 | I65: 0 | J65: 0 | K65: 0.84713498 | L65: 0 | M65: 0 | N65: 0 | O65: 1 | P65: 0 | Q65: 0 | R65: 0 | S65: 0
A68: Testing result of the logistic trained on 490 real + 280 synthetic rows (Python)
A69: class 1 recall | B69: 0.84444444
A70: class 1 precision | B70: 0.52777778
A71: class 1 F1 | B71: 0.64957265
A72: accuracy | B72: 0.72666667
A73: AUC testing | B73: 0.82968254
A74: average p on testing | B74: 0.47786114

Sheet 7 comparison
A1: The four methods on testing, and the unbalanced model with a different threshold
A2: Every row is evaluated on the same 300 testing customers (values from Python). The four corrections raise the recall of class 1 from 0.57 to between 0.83 and 0.87 and lower precision from 0.65 to between 0.50 and 0.56: none of them creates information, all of them move the operating point toward catching more defaulters. The AUC barely changes (0.81 to 0.83), because the AUC depends neither on the threshold nor on the balancing: the ranking of customers by risk is almost the same.
A3: The last row is the one worth the conversation: the unbalanced model, with threshold 0.30, has recall 0.856 and precision 0.513, almost the same as class weights (0.856 and 0.527). For a logistic, balancing and moving the threshold are two roads to the same place; the difference is that balancing shifts the probabilities (average p 0.48 against an actual rate of 0.30) and the threshold does not. When balancing does make sense: when the minority is so scarce (1%, 2%) that the model does not even learn to tell it apart and the AUC itself improves with weighting, or when the algorithm does not deliver a probability that can be thresholded.
A5: model | B5: threshold | C5: TP | D5: FP | E5: TN | F5: FN | G5: accuracy | H5: class 1 recall | I5: class 1 precision | J5: class 1 F1 | K5: class 0 recall | L5: AUC | M5: average p testing
A6: unbalanced | B6: 0.5 | C6: 51 | D6: 27 | E6: 183 | F6: 39 | G6: 0.78 | H6: 0.56666667 | I6: 0.65384615 | J6: 0.60714286 | K6: 0.87142857 | L6: 0.82169312 | M6: 0.33177079
A7: class weights balanced | B7: 0.5 | C7: 77 | D7: 69 | E7: 141 | F7: 13 | G7: 0.72666667 | H7: 0.85555556 | I7: 0.52739726 | J7: 0.65254237 | K7: 0.67142857 | L7: 0.82391534 | M7: 0.48420786
A8: undersampling 210 + 210 | B8: 0.5 | C8: 78 | D8: 78 | E8: 132 | F8: 12 | G8: 0.7 | H8: 0.86666667 | I8: 0.5 | J8: 0.63414634 | K8: 0.62857143 | L8: 0.81338624 | M8: 0.48642112
A9: oversampling, defaulters ×2 | B9: 0.5 | C9: 75 | D9: 59 | E9: 151 | F9: 15 | G9: 0.75333333 | H9: 0.83333333 | I9: 0.55970149 | J9: 0.66964286 | K9: 0.71904762 | L9: 0.82349206 | M9: 0.45557623
A10: SMOTE, 490 + 490 | B10: 0.5 | C10: 76 | D10: 68 | E10: 142 | F10: 14 | G10: 0.72666667 | H10: 0.84444444 | I10: 0.52777778 | J10: 0.64957265 | K10: 0.67619048 | L10: 0.82968254 | M10: 0.47786114
A11: unbalanced | B11: 0.3 | C11: 77 | D11: 73 | E11: 137 | F11: 13 | G11: 0.71333333 | H11: 0.85555556 | I11: 0.51333333 | J11: 0.64166667 | K11: 0.65238095 | L11: 0.82169312 | M11: 0.33177079
A12: unbalanced | B12: 0.25 | C12: 80 | D12: 86 | E12: 124 | F12: 10 | G12: 0.68 | H12: 0.88888889 | I12: 0.48192771 | J12: 0.625 | K12: 0.59047619 | L12: 0.82169312 | M12: 0.33177079
